Workbook

Sheet physics_results
A1: datetime | B1: ai_model | C1: statement_row_id | D1: statement | E1: ok | F1: final_numeric | G1: final_formula | H1: final_units | I1: error | J1: raw_response_text | K1: full_api_response | L1: prompt_tokens | M1: completion_tokens | N1: total_tokens | O1: prompt_version | P1: topic | Q1: cost | R1: is_correct_number | S1: is_correct_formula | T1: is_correct_units
A2: 2026-06-03-13-14-20 | B2: anthropic/claude-opus-4.7 | C2: 1 | D2: Частица пролетает расстояние l = 2 м равномерно, а затем тормозит с ускорением а = 5*10^5 м/с^2. При какой скорости частицы время движения ее от вылета до остановки будет наименьшим? Examples: Example 1: Calculate the height of a cliff if it takes 2.35 s for a rock to hit the ground when it is thrown straight up from the cliff with an initial velocity of 8.00 m/s. (b) How long would it take to reach the ground if it is thrown straight down with the same speed?* Solution s ↑ y₀ = ? ////| /\ | / \ | / \ | / ↓ | / | |______/________|____ y = 0 m (a) Knowns: \(t = 2.35\ \text{s}; y = 0\ \text{m}; v_0 = +8.00\ \text{m/s}; a = -9.8\ \text{m/s}^2\) Since we know \(t\), \(y\), \(v_0\), and \(a\) and want to find \(y_0\), we can use the equation \[ y = y_0 + v_0t + \frac{1}{2}at^2. \] \[ y = (0\ \text{m}) + (+8.00\ \text{m/s})(2.35\ \text{s}) + \frac{1}{2}(-9.80\ \text{m/s}^2)(2.35\ \text{s})^2 = -8.26\ \text{m}, \text{ so the cliff is} \] <u>8.26 m</u> high. (b) Knowns: \(y = 0\ \text{m}; y_0 = 8.26\ \text{m}; v_0 = -8.00\ \text{m/s}; a = -9.80\ \text{m/s}^2\) Now we know \(y\), \(y_0\), \(v_0\), and \(a\) and want to find \(t\), so we use the equation \[ y = y_0 + v_0t + \frac{1}{2}at^2 \] again. Rearranging, \[ t = \frac{-v_0 \pm \sqrt{v_0^2 - 4(0.5a)(y_0 - y)}}{2(0.5a)} \] \[ t = \frac{-(-8.00\ \text{m/s}) \pm \sqrt{(-8.00\ \text{m/s})^2 + 2(9.80\ \text{m/s}^2)(8.26\ \text{m} - 0\ \text{m})}}{(-9.80\ \text{m/s}^2)} \] \[ = \frac{8.00\ \text{m/s} \pm 15.03\ \text{m/s}}{-9.80\ \text{m/s}^2} \] \[ t = 0.717\ \text{s} \text{ or } -2.35\ \text{s} \Rightarrow t = \underline{0.717\ \text{s}} \] Example 2: *Calculate the force a 70.0-kg high jumper must exert on the ground to produce an upward acceleration 4.00 times the acceleration due to gravity. Explicitly show how you follow the steps in the Problem-Solving Strategy for Newton’s laws of motion.* Solution Step 1. Use Newton’s Laws of Motion. ↑ F | | (m) ↑ a | ↓ w Force acting on the high jumper. Step 2. Given: \(a = 4.00\ g = (4.00)(9.80\ \text{m/s}^2) = 39.2\ \text{m/s}^2;\ m = 70.0\ \text{kg}\) Find \(F\). Step 3. \(\sum F = +F - w = ma,\) so that \(F = ma + w = ma + mg = m(a + g)\) \[ F = (70.0\ \text{kg})[(39.2\ \text{m/s}^2) + (9.80\ \text{m/s}^2)] = \underline{3.43 \times 10^3\ \text{N}} \] The force exerted by the high-jumper is actually down on the ground, but F is up from the ground to help him jump. Step 4. This result is reasonable, since it is quite possible for a person to exert a force of the magnitude of \(10^3\ \text{N}\). Example 3: *A shopper pushes a grocery cart 20.0 m at constant speed on level ground, against a 35.0 N frictional force. He pushes in a direction 25.0° below the horizontal. (a) What is the work done on the cart by friction? (b) What is the work done on the cart by the gravitational force? (c) What is the work done on the cart by the shopper? (d) Find the force the shopper exerts, using energy considerations. (e) What is the total work done on the cart?* Solution (a) The work done by friction is in the opposite direction of the motion, so \(\theta = 180^\circ\), and therefore \(W_f = Fd \cos\theta = 35.0\ \text{N} \times 20.0\ \text{m} \times \cos 180^\circ = \underline{-700\ \text{J}}\) (b) The work done by gravity is perpendicular to the direction of motion, so \(\theta = 90^\circ\), and \(W_g = Fd \cos\theta = 35.0\ \text{N} \times 20.0\ \text{m} \times \cos 90^\circ = \underline{0\ \text{J}}\) (c) If the cart moves at a constant speed, no energy is transferred to it, from the work-energy theorem: \(\text{net } W = W_s + W_f = 0,\) or \(W_s = \underline{700\ \text{J}}\) (d) Use the equation \(W_s = Fd \cos\theta\), where \(\theta = 25^\circ\), and solve for the force: \[ F = \frac{W_s}{d \cos\theta} = \frac{700\ \text{J}}{20.0\ \text{m} \times \cos 25^\circ} = 38.62\ \text{N} = \underline{38.6\ \text{N}} \] (e) Since there is no change in speed, the work energy theorem says that there is no net work done on the cart: \(\text{net } W = W_f + W_s = -700\ \text{J} + 700\ \text{J} = \underline{0\ \text{J}}\) | E2: TRUE | F2: 1414.21 | G2: v=\sqrt{2al} | H2: m/s | J2: {"final_numeric":1414.21,"final_formula":"v=\\sqrt{2al}","final_units":"m/s"} | K2: {'id': 'gen-1780478058-z0ViJnvuAXLmt9Hs99ZQ', 'object': 'chat.completion', 'created': 1780478058, 'model': 'anthropic/claude-4.7-opus-20260416', 'provider': 'Anthropic', 'system_fingerprint': None, 'service_tier': 'default', 'choices': [{'index': 0, 'logprobs': None, 'finish_reason': 'stop', 'native_finish_reason': 'end_turn', 'message': {'role': 'assistant', 'content': '{"final_numeric":1414.21,"final_formula":"v=\\\\sqrt{2al}","final_units":"m/s"}', 'refusal': None, 'reasoning': None}}], 'usage': {'prompt_tokens': 2910, 'completion_tokens': 47, 'total_tokens': 2957, 'cost': 0.015725, 'is_byok': False, 'prompt_tokens_details': {'cached_tokens': 0, 'cache_write_tokens': 0, 'audio_tokens': 0, 'video_tokens': 0}, 'cost_details': {'upstream_inference_cost': 0.015725, 'upstream_inference_prompt_cost': 0.01455, 'upstream_inference_completions_cost': 0.001175}, 'completion_tokens_details': {'reasoning_tokens': 0, 'image_tokens': 0, 'audio_tokens': 0}}} | L2: 2910 | M2: 47 | N2: 2957 | O2: 0 | P2: =VLOOKUP(C2,problems!$A$2:$B$26,2) -> mechanics | Q2: =IFERROR(__xludf.DUMMYFUNCTION("INDEX(FILTER('stats2-openrouter_activity_2026'!C:C,L2='stats2-openrouter_activity_2026'!H:H,M2='stats2-openrouter_activity_2026'!I:I, B2='stats2-openrouter_activity_2026'!M:M),1)"),0.015725) -> 0.015725 | R2: =IFS( F2=VLOOKUP($C2,problems!$A$2:$G$26,6),1, True,0 ) -> 0 | S2: =IFS( G2=VLOOKUP($C2,problems!$A$2:$G$26,4),1, G2=VLOOKUP($C2,problems!$A$2:$G$26,5),1, True,0 ) -> 0 | T2: =IFS( H2=VLOOKUP($C2,problems!$A$2:$G$26,7),1, True,0 ) -> 1
A3: 2026-06-03-13-17-15 | B3: anthropic/claude-opus-4.7 | C3: 2 | D3: Точка движется по прямой согласно закону х = At + Bt^3, где А = 6 м/с; В = -0,125 м/с^3. Определить: среднюю скорость точки в интервале времени от t_{1} = 2 с до t_{2} = 6 с; Examples: Example 1: Calculate the height of a cliff if it takes 2.35 s for a rock to hit the ground when it is thrown straight up from the cliff with an initial velocity of 8.00 m/s. (b) How long would it take to reach the ground if it is thrown straight down with the same speed?* Solution s ↑ y₀ = ? ////| /\ | / \ | / \ | / ↓ | / | |______/________|____ y = 0 m (a) Knowns: \(t = 2.35\ \text{s}; y = 0\ \text{m}; v_0 = +8.00\ \text{m/s}; a = -9.8\ \text{m/s}^2\) Since we know \(t\), \(y\), \(v_0\), and \(a\) and want to find \(y_0\), we can use the equation \[ y = y_0 + v_0t + \frac{1}{2}at^2. \] \[ y = (0\ \text{m}) + (+8.00\ \text{m/s})(2.35\ \text{s}) + \frac{1}{2}(-9.80\ \text{m/s}^2)(2.35\ \text{s})^2 = -8.26\ \text{m}, \text{ so the cliff is} \] <u>8.26 m</u> high. (b) Knowns: \(y = 0\ \text{m}; y_0 = 8.26\ \text{m}; v_0 = -8.00\ \text{m/s}; a = -9.80\ \text{m/s}^2\) Now we know \(y\), \(y_0\), \(v_0\), and \(a\) and want to find \(t\), so we use the equation \[ y = y_0 + v_0t + \frac{1}{2}at^2 \] again. Rearranging, \[ t = \frac{-v_0 \pm \sqrt{v_0^2 - 4(0.5a)(y_0 - y)}}{2(0.5a)} \] \[ t = \frac{-(-8.00\ \text{m/s}) \pm \sqrt{(-8.00\ \text{m/s})^2 + 2(9.80\ \text{m/s}^2)(8.26\ \text{m} - 0\ \text{m})}}{(-9.80\ \text{m/s}^2)} \] \[ = \frac{8.00\ \text{m/s} \pm 15.03\ \text{m/s}}{-9.80\ \text{m/s}^2} \] \[ t = 0.717\ \text{s} \text{ or } -2.35\ \text{s} \Rightarrow t = \underline{0.717\ \text{s}} \] Example 2: *Calculate the force a 70.0-kg high jumper must exert on the ground to produce an upward acceleration 4.00 times the acceleration due to gravity. Explicitly show how you follow the steps in the Problem-Solving Strategy for Newton’s laws of motion.* Solution Step 1. Use Newton’s Laws of Motion. ↑ F | | (m) ↑ a | ↓ w Force acting on the high jumper. Step 2. Given: \(a = 4.00\ g = (4.00)(9.80\ \text{m/s}^2) = 39.2\ \text{m/s}^2;\ m = 70.0\ \text{kg}\) Find \(F\). Step 3. \(\sum F = +F - w = ma,\) so that \(F = ma + w = ma + mg = m(a + g)\) \[ F = (70.0\ \text{kg})[(39.2\ \text{m/s}^2) + (9.80\ \text{m/s}^2)] = \underline{3.43 \times 10^3\ \text{N}} \] The force exerted by the high-jumper is actually down on the ground, but F is up from the ground to help him jump. Step 4. This result is reasonable, since it is quite possible for a person to exert a force of the magnitude of \(10^3\ \text{N}\). Example 3: *A shopper pushes a grocery cart 20.0 m at constant speed on level ground, against a 35.0 N frictional force. He pushes in a direction 25.0° below the horizontal. (a) What is the work done on the cart by friction? (b) What is the work done on the cart by the gravitational force? (c) What is the work done on the cart by the shopper? (d) Find the force the shopper exerts, using energy considerations. (e) What is the total work done on the cart?* Solution (a) The work done by friction is in the opposite direction of the motion, so \(\theta = 180^\circ\), and therefore \(W_f = Fd \cos\theta = 35.0\ \text{N} \times 20.0\ \text{m} \times \cos 180^\circ = \underline{-700\ \text{J}}\) (b) The work done by gravity is perpendicular to the direction of motion, so \(\theta = 90^\circ\), and \(W_g = Fd \cos\theta = 35.0\ \text{N} \times 20.0\ \text{m} \times \cos 90^\circ = \underline{0\ \text{J}}\) (c) If the cart moves at a constant speed, no energy is transferred to it, from the work-energy theorem: \(\text{net } W = W_s + W_f = 0,\) or \(W_s = \underline{700\ \text{J}}\) (d) Use the equation \(W_s = Fd \cos\theta\), where \(\theta = 25^\circ\), and solve for the force: \[ F = \frac{W_s}{d \cos\theta} = \frac{700\ \text{J}}{20.0\ \text{m} \times \cos 25^\circ} = 38.62\ \text{N} = \underline{38.6\ \text{N}} \] (e) Since there is no change in speed, the work energy theorem says that there is no net work done on the cart: \(\text{net } W = W_f + W_s = -700\ \text{J} + 700\ \text{J} = \underline{0\ \text{J}}\) | E3: TRUE | F3: -0.5 | G3: \bar{v}=\frac{x(t_2)-x(t_1)}{t_2-t_1}=\frac{(At_2+Bt_2^3)-(At_1+Bt_1^3)}{t_2-t_1} | H3: m/s | J3: x(2)=12-0.125·8=11; x(6)=36-0.125·216=36-27=9; Δx=-2; Δt=4; v=-0.5 {"final_numeric":-0.5,"final_formula":"\\bar{v}=\\frac{x(t_2)-x(t_1)}{t_2-t_1}=\\frac{(At_2+Bt_2^3)-(At_1+Bt_1^3)}{t_2-t_1}","final_units":"m/s"} | K3: {'id': 'gen-1780478232-aOq3P3i0HH77RRU1BumA', 'object': 'chat.completion', 'created': 1780478232, 'model': 'anthropic/claude-4.7-opus-20260416', 'provider': 'Anthropic', 'system_fingerprint': None, 'service_tier': 'default', 'choices': [{'index': 0, 'logprobs': None, 'finish_reason': 'stop', 'native_finish_reason': 'end_turn', 'message': {'role': 'assistant', 'content': 'x(2)=12-0.125·8=11; x(6)=36-0.125·216=36-27=9; Δx=-2; Δt=4; v=-0.5\n\n{"final_numeric":-0.5,"final_formula":"\\\\bar{v}=\\\\frac{x(t_2)-x(t_1)}{t_2-t_1}=\\\\frac{(At_2+Bt_2^3)-(At_1+Bt_1^3)}{t_2-t_1}","final_units":"m/s"}', 'refusal': None, 'reasoning': None}}], 'usage': {'prompt_tokens': 2920, 'completion_tokens': 168, 'total_tokens': 3088, 'cost': 0.0188, 'is_byok': False, 'prompt_tokens_details': {'cached_tokens': 0, 'cache_write_tokens': 0, 'audio_tokens': 0, 'video_tokens': 0}, 'cost_details': {'upstream_inference_cost': 0.0188, 'upstream_inference_prompt_cost': 0.0146, 'upstream_inference_completions_cost': 0.0042}, 'completion_tokens_details': {'reasoning_tokens': 0, 'image_tokens': 0, 'audio_tokens': 0}}} | L3: 2920 | M3: 168 | N3: 3088 | O3: 0 | P3: =VLOOKUP(C3,problems!$A$2:$B$26,2) -> mechanics | Q3: =IFERROR(__xludf.DUMMYFUNCTION("INDEX(FILTER('stats2-openrouter_activity_2026'!C:C,L3='stats2-openrouter_activity_2026'!H:H,M3='stats2-openrouter_activity_2026'!I:I, B3='stats2-openrouter_activity_2026'!M:M),1)"),0.0188) -> 0.0188 | R3: =IFS( F3=VLOOKUP($C3,problems!$A$2:$G$26,6),1, True,0 ) -> 1 | S3: =IFS( G3=VLOOKUP($C3,problems!$A$2:$G$26,4),1, G3=VLOOKUP($C3,problems!$A$2:$G$26,5),1, True,0 ) -> 0 | T3: =IFS( H3=VLOOKUP($C3,problems!$A$2:$G$26,7),1, True,0 ) -> 1
A4: 2026-06-03-13-20-51 | B4: anthropic/claude-opus-4.7 | C4: 3 | D4: A truck is traveling east at 80 km/h. At an intersection 32 km ahead, a car is traveling north at 50 km/h. How long in hours after this moment will the vehicles be closest to each other? Examples: Example 1: Calculate the height of a cliff if it takes 2.35 s for a rock to hit the ground when it is thrown straight up from the cliff with an initial velocity of 8.00 m/s. (b) How long would it take to reach the ground if it is thrown straight down with the same speed?* Solution s ↑ y₀ = ? ////| /\ | / \ | / \ | / ↓ | / | |______/________|____ y = 0 m (a) Knowns: \(t = 2.35\ \text{s}; y = 0\ \text{m}; v_0 = +8.00\ \text{m/s}; a = -9.8\ \text{m/s}^2\) Since we know \(t\), \(y\), \(v_0\), and \(a\) and want to find \(y_0\), we can use the equation \[ y = y_0 + v_0t + \frac{1}{2}at^2. \] \[ y = (0\ \text{m}) + (+8.00\ \text{m/s})(2.35\ \text{s}) + \frac{1}{2}(-9.80\ \text{m/s}^2)(2.35\ \text{s})^2 = -8.26\ \text{m}, \text{ so the cliff is} \] <u>8.26 m</u> high. (b) Knowns: \(y = 0\ \text{m}; y_0 = 8.26\ \text{m}; v_0 = -8.00\ \text{m/s}; a = -9.80\ \text{m/s}^2\) Now we know \(y\), \(y_0\), \(v_0\), and \(a\) and want to find \(t\), so we use the equation \[ y = y_0 + v_0t + \frac{1}{2}at^2 \] again. Rearranging, \[ t = \frac{-v_0 \pm \sqrt{v_0^2 - 4(0.5a)(y_0 - y)}}{2(0.5a)} \] \[ t = \frac{-(-8.00\ \text{m/s}) \pm \sqrt{(-8.00\ \text{m/s})^2 + 2(9.80\ \text{m/s}^2)(8.26\ \text{m} - 0\ \text{m})}}{(-9.80\ \text{m/s}^2)} \] \[ = \frac{8.00\ \text{m/s} \pm 15.03\ \text{m/s}}{-9.80\ \text{m/s}^2} \] \[ t = 0.717\ \text{s} \text{ or } -2.35\ \text{s} \Rightarrow t = \underline{0.717\ \text{s}} \] Example 2: *Calculate the force a 70.0-kg high jumper must exert on the ground to produce an upward acceleration 4.00 times the acceleration due to gravity. Explicitly show how you follow the steps in the Problem-Solving Strategy for Newton’s laws of motion.* Solution Step 1. Use Newton’s Laws of Motion. ↑ F | | (m) ↑ a | ↓ w Force acting on the high jumper. Step 2. Given: \(a = 4.00\ g = (4.00)(9.80\ \text{m/s}^2) = 39.2\ \text{m/s}^2;\ m = 70.0\ \text{kg}\) Find \(F\). Step 3. \(\sum F = +F - w = ma,\) so that \(F = ma + w = ma + mg = m(a + g)\) \[ F = (70.0\ \text{kg})[(39.2\ \text{m/s}^2) + (9.80\ \text{m/s}^2)] = \underline{3.43 \times 10^3\ \text{N}} \] The force exerted by the high-jumper is actually down on the ground, but F is up from the ground to help him jump. Step 4. This result is reasonable, since it is quite possible for a person to exert a force of the magnitude of \(10^3\ \text{N}\). Example 3: *A shopper pushes a grocery cart 20.0 m at constant speed on level ground, against a 35.0 N frictional force. He pushes in a direction 25.0° below the horizontal. (a) What is the work done on the cart by friction? (b) What is the work done on the cart by the gravitational force? (c) What is the work done on the cart by the shopper? (d) Find the force the shopper exerts, using energy considerations. (e) What is the total work done on the cart?* Solution (a) The work done by friction is in the opposite direction of the motion, so \(\theta = 180^\circ\), and therefore \(W_f = Fd \cos\theta = 35.0\ \text{N} \times 20.0\ \text{m} \times \cos 180^\circ = \underline{-700\ \text{J}}\) (b) The work done by gravity is perpendicular to the direction of motion, so \(\theta = 90^\circ\), and \(W_g = Fd \cos\theta = 35.0\ \text{N} \times 20.0\ \text{m} \times \cos 90^\circ = \underline{0\ \text{J}}\) (c) If the cart moves at a constant speed, no energy is transferred to it, from the work-energy theorem: \(\text{net } W = W_s + W_f = 0,\) or \(W_s = \underline{700\ \text{J}}\) (d) Use the equation \(W_s = Fd \cos\theta\), where \(\theta = 25^\circ\), and solve for the force: \[ F = \frac{W_s}{d \cos\theta} = \frac{700\ \text{J}}{20.0\ \text{m} \times \cos 25^\circ} = 38.62\ \text{N} = \underline{38.6\ \text{N}} \] (e) Since there is no change in speed, the work energy theorem says that there is no net work done on the cart: \(\text{net } W = W_f + W_s = -700\ \text{J} + 700\ \text{J} = \underline{0\ \text{J}}\) | E4: TRUE | F4: 0.2872 | G4: t=\frac{80\cdot32}{80^2+50^2} | H4: h | J4: {"final_numeric":0.2872,"final_formula":"t=\\frac{80\\cdot32}{80^2+50^2}","final_units":"h"} | K4: {'id': 'gen-1780478450-e4ln6HTIHSLBWHnapZro', 'object': 'chat.completion', 'created': 1780478450, 'model': 'anthropic/claude-4.7-opus-20260416', 'provider': 'Anthropic', 'system_fingerprint': None, 'service_tier': 'default', 'choices': [{'index': 0, 'logprobs': None, 'finish_reason': 'stop', 'native_finish_reason': 'end_turn', 'message': {'role': 'assistant', 'content': '{"final_numeric":0.2872,"final_formula":"t=\\\\frac{80\\\\cdot32}{80^2+50^2}","final_units":"h"}', 'refusal': None, 'reasoning': None}}], 'usage': {'prompt_tokens': 2897, 'completion_tokens': 57, 'total_tokens': 2954, 'cost': 0.01591, 'is_byok': False, 'prompt_tokens_details': {'cached_tokens': 0, 'cache_write_tokens': 0, 'audio_tokens': 0, 'video_tokens': 0}, 'cost_details': {'upstream_inference_cost': 0.01591, 'upstream_inference_prompt_cost': 0.014485, 'upstream_inference_completions_cost': 0.001425}, 'completion_tokens_details': {'reasoning_tokens': 0, 'image_tokens': 0, 'audio_tokens': 0}}} | L4: 2897 | M4: 57 | N4: 2954 | O4: 0 | P4: =VLOOKUP(C4,problems!$A$2:$B$26,2) -> mechanics | Q4: =IFERROR(__xludf.DUMMYFUNCTION("INDEX(FILTER('stats2-openrouter_activity_2026'!C:C,L4='stats2-openrouter_activity_2026'!H:H,M4='stats2-openrouter_activity_2026'!I:I, B4='stats2-openrouter_activity_2026'!M:M),1)"),0.01591) -> 0.01591 | R4: =IFS( F4=VLOOKUP($C4,problems!$A$2:$G$26,6),1, True,0 ) -> 0 | S4: =IFS( G4=VLOOKUP($C4,problems!$A$2:$G$26,4),1, G4=VLOOKUP($C4,problems!$A$2:$G$26,5),1, True,0 ) -> 0 | T4: =IFS( H4=VLOOKUP($C4,problems!$A$2:$G$26,7),1, True,0 ) -> 1
A5: 2026-06-03-13-26-47 | B5: anthropic/claude-opus-4.7 | C5: 4 | D5: Закон движения материальной точки имеет вид: х = а_{1} + b_{1}*t + y_{1}*t^2; y = α_{2} + b_{2}*t + y_{2}*t^2, где b_{1} = b_{2} = 1 м/с, y_{1}= -1 м/с^2, y_{2} = 2 м/с^2. Каково ее ускорение? Определить угол между скоростью и ускорением в момент времени t = 1 с. Examples: Example 1: Calculate the height of a cliff if it takes 2.35 s for a rock to hit the ground when it is thrown straight up from the cliff with an initial velocity of 8.00 m/s. (b) How long would it take to reach the ground if it is thrown straight down with the same speed?* Solution s ↑ y₀ = ? ////| /\ | / \ | / \ | / ↓ | / | |______/________|____ y = 0 m (a) Knowns: \(t = 2.35\ \text{s}; y = 0\ \text{m}; v_0 = +8.00\ \text{m/s}; a = -9.8\ \text{m/s}^2\) Since we know \(t\), \(y\), \(v_0\), and \(a\) and want to find \(y_0\), we can use the equation \[ y = y_0 + v_0t + \frac{1}{2}at^2. \] \[ y = (0\ \text{m}) + (+8.00\ \text{m/s})(2.35\ \text{s}) + \frac{1}{2}(-9.80\ \text{m/s}^2)(2.35\ \text{s})^2 = -8.26\ \text{m}, \text{ so the cliff is} \] <u>8.26 m</u> high. (b) Knowns: \(y = 0\ \text{m}; y_0 = 8.26\ \text{m}; v_0 = -8.00\ \text{m/s}; a = -9.80\ \text{m/s}^2\) Now we know \(y\), \(y_0\), \(v_0\), and \(a\) and want to find \(t\), so we use the equation \[ y = y_0 + v_0t + \frac{1}{2}at^2 \] again. Rearranging, \[ t = \frac{-v_0 \pm \sqrt{v_0^2 - 4(0.5a)(y_0 - y)}}{2(0.5a)} \] \[ t = \frac{-(-8.00\ \text{m/s}) \pm \sqrt{(-8.00\ \text{m/s})^2 + 2(9.80\ \text{m/s}^2)(8.26\ \text{m} - 0\ \text{m})}}{(-9.80\ \text{m/s}^2)} \] \[ = \frac{8.00\ \text{m/s} \pm 15.03\ \text{m/s}}{-9.80\ \text{m/s}^2} \] \[ t = 0.717\ \text{s} \text{ or } -2.35\ \text{s} \Rightarrow t = \underline{0.717\ \text{s}} \] Example 2: *Calculate the force a 70.0-kg high jumper must exert on the ground to produce an upward acceleration 4.00 times the acceleration due to gravity. Explicitly show how you follow the steps in the Problem-Solving Strategy for Newton’s laws of motion.* Solution Step 1. Use Newton’s Laws of Motion. ↑ F | | (m) ↑ a | ↓ w Force acting on the high jumper. Step 2. Given: \(a = 4.00\ g = (4.00)(9.80\ \text{m/s}^2) = 39.2\ \text{m/s}^2;\ m = 70.0\ \text{kg}\) Find \(F\). Step 3. \(\sum F = +F - w = ma,\) so that \(F = ma + w = ma + mg = m(a + g)\) \[ F = (70.0\ \text{kg})[(39.2\ \text{m/s}^2) + (9.80\ \text{m/s}^2)] = \underline{3.43 \times 10^3\ \text{N}} \] The force exerted by the high-jumper is actually down on the ground, but F is up from the ground to help him jump. Step 4. This result is reasonable, since it is quite possible for a person to exert a force of the magnitude of \(10^3\ \text{N}\). Example 3: *A shopper pushes a grocery cart 20.0 m at constant speed on level ground, against a 35.0 N frictional force. He pushes in a direction 25.0° below the horizontal. (a) What is the work done on the cart by friction? (b) What is the work done on the cart by the gravitational force? (c) What is the work done on the cart by the shopper? (d) Find the force the shopper exerts, using energy considerations. (e) What is the total work done on the cart?* Solution (a) The work done by friction is in the opposite direction of the motion, so \(\theta = 180^\circ\), and therefore \(W_f = Fd \cos\theta = 35.0\ \text{N} \times 20.0\ \text{m} \times \cos 180^\circ = \underline{-700\ \text{J}}\) (b) The work done by gravity is perpendicular to the direction of motion, so \(\theta = 90^\circ\), and \(W_g = Fd \cos\theta = 35.0\ \text{N} \times 20.0\ \text{m} \times \cos 90^\circ = \underline{0\ \text{J}}\) (c) If the cart moves at a constant speed, no energy is transferred to it, from the work-energy theorem: \(\text{net } W = W_s + W_f = 0,\) or \(W_s = \underline{700\ \text{J}}\) (d) Use the equation \(W_s = Fd \cos\theta\), where \(\theta = 25^\circ\), and solve for the force: \[ F = \frac{W_s}{d \cos\theta} = \frac{700\ \text{J}}{20.0\ \text{m} \times \cos 25^\circ} = 38.62\ \text{N} = \underline{38.6\ \text{N}} \] (e) Since there is no change in speed, the work energy theorem says that there is no net work done on the cart: \(\text{net } W = W_f + W_s = -700\ \text{J} + 700\ \text{J} = \underline{0\ \text{J}}\) | E5: TRUE | F5: 119.74 | G5: \cos\theta = \frac{\vec{v}\cdot\vec{a}}{|\vec{v}||\vec{a}|} = \frac{(b_1+2\gamma_1 t)(2\gamma_1)+(b_2+2\gamma_2 t)(2\gamma_2)}{\sqrt{(b_1+2\gamma_1 t)^2+(b_2+2\gamma_2 t)^2}\cdot\sqrt{(2\gamma_1)^2+(2\gamma_2)^2}} | H5: degree | J5: {"final_numeric":119.74,"final_formula":"\\cos\\theta = \\frac{\\vec{v}\\cdot\\vec{a}}{|\\vec{v}||\\vec{a}|} = \\frac{(b_1+2\\gamma_1 t)(2\\gamma_1)+(b_2+2\\gamma_2 t)(2\\gamma_2)}{\\sqrt{(b_1+2\\gamma_1 t)^2+(b_2+2\\gamma_2 t)^2}\\cdot\\sqrt{(2\\gamma_1)^2+(2\\gamma_2)^2}}","final_units":"degree"} | K5: {'id': 'gen-1780478803-t0dGraWf6E2LcnSrIFfy', 'object': 'chat.completion', 'created': 1780478803, 'model': 'anthropic/claude-4.7-opus-20260416', 'provider': 'Anthropic', 'system_fingerprint': None, 'service_tier': 'default', 'choices': [{'index': 0, 'logprobs': None, 'finish_reason': 'stop', 'native_finish_reason': 'end_turn', 'message': {'role': 'assistant', 'content': '{"final_numeric":119.74,"final_formula":"\\\\cos\\\\theta = \\\\frac{\\\\vec{v}\\\\cdot\\\\vec{a}}{|\\\\vec{v}||\\\\vec{a}|} = \\\\frac{(b_1+2\\\\gamma_1 t)(2\\\\gamma_1)+(b_2+2\\\\gamma_2 t)(2\\\\gamma_2)}{\\\\sqrt{(b_1+2\\\\gamma_1 t)^2+(b_2+2\\\\gamma_2 t)^2}\\\\cdot\\\\sqrt{(2\\\\gamma_1)^2+(2\\\\gamma_2)^2}}","final_units":"degree"}', 'refusal': None, 'reasoning': None}}], 'usage': {'prompt_tokens': 2986, 'completion_tokens': 231, 'total_tokens': 3217, 'cost': 0.020705, 'is_byok': False, 'prompt_tokens_details': {'cached_tokens': 0, 'cache_write_tokens': 0, 'audio_tokens': 0, 'video_tokens': 0}, 'cost_details': {'upstream_inference_cost': 0.020705, 'upstream_inference_prompt_cost': 0.01493, 'upstream_inference_completions_cost': 0.005775}, 'completion_tokens_details': {'reasoning_tokens': 0, 'image_tokens': 0, 'audio_tokens': 0}}} | L5: 2986 | M5: 231 | N5: 3217 | O5: 0 | P5: =VLOOKUP(C5,problems!$A$2:$B$26,2) -> mechanics | Q5: =IFERROR(__xludf.DUMMYFUNCTION("INDEX(FILTER('stats2-openrouter_activity_2026'!C:C,L5='stats2-openrouter_activity_2026'!H:H,M5='stats2-openrouter_activity_2026'!I:I, B5='stats2-openrouter_activity_2026'!M:M),1)"),0.020705) -> 0.020705 | R5: =IFS( F5=VLOOKUP($C5,problems!$A$2:$G$26,6),1, True,0 ) -> 0 | S5: =IFS( G5=VLOOKUP($C5,problems!$A$2:$G$26,4),1, G5=VLOOKUP($C5,problems!$A$2:$G$26,5),1, True,0 ) -> 0 | T5: =IFS( H5=VLOOKUP($C5,problems!$A$2:$G$26,7),1, True,0 ) -> 0
A6: 2026-06-03-13-30-55 | B6: anthropic/claude-opus-4.7 | C6: 5 | D6: A crate is being pushed across a rough floor surface. If no force is applied on the crate, the crate will slow down and come to a stop. If the crate of mass 50 kg moving at speed 8 m/s comes to rest in 10 seconds, what is the rate at which the frictional force on the crate takes energy away from the crate? Examples: Example 1: Calculate the height of a cliff if it takes 2.35 s for a rock to hit the ground when it is thrown straight up from the cliff with an initial velocity of 8.00 m/s. (b) How long would it take to reach the ground if it is thrown straight down with the same speed?* Solution s ↑ y₀ = ? ////| /\ | / \ | / \ | / ↓ | / | |______/________|____ y = 0 m (a) Knowns: \(t = 2.35\ \text{s}; y = 0\ \text{m}; v_0 = +8.00\ \text{m/s}; a = -9.8\ \text{m/s}^2\) Since we know \(t\), \(y\), \(v_0\), and \(a\) and want to find \(y_0\), we can use the equation \[ y = y_0 + v_0t + \frac{1}{2}at^2. \] \[ y = (0\ \text{m}) + (+8.00\ \text{m/s})(2.35\ \text{s}) + \frac{1}{2}(-9.80\ \text{m/s}^2)(2.35\ \text{s})^2 = -8.26\ \text{m}, \text{ so the cliff is} \] <u>8.26 m</u> high. (b) Knowns: \(y = 0\ \text{m}; y_0 = 8.26\ \text{m}; v_0 = -8.00\ \text{m/s}; a = -9.80\ \text{m/s}^2\) Now we know \(y\), \(y_0\), \(v_0\), and \(a\) and want to find \(t\), so we use the equation \[ y = y_0 + v_0t + \frac{1}{2}at^2 \] again. Rearranging, \[ t = \frac{-v_0 \pm \sqrt{v_0^2 - 4(0.5a)(y_0 - y)}}{2(0.5a)} \] \[ t = \frac{-(-8.00\ \text{m/s}) \pm \sqrt{(-8.00\ \text{m/s})^2 + 2(9.80\ \text{m/s}^2)(8.26\ \text{m} - 0\ \text{m})}}{(-9.80\ \text{m/s}^2)} \] \[ = \frac{8.00\ \text{m/s} \pm 15.03\ \text{m/s}}{-9.80\ \text{m/s}^2} \] \[ t = 0.717\ \text{s} \text{ or } -2.35\ \text{s} \Rightarrow t = \underline{0.717\ \text{s}} \] Example 2: *Calculate the force a 70.0-kg high jumper must exert on the ground to produce an upward acceleration 4.00 times the acceleration due to gravity. Explicitly show how you follow the steps in the Problem-Solving Strategy for Newton’s laws of motion.* Solution Step 1. Use Newton’s Laws of Motion. ↑ F | | (m) ↑ a | ↓ w Force acting on the high jumper. Step 2. Given: \(a = 4.00\ g = (4.00)(9.80\ \text{m/s}^2) = 39.2\ \text{m/s}^2;\ m = 70.0\ \text{kg}\) Find \(F\). Step 3. \(\sum F = +F - w = ma,\) so that \(F = ma + w = ma + mg = m(a + g)\) \[ F = (70.0\ \text{kg})[(39.2\ \text{m/s}^2) + (9.80\ \text{m/s}^2)] = \underline{3.43 \times 10^3\ \text{N}} \] The force exerted by the high-jumper is actually down on the ground, but F is up from the ground to help him jump. Step 4. This result is reasonable, since it is quite possible for a person to exert a force of the magnitude of \(10^3\ \text{N}\). Example 3: *A shopper pushes a grocery cart 20.0 m at constant speed on level ground, against a 35.0 N frictional force. He pushes in a direction 25.0° below the horizontal. (a) What is the work done on the cart by friction? (b) What is the work done on the cart by the gravitational force? (c) What is the work done on the cart by the shopper? (d) Find the force the shopper exerts, using energy considerations. (e) What is the total work done on the cart?* Solution (a) The work done by friction is in the opposite direction of the motion, so \(\theta = 180^\circ\), and therefore \(W_f = Fd \cos\theta = 35.0\ \text{N} \times 20.0\ \text{m} \times \cos 180^\circ = \underline{-700\ \text{J}}\) (b) The work done by gravity is perpendicular to the direction of motion, so \(\theta = 90^\circ\), and \(W_g = Fd \cos\theta = 35.0\ \text{N} \times 20.0\ \text{m} \times \cos 90^\circ = \underline{0\ \text{J}}\) (c) If the cart moves at a constant speed, no energy is transferred to it, from the work-energy theorem: \(\text{net } W = W_s + W_f = 0,\) or \(W_s = \underline{700\ \text{J}}\) (d) Use the equation \(W_s = Fd \cos\theta\), where \(\theta = 25^\circ\), and solve for the force: \[ F = \frac{W_s}{d \cos\theta} = \frac{700\ \text{J}}{20.0\ \text{m} \times \cos 25^\circ} = 38.62\ \text{N} = \underline{38.6\ \text{N}} \] (e) Since there is no change in speed, the work energy theorem says that there is no net work done on the cart: \(\text{net } W = W_f + W_s = -700\ \text{J} + 700\ \text{J} = \underline{0\ \text{J}}\) | E6: TRUE | F6: 160 | G6: P = \frac{\frac{1}{2}mv^2}{t} = \frac{0.5 \times 50 \times 8^2}{10} | H6: W | J6: {"final_numeric":160,"final_formula":"P = \\frac{\\frac{1}{2}mv^2}{t} = \\frac{0.5 \\times 50 \\times 8^2}{10}","final_units":"W"} | K6: {'id': 'gen-1780479053-J2MI2nWPFY99tzEBuKrj', 'object': 'chat.completion', 'created': 1780479053, 'model': 'anthropic/claude-4.7-opus-20260416', 'provider': 'Anthropic', 'system_fingerprint': None, 'service_tier': 'default', 'choices': [{'index': 0, 'logprobs': None, 'finish_reason': 'stop', 'native_finish_reason': 'end_turn', 'message': {'role': 'assistant', 'content': '{"final_numeric":160,"final_formula":"P = \\\\frac{\\\\frac{1}{2}mv^2}{t} = \\\\frac{0.5 \\\\times 50 \\\\times 8^2}{10}","final_units":"W"}', 'refusal': None, 'reasoning': None}}], 'usage': {'prompt_tokens': 2935, 'completion_tokens': 82, 'total_tokens': 3017, 'cost': 0.016725, 'is_byok': False, 'prompt_tokens_details': {'cached_tokens': 0, 'cache_write_tokens': 0, 'audio_tokens': 0, 'video_tokens': 0}, 'cost_details': {'upstream_inference_cost': 0.016725, 'upstream_inference_prompt_cost': 0.014675, 'upstream_inference_completions_cost': 0.00205}, 'completion_tokens_details': {'reasoning_tokens': 0, 'image_tokens': 0, 'audio_tokens': 0}}} | L6: 2935 | M6: 82 | N6: 3017 | O6: 0 | P6: =VLOOKUP(C6,problems!$A$2:$B$26,2) -> mechanics | Q6: =IFERROR(__xludf.DUMMYFUNCTION("INDEX(FILTER('stats2-openrouter_activity_2026'!C:C,L6='stats2-openrouter_activity_2026'!H:H,M6='stats2-openrouter_activity_2026'!I:I, B6='stats2-openrouter_activity_2026'!M:M),1)"),0.016725) -> 0.016725 | R6: =IFS( F6=VLOOKUP($C6,problems!$A$2:$G$26,6),1, True,0 ) -> 1 | S6: =IFS( G6=VLOOKUP($C6,problems!$A$2:$G$26,4),1, G6=VLOOKUP($C6,problems!$A$2:$G$26,5),1, True,0 ) -> 0 | T6: =IFS( H6=VLOOKUP($C6,problems!$A$2:$G$26,7),1, True,0 ) -> 0
A7: 2026-06-03-13-34-25 | B7: anthropic/claude-opus-4.7 | C7: 6 | D7: Eight bumper cars, each with a mass of 322 kg, are running in a room 21.0 m long and 13.0 m wide. They have no drivers, so they just bounce around on their own. The rms speed of the cars is 2.50 m/s. Repeating the arguments of Pressure, Temperature, and RMS Speed, find the average force per unit length (analogous to pressure) that the cars exert on the walls. Examples: Example 1: *(a) In the deep space between galaxies, the density of atoms is as low as \(10^6\ \text{atoms/m}^3\), and the temperature is a frigid 2.7 K. What is the pressure? (b) What volume (in \(m^3\)) is occupied by 1 mol of gas? (c) If this volume is a cube, what is the length of its sides in kilometers?* Solution (a) Use the ideal gas law, where \[ PV = NkT \] \[ P = \frac{N}{V} k T = \frac{10^6}{1\ \text{m}^3} (1.38 \times 10^{-23}\ \text{J/K})(2.7\ \text{K}) \] \[ = 3.73 \times 10^{-17}\ \text{N/m}^2 = 3.7 \times 10^{-17}\ \text{N/m}^2 = \underline{3.7 \times 10^{-17}\ \text{Pa}} \] (b) Now, using the pressure found in part (a), let \(n = 1.00\ \text{mol}\). Use the ideal gas law: \[ PV = nRT \] \[ V = \frac{nRT}{P} = \frac{(1.00\ \text{mol})(8.31\ \text{J/mol·K})(2.7\ \text{K})}{3.73 \times 10^{-17}\ \text{N/m}^2} = 6.02 \times 10^{17}\ \text{m}^3 = \underline{6.0 \times 10^{17}\ \text{m}^3} \] (c) Since the volume of a cube is its length cubed: \[ L = V^{1/3} = (6.02 \times 10^{17}\ \text{m}^3)^{1/3} = 8.45 \times 10^5\ \text{m} = \underline{8.4 \times 10^2\ \text{km}} \] Example 2: *Following vigorous exercise, the body temperature of an 80.0-kg person is 40.0°C. At what rate in watts must the person transfer thermal energy to reduce the body temperature to 37.0°C in 30.0 min, assuming the body continues to produce energy at the rate of 150 W? (1 watt = 1 joule/second or 1 W = 1 J/s)* Solution First, calculate how much heat must be dissipated: \[ Q = m c_\text{human body} \Delta T = (80.0\ \text{kg})(3500\ \text{J/kg·°C})(40°C - 37°C) = 8.40 \times 10^5\ \text{J} \] Then, since power is heat divided by time, we can get the power required to produce the calculated amount of heat in 30.0 minutes: \[ P_\text{cooling} = \frac{Q}{t} = \frac{8.40 \times 10^5\ \text{J}}{(30\ \text{min})(60\ \text{s/min})} = 4.67 \times 10^2\ \text{W} \] Now, since the body continues to produce heat at a rate of 150 W, we need to add that to the required cooling power: \[ P_\text{required} = P_\text{cooling} + P_\text{body} = 467\ \text{W} + 150\ \text{W} = \underline{617\ \text{W}} \] Example 3: (a) What is the average metabolic rate in watts of a man who metabolizes 10,500 kJ of food energy in one day? (b) What is the maximum amount of work in joules he can do without breaking down fat, assuming a maximum efficiency of 20.0%? (c) Compare his work output with the daily output of a 187-W (0.250-horsepower) motor.* Solution (a) The metabolic rate is the power, so that: [ P = \frac{Q}{t} = \frac{10500\text{ kJ}}{1\text{ day}} \times \frac{1000\text{ J}}{1\text{ kJ}} \times \frac{1\text{ day}}{8.64\times10^4\text{ s}} = 122\text{ W} ] (b) Efficiency is defined to be the ratio of what we get to what we spend, or [ Eff = \frac{W}{E_{\text{in}}}, ] so we can determine the work done, knowing the efficiency: [ W = Eff \cdot E_{\text{in}} = 0.200(10500\text{ kJ}) \times \frac{1000\text{ J}}{1\text{ kJ}} = \underline{2.10\times10^6\text{ J}} ] (c) To compare with a 0.250 hp motor, we need to know how much work the motor does in one day: [ W = Pt = (0.250\text{ hp})(1\text{day}) \times \frac{746\text{ W}}{1\text{ hp}} \times \frac{8.64\times10^4\text{ s}}{1\text{day}} = 1.61\times10^7\text{ J}. ] So, the man’s work output is: [ \frac{W_{\text{motor}}}{W_{\text{man}}} ======================================= \frac{1.61\times10^7\text{ J}}{2.10\times10^6\text{ J}} = 7.67 \Rightarrow \underline{7.67\text{ times less than}} ] [ \underline{\text{the motor}}. ] Thus the motor produces 7.67 times the work done by the man. | E7: TRUE | F7: 29.5 | G7: F/L = \frac{N m v_{rms}^2}{2(L+W)} = \frac{8 \cdot 322 \cdot 2.5^2}{2(21+13)} | H7: N/m | J7: {"final_numeric":29.5,"final_formula":"F/L = \\frac{N m v_{rms}^2}{2(L+W)} = \\frac{8 \\cdot 322 \\cdot 2.5^2}{2(21+13)}","final_units":"N/m"} | K7: {'id': 'gen-1780479262-LMxe4IeVWAgNXjvvEYTS', 'object': 'chat.completion', 'created': 1780479262, 'model': 'anthropic/claude-4.7-opus-20260416', 'provider': 'Anthropic', 'system_fingerprint': None, 'service_tier': 'default', 'choices': [{'index': 0, 'logprobs': None, 'finish_reason': 'stop', 'native_finish_reason': 'end_turn', 'message': {'role': 'assistant', 'content': '{"final_numeric":29.5,"final_formula":"F/L = \\\\frac{N m v_{rms}^2}{2(L+W)} = \\\\frac{8 \\\\cdot 322 \\\\cdot 2.5^2}{2(21+13)}","final_units":"N/m"}', 'refusal': None, 'reasoning': None}}], 'usage': {'prompt_tokens': 2711, 'completion_tokens': 98, 'total_tokens': 2809, 'cost': 0.016005, 'is_byok': False, 'prompt_tokens_details': {'cached_tokens': 0, 'cache_write_tokens': 0, 'audio_tokens': 0, 'video_tokens': 0}, 'cost_details': {'upstream_inference_cost': 0.016005, 'upstream_inference_prompt_cost': 0.013555, 'upstream_inference_completions_cost': 0.00245}, 'completion_tokens_details': {'reasoning_tokens': 0, 'image_tokens': 0, 'audio_tokens': 0}}} | L7: 2711 | M7: 98 | N7: 2809 | O7: 0 | P7: =VLOOKUP(C7,problems!$A$2:$B$26,2) -> thermodynamics | Q7: =IFERROR(__xludf.DUMMYFUNCTION("INDEX(FILTER('stats2-openrouter_activity_2026'!C:C,L7='stats2-openrouter_activity_2026'!H:H,M7='stats2-openrouter_activity_2026'!I:I, B7='stats2-openrouter_activity_2026'!M:M),1)"),0.016005) -> 0.016005 | R7: =IFS( F7=VLOOKUP($C7,problems!$A$2:$G$26,6),1, True,0 ) -> 1 | S7: =IFS( G7=VLOOKUP($C7,problems!$A$2:$G$26,4),1, G7=VLOOKUP($C7,problems!$A$2:$G$26,5),1, True,0 ) -> 0 | T7: =IFS( H7=VLOOKUP($C7,problems!$A$2:$G$26,7),1, True,0 ) -> 1
A8: 2026-06-03-13-38-20 | B8: anthropic/claude-opus-4.7 | C8: 7 | D8: Какую работу в кДж совершает при изотермическом расширении водород, взятый при температуре t = 11 °С, если его объем увеличивается в 3 раза? Масса водорода m = 5 г. Examples: Example 1: *(a) In the deep space between galaxies, the density of atoms is as low as \(10^6\ \text{atoms/m}^3\), and the temperature is a frigid 2.7 K. What is the pressure? (b) What volume (in \(m^3\)) is occupied by 1 mol of gas? (c) If this volume is a cube, what is the length of its sides in kilometers?* Solution (a) Use the ideal gas law, where \[ PV = NkT \] \[ P = \frac{N}{V} k T = \frac{10^6}{1\ \text{m}^3} (1.38 \times 10^{-23}\ \text{J/K})(2.7\ \text{K}) \] \[ = 3.73 \times 10^{-17}\ \text{N/m}^2 = 3.7 \times 10^{-17}\ \text{N/m}^2 = \underline{3.7 \times 10^{-17}\ \text{Pa}} \] (b) Now, using the pressure found in part (a), let \(n = 1.00\ \text{mol}\). Use the ideal gas law: \[ PV = nRT \] \[ V = \frac{nRT}{P} = \frac{(1.00\ \text{mol})(8.31\ \text{J/mol·K})(2.7\ \text{K})}{3.73 \times 10^{-17}\ \text{N/m}^2} = 6.02 \times 10^{17}\ \text{m}^3 = \underline{6.0 \times 10^{17}\ \text{m}^3} \] (c) Since the volume of a cube is its length cubed: \[ L = V^{1/3} = (6.02 \times 10^{17}\ \text{m}^3)^{1/3} = 8.45 \times 10^5\ \text{m} = \underline{8.4 \times 10^2\ \text{km}} \] Example 2: *Following vigorous exercise, the body temperature of an 80.0-kg person is 40.0°C. At what rate in watts must the person transfer thermal energy to reduce the body temperature to 37.0°C in 30.0 min, assuming the body continues to produce energy at the rate of 150 W? (1 watt = 1 joule/second or 1 W = 1 J/s)* Solution First, calculate how much heat must be dissipated: \[ Q = m c_\text{human body} \Delta T = (80.0\ \text{kg})(3500\ \text{J/kg·°C})(40°C - 37°C) = 8.40 \times 10^5\ \text{J} \] Then, since power is heat divided by time, we can get the power required to produce the calculated amount of heat in 30.0 minutes: \[ P_\text{cooling} = \frac{Q}{t} = \frac{8.40 \times 10^5\ \text{J}}{(30\ \text{min})(60\ \text{s/min})} = 4.67 \times 10^2\ \text{W} \] Now, since the body continues to produce heat at a rate of 150 W, we need to add that to the required cooling power: \[ P_\text{required} = P_\text{cooling} + P_\text{body} = 467\ \text{W} + 150\ \text{W} = \underline{617\ \text{W}} \] Example 3: (a) What is the average metabolic rate in watts of a man who metabolizes 10,500 kJ of food energy in one day? (b) What is the maximum amount of work in joules he can do without breaking down fat, assuming a maximum efficiency of 20.0%? (c) Compare his work output with the daily output of a 187-W (0.250-horsepower) motor.* Solution (a) The metabolic rate is the power, so that: [ P = \frac{Q}{t} = \frac{10500\text{ kJ}}{1\text{ day}} \times \frac{1000\text{ J}}{1\text{ kJ}} \times \frac{1\text{ day}}{8.64\times10^4\text{ s}} = 122\text{ W} ] (b) Efficiency is defined to be the ratio of what we get to what we spend, or [ Eff = \frac{W}{E_{\text{in}}}, ] so we can determine the work done, knowing the efficiency: [ W = Eff \cdot E_{\text{in}} = 0.200(10500\text{ kJ}) \times \frac{1000\text{ J}}{1\text{ kJ}} = \underline{2.10\times10^6\text{ J}} ] (c) To compare with a 0.250 hp motor, we need to know how much work the motor does in one day: [ W = Pt = (0.250\text{ hp})(1\text{day}) \times \frac{746\text{ W}}{1\text{ hp}} \times \frac{8.64\times10^4\text{ s}}{1\text{day}} = 1.61\times10^7\text{ J}. ] So, the man’s work output is: [ \frac{W_{\text{motor}}}{W_{\text{man}}} ======================================= \frac{1.61\times10^7\text{ J}}{2.10\times10^6\text{ J}} = 7.67 \Rightarrow \underline{7.67\text{ times less than}} ] [ \underline{\text{the motor}}. ] Thus the motor produces 7.67 times the work done by the man. | E8: TRUE | F8: 16.2 | G8: A = \frac{m}{M}RT\ln\frac{V_2}{V_1} | H8: kJ | J8: {"final_numeric":16.2,"final_formula":"A = \\frac{m}{M}RT\\ln\\frac{V_2}{V_1}","final_units":"kJ"} | K8: {'id': 'gen-1780479498-djsXCCEClRIvfmTJZhZ2', 'object': 'chat.completion', 'created': 1780479498, 'model': 'anthropic/claude-4.7-opus-20260416', 'provider': 'Anthropic', 'system_fingerprint': None, 'service_tier': 'default', 'choices': [{'index': 0, 'logprobs': None, 'finish_reason': 'stop', 'native_finish_reason': 'end_turn', 'message': {'role': 'assistant', 'content': '{"final_numeric":16.2,"final_formula":"A = \\\\frac{m}{M}RT\\\\ln\\\\frac{V_2}{V_1}","final_units":"kJ"}', 'refusal': None, 'reasoning': None}}], 'usage': {'prompt_tokens': 2645, 'completion_tokens': 66, 'total_tokens': 2711, 'cost': 0.014875, 'is_byok': False, 'prompt_tokens_details': {'cached_tokens': 0, 'cache_write_tokens': 0, 'audio_tokens': 0, 'video_tokens': 0}, 'cost_details': {'upstream_inference_cost': 0.014875, 'upstream_inference_prompt_cost': 0.013225, 'upstream_inference_completions_cost': 0.00165}, 'completion_tokens_details': {'reasoning_tokens': 0, 'image_tokens': 0, 'audio_tokens': 0}}} | L8: 2645 | M8: 66 | N8: 2711 | O8: 0 | P8: =VLOOKUP(C8,problems!$A$2:$B$26,2) -> thermodynamics | Q8: =IFERROR(__xludf.DUMMYFUNCTION("INDEX(FILTER('stats2-openrouter_activity_2026'!C:C,L8='stats2-openrouter_activity_2026'!H:H,M8='stats2-openrouter_activity_2026'!I:I, B8='stats2-openrouter_activity_2026'!M:M),1)"),0.014875) -> 0.014875 | R8: =IFS( F8=VLOOKUP($C8,problems!$A$2:$G$26,6),1, True,0 ) -> 0 | S8: =IFS( G8=VLOOKUP($C8,problems!$A$2:$G$26,4),1, G8=VLOOKUP($C8,problems!$A$2:$G$26,5),1, True,0 ) -> 0 | T8: =IFS( H8=VLOOKUP($C8,problems!$A$2:$G$26,7),1, True,0 ) -> 1
A9: 2026-06-03-15-16-59 | B9: anthropic/claude-opus-4.7 | C9: 8 | D9: When an air bubble rises from the bottom to the top of a freshwater lake, its volume increases by 80%. If the temperatures at the bottom and the top of the lake are 4.0 and 10 °C, respectively, how deep is the lake? Examples: Example 1: *(a) In the deep space between galaxies, the density of atoms is as low as \(10^6\ \text{atoms/m}^3\), and the temperature is a frigid 2.7 K. What is the pressure? (b) What volume (in \(m^3\)) is occupied by 1 mol of gas? (c) If this volume is a cube, what is the length of its sides in kilometers?* Solution (a) Use the ideal gas law, where \[ PV = NkT \] \[ P = \frac{N}{V} k T = \frac{10^6}{1\ \text{m}^3} (1.38 \times 10^{-23}\ \text{J/K})(2.7\ \text{K}) \] \[ = 3.73 \times 10^{-17}\ \text{N/m}^2 = 3.7 \times 10^{-17}\ \text{N/m}^2 = \underline{3.7 \times 10^{-17}\ \text{Pa}} \] (b) Now, using the pressure found in part (a), let \(n = 1.00\ \text{mol}\). Use the ideal gas law: \[ PV = nRT \] \[ V = \frac{nRT}{P} = \frac{(1.00\ \text{mol})(8.31\ \text{J/mol·K})(2.7\ \text{K})}{3.73 \times 10^{-17}\ \text{N/m}^2} = 6.02 \times 10^{17}\ \text{m}^3 = \underline{6.0 \times 10^{17}\ \text{m}^3} \] (c) Since the volume of a cube is its length cubed: \[ L = V^{1/3} = (6.02 \times 10^{17}\ \text{m}^3)^{1/3} = 8.45 \times 10^5\ \text{m} = \underline{8.4 \times 10^2\ \text{km}} \] Example 2: *Following vigorous exercise, the body temperature of an 80.0-kg person is 40.0°C. At what rate in watts must the person transfer thermal energy to reduce the body temperature to 37.0°C in 30.0 min, assuming the body continues to produce energy at the rate of 150 W? (1 watt = 1 joule/second or 1 W = 1 J/s)* Solution First, calculate how much heat must be dissipated: \[ Q = m c_\text{human body} \Delta T = (80.0\ \text{kg})(3500\ \text{J/kg·°C})(40°C - 37°C) = 8.40 \times 10^5\ \text{J} \] Then, since power is heat divided by time, we can get the power required to produce the calculated amount of heat in 30.0 minutes: \[ P_\text{cooling} = \frac{Q}{t} = \frac{8.40 \times 10^5\ \text{J}}{(30\ \text{min})(60\ \text{s/min})} = 4.67 \times 10^2\ \text{W} \] Now, since the body continues to produce heat at a rate of 150 W, we need to add that to the required cooling power: \[ P_\text{required} = P_\text{cooling} + P_\text{body} = 467\ \text{W} + 150\ \text{W} = \underline{617\ \text{W}} \] Example 3: (a) What is the average metabolic rate in watts of a man who metabolizes 10,500 kJ of food energy in one day? (b) What is the maximum amount of work in joules he can do without breaking down fat, assuming a maximum efficiency of 20.0%? (c) Compare his work output with the daily output of a 187-W (0.250-horsepower) motor.* Solution (a) The metabolic rate is the power, so that: [ P = \frac{Q}{t} = \frac{10500\text{ kJ}}{1\text{ day}} \times \frac{1000\text{ J}}{1\text{ kJ}} \times \frac{1\text{ day}}{8.64\times10^4\text{ s}} = 122\text{ W} ] (b) Efficiency is defined to be the ratio of what we get to what we spend, or [ Eff = \frac{W}{E_{\text{in}}}, ] so we can determine the work done, knowing the efficiency: [ W = Eff \cdot E_{\text{in}} = 0.200(10500\text{ kJ}) \times \frac{1000\text{ J}}{1\text{ kJ}} = \underline{2.10\times10^6\text{ J}} ] (c) To compare with a 0.250 hp motor, we need to know how much work the motor does in one day: [ W = Pt = (0.250\text{ hp})(1\text{day}) \times \frac{746\text{ W}}{1\text{ hp}} \times \frac{8.64\times10^4\text{ s}}{1\text{day}} = 1.61\times10^7\text{ J}. ] So, the man’s work output is: [ \frac{W_{\text{motor}}}{W_{\text{man}}} ======================================= \frac{1.61\times10^7\text{ J}}{2.10\times10^6\text{ J}} = 7.67 \Rightarrow \underline{7.67\text{ times less than}} ] [ \underline{\text{the motor}}. ] Thus the motor produces 7.67 times the work done by the man. | E9: TRUE | F9: 7.69 | G9: h = \frac{P_{atm}}{\rho g}\left(\frac{V_2 T_1}{V_1 T_2} - 1\right) | H9: m | J9: {"final_numeric":7.69,"final_formula":"h = \\frac{P_{atm}}{\\rho g}\\left(\\frac{V_2 T_1}{V_1 T_2} - 1\\right)","final_units":"m"} | K9: {'id': 'gen-1780485416-H32uHHK6PCcWZjT2QpXq', 'object': 'chat.completion', 'created': 1780485416, 'model': 'anthropic/claude-4.7-opus-20260416', 'provider': 'Anthropic', 'system_fingerprint': None, 'service_tier': 'default', 'choices': [{'index': 0, 'logprobs': None, 'finish_reason': 'stop', 'native_finish_reason': 'end_turn', 'message': {'role': 'assistant', 'content': '{"final_numeric":7.69,"final_formula":"h = \\\\frac{P_{atm}}{\\\\rho g}\\\\left(\\\\frac{V_2 T_1}{V_1 T_2} - 1\\\\right)","final_units":"m"}', 'refusal': None, 'reasoning': None}}], 'usage': {'prompt_tokens': 2625, 'completion_tokens': 86, 'total_tokens': 2711, 'cost': 0.015275, 'is_byok': False, 'prompt_tokens_details': {'cached_tokens': 0, 'cache_write_tokens': 0, 'audio_tokens': 0, 'video_tokens': 0}, 'cost_details': {'upstream_inference_cost': 0.015275, 'upstream_inference_prompt_cost': 0.013125, 'upstream_inference_completions_cost': 0.00215}, 'completion_tokens_details': {'reasoning_tokens': 0, 'image_tokens': 0, 'audio_tokens': 0}}} | L9: 2625 | M9: 86 | N9: 2711 | O9: 0 | P9: =VLOOKUP(C9,problems!$A$2:$B$26,2) -> thermodynamics | Q9: =IFERROR(__xludf.DUMMYFUNCTION("INDEX(FILTER('stats2-openrouter_activity_2026'!C:C,L9='stats2-openrouter_activity_2026'!H:H,M9='stats2-openrouter_activity_2026'!I:I, B9='stats2-openrouter_activity_2026'!M:M),1)"),0.015275) -> 0.015275 | R9: =IFS( F9=VLOOKUP($C9,problems!$A$2:$G$26,6),1, True,0 ) -> 0 | S9: =IFS( G9=VLOOKUP($C9,problems!$A$2:$G$26,4),1, G9=VLOOKUP($C9,problems!$A$2:$G$26,5),1, True,0 ) -> 0 | T9: =IFS( H9=VLOOKUP($C9,problems!$A$2:$G$26,7),1, True,0 ) -> 1
A10: 2026-06-03-15-38-08 | B10: anthropic/claude-opus-4.7 | C10: 9 | D10: On a warm day when the air temperature is 30°C, a metal can is slowly cooled by adding bits of ice to liquid water in it. Condensation first appears when the can reaches 15°C. What is the relative humidity of the air? Examples: Example 1: *(a) In the deep space between galaxies, the density of atoms is as low as \(10^6\ \text{atoms/m}^3\), and the temperature is a frigid 2.7 K. What is the pressure? (b) What volume (in \(m^3\)) is occupied by 1 mol of gas? (c) If this volume is a cube, what is the length of its sides in kilometers?* Solution (a) Use the ideal gas law, where \[ PV = NkT \] \[ P = \frac{N}{V} k T = \frac{10^6}{1\ \text{m}^3} (1.38 \times 10^{-23}\ \text{J/K})(2.7\ \text{K}) \] \[ = 3.73 \times 10^{-17}\ \text{N/m}^2 = 3.7 \times 10^{-17}\ \text{N/m}^2 = \underline{3.7 \times 10^{-17}\ \text{Pa}} \] (b) Now, using the pressure found in part (a), let \(n = 1.00\ \text{mol}\). Use the ideal gas law: \[ PV = nRT \] \[ V = \frac{nRT}{P} = \frac{(1.00\ \text{mol})(8.31\ \text{J/mol·K})(2.7\ \text{K})}{3.73 \times 10^{-17}\ \text{N/m}^2} = 6.02 \times 10^{17}\ \text{m}^3 = \underline{6.0 \times 10^{17}\ \text{m}^3} \] (c) Since the volume of a cube is its length cubed: \[ L = V^{1/3} = (6.02 \times 10^{17}\ \text{m}^3)^{1/3} = 8.45 \times 10^5\ \text{m} = \underline{8.4 \times 10^2\ \text{km}} \] Example 2: *Following vigorous exercise, the body temperature of an 80.0-kg person is 40.0°C. At what rate in watts must the person transfer thermal energy to reduce the body temperature to 37.0°C in 30.0 min, assuming the body continues to produce energy at the rate of 150 W? (1 watt = 1 joule/second or 1 W = 1 J/s)* Solution First, calculate how much heat must be dissipated: \[ Q = m c_\text{human body} \Delta T = (80.0\ \text{kg})(3500\ \text{J/kg·°C})(40°C - 37°C) = 8.40 \times 10^5\ \text{J} \] Then, since power is heat divided by time, we can get the power required to produce the calculated amount of heat in 30.0 minutes: \[ P_\text{cooling} = \frac{Q}{t} = \frac{8.40 \times 10^5\ \text{J}}{(30\ \text{min})(60\ \text{s/min})} = 4.67 \times 10^2\ \text{W} \] Now, since the body continues to produce heat at a rate of 150 W, we need to add that to the required cooling power: \[ P_\text{required} = P_\text{cooling} + P_\text{body} = 467\ \text{W} + 150\ \text{W} = \underline{617\ \text{W}} \] Example 3: (a) What is the average metabolic rate in watts of a man who metabolizes 10,500 kJ of food energy in one day? (b) What is the maximum amount of work in joules he can do without breaking down fat, assuming a maximum efficiency of 20.0%? (c) Compare his work output with the daily output of a 187-W (0.250-horsepower) motor.* Solution (a) The metabolic rate is the power, so that: [ P = \frac{Q}{t} = \frac{10500\text{ kJ}}{1\text{ day}} \times \frac{1000\text{ J}}{1\text{ kJ}} \times \frac{1\text{ day}}{8.64\times10^4\text{ s}} = 122\text{ W} ] (b) Efficiency is defined to be the ratio of what we get to what we spend, or [ Eff = \frac{W}{E_{\text{in}}}, ] so we can determine the work done, knowing the efficiency: [ W = Eff \cdot E_{\text{in}} = 0.200(10500\text{ kJ}) \times \frac{1000\text{ J}}{1\text{ kJ}} = \underline{2.10\times10^6\text{ J}} ] (c) To compare with a 0.250 hp motor, we need to know how much work the motor does in one day: [ W = Pt = (0.250\text{ hp})(1\text{day}) \times \frac{746\text{ W}}{1\text{ hp}} \times \frac{8.64\times10^4\text{ s}}{1\text{day}} = 1.61\times10^7\text{ J}. ] So, the man’s work output is: [ \frac{W_{\text{motor}}}{W_{\text{man}}} ======================================= \frac{1.61\times10^7\text{ J}}{2.10\times10^6\text{ J}} = 7.67 \Rightarrow \underline{7.67\text{ times less than}} ] [ \underline{\text{the motor}}. ] Thus the motor produces 7.67 times the work done by the man. | E10: TRUE | F10: 40.2 | G10: RH = \frac{P_{sat}(15°C)}{P_{sat}(30°C)} \times 100\% = \frac{12.8}{31.8} \times 100\% | H10: % | J10: {"final_numeric":40.2,"final_formula":"RH = \\frac{P_{sat}(15°C)}{P_{sat}(30°C)} \\times 100\\% = \\frac{12.8}{31.8} \\times 100\\%","final_units":"%"} | K10: {'id': 'gen-1780486685-6W2j8gcqvdeqzo72Yl8R', 'object': 'chat.completion', 'created': 1780486685, 'model': 'anthropic/claude-4.7-opus-20260416', 'provider': 'Anthropic', 'system_fingerprint': None, 'service_tier': 'default', 'choices': [{'index': 0, 'logprobs': None, 'finish_reason': 'stop', 'native_finish_reason': 'end_turn', 'message': {'role': 'assistant', 'content': '{"final_numeric":40.2,"final_formula":"RH = \\\\frac{P_{sat}(15°C)}{P_{sat}(30°C)} \\\\times 100\\\\% = \\\\frac{12.8}{31.8} \\\\times 100\\\\%","final_units":"%"}', 'refusal': None, 'reasoning': None}}], 'usage': {'prompt_tokens': 2621, 'completion_tokens': 96, 'total_tokens': 2717, 'cost': 0.015505, 'is_byok': False, 'prompt_tokens_details': {'cached_tokens': 0, 'cache_write_tokens': 0, 'audio_tokens': 0, 'video_tokens': 0}, 'cost_details': {'upstream_inference_cost': 0.015505, 'upstream_inference_prompt_cost': 0.013105, 'upstream_inference_completions_cost': 0.0024}, 'completion_tokens_details': {'reasoning_tokens': 0, 'image_tokens': 0, 'audio_tokens': 0}}} | L10: 2621 | M10: 96 | N10: 2717 | O10: 0 | P10: =VLOOKUP(C10,problems!$A$2:$B$26,2) -> thermodynamics | Q10: =IFERROR(__xludf.DUMMYFUNCTION("INDEX(FILTER('stats2-openrouter_activity_2026'!C:C,L10='stats2-openrouter_activity_2026'!H:H,M10='stats2-openrouter_activity_2026'!I:I, B10='stats2-openrouter_activity_2026'!M:M),1)"),0.015505) -> 0.015505 | R10: =IFS( F10=VLOOKUP($C10,problems!$A$2:$G$26,6),1, True,0 ) -> 0 | S10: =IFS( G10=VLOOKUP($C10,problems!$A$2:$G$26,4),1, G10=VLOOKUP($C10,problems!$A$2:$G$26,5),1, True,0 ) -> 0 | T10: =IFS( H10=VLOOKUP($C10,problems!$A$2:$G$26,7),1, True,0 ) -> 1
A11: 2026-06-03-15-41-37 | B11: anthropic/claude-opus-4.7 | C11: 10 | D11: Газ, занимающий объем V_{1} = 10 л при давлении р_{1} = 2*10^5 Па, расширяется изотермически до объема V_{2} = 28 л. Какую работу в кДж он при этом совершает? Examples: Example 1: *(a) In the deep space between galaxies, the density of atoms is as low as \(10^6\ \text{atoms/m}^3\), and the temperature is a frigid 2.7 K. What is the pressure? (b) What volume (in \(m^3\)) is occupied by 1 mol of gas? (c) If this volume is a cube, what is the length of its sides in kilometers?* Solution (a) Use the ideal gas law, where \[ PV = NkT \] \[ P = \frac{N}{V} k T = \frac{10^6}{1\ \text{m}^3} (1.38 \times 10^{-23}\ \text{J/K})(2.7\ \text{K}) \] \[ = 3.73 \times 10^{-17}\ \text{N/m}^2 = 3.7 \times 10^{-17}\ \text{N/m}^2 = \underline{3.7 \times 10^{-17}\ \text{Pa}} \] (b) Now, using the pressure found in part (a), let \(n = 1.00\ \text{mol}\). Use the ideal gas law: \[ PV = nRT \] \[ V = \frac{nRT}{P} = \frac{(1.00\ \text{mol})(8.31\ \text{J/mol·K})(2.7\ \text{K})}{3.73 \times 10^{-17}\ \text{N/m}^2} = 6.02 \times 10^{17}\ \text{m}^3 = \underline{6.0 \times 10^{17}\ \text{m}^3} \] (c) Since the volume of a cube is its length cubed: \[ L = V^{1/3} = (6.02 \times 10^{17}\ \text{m}^3)^{1/3} = 8.45 \times 10^5\ \text{m} = \underline{8.4 \times 10^2\ \text{km}} \] Example 2: *Following vigorous exercise, the body temperature of an 80.0-kg person is 40.0°C. At what rate in watts must the person transfer thermal energy to reduce the body temperature to 37.0°C in 30.0 min, assuming the body continues to produce energy at the rate of 150 W? (1 watt = 1 joule/second or 1 W = 1 J/s)* Solution First, calculate how much heat must be dissipated: \[ Q = m c_\text{human body} \Delta T = (80.0\ \text{kg})(3500\ \text{J/kg·°C})(40°C - 37°C) = 8.40 \times 10^5\ \text{J} \] Then, since power is heat divided by time, we can get the power required to produce the calculated amount of heat in 30.0 minutes: \[ P_\text{cooling} = \frac{Q}{t} = \frac{8.40 \times 10^5\ \text{J}}{(30\ \text{min})(60\ \text{s/min})} = 4.67 \times 10^2\ \text{W} \] Now, since the body continues to produce heat at a rate of 150 W, we need to add that to the required cooling power: \[ P_\text{required} = P_\text{cooling} + P_\text{body} = 467\ \text{W} + 150\ \text{W} = \underline{617\ \text{W}} \] Example 3: (a) What is the average metabolic rate in watts of a man who metabolizes 10,500 kJ of food energy in one day? (b) What is the maximum amount of work in joules he can do without breaking down fat, assuming a maximum efficiency of 20.0%? (c) Compare his work output with the daily output of a 187-W (0.250-horsepower) motor.* Solution (a) The metabolic rate is the power, so that: [ P = \frac{Q}{t} = \frac{10500\text{ kJ}}{1\text{ day}} \times \frac{1000\text{ J}}{1\text{ kJ}} \times \frac{1\text{ day}}{8.64\times10^4\text{ s}} = 122\text{ W} ] (b) Efficiency is defined to be the ratio of what we get to what we spend, or [ Eff = \frac{W}{E_{\text{in}}}, ] so we can determine the work done, knowing the efficiency: [ W = Eff \cdot E_{\text{in}} = 0.200(10500\text{ kJ}) \times \frac{1000\text{ J}}{1\text{ kJ}} = \underline{2.10\times10^6\text{ J}} ] (c) To compare with a 0.250 hp motor, we need to know how much work the motor does in one day: [ W = Pt = (0.250\text{ hp})(1\text{day}) \times \frac{746\text{ W}}{1\text{ hp}} \times \frac{8.64\times10^4\text{ s}}{1\text{day}} = 1.61\times10^7\text{ J}. ] So, the man’s work output is: [ \frac{W_{\text{motor}}}{W_{\text{man}}} ======================================= \frac{1.61\times10^7\text{ J}}{2.10\times10^6\text{ J}} = 7.67 \Rightarrow \underline{7.67\text{ times less than}} ] [ \underline{\text{the motor}}. ] Thus the motor produces 7.67 times the work done by the man. | E11: TRUE | F11: 2.06 | G11: A = p_1 V_1 \ln\frac{V_2}{V_1} | H11: kJ | J11: {"final_numeric":2.06,"final_formula":"A = p_1 V_1 \\ln\\frac{V_2}{V_1}","final_units":"kJ"} | K11: {'id': 'gen-1780486895-VI2O8x2deEmhB6f1wB8I', 'object': 'chat.completion', 'created': 1780486895, 'model': 'anthropic/claude-4.7-opus-20260416', 'provider': 'Anthropic', 'system_fingerprint': None, 'service_tier': 'default', 'choices': [{'index': 0, 'logprobs': None, 'finish_reason': 'stop', 'native_finish_reason': 'end_turn', 'message': {'role': 'assistant', 'content': '{"final_numeric":2.06,"final_formula":"A = p_1 V_1 \\\\ln\\\\frac{V_2}{V_1}","final_units":"kJ"}', 'refusal': None, 'reasoning': None}}], 'usage': {'prompt_tokens': 2626, 'completion_tokens': 62, 'total_tokens': 2688, 'cost': 0.01468, 'is_byok': False, 'prompt_tokens_details': {'cached_tokens': 0, 'cache_write_tokens': 0, 'audio_tokens': 0, 'video_tokens': 0}, 'cost_details': {'upstream_inference_cost': 0.01468, 'upstream_inference_prompt_cost': 0.01313, 'upstream_inference_completions_cost': 0.00155}, 'completion_tokens_details': {'reasoning_tokens': 0, 'image_tokens': 0, 'audio_tokens': 0}}} | L11: 2626 | M11: 62 | N11: 2688 | O11: 0 | P11: =VLOOKUP(C11,problems!$A$2:$B$26,2) -> thermodynamics | Q11: =IFERROR(__xludf.DUMMYFUNCTION("INDEX(FILTER('stats2-openrouter_activity_2026'!C:C,L11='stats2-openrouter_activity_2026'!H:H,M11='stats2-openrouter_activity_2026'!I:I, B11='stats2-openrouter_activity_2026'!M:M),1)"),0.01468) -> 0.01468 | R11: =IFS( F11=VLOOKUP($C11,problems!$A$2:$G$26,6),1, True,0 ) -> 1 | S11: =IFS( G11=VLOOKUP($C11,problems!$A$2:$G$26,4),1, G11=VLOOKUP($C11,problems!$A$2:$G$26,5),1, True,0 ) -> 0 | T11: =IFS( H11=VLOOKUP($C11,problems!$A$2:$G$26,7),1, True,0 ) -> 1
A12: 2026-06-03-15-43-02 | B12: anthropic/claude-opus-4.7 | C12: 11 | D12: The print in many books averages 3.50 mm in height. How high in mm is the image of the print on the retina when the book is held 30.0 cm from the eye? Examples: Example 1: *Calculate the power of the eye when viewing an object 3.00 m away.* Solution Using the lens-to-retina distance of 2.00 cm and the equation (P = \frac{1}{d_o} + \frac{1}{d_i}) we can determine the power at an object distance of 3.00 m: [ P = \frac{1}{d_o} + \frac{1}{d_i} = \frac{1}{3.00\text{ m}} + \frac{1}{0.0200\text{ m}} = \underline{+50.3\text{ D}} ] Example 2: *What was the previous far point of a patient who had laser vision correction that reduced the power of her eye by 7.00 D, producing normal distant vision for her?* Solution Since normal distant vision has a power of 50.0 D (Example 26.2) and the laser vision correction reduced the power of her eye by 7.00 D, she originally had a power of 57.0 D. We can determine her original far point using [ P = \frac{1}{d_o} + \frac{1}{d_i} \Rightarrow d_o = \left(P - \frac{1}{d_i}\right)^{-1} =================================== \left(57.0\text{ D} - \frac{1}{0.0200\text{ m}}\right)^{-1} = \underline{0.143\text{ m}} ] Originally, without corrective lenses, she could only see images 14.3 cm (or closer) to her eye. Example 3: *Calculate the angle for the third-order maximum of 580-nm wavelength yellow light falling on double slits separated by 0.100 mm.* Solution Using the equation (d \sin \theta = m \lambda) for (m = 0,1,2,3,\dots), we can calculate the angle for (m = 3), given the wavelength and the slit separation: [ \theta = \sin^{-1} \left( \frac{m \lambda}{d} \right) = \sin^{-1} \left[ \frac{(3)(5.80 \times 10^{-7}\text{ m})}{1.00 \times 10^{-4}\text{ m}} \right] = \underline{0.997^\circ} ] | E12: TRUE | F12: 0.000233 | G12: h_i = h_o \cdot \frac{d_i}{d_o} = 3.50\text{ mm} \cdot \frac{2.00\text{ cm}}{30.0\text{ cm}} | H12: m | J12: {"final_numeric":0.000233,"final_formula":"h_i = h_o \\cdot \\frac{d_i}{d_o} = 3.50\\text{ mm} \\cdot \\frac{2.00\\text{ cm}}{30.0\\text{ cm}}","final_units":"m"} | K12: {'id': 'gen-1780486980-BICzq0WfdKWXphUTZF5O', 'object': 'chat.completion', 'created': 1780486980, 'model': 'anthropic/claude-4.7-opus-20260416', 'provider': 'Anthropic', 'system_fingerprint': None, 'service_tier': 'default', 'choices': [{'index': 0, 'logprobs': None, 'finish_reason': 'stop', 'native_finish_reason': 'end_turn', 'message': {'role': 'assistant', 'content': '{"final_numeric":0.000233,"final_formula":"h_i = h_o \\\\cdot \\\\frac{d_i}{d_o} = 3.50\\\\text{ mm} \\\\cdot \\\\frac{2.00\\\\text{ cm}}{30.0\\\\text{ cm}}","final_units":"m"}', 'refusal': None, 'reasoning': None}}], 'usage': {'prompt_tokens': 1506, 'completion_tokens': 107, 'total_tokens': 1613, 'cost': 0.010205, 'is_byok': False, 'prompt_tokens_details': {'cached_tokens': 0, 'cache_write_tokens': 0, 'audio_tokens': 0, 'video_tokens': 0}, 'cost_details': {'upstream_inference_cost': 0.010205, 'upstream_inference_prompt_cost': 0.00753, 'upstream_inference_completions_cost': 0.002675}, 'completion_tokens_details': {'reasoning_tokens': 0, 'image_tokens': 0, 'audio_tokens': 0}}} | L12: 1506 | M12: 107 | N12: 1613 | O12: 0 | P12: =VLOOKUP(C12,problems!$A$2:$B$26,2) -> optics | Q12: =IFERROR(__xludf.DUMMYFUNCTION("INDEX(FILTER('stats2-openrouter_activity_2026'!C:C,L12='stats2-openrouter_activity_2026'!H:H,M12='stats2-openrouter_activity_2026'!I:I, B12='stats2-openrouter_activity_2026'!M:M),1)"),0.010205) -> 0.010205 | R12: =IFS( F12=VLOOKUP($C12,problems!$A$2:$G$26,6),1, True,0 ) -> 0 | S12: =IFS( G12=VLOOKUP($C12,problems!$A$2:$G$26,4),1, G12=VLOOKUP($C12,problems!$A$2:$G$26,5),1, True,0 ) -> 0 | T12: =IFS( H12=VLOOKUP($C12,problems!$A$2:$G$26,7),1, True,0 ) -> 0
A13: 2026-06-03-15-45-12 | B13: anthropic/claude-opus-4.7 | C13: 12 | D13: What is the angular magnification of a telescope that has a 100 cm-focal length objective and a 2.50 cm-focal length eyepiece? Examples: Example 1: *Calculate the power of the eye when viewing an object 3.00 m away.* Solution Using the lens-to-retina distance of 2.00 cm and the equation (P = \frac{1}{d_o} + \frac{1}{d_i}) we can determine the power at an object distance of 3.00 m: [ P = \frac{1}{d_o} + \frac{1}{d_i} = \frac{1}{3.00\text{ m}} + \frac{1}{0.0200\text{ m}} = \underline{+50.3\text{ D}} ] Example 2: *What was the previous far point of a patient who had laser vision correction that reduced the power of her eye by 7.00 D, producing normal distant vision for her?* Solution Since normal distant vision has a power of 50.0 D (Example 26.2) and the laser vision correction reduced the power of her eye by 7.00 D, she originally had a power of 57.0 D. We can determine her original far point using [ P = \frac{1}{d_o} + \frac{1}{d_i} \Rightarrow d_o = \left(P - \frac{1}{d_i}\right)^{-1} =================================== \left(57.0\text{ D} - \frac{1}{0.0200\text{ m}}\right)^{-1} = \underline{0.143\text{ m}} ] Originally, without corrective lenses, she could only see images 14.3 cm (or closer) to her eye. Example 3: *Calculate the angle for the third-order maximum of 580-nm wavelength yellow light falling on double slits separated by 0.100 mm.* Solution Using the equation (d \sin \theta = m \lambda) for (m = 0,1,2,3,\dots), we can calculate the angle for (m = 3), given the wavelength and the slit separation: [ \theta = \sin^{-1} \left( \frac{m \lambda}{d} \right) = \sin^{-1} \left[ \frac{(3)(5.80 \times 10^{-7}\text{ m})}{1.00 \times 10^{-4}\text{ m}} \right] = \underline{0.997^\circ} ] | E13: TRUE | F13: -40 | G13: M=-\frac{f_o}{f_e}=-\frac{100\text{ cm}}{2.50\text{ cm}}=-40 | H13: 1 | J13: {"final_numeric":-40,"final_formula":"M=-\\frac{f_o}{f_e}=-\\frac{100\\text{ cm}}{2.50\\text{ cm}}=-40","final_units":"1"} | K13: {'id': 'gen-1780487110-9KTjKKazmmMSIHtAIcv5', 'object': 'chat.completion', 'created': 1780487110, 'model': 'anthropic/claude-4.7-opus-20260416', 'provider': 'Anthropic', 'system_fingerprint': None, 'service_tier': 'default', 'choices': [{'index': 0, 'logprobs': None, 'finish_reason': 'stop', 'native_finish_reason': 'end_turn', 'message': {'role': 'assistant', 'content': '{"final_numeric":-40,"final_formula":"M=-\\\\frac{f_o}{f_e}=-\\\\frac{100\\\\text{ cm}}{2.50\\\\text{ cm}}=-40","final_units":"1"}', 'refusal': None, 'reasoning': None}}], 'usage': {'prompt_tokens': 1503, 'completion_tokens': 81, 'total_tokens': 1584, 'cost': 0.00954, 'is_byok': False, 'prompt_tokens_details': {'cached_tokens': 0, 'cache_write_tokens': 0, 'audio_tokens': 0, 'video_tokens': 0}, 'cost_details': {'upstream_inference_cost': 0.00954, 'upstream_inference_prompt_cost': 0.007515, 'upstream_inference_completions_cost': 0.002025}, 'completion_tokens_details': {'reasoning_tokens': 0, 'image_tokens': 0, 'audio_tokens': 0}}} | L13: 1503 | M13: 81 | N13: 1584 | O13: 0 | P13: =VLOOKUP(C13,problems!$A$2:$B$26,2) -> optics | Q13: =IFERROR(__xludf.DUMMYFUNCTION("INDEX(FILTER('stats2-openrouter_activity_2026'!C:C,L13='stats2-openrouter_activity_2026'!H:H,M13='stats2-openrouter_activity_2026'!I:I, B13='stats2-openrouter_activity_2026'!M:M),1)"),0.00954) -> 0.00954 | R13: =IFS( F13=VLOOKUP($C13,problems!$A$2:$G$26,6),1, True,0 ) -> 1 | S13: =IFS( G13=VLOOKUP($C13,problems!$A$2:$G$26,4),1, G13=VLOOKUP($C13,problems!$A$2:$G$26,5),1, True,0 ) -> 0 | T13: =IFS( H13=VLOOKUP($C13,problems!$A$2:$G$26,7),1, True,0 ) -> 1
A14: 2026-06-03-15-47-05 | B14: anthropic/claude-opus-4.7 | C14: 13 | D14: Луч последовательно отражается от двух плоских зеркал, причем луч, падающий на первое зеркало, параллелен плоскости второго зеркала, а дважды отраженный луч параллелен плоскости первого зеркала. Чему равен угол phi между зеркалами? Examples: Example 1: *Calculate the power of the eye when viewing an object 3.00 m away.* Solution Using the lens-to-retina distance of 2.00 cm and the equation (P = \frac{1}{d_o} + \frac{1}{d_i}) we can determine the power at an object distance of 3.00 m: [ P = \frac{1}{d_o} + \frac{1}{d_i} = \frac{1}{3.00\text{ m}} + \frac{1}{0.0200\text{ m}} = \underline{+50.3\text{ D}} ] Example 2: *What was the previous far point of a patient who had laser vision correction that reduced the power of her eye by 7.00 D, producing normal distant vision for her?* Solution Since normal distant vision has a power of 50.0 D (Example 26.2) and the laser vision correction reduced the power of her eye by 7.00 D, she originally had a power of 57.0 D. We can determine her original far point using [ P = \frac{1}{d_o} + \frac{1}{d_i} \Rightarrow d_o = \left(P - \frac{1}{d_i}\right)^{-1} =================================== \left(57.0\text{ D} - \frac{1}{0.0200\text{ m}}\right)^{-1} = \underline{0.143\text{ m}} ] Originally, without corrective lenses, she could only see images 14.3 cm (or closer) to her eye. Example 3: *Calculate the angle for the third-order maximum of 580-nm wavelength yellow light falling on double slits separated by 0.100 mm.* Solution Using the equation (d \sin \theta = m \lambda) for (m = 0,1,2,3,\dots), we can calculate the angle for (m = 3), given the wavelength and the slit separation: [ \theta = \sin^{-1} \left( \frac{m \lambda}{d} \right) = \sin^{-1} \left[ \frac{(3)(5.80 \times 10^{-7}\text{ m})}{1.00 \times 10^{-4}\text{ m}} \right] = \underline{0.997^\circ} ] | E14: TRUE | F14: 60 | G14: \varphi=60^\circ | H14: degree | J14: {"final_numeric":60,"final_formula":"\\varphi=60^\\circ","final_units":"degree"} | K14: {'id': 'gen-1780487224-JlMsrcLPqWIelqYXstj5', 'object': 'chat.completion', 'created': 1780487224, 'model': 'anthropic/claude-4.7-opus-20260416', 'provider': 'Anthropic', 'system_fingerprint': None, 'service_tier': 'default', 'choices': [{'index': 0, 'logprobs': None, 'finish_reason': 'stop', 'native_finish_reason': 'end_turn', 'message': {'role': 'assistant', 'content': '{"final_numeric":60,"final_formula":"\\\\varphi=60^\\\\circ","final_units":"degree"}', 'refusal': None, 'reasoning': None}}], 'usage': {'prompt_tokens': 1550, 'completion_tokens': 43, 'total_tokens': 1593, 'cost': 0.008825, 'is_byok': False, 'prompt_tokens_details': {'cached_tokens': 0, 'cache_write_tokens': 0, 'audio_tokens': 0, 'video_tokens': 0}, 'cost_details': {'upstream_inference_cost': 0.008825, 'upstream_inference_prompt_cost': 0.00775, 'upstream_inference_completions_cost': 0.001075}, 'completion_tokens_details': {'reasoning_tokens': 0, 'image_tokens': 0, 'audio_tokens': 0}}} | L14: 1550 | M14: 43 | N14: 1593 | O14: 0 | P14: =VLOOKUP(C14,problems!$A$2:$B$26,2) -> optics | Q14: =IFERROR(__xludf.DUMMYFUNCTION("INDEX(FILTER('stats2-openrouter_activity_2026'!C:C,L14='stats2-openrouter_activity_2026'!H:H,M14='stats2-openrouter_activity_2026'!I:I, B14='stats2-openrouter_activity_2026'!M:M),1)"),0.008825) -> 0.008825 | R14: =IFS( F14=VLOOKUP($C14,problems!$A$2:$G$26,6),1, True,0 ) -> 1 | S14: =IFS( G14=VLOOKUP($C14,problems!$A$2:$G$26,4),1, G14=VLOOKUP($C14,problems!$A$2:$G$26,5),1, True,0 ) -> 0 | T14: =IFS( H14=VLOOKUP($C14,problems!$A$2:$G$26,7),1, True,0 ) -> 0
A15: 2026-06-03-15-48-58 | B15: anthropic/claude-opus-4.7 | C15: 14 | D15: На дне сосуда, заполненного водой, лежит плоское зеркало. Человек, наклонившийся над сосудом, видит изображение своего лица в зеркале на расстоянии d = 25 см, если расстояние от лица до поверхности воды һ = 5 см. Определить глубину сосуда l в см. Examples: Example 1: *Calculate the power of the eye when viewing an object 3.00 m away.* Solution Using the lens-to-retina distance of 2.00 cm and the equation (P = \frac{1}{d_o} + \frac{1}{d_i}) we can determine the power at an object distance of 3.00 m: [ P = \frac{1}{d_o} + \frac{1}{d_i} = \frac{1}{3.00\text{ m}} + \frac{1}{0.0200\text{ m}} = \underline{+50.3\text{ D}} ] Example 2: *What was the previous far point of a patient who had laser vision correction that reduced the power of her eye by 7.00 D, producing normal distant vision for her?* Solution Since normal distant vision has a power of 50.0 D (Example 26.2) and the laser vision correction reduced the power of her eye by 7.00 D, she originally had a power of 57.0 D. We can determine her original far point using [ P = \frac{1}{d_o} + \frac{1}{d_i} \Rightarrow d_o = \left(P - \frac{1}{d_i}\right)^{-1} =================================== \left(57.0\text{ D} - \frac{1}{0.0200\text{ m}}\right)^{-1} = \underline{0.143\text{ m}} ] Originally, without corrective lenses, she could only see images 14.3 cm (or closer) to her eye. Example 3: *Calculate the angle for the third-order maximum of 580-nm wavelength yellow light falling on double slits separated by 0.100 mm.* Solution Using the equation (d \sin \theta = m \lambda) for (m = 0,1,2,3,\dots), we can calculate the angle for (m = 3), given the wavelength and the slit separation: [ \theta = \sin^{-1} \left( \frac{m \lambda}{d} \right) = \sin^{-1} \left[ \frac{(3)(5.80 \times 10^{-7}\text{ m})}{1.00 \times 10^{-4}\text{ m}} \right] = \underline{0.997^\circ} ] | E15: TRUE | F15: 13.3 | G15: l = \frac{n(d-h)}{2} | H15: cm | J15: Image distance from face = d = 25 cm. Face is h = 5 cm above water. The image appears at distance d below face, so apparent depth of mirror image below water surface = d - h = 20 cm. The mirror image is at depth 2l below surface (real), apparent depth = 2l/n. So 2l/n = 20, l = 20·n/2 = 10·1.33 ≈ 13.3 cm. {"final_numeric": 13.3, "final_formula": "l = \\frac{n(d-h)}{2}", "final_units": "cm"} | K15: {'id': 'gen-1780487335-sOGfu9oQ6VAO6UmrizqR', 'object': 'chat.completion', 'created': 1780487335, 'model': 'anthropic/claude-4.7-opus-20260416', 'provider': 'Anthropic', 'system_fingerprint': None, 'service_tier': 'default', 'choices': [{'index': 0, 'logprobs': None, 'finish_reason': 'stop', 'native_finish_reason': 'end_turn', 'message': {'role': 'assistant', 'content': 'Image distance from face = d = 25 cm. Face is h = 5 cm above water. The image appears at distance d below face, so apparent depth of mirror image below water surface = d - h = 20 cm. The mirror image is at depth 2l below surface (real), apparent depth = 2l/n. So 2l/n = 20, l = 20·n/2 = 10·1.33 ≈ 13.3 cm.\n\n{"final_numeric": 13.3, "final_formula": "l = \\\\frac{n(d-h)}{2}", "final_units": "cm"}', 'refusal': None, 'reasoning': None}}], 'usage': {'prompt_tokens': 1563, 'completion_tokens': 187, 'total_tokens': 1750, 'cost': 0.01249, 'is_byok': False, 'prompt_tokens_details': {'cached_tokens': 0, 'cache_write_tokens': 0, 'audio_tokens': 0, 'video_tokens': 0}, 'cost_details': {'upstream_inference_cost': 0.01249, 'upstream_inference_prompt_cost': 0.007815, 'upstream_inference_completions_cost': 0.004675}, 'completion_tokens_details': {'reasoning_tokens': 0, 'image_tokens': 0, 'audio_tokens': 0}}} | L15: 1563 | M15: 187 | N15: 1750 | O15: 0 | P15: =VLOOKUP(C15,problems!$A$2:$B$26,2) -> optics | Q15: =IFERROR(__xludf.DUMMYFUNCTION("INDEX(FILTER('stats2-openrouter_activity_2026'!C:C,L15='stats2-openrouter_activity_2026'!H:H,M15='stats2-openrouter_activity_2026'!I:I, B15='stats2-openrouter_activity_2026'!M:M),1)"),0.01249) -> 0.01249 | R15: =IFS( F15=VLOOKUP($C15,problems!$A$2:$G$26,6),1, True,0 ) -> 0 | S15: =IFS( G15=VLOOKUP($C15,problems!$A$2:$G$26,4),1, G15=VLOOKUP($C15,problems!$A$2:$G$26,5),1, True,0 ) -> 0 | T15: =IFS( H15=VLOOKUP($C15,problems!$A$2:$G$26,7),1, True,0 ) -> 1
A16: 2026-06-03-15-52-28 | B16: anthropic/claude-opus-4.7 | C16: 15 | D16: Calculate the wavelength of light in nm that produces its first minimum at an angle of 36.9° when falling on a single slit of width 1.00𝜇m. Examples: Example 1: *Calculate the power of the eye when viewing an object 3.00 m away.* Solution Using the lens-to-retina distance of 2.00 cm and the equation (P = \frac{1}{d_o} + \frac{1}{d_i}) we can determine the power at an object distance of 3.00 m: [ P = \frac{1}{d_o} + \frac{1}{d_i} = \frac{1}{3.00\text{ m}} + \frac{1}{0.0200\text{ m}} = \underline{+50.3\text{ D}} ] Example 2: *What was the previous far point of a patient who had laser vision correction that reduced the power of her eye by 7.00 D, producing normal distant vision for her?* Solution Since normal distant vision has a power of 50.0 D (Example 26.2) and the laser vision correction reduced the power of her eye by 7.00 D, she originally had a power of 57.0 D. We can determine her original far point using [ P = \frac{1}{d_o} + \frac{1}{d_i} \Rightarrow d_o = \left(P - \frac{1}{d_i}\right)^{-1} =================================== \left(57.0\text{ D} - \frac{1}{0.0200\text{ m}}\right)^{-1} = \underline{0.143\text{ m}} ] Originally, without corrective lenses, she could only see images 14.3 cm (or closer) to her eye. Example 3: *Calculate the angle for the third-order maximum of 580-nm wavelength yellow light falling on double slits separated by 0.100 mm.* Solution Using the equation (d \sin \theta = m \lambda) for (m = 0,1,2,3,\dots), we can calculate the angle for (m = 3), given the wavelength and the slit separation: [ \theta = \sin^{-1} \left( \frac{m \lambda}{d} \right) = \sin^{-1} \left[ \frac{(3)(5.80 \times 10^{-7}\text{ m})}{1.00 \times 10^{-4}\text{ m}} \right] = \underline{0.997^\circ} ] | E16: TRUE | F16: 600 | G16: \lambda = D\sin\theta = (1.00\times10^{-6})\sin(36.9°) | H16: nm | J16: {"final_numeric":600,"final_formula":"\\lambda = D\\sin\\theta = (1.00\\times10^{-6})\\sin(36.9°)","final_units":"nm"} | K16: {'id': 'gen-1780487546-b3aHfNVkIORQdYsX0mfe', 'object': 'chat.completion', 'created': 1780487546, 'model': 'anthropic/claude-4.7-opus-20260416', 'provider': 'Anthropic', 'system_fingerprint': None, 'service_tier': 'default', 'choices': [{'index': 0, 'logprobs': None, 'finish_reason': 'stop', 'native_finish_reason': 'end_turn', 'message': {'role': 'assistant', 'content': '{"final_numeric":600,"final_formula":"\\\\lambda = D\\\\sin\\\\theta = (1.00\\\\times10^{-6})\\\\sin(36.9°)","final_units":"nm"}', 'refusal': None, 'reasoning': None}}], 'usage': {'prompt_tokens': 1509, 'completion_tokens': 70, 'total_tokens': 1579, 'cost': 0.009295, 'is_byok': False, 'prompt_tokens_details': {'cached_tokens': 0, 'cache_write_tokens': 0, 'audio_tokens': 0, 'video_tokens': 0}, 'cost_details': {'upstream_inference_cost': 0.009295, 'upstream_inference_prompt_cost': 0.007545, 'upstream_inference_completions_cost': 0.00175}, 'completion_tokens_details': {'reasoning_tokens': 0, 'image_tokens': 0, 'audio_tokens': 0}}} | L16: 1509 | M16: 70 | N16: 1579 | O16: 0 | P16: =VLOOKUP(C16,problems!$A$2:$B$26,2) -> optics | Q16: =IFERROR(__xludf.DUMMYFUNCTION("INDEX(FILTER('stats2-openrouter_activity_2026'!C:C,L16='stats2-openrouter_activity_2026'!H:H,M16='stats2-openrouter_activity_2026'!I:I, B16='stats2-openrouter_activity_2026'!M:M),1)"),0.009295) -> 0.009295 | R16: =IFS( F16=VLOOKUP($C16,problems!$A$2:$G$26,6),1, True,0 ) -> 1 | S16: =IFS( G16=VLOOKUP($C16,problems!$A$2:$G$26,4),1, G16=VLOOKUP($C16,problems!$A$2:$G$26,5),1, True,0 ) -> 0 | T16: =IFS( H16=VLOOKUP($C16,problems!$A$2:$G$26,7),1, True,0 ) -> 1
A17: 2026-06-03-15-54-03 | B17: anthropic/claude-opus-4.7 | C17: 16 | D17: На концах тонкого непроводящего горизонтального стержня длиной l = 1 м закреплены две маленькие бусинки, а третья надета на стержень, по которому она может перемещаться без трения. Всем бусинкам сообщают одинаковые заряды q = 10^-6 Кл. Найти период малых колебаний подвижной бусинки. Масса бусинки m = 5 г. Examples: Example 1: *Common static electricity involves charges ranging from nanocoulombs to microcoulombs. (a) How many electrons are needed to form a charge of −2.00 nC? (b) How many electrons must be removed from a neutral object to leave a net charge of 0.500 μC?* Solution (a) Since one electron has a charge of (q_e = -1.6 \times 10^{-19}~\text{C}), we can determine the number of electrons necessary to generate a total charge of −2.00 nC by using the equation (N q_e = Q), so that [ N = \frac{Q}{q_e} = \frac{-2.00 \times 10^{-9}~\text{C}}{-1.60 \times 10^{-19}~\text{C}} = \underline{1.25 \times 10^{10}~\text{electrons}}. ] (b) Similarly, we can determine the number of electrons removed from a neutral object to leave a charge of 0.500 μC: [ N = \frac{Q}{q_e} = \frac{0.500 \times 10^{-6}~\text{C}}{1.60 \times 10^{-19}~\text{C}} = \underline{3.13 \times 10^{12}~\text{electrons}}. ] Example 2: *(a) Will the electric field strength between two parallel conducting plates exceed the breakdown strength for air ((3.0\times10^6\text{ V/m})) if the plates are separated by 2.00 mm and a potential difference of (5.0\times10^3\text{ V}) is applied? (b) How close together can the plates be with this applied voltage?* Solution (a) Using the equation [ E = \frac{V_{AB}}{d}, ] we can determine the electric field strength produced between two parallel plates since we know their separation distance and the potential difference across the plates: [ E = \frac{V_{AB}}{d} = \frac{5.0\times10^3\text{ V}}{2.00\times10^{-3}\text{ m}} = 2.5\times10^6\text{ V/m} < 3\times10^6\text{ V/m}. ] No, the field strength is smaller than the breakdown strength for air. (b) Using the equation (E = V_{AB}/d), we can now solve for the separation distance, given the potential difference and the maximum electric field strength: [ d = \frac{V_{AB}}{E} = \frac{5.0\times10^3\text{ V}}{3.0\times10^6\text{ V/m}} = 1.67\times10^{-3}\text{ m} = \underline{1.7\text{ mm}}. ] So, the plates must not be closer than 1.7 mm to avoid exceeding the breakdown strength of air. Example 3: *(a) Common transparent tape becomes charged when pulled from a dispenser. If one piece is placed above another, the repulsive force can be great enough to support the top piece’s weight. Assuming equal point charges (only an approximation), calculate the magnitude of the charge if electrostatic force is great enough to support the weight of a 10.0 mg piece of tape held 1.00 cm above another. (b) Discuss whether the magnitude of this charge is consistent with what is typical of static electricity.* **Solution** (a) If the electrostatic force is to support the weight of 10.0 mg piece of tape, it must be a force equal to the gravitational force on the tape, so using the equation [ F_1 = k \frac{q_1 q_2}{r_1^2} ] and the assumption that the point charges are equal, we can set electrostatic force equal to gravitational force. [ F = k \frac{q_1 q_2}{r^2} = \frac{k q^2}{r^2} = mg \implies q = \left(\frac{r^2 mg}{k}\right)^{1/2} ] [ q = \left[\frac{(0.0100\ \text{m})^2 (10.0\times10^{-6}\ \text{kg}) (9.80\ \text{m/s}^2)}{8.99\times10^9\ \text{N·m}^2/\text{C}^2}\right]^{1/2} = 1.04\times 10^{-9}\ \text{C}. ] (b) This charge is approximately 1 nC, which is consistent with the magnitude of the charge of typical static electricity. | E17: TRUE | F17: 0.828 | G17: T = 2\pi\sqrt{\dfrac{ml^3}{32kq^2}} | H17: s | J17: Bead at position x from center, fixed beads at ±l/2. Force on middle bead: F = kq²[1/(l/2+x)² - 1/(l/2-x)²] For small x: F ≈ kq² · [-4x · 2/(l/2)³·... ] let me compute. 1/(a+x)² - 1/(a-x)² ≈ -4x/a³ for small x, where a=l/2. So F ≈ kq²(-4x)/(l/2)³ = -32kq²x/l³ This is restoring force: mẍ = -32kq²x/l³ ω² = 32kq²/(ml³) T = 2π√(ml³/(32kq²)) Numerically: k=9×10⁹, q²=10⁻¹², m=5×10⁻³, l³=1 32·9×10⁹·10⁻¹² = 32·9×10⁻³ = 0.288 ml³/(32kq²) = 5×10⁻³/0.288 = 0.01736 √ = 0.1318 T = 2π·0.1318 = 0.828 s {"final_numeric": 0.828, "final_formula": "T = 2\\pi\\sqrt{\\dfrac{ml^3}{32kq^2}}", "final_units": "s"} | K17: {'id': 'gen-1780487635-biWuEzFo8NfQOyCAddu7', 'object': 'chat.completion', 'created': 1780487635, 'model': 'anthropic/claude-4.7-opus-20260416', 'provider': 'Anthropic', 'system_fingerprint': None, 'service_tier': 'default', 'choices': [{'index': 0, 'logprobs': None, 'finish_reason': 'stop', 'native_finish_reason': 'end_turn', 'message': {'role': 'assistant', 'content': 'Bead at position x from center, fixed beads at ±l/2.\n\nForce on middle bead: F = kq²[1/(l/2+x)² - 1/(l/2-x)²]\n\nFor small x: F ≈ kq² · [-4x · 2/(l/2)³·... ] let me compute.\n\n1/(a+x)² - 1/(a-x)² ≈ -4x/a³ for small x, where a=l/2.\n\nSo F ≈ kq²(-4x)/(l/2)³ = -32kq²x/l³\n\nThis is restoring force: mẍ = -32kq²x/l³\n\nω² = 32kq²/(ml³)\n\nT = 2π√(ml³/(32kq²))\n\nNumerically: k=9×10⁹, q²=10⁻¹², m=5×10⁻³, l³=1\n32·9×10⁹·10⁻¹² = 32·9×10⁻³ = 0.288\nml³/(32kq²) = 5×10⁻³/0.288 = 0.01736\n√ = 0.1318\nT = 2π·0.1318 = 0.828 s\n\n{"final_numeric": 0.828, "final_formula": "T = 2\\\\pi\\\\sqrt{\\\\dfrac{ml^3}{32kq^2}}", "final_units": "s"}', 'refusal': None, 'reasoning': None}}], 'usage': {'prompt_tokens': 2300, 'completion_tokens': 428, 'total_tokens': 2728, 'cost': 0.0222, 'is_byok': False, 'prompt_tokens_details': {'cached_tokens': 0, 'cache_write_tokens': 0, 'audio_tokens': 0, 'video_tokens': 0}, 'cost_details': {'upstream_inference_cost': 0.0222, 'upstream_inference_prompt_cost': 0.0115, 'upstream_inference_completions_cost': 0.0107}, 'completion_tokens_details': {'reasoning_tokens': 0, 'image_tokens': 0, 'audio_tokens': 0}}} | L17: 2300 | M17: 428 | N17: 2728 | O17: 0 | P17: =VLOOKUP(C17,problems!$A$2:$B$26,2) -> electrostatics | Q17: =IFERROR(__xludf.DUMMYFUNCTION("INDEX(FILTER('stats2-openrouter_activity_2026'!C:C,L17='stats2-openrouter_activity_2026'!H:H,M17='stats2-openrouter_activity_2026'!I:I, B17='stats2-openrouter_activity_2026'!M:M),1)"),0.0222) -> 0.0222 | R17: =IFS( F17=VLOOKUP($C17,problems!$A$2:$G$26,6),1, True,0 ) -> 0 | S17: =IFS( G17=VLOOKUP($C17,problems!$A$2:$G$26,4),1, G17=VLOOKUP($C17,problems!$A$2:$G$26,5),1, True,0 ) -> 0 | T17: =IFS( H17=VLOOKUP($C17,problems!$A$2:$G$26,7),1, True,0 ) -> 1
A18: 2026-06-03-15-56-02 | B18: anthropic/claude-opus-4.7 | C18: 17 | D18: При напряженности электрического поля Е = 10^6 В/м воздух перестает быть надежным изолятором и в нем происходит искровой разряд. Каким должен быть радиус металлического шара, чтобы на нем мог удержаться заряд q = 1 Кл? Examples: Example 1: *Common static electricity involves charges ranging from nanocoulombs to microcoulombs. (a) How many electrons are needed to form a charge of −2.00 nC? (b) How many electrons must be removed from a neutral object to leave a net charge of 0.500 μC?* Solution (a) Since one electron has a charge of (q_e = -1.6 \times 10^{-19}~\text{C}), we can determine the number of electrons necessary to generate a total charge of −2.00 nC by using the equation (N q_e = Q), so that [ N = \frac{Q}{q_e} = \frac{-2.00 \times 10^{-9}~\text{C}}{-1.60 \times 10^{-19}~\text{C}} = \underline{1.25 \times 10^{10}~\text{electrons}}. ] (b) Similarly, we can determine the number of electrons removed from a neutral object to leave a charge of 0.500 μC: [ N = \frac{Q}{q_e} = \frac{0.500 \times 10^{-6}~\text{C}}{1.60 \times 10^{-19}~\text{C}} = \underline{3.13 \times 10^{12}~\text{electrons}}. ] Example 2: *(a) Will the electric field strength between two parallel conducting plates exceed the breakdown strength for air ((3.0\times10^6\text{ V/m})) if the plates are separated by 2.00 mm and a potential difference of (5.0\times10^3\text{ V}) is applied? (b) How close together can the plates be with this applied voltage?* Solution (a) Using the equation [ E = \frac{V_{AB}}{d}, ] we can determine the electric field strength produced between two parallel plates since we know their separation distance and the potential difference across the plates: [ E = \frac{V_{AB}}{d} = \frac{5.0\times10^3\text{ V}}{2.00\times10^{-3}\text{ m}} = 2.5\times10^6\text{ V/m} < 3\times10^6\text{ V/m}. ] No, the field strength is smaller than the breakdown strength for air. (b) Using the equation (E = V_{AB}/d), we can now solve for the separation distance, given the potential difference and the maximum electric field strength: [ d = \frac{V_{AB}}{E} = \frac{5.0\times10^3\text{ V}}{3.0\times10^6\text{ V/m}} = 1.67\times10^{-3}\text{ m} = \underline{1.7\text{ mm}}. ] So, the plates must not be closer than 1.7 mm to avoid exceeding the breakdown strength of air. Example 3: *(a) Common transparent tape becomes charged when pulled from a dispenser. If one piece is placed above another, the repulsive force can be great enough to support the top piece’s weight. Assuming equal point charges (only an approximation), calculate the magnitude of the charge if electrostatic force is great enough to support the weight of a 10.0 mg piece of tape held 1.00 cm above another. (b) Discuss whether the magnitude of this charge is consistent with what is typical of static electricity.* **Solution** (a) If the electrostatic force is to support the weight of 10.0 mg piece of tape, it must be a force equal to the gravitational force on the tape, so using the equation [ F_1 = k \frac{q_1 q_2}{r_1^2} ] and the assumption that the point charges are equal, we can set electrostatic force equal to gravitational force. [ F = k \frac{q_1 q_2}{r^2} = \frac{k q^2}{r^2} = mg \implies q = \left(\frac{r^2 mg}{k}\right)^{1/2} ] [ q = \left[\frac{(0.0100\ \text{m})^2 (10.0\times10^{-6}\ \text{kg}) (9.80\ \text{m/s}^2)}{8.99\times10^9\ \text{N·m}^2/\text{C}^2}\right]^{1/2} = 1.04\times 10^{-9}\ \text{C}. ] (b) This charge is approximately 1 nC, which is consistent with the magnitude of the charge of typical static electricity. | E18: TRUE | F18: 94.87 | G18: R=\sqrt{\frac{kq}{E}}=\sqrt{\frac{9\times10^9\cdot 1}{10^6}} | H18: m | J18: {"final_numeric":94.87,"final_formula":"R=\\sqrt{\\frac{kq}{E}}=\\sqrt{\\frac{9\\times10^9\\cdot 1}{10^6}}","final_units":"m"} | K18: {'id': 'gen-1780487760-dyiFGvHHwJ07cVHCkTcN', 'object': 'chat.completion', 'created': 1780487760, 'model': 'anthropic/claude-4.7-opus-20260416', 'provider': 'Anthropic', 'system_fingerprint': None, 'service_tier': 'default', 'choices': [{'index': 0, 'logprobs': None, 'finish_reason': 'stop', 'native_finish_reason': 'end_turn', 'message': {'role': 'assistant', 'content': '{"final_numeric":94.87,"final_formula":"R=\\\\sqrt{\\\\frac{kq}{E}}=\\\\sqrt{\\\\frac{9\\\\times10^9\\\\cdot 1}{10^6}}","final_units":"m"}', 'refusal': None, 'reasoning': None}}], 'usage': {'prompt_tokens': 2259, 'completion_tokens': 87, 'total_tokens': 2346, 'cost': 0.01347, 'is_byok': False, 'prompt_tokens_details': {'cached_tokens': 0, 'cache_write_tokens': 0, 'audio_tokens': 0, 'video_tokens': 0}, 'cost_details': {'upstream_inference_cost': 0.01347, 'upstream_inference_prompt_cost': 0.011295, 'upstream_inference_completions_cost': 0.002175}, 'completion_tokens_details': {'reasoning_tokens': 0, 'image_tokens': 0, 'audio_tokens': 0}}} | L18: 2259 | M18: 87 | N18: 2346 | O18: 0 | P18: =VLOOKUP(C18,problems!$A$2:$B$26,2) -> electrostatics | Q18: =IFERROR(__xludf.DUMMYFUNCTION("INDEX(FILTER('stats2-openrouter_activity_2026'!C:C,L18='stats2-openrouter_activity_2026'!H:H,M18='stats2-openrouter_activity_2026'!I:I, B18='stats2-openrouter_activity_2026'!M:M),1)"),0.01347) -> 0.01347 | R18: =IFS( F18=VLOOKUP($C18,problems!$A$2:$G$26,6),1, True,0 ) -> 0 | S18: =IFS( G18=VLOOKUP($C18,problems!$A$2:$G$26,4),1, G18=VLOOKUP($C18,problems!$A$2:$G$26,5),1, True,0 ) -> 0 | T18: =IFS( H18=VLOOKUP($C18,problems!$A$2:$G$26,7),1, True,0 ) -> 1
A19: 2026-06-03-15-57-39 | B19: anthropic/claude-opus-4.7 | C19: 18 | D19: Электрон движется в направлении силовой линии однородного электрического поля, напряженность которого Е = 100 В/м. Какое расстояние пролетит он до полной остановки в см, если начальная скорость электрона v = 10^6 м/с? Examples: Example 1: *Common static electricity involves charges ranging from nanocoulombs to microcoulombs. (a) How many electrons are needed to form a charge of −2.00 nC? (b) How many electrons must be removed from a neutral object to leave a net charge of 0.500 μC?* Solution (a) Since one electron has a charge of (q_e = -1.6 \times 10^{-19}~\text{C}), we can determine the number of electrons necessary to generate a total charge of −2.00 nC by using the equation (N q_e = Q), so that [ N = \frac{Q}{q_e} = \frac{-2.00 \times 10^{-9}~\text{C}}{-1.60 \times 10^{-19}~\text{C}} = \underline{1.25 \times 10^{10}~\text{electrons}}. ] (b) Similarly, we can determine the number of electrons removed from a neutral object to leave a charge of 0.500 μC: [ N = \frac{Q}{q_e} = \frac{0.500 \times 10^{-6}~\text{C}}{1.60 \times 10^{-19}~\text{C}} = \underline{3.13 \times 10^{12}~\text{electrons}}. ] Example 2: *(a) Will the electric field strength between two parallel conducting plates exceed the breakdown strength for air ((3.0\times10^6\text{ V/m})) if the plates are separated by 2.00 mm and a potential difference of (5.0\times10^3\text{ V}) is applied? (b) How close together can the plates be with this applied voltage?* Solution (a) Using the equation [ E = \frac{V_{AB}}{d}, ] we can determine the electric field strength produced between two parallel plates since we know their separation distance and the potential difference across the plates: [ E = \frac{V_{AB}}{d} = \frac{5.0\times10^3\text{ V}}{2.00\times10^{-3}\text{ m}} = 2.5\times10^6\text{ V/m} < 3\times10^6\text{ V/m}. ] No, the field strength is smaller than the breakdown strength for air. (b) Using the equation (E = V_{AB}/d), we can now solve for the separation distance, given the potential difference and the maximum electric field strength: [ d = \frac{V_{AB}}{E} = \frac{5.0\times10^3\text{ V}}{3.0\times10^6\text{ V/m}} = 1.67\times10^{-3}\text{ m} = \underline{1.7\text{ mm}}. ] So, the plates must not be closer than 1.7 mm to avoid exceeding the breakdown strength of air. Example 3: *(a) Common transparent tape becomes charged when pulled from a dispenser. If one piece is placed above another, the repulsive force can be great enough to support the top piece’s weight. Assuming equal point charges (only an approximation), calculate the magnitude of the charge if electrostatic force is great enough to support the weight of a 10.0 mg piece of tape held 1.00 cm above another. (b) Discuss whether the magnitude of this charge is consistent with what is typical of static electricity.* **Solution** (a) If the electrostatic force is to support the weight of 10.0 mg piece of tape, it must be a force equal to the gravitational force on the tape, so using the equation [ F_1 = k \frac{q_1 q_2}{r_1^2} ] and the assumption that the point charges are equal, we can set electrostatic force equal to gravitational force. [ F = k \frac{q_1 q_2}{r^2} = \frac{k q^2}{r^2} = mg \implies q = \left(\frac{r^2 mg}{k}\right)^{1/2} ] [ q = \left[\frac{(0.0100\ \text{m})^2 (10.0\times10^{-6}\ \text{kg}) (9.80\ \text{m/s}^2)}{8.99\times10^9\ \text{N·m}^2/\text{C}^2}\right]^{1/2} = 1.04\times 10^{-9}\ \text{C}. ] (b) This charge is approximately 1 nC, which is consistent with the magnitude of the charge of typical static electricity. | E19: TRUE | F19: 2.84 | G19: d = \frac{m v^2}{2eE} | H19: cm | J19: {"final_numeric":2.84,"final_formula":"d = \\frac{m v^2}{2eE}","final_units":"cm"} | K19: {'id': 'gen-1780487857-qHoJFLHF4MgMDO21lFNg', 'object': 'chat.completion', 'created': 1780487857, 'model': 'anthropic/claude-4.7-opus-20260416', 'provider': 'Anthropic', 'system_fingerprint': None, 'service_tier': 'default', 'choices': [{'index': 0, 'logprobs': None, 'finish_reason': 'stop', 'native_finish_reason': 'end_turn', 'message': {'role': 'assistant', 'content': '{"final_numeric":2.84,"final_formula":"d = \\\\frac{m v^2}{2eE}","final_units":"cm"}', 'refusal': None, 'reasoning': None}}], 'usage': {'prompt_tokens': 2250, 'completion_tokens': 50, 'total_tokens': 2300, 'cost': 0.0125, 'is_byok': False, 'prompt_tokens_details': {'cached_tokens': 0, 'cache_write_tokens': 0, 'audio_tokens': 0, 'video_tokens': 0}, 'cost_details': {'upstream_inference_cost': 0.0125, 'upstream_inference_prompt_cost': 0.01125, 'upstream_inference_completions_cost': 0.00125}, 'completion_tokens_details': {'reasoning_tokens': 0, 'image_tokens': 0, 'audio_tokens': 0}}} | L19: 2250 | M19: 50 | N19: 2300 | O19: 0 | P19: =VLOOKUP(C19,problems!$A$2:$B$26,2) -> electrostatics | Q19: =IFERROR(__xludf.DUMMYFUNCTION("INDEX(FILTER('stats2-openrouter_activity_2026'!C:C,L19='stats2-openrouter_activity_2026'!H:H,M19='stats2-openrouter_activity_2026'!I:I, B19='stats2-openrouter_activity_2026'!M:M),1)"),0.0125) -> 0.0125 | R19: =IFS( F19=VLOOKUP($C19,problems!$A$2:$G$26,6),1, True,0 ) -> 0 | S19: =IFS( G19=VLOOKUP($C19,problems!$A$2:$G$26,4),1, G19=VLOOKUP($C19,problems!$A$2:$G$26,5),1, True,0 ) -> 0 | T19: =IFS( H19=VLOOKUP($C19,problems!$A$2:$G$26,7),1, True,0 ) -> 1
A20: 2026-06-03-15-59-18 | B20: anthropic/claude-opus-4.7 | C20: 19 | D20: Два одинаковых воздушных конденсатора соединены последовательно и подключены к батарее с постоянной ЭДС. Один из них заполняют диэлектриком с диэлектрической проницаемостью epsilon = 4. Во сколько раз изменится напряженность электрического поля в этом конденсаторе? Examples: Example 1: *Common static electricity involves charges ranging from nanocoulombs to microcoulombs. (a) How many electrons are needed to form a charge of −2.00 nC? (b) How many electrons must be removed from a neutral object to leave a net charge of 0.500 μC?* Solution (a) Since one electron has a charge of (q_e = -1.6 \times 10^{-19}~\text{C}), we can determine the number of electrons necessary to generate a total charge of −2.00 nC by using the equation (N q_e = Q), so that [ N = \frac{Q}{q_e} = \frac{-2.00 \times 10^{-9}~\text{C}}{-1.60 \times 10^{-19}~\text{C}} = \underline{1.25 \times 10^{10}~\text{electrons}}. ] (b) Similarly, we can determine the number of electrons removed from a neutral object to leave a charge of 0.500 μC: [ N = \frac{Q}{q_e} = \frac{0.500 \times 10^{-6}~\text{C}}{1.60 \times 10^{-19}~\text{C}} = \underline{3.13 \times 10^{12}~\text{electrons}}. ] Example 2: *(a) Will the electric field strength between two parallel conducting plates exceed the breakdown strength for air ((3.0\times10^6\text{ V/m})) if the plates are separated by 2.00 mm and a potential difference of (5.0\times10^3\text{ V}) is applied? (b) How close together can the plates be with this applied voltage?* Solution (a) Using the equation [ E = \frac{V_{AB}}{d}, ] we can determine the electric field strength produced between two parallel plates since we know their separation distance and the potential difference across the plates: [ E = \frac{V_{AB}}{d} = \frac{5.0\times10^3\text{ V}}{2.00\times10^{-3}\text{ m}} = 2.5\times10^6\text{ V/m} < 3\times10^6\text{ V/m}. ] No, the field strength is smaller than the breakdown strength for air. (b) Using the equation (E = V_{AB}/d), we can now solve for the separation distance, given the potential difference and the maximum electric field strength: [ d = \frac{V_{AB}}{E} = \frac{5.0\times10^3\text{ V}}{3.0\times10^6\text{ V/m}} = 1.67\times10^{-3}\text{ m} = \underline{1.7\text{ mm}}. ] So, the plates must not be closer than 1.7 mm to avoid exceeding the breakdown strength of air. Example 3: *(a) Common transparent tape becomes charged when pulled from a dispenser. If one piece is placed above another, the repulsive force can be great enough to support the top piece’s weight. Assuming equal point charges (only an approximation), calculate the magnitude of the charge if electrostatic force is great enough to support the weight of a 10.0 mg piece of tape held 1.00 cm above another. (b) Discuss whether the magnitude of this charge is consistent with what is typical of static electricity.* **Solution** (a) If the electrostatic force is to support the weight of 10.0 mg piece of tape, it must be a force equal to the gravitational force on the tape, so using the equation [ F_1 = k \frac{q_1 q_2}{r_1^2} ] and the assumption that the point charges are equal, we can set electrostatic force equal to gravitational force. [ F = k \frac{q_1 q_2}{r^2} = \frac{k q^2}{r^2} = mg \implies q = \left(\frac{r^2 mg}{k}\right)^{1/2} ] [ q = \left[\frac{(0.0100\ \text{m})^2 (10.0\times10^{-6}\ \text{kg}) (9.80\ \text{m/s}^2)}{8.99\times10^9\ \text{N·m}^2/\text{C}^2}\right]^{1/2} = 1.04\times 10^{-9}\ \text{C}. ] (b) This charge is approximately 1 nC, which is consistent with the magnitude of the charge of typical static electricity. | E20: TRUE | F20: 0.1 | G20: \frac{E}{E_0} = \frac{2}{\varepsilon(1+\varepsilon)} | H20: 1 | J20: Initially: two equal capacitors C in series, voltage on each = U/2, field E0 = U/(2d). After: C1=C, C2=εC. Voltage on dielectric one: U2 = U·C/(C+εC) = U/(1+ε). Field in dielectric: E = U2/(εd) = U/[εd(1+ε)]. Ratio E/E0 = [U/(εd(1+ε))]/[U/(2d)] = 2/[ε(1+ε)] = 2/(4·5) = 2/20 = 0.1. {"final_numeric": 0.1, "final_formula": "\\frac{E}{E_0} = \\frac{2}{\\varepsilon(1+\\varepsilon)}", "final_units": "1"} | K20: {'id': 'gen-1780487953-03ILG4KauQyg2MzWZW9j', 'object': 'chat.completion', 'created': 1780487953, 'model': 'anthropic/claude-4.7-opus-20260416', 'provider': 'Anthropic', 'system_fingerprint': None, 'service_tier': 'default', 'choices': [{'index': 0, 'logprobs': None, 'finish_reason': 'stop', 'native_finish_reason': 'end_turn', 'message': {'role': 'assistant', 'content': 'Initially: two equal capacitors C in series, voltage on each = U/2, field E0 = U/(2d).\n\nAfter: C1=C, C2=εC. Voltage on dielectric one: U2 = U·C/(C+εC) = U/(1+ε).\nField in dielectric: E = U2/(εd) = U/[εd(1+ε)].\n\nRatio E/E0 = [U/(εd(1+ε))]/[U/(2d)] = 2/[ε(1+ε)] = 2/(4·5) = 2/20 = 0.1.\n\n{"final_numeric": 0.1, "final_formula": "\\\\frac{E}{E_0} = \\\\frac{2}{\\\\varepsilon(1+\\\\varepsilon)}", "final_units": "1"}', 'refusal': None, 'reasoning': None}}], 'usage': {'prompt_tokens': 2274, 'completion_tokens': 258, 'total_tokens': 2532, 'cost': 0.01782, 'is_byok': False, 'prompt_tokens_details': {'cached_tokens': 0, 'cache_write_tokens': 0, 'audio_tokens': 0, 'video_tokens': 0}, 'cost_details': {'upstream_inference_cost': 0.01782, 'upstream_inference_prompt_cost': 0.01137, 'upstream_inference_completions_cost': 0.00645}, 'completion_tokens_details': {'reasoning_tokens': 0, 'image_tokens': 0, 'audio_tokens': 0}}} | L20: 2274 | M20: 258 | N20: 2532 | O20: 0 | P20: =VLOOKUP(C20,problems!$A$2:$B$26,2) -> electrostatics | Q20: =IFERROR(__xludf.DUMMYFUNCTION("INDEX(FILTER('stats2-openrouter_activity_2026'!C:C,L20='stats2-openrouter_activity_2026'!H:H,M20='stats2-openrouter_activity_2026'!I:I, B20='stats2-openrouter_activity_2026'!M:M),1)"),0.01782) -> 0.01782 | R20: =IFS( F20=VLOOKUP($C20,problems!$A$2:$G$26,6),1, True,0 ) -> 0 | S20: =IFS( G20=VLOOKUP($C20,problems!$A$2:$G$26,4),1, G20=VLOOKUP($C20,problems!$A$2:$G$26,5),1, True,0 ) -> 0 | T20: =IFS( H20=VLOOKUP($C20,problems!$A$2:$G$26,7),1, True,0 ) -> 1
A21: 2026-06-03-16-00-52 | B21: anthropic/claude-opus-4.7 | C21: 20 | D21: A particle of mass m and charge −𝑞 moves along a straight line away from a fixed particle of charge Q. When the distance between the two particles is 𝑟_{0},−𝑞 is moving with a speed 𝑣_{0}. What do you have to assume about 𝑣0 to make this calculation? (formula only) Examples: Example 1: *Common static electricity involves charges ranging from nanocoulombs to microcoulombs. (a) How many electrons are needed to form a charge of −2.00 nC? (b) How many electrons must be removed from a neutral object to leave a net charge of 0.500 μC?* Solution (a) Since one electron has a charge of (q_e = -1.6 \times 10^{-19}~\text{C}), we can determine the number of electrons necessary to generate a total charge of −2.00 nC by using the equation (N q_e = Q), so that [ N = \frac{Q}{q_e} = \frac{-2.00 \times 10^{-9}~\text{C}}{-1.60 \times 10^{-19}~\text{C}} = \underline{1.25 \times 10^{10}~\text{electrons}}. ] (b) Similarly, we can determine the number of electrons removed from a neutral object to leave a charge of 0.500 μC: [ N = \frac{Q}{q_e} = \frac{0.500 \times 10^{-6}~\text{C}}{1.60 \times 10^{-19}~\text{C}} = \underline{3.13 \times 10^{12}~\text{electrons}}. ] Example 2: *(a) Will the electric field strength between two parallel conducting plates exceed the breakdown strength for air ((3.0\times10^6\text{ V/m})) if the plates are separated by 2.00 mm and a potential difference of (5.0\times10^3\text{ V}) is applied? (b) How close together can the plates be with this applied voltage?* Solution (a) Using the equation [ E = \frac{V_{AB}}{d}, ] we can determine the electric field strength produced between two parallel plates since we know their separation distance and the potential difference across the plates: [ E = \frac{V_{AB}}{d} = \frac{5.0\times10^3\text{ V}}{2.00\times10^{-3}\text{ m}} = 2.5\times10^6\text{ V/m} < 3\times10^6\text{ V/m}. ] No, the field strength is smaller than the breakdown strength for air. (b) Using the equation (E = V_{AB}/d), we can now solve for the separation distance, given the potential difference and the maximum electric field strength: [ d = \frac{V_{AB}}{E} = \frac{5.0\times10^3\text{ V}}{3.0\times10^6\text{ V/m}} = 1.67\times10^{-3}\text{ m} = \underline{1.7\text{ mm}}. ] So, the plates must not be closer than 1.7 mm to avoid exceeding the breakdown strength of air. Example 3: *(a) Common transparent tape becomes charged when pulled from a dispenser. If one piece is placed above another, the repulsive force can be great enough to support the top piece’s weight. Assuming equal point charges (only an approximation), calculate the magnitude of the charge if electrostatic force is great enough to support the weight of a 10.0 mg piece of tape held 1.00 cm above another. (b) Discuss whether the magnitude of this charge is consistent with what is typical of static electricity.* **Solution** (a) If the electrostatic force is to support the weight of 10.0 mg piece of tape, it must be a force equal to the gravitational force on the tape, so using the equation [ F_1 = k \frac{q_1 q_2}{r_1^2} ] and the assumption that the point charges are equal, we can set electrostatic force equal to gravitational force. [ F = k \frac{q_1 q_2}{r^2} = \frac{k q^2}{r^2} = mg \implies q = \left(\frac{r^2 mg}{k}\right)^{1/2} ] [ q = \left[\frac{(0.0100\ \text{m})^2 (10.0\times10^{-6}\ \text{kg}) (9.80\ \text{m/s}^2)}{8.99\times10^9\ \text{N·m}^2/\text{C}^2}\right]^{1/2} = 1.04\times 10^{-9}\ \text{C}. ] (b) This charge is approximately 1 nC, which is consistent with the magnitude of the charge of typical static electricity. | E21: TRUE | G21: v_0 \geq \sqrt{\dfrac{2kQq}{mr_0}} | H21: m/s | J21: {"final_numeric":null,"final_formula":"v_0 \\geq \\sqrt{\\dfrac{2kQq}{mr_0}}","final_units":"m/s"} | K21: {'id': 'gen-1780488050-Hl3Mq5M9kF9fw0seZvp9', 'object': 'chat.completion', 'created': 1780488050, 'model': 'anthropic/claude-4.7-opus-20260416', 'provider': 'Anthropic', 'system_fingerprint': None, 'service_tier': 'default', 'choices': [{'index': 0, 'logprobs': None, 'finish_reason': 'stop', 'native_finish_reason': 'end_turn', 'message': {'role': 'assistant', 'content': '{"final_numeric":null,"final_formula":"v_0 \\\\geq \\\\sqrt{\\\\dfrac{2kQq}{mr_0}}","final_units":"m/s"}', 'refusal': None, 'reasoning': None}}], 'usage': {'prompt_tokens': 2274, 'completion_tokens': 66, 'total_tokens': 2340, 'cost': 0.01302, 'is_byok': False, 'prompt_tokens_details': {'cached_tokens': 0, 'cache_write_tokens': 0, 'audio_tokens': 0, 'video_tokens': 0}, 'cost_details': {'upstream_inference_cost': 0.01302, 'upstream_inference_prompt_cost': 0.01137, 'upstream_inference_completions_cost': 0.00165}, 'completion_tokens_details': {'reasoning_tokens': 0, 'image_tokens': 0, 'audio_tokens': 0}}} | L21: 2274 | M21: 66 | N21: 2340 | O21: 0 | P21: =VLOOKUP(C21,problems!$A$2:$B$26,2) -> electrostatics | Q21: =IFERROR(__xludf.DUMMYFUNCTION("INDEX(FILTER('stats2-openrouter_activity_2026'!C:C,L21='stats2-openrouter_activity_2026'!H:H,M21='stats2-openrouter_activity_2026'!I:I, B21='stats2-openrouter_activity_2026'!M:M),1)"),0.01302) -> 0.01302 | R21: =IFS( F21=VLOOKUP($C21,problems!$A$2:$G$26,6),1, True,0 ) -> 1 | S21: =IFS( G21=VLOOKUP($C21,problems!$A$2:$G$26,4),1, G21=VLOOKUP($C21,problems!$A$2:$G$26,5),1, True,0 ) -> 0 | T21: =IFS( H21=VLOOKUP($C21,problems!$A$2:$G$26,7),1, True,0 ) -> 0
A22: 2026-06-03-16-02-35 | B22: anthropic/claude-opus-4.7 | C22: 21 | D22: При переходе электронов с некоторой более удаленной орби65ты на вторую боровскую орбиту, атомы водорода испускают монохроматический пучок света. При падении этого пучка по нормали на дифракционную решетку максимум второго порядка (k = 2) наблюдается под углом дифракции phi = 30°. Постоянная дифракционной решетки d = 2,6 мкм. Определить номер орбиты n, на котором первоначально находились электроны в атомах водорода. Examples: Example 1: *(a) Calculate the radius of (^{58}\mathrm{Ni}), one of the most tightly bound stable nuclei. (b) What is the ratio of the radius of (^{58}\mathrm{Ni}) to that of (^{258}\mathrm{Ha}), one of the largest nuclei ever made? Note that the radius of the largest nucleus is still much smaller than the size of an atom.* **Solution** (a) Using the equation ( r = r_0 A^{1/3} ) we can approximate the radius of (^{58}\mathrm{Ni}): [ r_{\mathrm{Ni}} = r_0 A_{\mathrm{Ni}}^{1/3} = \left(1.2 \times 10^{-15}\ \mathrm{m}\right) (58)^{1/3} = 4.6 \times 10^{-15}\ \mathrm{m} = \underline{4.6\ \mathrm{fm}} ] (b) Again using this equation, this time we can approximate the radius of (^{258}\mathrm{Ha}): [ r_{\mathrm{Ha}} = \left(1.2 \times 10^{-15}\ \mathrm{m}\right) (258)^{1/3} = 7.6 \times 10^{-15}\ \mathrm{m} = \underline{7.6\ \mathrm{fm}} ] Finally, taking the ratio of Ni to Ha gives: [ \frac{r_{\mathrm{Ni}}}{r_{\mathrm{Ha}}} = \frac{4.645 \times 10^{-15}\ \mathrm{m}}{7.639 \times 10^{-15}\ \mathrm{m}} = \underline{0.61\ \text{to 1}} ] Example 2: *The (\beta^-) particles emitted in the decay of (^3\mathrm{H}) (tritium) interact with matter to create light in a glow-in-the-dark exit sign. At the time of manufacture, such a sign contains (15.0\ \mathrm{Ci}) of (^3\mathrm{H}). (a) What is the mass of the tritium? (b) What is its activity 5.00 y after manufacture?* **Solution** Using the equation (R = \dfrac{0.693 N}{t_{1/2}}), we can write the activity in terms of the half-life, the atomic mass, (M), and the mass of the sample (m): [ \text{(a)}\quad R = \frac{0.693N}{t_{1/2}} = \frac{(0.693)(m/M)}{t_{1/2}} ] The atomic mass of tritium (from Appendix A) is: [ M = 3.016050\ \mathrm{u} \left(\frac{1.6605 \times 10^{-27}\ \mathrm{kg}}{1\ \mathrm{u}}\right) = 5.0082 \times 10^{-27}\ \mathrm{kg/atom} ] and the half-life is 12.33 y (from Appendix B), so we can determine the original mass of tritium: [ m = \frac{R t_{1/2} M}{0.693} \quad \text{or} \quad m = \frac{(15.0\ \mathrm{Ci})(12.33\ \mathrm{y})(5.0082\times 10^{-27}\ \mathrm{kg}) M}{0.693} \left(\frac{3.70 \times 10^{10}\ \mathrm{Bq}}{1\ \mathrm{Ci}}\right) \left(\frac{3.156\times10^7\ \mathrm{s}}{1\ \mathrm{y}}\right) = 1.56\times10^{-6}\ \mathrm{kg} = \underline{1.56\ \mathrm{mg}} ] [ \text{(b)}\quad R = R_0 e^{-\lambda t} = R_0 \exp\left[-\frac{0.693}{t_{1/2}} t \right] = (15.0\ \mathrm{Ci}) \exp\left[-\frac{0.693(5.00\ \mathrm{y})}{12.33\ \mathrm{y}} \right] = \underline{11.3\ \mathrm{Ci}} ] Example 3: *A neutron generator uses an (\alpha) source, such as radium, to bombard beryllium, inducing the reaction (^4\mathrm{He} + ^9\mathrm{Be} \rightarrow ^{12}\mathrm{C} + n). Such neutron sources are called RaBe sources, or PuBe sources if they use plutonium to get the (\alpha)s. Calculate the energy output of the reaction in MeV.c* **Solution** Using (E = \Delta mc^2), we can determine the energy output of the reaction by calculating the change in mass of the constituents in the reaction, where the masses are found either in Appendix A or Table 31.2: [ E = (m_i - m_f)c^2 = (4.002603 + 9.02182 - 12.000000 - 1.008665)(931.5\ \mathrm{MeV}) = \underline{5.701\ \mathrm{MeV}} ] | E22: TRUE | F22: 3 | G22: \frac{1}{n^2}=\frac{1}{4}-\frac{k}{R\,d\sin\varphi} | H22: 1 | J22: λ = d sin φ / k = 2.6e-6 * 0.5 / 2 = 6.5e-7 m 1/λ = R(1/4 - 1/n²) R = 1.097e7 1/λ = 1/6.5e-7 = 1.5385e6 1.5385e6 / 1.097e7 = 0.14024 1/4 - 1/n² = 0.14024 1/n² = 0.25 - 0.14024 = 0.10976 n² = 9.111 n ≈ 3 {"final_numeric":3,"final_formula":"\\frac{1}{n^2}=\\frac{1}{4}-\\frac{k}{R\\,d\\sin\\varphi}","final_units":"1"} | K22: {'id': 'gen-1780488152-yxrqH7OJuHnd4Hq94YJZ', 'object': 'chat.completion', 'created': 1780488152, 'model': 'anthropic/claude-4.7-opus-20260416', 'provider': 'Anthropic', 'system_fingerprint': None, 'service_tier': 'default', 'choices': [{'index': 0, 'logprobs': None, 'finish_reason': 'stop', 'native_finish_reason': 'end_turn', 'message': {'role': 'assistant', 'content': 'λ = d sin φ / k = 2.6e-6 * 0.5 / 2 = 6.5e-7 m\n\n1/λ = R(1/4 - 1/n²)\nR = 1.097e7\n1/λ = 1/6.5e-7 = 1.5385e6\n1.5385e6 / 1.097e7 = 0.14024\n1/4 - 1/n² = 0.14024\n1/n² = 0.25 - 0.14024 = 0.10976\nn² = 9.111\nn ≈ 3\n\n{"final_numeric":3,"final_formula":"\\\\frac{1}{n^2}=\\\\frac{1}{4}-\\\\frac{k}{R\\\\,d\\\\sin\\\\varphi}","final_units":"1"}', 'refusal': None, 'reasoning': None}}], 'usage': {'prompt_tokens': 2636, 'completion_tokens': 248, 'total_tokens': 2884, 'cost': 0.01938, 'is_byok': False, 'prompt_tokens_details': {'cached_tokens': 0, 'cache_write_tokens': 0, 'audio_tokens': 0, 'video_tokens': 0}, 'cost_details': {'upstream_inference_cost': 0.01938, 'upstream_inference_prompt_cost': 0.01318, 'upstream_inference_completions_cost': 0.0062}, 'completion_tokens_details': {'reasoning_tokens': 0, 'image_tokens': 0, 'audio_tokens': 0}}} | L22: 2636 | M22: 248 | N22: 2884 | O22: 0 | P22: =VLOOKUP(C22,problems!$A$2:$B$26,2) -> nuclear | Q22: =IFERROR(__xludf.DUMMYFUNCTION("INDEX(FILTER('stats2-openrouter_activity_2026'!C:C,L22='stats2-openrouter_activity_2026'!H:H,M22='stats2-openrouter_activity_2026'!I:I, B22='stats2-openrouter_activity_2026'!M:M),1)"),0.01938) -> 0.01938 | R22: =IFS( F22=VLOOKUP($C22,problems!$A$2:$G$26,6),1, True,0 ) -> 0 | S22: =IFS( G22=VLOOKUP($C22,problems!$A$2:$G$26,4),1, G22=VLOOKUP($C22,problems!$A$2:$G$26,5),1, True,0 ) -> 0 | T22: =IFS( H22=VLOOKUP($C22,problems!$A$2:$G$26,7),1, True,0 ) -> 1
A23: 2026-06-03-16-04-04 | B23: anthropic/claude-opus-4.7 | C23: 22 | D23: Подводная лодка «Наутилус» (США) имеет мощность топливных установок Р = 14,7 МВт, КПД n = 25%. Топливом служит обогащенный уран массой то m_{0} - 1 кг, при делении ядер которого выделяется энергия E = 6,9 * 10^13 Дж. Определить запас горючего, необходимого для годового плавания лодки. Examples: Example 1: *(a) Calculate the radius of (^{58}\mathrm{Ni}), one of the most tightly bound stable nuclei. (b) What is the ratio of the radius of (^{58}\mathrm{Ni}) to that of (^{258}\mathrm{Ha}), one of the largest nuclei ever made? Note that the radius of the largest nucleus is still much smaller than the size of an atom.* **Solution** (a) Using the equation ( r = r_0 A^{1/3} ) we can approximate the radius of (^{58}\mathrm{Ni}): [ r_{\mathrm{Ni}} = r_0 A_{\mathrm{Ni}}^{1/3} = \left(1.2 \times 10^{-15}\ \mathrm{m}\right) (58)^{1/3} = 4.6 \times 10^{-15}\ \mathrm{m} = \underline{4.6\ \mathrm{fm}} ] (b) Again using this equation, this time we can approximate the radius of (^{258}\mathrm{Ha}): [ r_{\mathrm{Ha}} = \left(1.2 \times 10^{-15}\ \mathrm{m}\right) (258)^{1/3} = 7.6 \times 10^{-15}\ \mathrm{m} = \underline{7.6\ \mathrm{fm}} ] Finally, taking the ratio of Ni to Ha gives: [ \frac{r_{\mathrm{Ni}}}{r_{\mathrm{Ha}}} = \frac{4.645 \times 10^{-15}\ \mathrm{m}}{7.639 \times 10^{-15}\ \mathrm{m}} = \underline{0.61\ \text{to 1}} ] Example 2: *The (\beta^-) particles emitted in the decay of (^3\mathrm{H}) (tritium) interact with matter to create light in a glow-in-the-dark exit sign. At the time of manufacture, such a sign contains (15.0\ \mathrm{Ci}) of (^3\mathrm{H}). (a) What is the mass of the tritium? (b) What is its activity 5.00 y after manufacture?* **Solution** Using the equation (R = \dfrac{0.693 N}{t_{1/2}}), we can write the activity in terms of the half-life, the atomic mass, (M), and the mass of the sample (m): [ \text{(a)}\quad R = \frac{0.693N}{t_{1/2}} = \frac{(0.693)(m/M)}{t_{1/2}} ] The atomic mass of tritium (from Appendix A) is: [ M = 3.016050\ \mathrm{u} \left(\frac{1.6605 \times 10^{-27}\ \mathrm{kg}}{1\ \mathrm{u}}\right) = 5.0082 \times 10^{-27}\ \mathrm{kg/atom} ] and the half-life is 12.33 y (from Appendix B), so we can determine the original mass of tritium: [ m = \frac{R t_{1/2} M}{0.693} \quad \text{or} \quad m = \frac{(15.0\ \mathrm{Ci})(12.33\ \mathrm{y})(5.0082\times 10^{-27}\ \mathrm{kg}) M}{0.693} \left(\frac{3.70 \times 10^{10}\ \mathrm{Bq}}{1\ \mathrm{Ci}}\right) \left(\frac{3.156\times10^7\ \mathrm{s}}{1\ \mathrm{y}}\right) = 1.56\times10^{-6}\ \mathrm{kg} = \underline{1.56\ \mathrm{mg}} ] [ \text{(b)}\quad R = R_0 e^{-\lambda t} = R_0 \exp\left[-\frac{0.693}{t_{1/2}} t \right] = (15.0\ \mathrm{Ci}) \exp\left[-\frac{0.693(5.00\ \mathrm{y})}{12.33\ \mathrm{y}} \right] = \underline{11.3\ \mathrm{Ci}} ] Example 3: *A neutron generator uses an (\alpha) source, such as radium, to bombard beryllium, inducing the reaction (^4\mathrm{He} + ^9\mathrm{Be} \rightarrow ^{12}\mathrm{C} + n). Such neutron sources are called RaBe sources, or PuBe sources if they use plutonium to get the (\alpha)s. Calculate the energy output of the reaction in MeV.c* **Solution** Using (E = \Delta mc^2), we can determine the energy output of the reaction by calculating the change in mass of the constituents in the reaction, where the masses are found either in Appendix A or Table 31.2: [ E = (m_i - m_f)c^2 = (4.002603 + 9.02182 - 12.000000 - 1.008665)(931.5\ \mathrm{MeV}) = \underline{5.701\ \mathrm{MeV}} ] | E23: TRUE | F23: 26.86 | G23: m = \frac{P \cdot t \cdot m_0}{\eta \cdot E} | H23: kg | J23: {"final_numeric":26.86,"final_formula":"m = \\frac{P \\cdot t \\cdot m_0}{\\eta \\cdot E}","final_units":"kg"} | K23: {'id': 'gen-1780488243-9d3M2d8dM1IBScLfRZmm', 'object': 'chat.completion', 'created': 1780488243, 'model': 'anthropic/claude-4.7-opus-20260416', 'provider': 'Anthropic', 'system_fingerprint': None, 'service_tier': 'default', 'choices': [{'index': 0, 'logprobs': None, 'finish_reason': 'stop', 'native_finish_reason': 'end_turn', 'message': {'role': 'assistant', 'content': '{"final_numeric":26.86,"final_formula":"m = \\\\frac{P \\\\cdot t \\\\cdot m_0}{\\\\eta \\\\cdot E}","final_units":"kg"}', 'refusal': None, 'reasoning': None}}], 'usage': {'prompt_tokens': 2605, 'completion_tokens': 68, 'total_tokens': 2673, 'cost': 0.014725, 'is_byok': False, 'prompt_tokens_details': {'cached_tokens': 0, 'cache_write_tokens': 0, 'audio_tokens': 0, 'video_tokens': 0}, 'cost_details': {'upstream_inference_cost': 0.014725, 'upstream_inference_prompt_cost': 0.013025, 'upstream_inference_completions_cost': 0.0017}, 'completion_tokens_details': {'reasoning_tokens': 0, 'image_tokens': 0, 'audio_tokens': 0}}} | L23: 2605 | M23: 68 | N23: 2673 | O23: 0 | P23: =VLOOKUP(C23,problems!$A$2:$B$26,2) -> nuclear | Q23: =IFERROR(__xludf.DUMMYFUNCTION("INDEX(FILTER('stats2-openrouter_activity_2026'!C:C,L23='stats2-openrouter_activity_2026'!H:H,M23='stats2-openrouter_activity_2026'!I:I, B23='stats2-openrouter_activity_2026'!M:M),1)"),0.014725) -> 0.014725 | R23: =IFS( F23=VLOOKUP($C23,problems!$A$2:$G$26,6),1, True,0 ) -> 0 | S23: =IFS( G23=VLOOKUP($C23,problems!$A$2:$G$26,4),1, G23=VLOOKUP($C23,problems!$A$2:$G$26,5),1, True,0 ) -> 0 | T23: =IFS( H23=VLOOKUP($C23,problems!$A$2:$G$26,7),1, True,0 ) -> 1
A24: 2026-06-03-16-05-53 | B24: anthropic/claude-opus-4.7 | C24: 23 | D24: При определении периода полураспада короткоживущего радиоактивного изотопа использовался счетчик импульсов. За минуту в начале наблюдения было насчитано delta(n_{0}) = 250 импульсов, а через время t = 1 ч было зарегистрировано delta(n) = 92 импульса. Чему равен период полураспада в мин данного изотопа? Examples: Example 1: *(a) Calculate the radius of (^{58}\mathrm{Ni}), one of the most tightly bound stable nuclei. (b) What is the ratio of the radius of (^{58}\mathrm{Ni}) to that of (^{258}\mathrm{Ha}), one of the largest nuclei ever made? Note that the radius of the largest nucleus is still much smaller than the size of an atom.* **Solution** (a) Using the equation ( r = r_0 A^{1/3} ) we can approximate the radius of (^{58}\mathrm{Ni}): [ r_{\mathrm{Ni}} = r_0 A_{\mathrm{Ni}}^{1/3} = \left(1.2 \times 10^{-15}\ \mathrm{m}\right) (58)^{1/3} = 4.6 \times 10^{-15}\ \mathrm{m} = \underline{4.6\ \mathrm{fm}} ] (b) Again using this equation, this time we can approximate the radius of (^{258}\mathrm{Ha}): [ r_{\mathrm{Ha}} = \left(1.2 \times 10^{-15}\ \mathrm{m}\right) (258)^{1/3} = 7.6 \times 10^{-15}\ \mathrm{m} = \underline{7.6\ \mathrm{fm}} ] Finally, taking the ratio of Ni to Ha gives: [ \frac{r_{\mathrm{Ni}}}{r_{\mathrm{Ha}}} = \frac{4.645 \times 10^{-15}\ \mathrm{m}}{7.639 \times 10^{-15}\ \mathrm{m}} = \underline{0.61\ \text{to 1}} ] Example 2: *The (\beta^-) particles emitted in the decay of (^3\mathrm{H}) (tritium) interact with matter to create light in a glow-in-the-dark exit sign. At the time of manufacture, such a sign contains (15.0\ \mathrm{Ci}) of (^3\mathrm{H}). (a) What is the mass of the tritium? (b) What is its activity 5.00 y after manufacture?* **Solution** Using the equation (R = \dfrac{0.693 N}{t_{1/2}}), we can write the activity in terms of the half-life, the atomic mass, (M), and the mass of the sample (m): [ \text{(a)}\quad R = \frac{0.693N}{t_{1/2}} = \frac{(0.693)(m/M)}{t_{1/2}} ] The atomic mass of tritium (from Appendix A) is: [ M = 3.016050\ \mathrm{u} \left(\frac{1.6605 \times 10^{-27}\ \mathrm{kg}}{1\ \mathrm{u}}\right) = 5.0082 \times 10^{-27}\ \mathrm{kg/atom} ] and the half-life is 12.33 y (from Appendix B), so we can determine the original mass of tritium: [ m = \frac{R t_{1/2} M}{0.693} \quad \text{or} \quad m = \frac{(15.0\ \mathrm{Ci})(12.33\ \mathrm{y})(5.0082\times 10^{-27}\ \mathrm{kg}) M}{0.693} \left(\frac{3.70 \times 10^{10}\ \mathrm{Bq}}{1\ \mathrm{Ci}}\right) \left(\frac{3.156\times10^7\ \mathrm{s}}{1\ \mathrm{y}}\right) = 1.56\times10^{-6}\ \mathrm{kg} = \underline{1.56\ \mathrm{mg}} ] [ \text{(b)}\quad R = R_0 e^{-\lambda t} = R_0 \exp\left[-\frac{0.693}{t_{1/2}} t \right] = (15.0\ \mathrm{Ci}) \exp\left[-\frac{0.693(5.00\ \mathrm{y})}{12.33\ \mathrm{y}} \right] = \underline{11.3\ \mathrm{Ci}} ] Example 3: *A neutron generator uses an (\alpha) source, such as radium, to bombard beryllium, inducing the reaction (^4\mathrm{He} + ^9\mathrm{Be} \rightarrow ^{12}\mathrm{C} + n). Such neutron sources are called RaBe sources, or PuBe sources if they use plutonium to get the (\alpha)s. Calculate the energy output of the reaction in MeV.c* **Solution** Using (E = \Delta mc^2), we can determine the energy output of the reaction by calculating the change in mass of the constituents in the reaction, where the masses are found either in Appendix A or Table 31.2: [ E = (m_i - m_f)c^2 = (4.002603 + 9.02182 - 12.000000 - 1.008665)(931.5\ \mathrm{MeV}) = \underline{5.701\ \mathrm{MeV}} ] | E24: TRUE | F24: 41.6 | G24: T_{1/2} = \frac{t \ln 2}{\ln(\Delta n_0/\Delta n)} = \frac{60 \ln 2}{\ln(250/92)} | H24: min | J24: {"final_numeric":41.6,"final_formula":"T_{1/2} = \\frac{t \\ln 2}{\\ln(\\Delta n_0/\\Delta n)} = \\frac{60 \\ln 2}{\\ln(250/92)}","final_units":"min"} | K24: {'id': 'gen-1780488350-IdiJ3UmuCfm6uNPe0HGR', 'object': 'chat.completion', 'created': 1780488350, 'model': 'anthropic/claude-4.7-opus-20260416', 'provider': 'Anthropic', 'system_fingerprint': None, 'service_tier': 'default', 'choices': [{'index': 0, 'logprobs': None, 'finish_reason': 'stop', 'native_finish_reason': 'end_turn', 'message': {'role': 'assistant', 'content': '{"final_numeric":41.6,"final_formula":"T_{1/2} = \\\\frac{t \\\\ln 2}{\\\\ln(\\\\Delta n_0/\\\\Delta n)} = \\\\frac{60 \\\\ln 2}{\\\\ln(250/92)}","final_units":"min"}', 'refusal': None, 'reasoning': None}}], 'usage': {'prompt_tokens': 2596, 'completion_tokens': 102, 'total_tokens': 2698, 'cost': 0.01553, 'is_byok': False, 'prompt_tokens_details': {'cached_tokens': 0, 'cache_write_tokens': 0, 'audio_tokens': 0, 'video_tokens': 0}, 'cost_details': {'upstream_inference_cost': 0.01553, 'upstream_inference_prompt_cost': 0.01298, 'upstream_inference_completions_cost': 0.00255}, 'completion_tokens_details': {'reasoning_tokens': 0, 'image_tokens': 0, 'audio_tokens': 0}}} | L24: 2596 | M24: 102 | N24: 2698 | O24: 0 | P24: =VLOOKUP(C24,problems!$A$2:$B$26,2) -> nuclear | Q24: =IFERROR(__xludf.DUMMYFUNCTION("INDEX(FILTER('stats2-openrouter_activity_2026'!C:C,L24='stats2-openrouter_activity_2026'!H:H,M24='stats2-openrouter_activity_2026'!I:I, B24='stats2-openrouter_activity_2026'!M:M),1)"),0.01553) -> 0.01553 | R24: =IFS( F24=VLOOKUP($C24,problems!$A$2:$G$26,6),1, True,0 ) -> 0 | S24: =IFS( G24=VLOOKUP($C24,problems!$A$2:$G$26,4),1, G24=VLOOKUP($C24,problems!$A$2:$G$26,5),1, True,0 ) -> 0 | T24: =IFS( H24=VLOOKUP($C24,problems!$A$2:$G$26,7),1, True,0 ) -> 1
A25: 2026-06-03-16-08-54 | B25: anthropic/claude-opus-4.7 | C25: 24 | D25: The wiki-phony site states that the atomic mass of chlorine is 40 g/mol. Check this result. Hint: The two, most common stable isotopes of chlorine are: {}^{35}_{17}\mathrm{Cl} and {}^{37}_{17}\mathrm{Cl}. (The abundance of Cl-35 is 75.8%, and the abundance of Cl-37 is 24.2%.) Examples: Example 1: *(a) Calculate the radius of (^{58}\mathrm{Ni}), one of the most tightly bound stable nuclei. (b) What is the ratio of the radius of (^{58}\mathrm{Ni}) to that of (^{258}\mathrm{Ha}), one of the largest nuclei ever made? Note that the radius of the largest nucleus is still much smaller than the size of an atom.* **Solution** (a) Using the equation ( r = r_0 A^{1/3} ) we can approximate the radius of (^{58}\mathrm{Ni}): [ r_{\mathrm{Ni}} = r_0 A_{\mathrm{Ni}}^{1/3} = \left(1.2 \times 10^{-15}\ \mathrm{m}\right) (58)^{1/3} = 4.6 \times 10^{-15}\ \mathrm{m} = \underline{4.6\ \mathrm{fm}} ] (b) Again using this equation, this time we can approximate the radius of (^{258}\mathrm{Ha}): [ r_{\mathrm{Ha}} = \left(1.2 \times 10^{-15}\ \mathrm{m}\right) (258)^{1/3} = 7.6 \times 10^{-15}\ \mathrm{m} = \underline{7.6\ \mathrm{fm}} ] Finally, taking the ratio of Ni to Ha gives: [ \frac{r_{\mathrm{Ni}}}{r_{\mathrm{Ha}}} = \frac{4.645 \times 10^{-15}\ \mathrm{m}}{7.639 \times 10^{-15}\ \mathrm{m}} = \underline{0.61\ \text{to 1}} ] Example 2: *The (\beta^-) particles emitted in the decay of (^3\mathrm{H}) (tritium) interact with matter to create light in a glow-in-the-dark exit sign. At the time of manufacture, such a sign contains (15.0\ \mathrm{Ci}) of (^3\mathrm{H}). (a) What is the mass of the tritium? (b) What is its activity 5.00 y after manufacture?* **Solution** Using the equation (R = \dfrac{0.693 N}{t_{1/2}}), we can write the activity in terms of the half-life, the atomic mass, (M), and the mass of the sample (m): [ \text{(a)}\quad R = \frac{0.693N}{t_{1/2}} = \frac{(0.693)(m/M)}{t_{1/2}} ] The atomic mass of tritium (from Appendix A) is: [ M = 3.016050\ \mathrm{u} \left(\frac{1.6605 \times 10^{-27}\ \mathrm{kg}}{1\ \mathrm{u}}\right) = 5.0082 \times 10^{-27}\ \mathrm{kg/atom} ] and the half-life is 12.33 y (from Appendix B), so we can determine the original mass of tritium: [ m = \frac{R t_{1/2} M}{0.693} \quad \text{or} \quad m = \frac{(15.0\ \mathrm{Ci})(12.33\ \mathrm{y})(5.0082\times 10^{-27}\ \mathrm{kg}) M}{0.693} \left(\frac{3.70 \times 10^{10}\ \mathrm{Bq}}{1\ \mathrm{Ci}}\right) \left(\frac{3.156\times10^7\ \mathrm{s}}{1\ \mathrm{y}}\right) = 1.56\times10^{-6}\ \mathrm{kg} = \underline{1.56\ \mathrm{mg}} ] [ \text{(b)}\quad R = R_0 e^{-\lambda t} = R_0 \exp\left[-\frac{0.693}{t_{1/2}} t \right] = (15.0\ \mathrm{Ci}) \exp\left[-\frac{0.693(5.00\ \mathrm{y})}{12.33\ \mathrm{y}} \right] = \underline{11.3\ \mathrm{Ci}} ] Example 3: *A neutron generator uses an (\alpha) source, such as radium, to bombard beryllium, inducing the reaction (^4\mathrm{He} + ^9\mathrm{Be} \rightarrow ^{12}\mathrm{C} + n). Such neutron sources are called RaBe sources, or PuBe sources if they use plutonium to get the (\alpha)s. Calculate the energy output of the reaction in MeV.c* **Solution** Using (E = \Delta mc^2), we can determine the energy output of the reaction by calculating the change in mass of the constituents in the reaction, where the masses are found either in Appendix A or Table 31.2: [ E = (m_i - m_f)c^2 = (4.002603 + 9.02182 - 12.000000 - 1.008665)(931.5\ \mathrm{MeV}) = \underline{5.701\ \mathrm{MeV}} ] | E25: TRUE | F25: 35.484 | G25: M = 0.758 \times 35 + 0.242 \times 37 | H25: g/mol | J25: {"final_numeric":35.484,"final_formula":"M = 0.758 \\times 35 + 0.242 \\times 37","final_units":"g/mol"} | K25: {'id': 'gen-1780488531-FL1aCFzCacoADwE9vBEW', 'object': 'chat.completion', 'created': 1780488531, 'model': 'anthropic/claude-4.7-opus-20260416', 'provider': 'Anthropic', 'system_fingerprint': None, 'service_tier': 'default', 'choices': [{'index': 0, 'logprobs': None, 'finish_reason': 'stop', 'native_finish_reason': 'end_turn', 'message': {'role': 'assistant', 'content': '{"final_numeric":35.484,"final_formula":"M = 0.758 \\\\times 35 + 0.242 \\\\times 37","final_units":"g/mol"}', 'refusal': None, 'reasoning': None}}], 'usage': {'prompt_tokens': 2611, 'completion_tokens': 59, 'total_tokens': 2670, 'cost': 0.01453, 'is_byok': False, 'prompt_tokens_details': {'cached_tokens': 0, 'cache_write_tokens': 0, 'audio_tokens': 0, 'video_tokens': 0}, 'cost_details': {'upstream_inference_cost': 0.01453, 'upstream_inference_prompt_cost': 0.013055, 'upstream_inference_completions_cost': 0.001475}, 'completion_tokens_details': {'reasoning_tokens': 0, 'image_tokens': 0, 'audio_tokens': 0}}} | L25: 2611 | M25: 59 | N25: 2670 | O25: 0 | P25: =VLOOKUP(C25,problems!$A$2:$B$26,2) -> nuclear | Q25: =IFERROR(__xludf.DUMMYFUNCTION("INDEX(FILTER('stats2-openrouter_activity_2026'!C:C,L25='stats2-openrouter_activity_2026'!H:H,M25='stats2-openrouter_activity_2026'!I:I, B25='stats2-openrouter_activity_2026'!M:M),1)"),0.01453) -> 0.01453 | R25: =IFS( F25=VLOOKUP($C25,problems!$A$2:$G$26,6),1, True,0 ) -> 0 | S25: =IFS( G25=VLOOKUP($C25,problems!$A$2:$G$26,4),1, G25=VLOOKUP($C25,problems!$A$2:$G$26,5),1, True,0 ) -> 0 | T25: =IFS( H25=VLOOKUP($C25,problems!$A$2:$G$26,7),1, True,0 ) -> 1
A26: 2026-06-03-16-10-01 | B26: anthropic/claude-opus-4.7 | C26: 25 | D26: In the 1980s, the term picowave was used to describe food irradiation in order to overcome public resistance by playing on the well-known safety of microwave radiation. Find the energy in MeV of a photon having a wavelength of a picometer. Examples: Example 1: *(a) Calculate the radius of (^{58}\mathrm{Ni}), one of the most tightly bound stable nuclei. (b) What is the ratio of the radius of (^{58}\mathrm{Ni}) to that of (^{258}\mathrm{Ha}), one of the largest nuclei ever made? Note that the radius of the largest nucleus is still much smaller than the size of an atom.* **Solution** (a) Using the equation ( r = r_0 A^{1/3} ) we can approximate the radius of (^{58}\mathrm{Ni}): [ r_{\mathrm{Ni}} = r_0 A_{\mathrm{Ni}}^{1/3} = \left(1.2 \times 10^{-15}\ \mathrm{m}\right) (58)^{1/3} = 4.6 \times 10^{-15}\ \mathrm{m} = \underline{4.6\ \mathrm{fm}} ] (b) Again using this equation, this time we can approximate the radius of (^{258}\mathrm{Ha}): [ r_{\mathrm{Ha}} = \left(1.2 \times 10^{-15}\ \mathrm{m}\right) (258)^{1/3} = 7.6 \times 10^{-15}\ \mathrm{m} = \underline{7.6\ \mathrm{fm}} ] Finally, taking the ratio of Ni to Ha gives: [ \frac{r_{\mathrm{Ni}}}{r_{\mathrm{Ha}}} = \frac{4.645 \times 10^{-15}\ \mathrm{m}}{7.639 \times 10^{-15}\ \mathrm{m}} = \underline{0.61\ \text{to 1}} ] Example 2: *The (\beta^-) particles emitted in the decay of (^3\mathrm{H}) (tritium) interact with matter to create light in a glow-in-the-dark exit sign. At the time of manufacture, such a sign contains (15.0\ \mathrm{Ci}) of (^3\mathrm{H}). (a) What is the mass of the tritium? (b) What is its activity 5.00 y after manufacture?* **Solution** Using the equation (R = \dfrac{0.693 N}{t_{1/2}}), we can write the activity in terms of the half-life, the atomic mass, (M), and the mass of the sample (m): [ \text{(a)}\quad R = \frac{0.693N}{t_{1/2}} = \frac{(0.693)(m/M)}{t_{1/2}} ] The atomic mass of tritium (from Appendix A) is: [ M = 3.016050\ \mathrm{u} \left(\frac{1.6605 \times 10^{-27}\ \mathrm{kg}}{1\ \mathrm{u}}\right) = 5.0082 \times 10^{-27}\ \mathrm{kg/atom} ] and the half-life is 12.33 y (from Appendix B), so we can determine the original mass of tritium: [ m = \frac{R t_{1/2} M}{0.693} \quad \text{or} \quad m = \frac{(15.0\ \mathrm{Ci})(12.33\ \mathrm{y})(5.0082\times 10^{-27}\ \mathrm{kg}) M}{0.693} \left(\frac{3.70 \times 10^{10}\ \mathrm{Bq}}{1\ \mathrm{Ci}}\right) \left(\frac{3.156\times10^7\ \mathrm{s}}{1\ \mathrm{y}}\right) = 1.56\times10^{-6}\ \mathrm{kg} = \underline{1.56\ \mathrm{mg}} ] [ \text{(b)}\quad R = R_0 e^{-\lambda t} = R_0 \exp\left[-\frac{0.693}{t_{1/2}} t \right] = (15.0\ \mathrm{Ci}) \exp\left[-\frac{0.693(5.00\ \mathrm{y})}{12.33\ \mathrm{y}} \right] = \underline{11.3\ \mathrm{Ci}} ] Example 3: *A neutron generator uses an (\alpha) source, such as radium, to bombard beryllium, inducing the reaction (^4\mathrm{He} + ^9\mathrm{Be} \rightarrow ^{12}\mathrm{C} + n). Such neutron sources are called RaBe sources, or PuBe sources if they use plutonium to get the (\alpha)s. Calculate the energy output of the reaction in MeV.c* **Solution** Using (E = \Delta mc^2), we can determine the energy output of the reaction by calculating the change in mass of the constituents in the reaction, where the masses are found either in Appendix A or Table 31.2: [ E = (m_i - m_f)c^2 = (4.002603 + 9.02182 - 12.000000 - 1.008665)(931.5\ \mathrm{MeV}) = \underline{5.701\ \mathrm{MeV}} ] | E26: TRUE | F26: 1.24 | G26: E=\frac{hc}{\lambda} | H26: MeV | J26: {"final_numeric":1.24,"final_formula":"E=\\frac{hc}{\\lambda}","final_units":"MeV"} | K26: {'id': 'gen-1780488599-Wb8HXvwQgYwWrqpr3Cb1', 'object': 'chat.completion', 'created': 1780488599, 'model': 'anthropic/claude-4.7-opus-20260416', 'provider': 'Anthropic', 'system_fingerprint': None, 'service_tier': 'default', 'choices': [{'index': 0, 'logprobs': None, 'finish_reason': 'stop', 'native_finish_reason': 'end_turn', 'message': {'role': 'assistant', 'content': '{"final_numeric":1.24,"final_formula":"E=\\\\frac{hc}{\\\\lambda}","final_units":"MeV"}', 'refusal': None, 'reasoning': None}}], 'usage': {'prompt_tokens': 2548, 'completion_tokens': 51, 'total_tokens': 2599, 'cost': 0.014015, 'is_byok': False, 'prompt_tokens_details': {'cached_tokens': 0, 'cache_write_tokens': 0, 'audio_tokens': 0, 'video_tokens': 0}, 'cost_details': {'upstream_inference_cost': 0.014015, 'upstream_inference_prompt_cost': 0.01274, 'upstream_inference_completions_cost': 0.001275}, 'completion_tokens_details': {'reasoning_tokens': 0, 'image_tokens': 0, 'audio_tokens': 0}}} | L26: 2548 | M26: 51 | N26: 2599 | O26: 0 | P26: =VLOOKUP(C26,problems!$A$2:$B$26,2) -> nuclear | Q26: =IFERROR(__xludf.DUMMYFUNCTION("INDEX(FILTER('stats2-openrouter_activity_2026'!C:C,L26='stats2-openrouter_activity_2026'!H:H,M26='stats2-openrouter_activity_2026'!I:I, B26='stats2-openrouter_activity_2026'!M:M),1)"),0.014015) -> 0.014015 | R26: =IFS( F26=VLOOKUP($C26,problems!$A$2:$G$26,6),1, True,0 ) -> 1 | S26: =IFS( G26=VLOOKUP($C26,problems!$A$2:$G$26,4),1, G26=VLOOKUP($C26,problems!$A$2:$G$26,5),1, True,0 ) -> 0 | T26: =IFS( H26=VLOOKUP($C26,problems!$A$2:$G$26,7),1, True,0 ) -> 1
A27: 2026-06-03-13-14-26 | B27: anthropic/claude-sonnet-4.5 | C27: 1 | D27: Частица пролетает расстояние l = 2 м равномерно, а затем тормозит с ускорением а = 5*10^5 м/с^2. При какой скорости частицы время движения ее от вылета до остановки будет наименьшим? Examples: Example 1: Calculate the height of a cliff if it takes 2.35 s for a rock to hit the ground when it is thrown straight up from the cliff with an initial velocity of 8.00 m/s. (b) How long would it take to reach the ground if it is thrown straight down with the same speed?* Solution s ↑ y₀ = ? ////| /\ | / \ | / \ | / ↓ | / | |______/________|____ y = 0 m (a) Knowns: \(t = 2.35\ \text{s}; y = 0\ \text{m}; v_0 = +8.00\ \text{m/s}; a = -9.8\ \text{m/s}^2\) Since we know \(t\), \(y\), \(v_0\), and \(a\) and want to find \(y_0\), we can use the equation \[ y = y_0 + v_0t + \frac{1}{2}at^2. \] \[ y = (0\ \text{m}) + (+8.00\ \text{m/s})(2.35\ \text{s}) + \frac{1}{2}(-9.80\ \text{m/s}^2)(2.35\ \text{s})^2 = -8.26\ \text{m}, \text{ so the cliff is} \] <u>8.26 m</u> high. (b) Knowns: \(y = 0\ \text{m}; y_0 = 8.26\ \text{m}; v_0 = -8.00\ \text{m/s}; a = -9.80\ \text{m/s}^2\) Now we know \(y\), \(y_0\), \(v_0\), and \(a\) and want to find \(t\), so we use the equation \[ y = y_0 + v_0t + \frac{1}{2}at^2 \] again. Rearranging, \[ t = \frac{-v_0 \pm \sqrt{v_0^2 - 4(0.5a)(y_0 - y)}}{2(0.5a)} \] \[ t = \frac{-(-8.00\ \text{m/s}) \pm \sqrt{(-8.00\ \text{m/s})^2 + 2(9.80\ \text{m/s}^2)(8.26\ \text{m} - 0\ \text{m})}}{(-9.80\ \text{m/s}^2)} \] \[ = \frac{8.00\ \text{m/s} \pm 15.03\ \text{m/s}}{-9.80\ \text{m/s}^2} \] \[ t = 0.717\ \text{s} \text{ or } -2.35\ \text{s} \Rightarrow t = \underline{0.717\ \text{s}} \] Example 2: *Calculate the force a 70.0-kg high jumper must exert on the ground to produce an upward acceleration 4.00 times the acceleration due to gravity. Explicitly show how you follow the steps in the Problem-Solving Strategy for Newton’s laws of motion.* Solution Step 1. Use Newton’s Laws of Motion. ↑ F | | (m) ↑ a | ↓ w Force acting on the high jumper. Step 2. Given: \(a = 4.00\ g = (4.00)(9.80\ \text{m/s}^2) = 39.2\ \text{m/s}^2;\ m = 70.0\ \text{kg}\) Find \(F\). Step 3. \(\sum F = +F - w = ma,\) so that \(F = ma + w = ma + mg = m(a + g)\) \[ F = (70.0\ \text{kg})[(39.2\ \text{m/s}^2) + (9.80\ \text{m/s}^2)] = \underline{3.43 \times 10^3\ \text{N}} \] The force exerted by the high-jumper is actually down on the ground, but F is up from the ground to help him jump. Step 4. This result is reasonable, since it is quite possible for a person to exert a force of the magnitude of \(10^3\ \text{N}\). Example 3: *A shopper pushes a grocery cart 20.0 m at constant speed on level ground, against a 35.0 N frictional force. He pushes in a direction 25.0° below the horizontal. (a) What is the work done on the cart by friction? (b) What is the work done on the cart by the gravitational force? (c) What is the work done on the cart by the shopper? (d) Find the force the shopper exerts, using energy considerations. (e) What is the total work done on the cart?* Solution (a) The work done by friction is in the opposite direction of the motion, so \(\theta = 180^\circ\), and therefore \(W_f = Fd \cos\theta = 35.0\ \text{N} \times 20.0\ \text{m} \times \cos 180^\circ = \underline{-700\ \text{J}}\) (b) The work done by gravity is perpendicular to the direction of motion, so \(\theta = 90^\circ\), and \(W_g = Fd \cos\theta = 35.0\ \text{N} \times 20.0\ \text{m} \times \cos 90^\circ = \underline{0\ \text{J}}\) (c) If the cart moves at a constant speed, no energy is transferred to it, from the work-energy theorem: \(\text{net } W = W_s + W_f = 0,\) or \(W_s = \underline{700\ \text{J}}\) (d) Use the equation \(W_s = Fd \cos\theta\), where \(\theta = 25^\circ\), and solve for the force: \[ F = \frac{W_s}{d \cos\theta} = \frac{700\ \text{J}}{20.0\ \text{m} \times \cos 25^\circ} = 38.62\ \text{N} = \underline{38.6\ \text{N}} \] (e) Since there is no change in speed, the work energy theorem says that there is no net work done on the cart: \(\text{net } W = W_f + W_s = -700\ \text{J} + 700\ \text{J} = \underline{0\ \text{J}}\) | E27: TRUE | F27: 1000 | G27: v = \sqrt{la} = \sqrt{2 \times 5 \times 10^5} = 1000 | H27: m/s | J27: I need to find the velocity at which the total time from launch to stop is minimized. **Given:** - Distance traveled uniformly: l = 2 m - Deceleration: a = 5×10⁵ m/s² **Solution:** The particle moves in two phases: 1. Uniform motion at velocity v over distance l 2. Deceleration from velocity v to rest **Phase 1 (uniform motion):** - Time: t₁ = l/v **Phase 2 (deceleration):** Using the kinematic equation: v² = v₀² + 2as For stopping: 0 = v² - 2a·s₂ Where s₂ is the braking distance: s₂ = v²/(2a) Time for braking using v = v₀ + at: 0 = v - a·t₂ So: t₂ = v/a **Total time:** T = t₁ + t₂ = l/v + v/a **To minimize, take derivative and set to zero:** dT/dv = -l/v² + 1/a = 0 Solving for v: 1/a = l/v² v² = la v = √(la) **Substituting values:** v = √(2 m × 5×10⁵ m/s²) v = √(10⁶ m²/s²) v = 10³ m/s v = 1000 m/s **Verification (second derivative):** d²T/dv² = 2l/v³ > 0, confirming this is a minimum. { "final_numeric": 1000, "final_formula": "v = \\sqrt{la} = \\sqrt{2 \\times 5 \\times 10^5} = 1000", "final_units": "m/s" } | K27: {'id': 'gen-1780478058-iTDtLqA687WRLB15dCOP', 'object': 'chat.completion', 'created': 1780478058, 'model': 'anthropic/claude-4.5-sonnet-20250929', 'provider': 'Amazon Bedrock', 'system_fingerprint': None, 'service_tier': None, 'choices': [{'index': 0, 'logprobs': None, 'finish_reason': 'stop', 'native_finish_reason': 'end_turn', 'message': {'role': 'assistant', 'content': 'I need to find the velocity at which the total time from launch to stop is minimized.\n\n**Given:**\n- Distance traveled uniformly: l = 2 m\n- Deceleration: a = 5×10⁵ m/s²\n\n**Solution:**\n\nThe particle moves in two phases:\n1. Uniform motion at velocity v over distance l\n2. Deceleration from velocity v to rest\n\n**Phase 1 (uniform motion):**\n- Time: t₁ = l/v\n\n**Phase 2 (deceleration):**\nUsing the kinematic equation: v² = v₀² + 2as\n\nFor stopping: 0 = v² - 2a·s₂\n\nWhere s₂ is the braking distance: s₂ = v²/(2a)\n\nTime for braking using v = v₀ + at:\n0 = v - a·t₂\n\nSo: t₂ = v/a\n\n**Total time:**\nT = t₁ + t₂ = l/v + v/a\n\n**To minimize, take derivative and set to zero:**\ndT/dv = -l/v² + 1/a = 0\n\nSolving for v:\n1/a = l/v²\n\nv² = la\n\nv = √(la)\n\n**Substituting values:**\nv = √(2 m × 5×10⁵ m/s²)\nv = √(10⁶ m²/s²)\nv = 10³ m/s\nv = 1000 m/s\n\n**Verification (second derivative):**\nd²T/dv² = 2l/v³ > 0, confirming this is a minimum.\n\n{\n "final_numeric": 1000,\n "final_formula": "v = \\\\sqrt{la} = \\\\sqrt{2 \\\\times 5 \\\\times 10^5} = 1000",\n "final_units": "m/s"\n}', 'refusal': None, 'reasoning': None}}], 'usage': {'prompt_tokens': 2376, 'completion_tokens': 481, 'total_tokens': 2857, 'cost': 0.014343, 'is_byok': False, 'prompt_tokens_details': {'cached_tokens': 0, 'cache_write_tokens': 0, 'audio_tokens': 0, 'video_tokens': 0}, 'cost_details': {'upstream_inference_cost': 0.014343, 'upstream_inference_prompt_cost': 0.007128, 'upstream_inference_completions_cost': 0.007215}, 'completion_tokens_details': {'reasoning_tokens': 0, 'image_tokens': 0, 'audio_tokens': 0}}} | L27: 2376 | M27: 481 | N27: 2857 | O27: 0 | P27: =VLOOKUP(C27,problems!$A$2:$B$26,2) -> mechanics | Q27: =IFERROR(__xludf.DUMMYFUNCTION("INDEX(FILTER('stats2-openrouter_activity_2026'!C:C,L27='stats2-openrouter_activity_2026'!H:H,M27='stats2-openrouter_activity_2026'!I:I, B27='stats2-openrouter_activity_2026'!M:M),1)"),0.014343) -> 0.014343 | R27: =IFS( F27=VLOOKUP($C27,problems!$A$2:$G$26,6),1, True,0 ) -> 1 | S27: =IFS( G27=VLOOKUP($C27,problems!$A$2:$G$26,4),1, G27=VLOOKUP($C27,problems!$A$2:$G$26,5),1, True,0 ) -> 0 | T27: =IFS( H27=VLOOKUP($C27,problems!$A$2:$G$26,7),1, True,0 ) -> 1
A28: 2026-06-03-13-17-18 | B28: anthropic/claude-sonnet-4.5 | C28: 2 | D28: Точка движется по прямой согласно закону х = At + Bt^3, где А = 6 м/с; В = -0,125 м/с^3. Определить: среднюю скорость точки в интервале времени от t_{1} = 2 с до t_{2} = 6 с; Examples: Example 1: Calculate the height of a cliff if it takes 2.35 s for a rock to hit the ground when it is thrown straight up from the cliff with an initial velocity of 8.00 m/s. (b) How long would it take to reach the ground if it is thrown straight down with the same speed?* Solution s ↑ y₀ = ? ////| /\ | / \ | / \ | / ↓ | / | |______/________|____ y = 0 m (a) Knowns: \(t = 2.35\ \text{s}; y = 0\ \text{m}; v_0 = +8.00\ \text{m/s}; a = -9.8\ \text{m/s}^2\) Since we know \(t\), \(y\), \(v_0\), and \(a\) and want to find \(y_0\), we can use the equation \[ y = y_0 + v_0t + \frac{1}{2}at^2. \] \[ y = (0\ \text{m}) + (+8.00\ \text{m/s})(2.35\ \text{s}) + \frac{1}{2}(-9.80\ \text{m/s}^2)(2.35\ \text{s})^2 = -8.26\ \text{m}, \text{ so the cliff is} \] <u>8.26 m</u> high. (b) Knowns: \(y = 0\ \text{m}; y_0 = 8.26\ \text{m}; v_0 = -8.00\ \text{m/s}; a = -9.80\ \text{m/s}^2\) Now we know \(y\), \(y_0\), \(v_0\), and \(a\) and want to find \(t\), so we use the equation \[ y = y_0 + v_0t + \frac{1}{2}at^2 \] again. Rearranging, \[ t = \frac{-v_0 \pm \sqrt{v_0^2 - 4(0.5a)(y_0 - y)}}{2(0.5a)} \] \[ t = \frac{-(-8.00\ \text{m/s}) \pm \sqrt{(-8.00\ \text{m/s})^2 + 2(9.80\ \text{m/s}^2)(8.26\ \text{m} - 0\ \text{m})}}{(-9.80\ \text{m/s}^2)} \] \[ = \frac{8.00\ \text{m/s} \pm 15.03\ \text{m/s}}{-9.80\ \text{m/s}^2} \] \[ t = 0.717\ \text{s} \text{ or } -2.35\ \text{s} \Rightarrow t = \underline{0.717\ \text{s}} \] Example 2: *Calculate the force a 70.0-kg high jumper must exert on the ground to produce an upward acceleration 4.00 times the acceleration due to gravity. Explicitly show how you follow the steps in the Problem-Solving Strategy for Newton’s laws of motion.* Solution Step 1. Use Newton’s Laws of Motion. ↑ F | | (m) ↑ a | ↓ w Force acting on the high jumper. Step 2. Given: \(a = 4.00\ g = (4.00)(9.80\ \text{m/s}^2) = 39.2\ \text{m/s}^2;\ m = 70.0\ \text{kg}\) Find \(F\). Step 3. \(\sum F = +F - w = ma,\) so that \(F = ma + w = ma + mg = m(a + g)\) \[ F = (70.0\ \text{kg})[(39.2\ \text{m/s}^2) + (9.80\ \text{m/s}^2)] = \underline{3.43 \times 10^3\ \text{N}} \] The force exerted by the high-jumper is actually down on the ground, but F is up from the ground to help him jump. Step 4. This result is reasonable, since it is quite possible for a person to exert a force of the magnitude of \(10^3\ \text{N}\). Example 3: *A shopper pushes a grocery cart 20.0 m at constant speed on level ground, against a 35.0 N frictional force. He pushes in a direction 25.0° below the horizontal. (a) What is the work done on the cart by friction? (b) What is the work done on the cart by the gravitational force? (c) What is the work done on the cart by the shopper? (d) Find the force the shopper exerts, using energy considerations. (e) What is the total work done on the cart?* Solution (a) The work done by friction is in the opposite direction of the motion, so \(\theta = 180^\circ\), and therefore \(W_f = Fd \cos\theta = 35.0\ \text{N} \times 20.0\ \text{m} \times \cos 180^\circ = \underline{-700\ \text{J}}\) (b) The work done by gravity is perpendicular to the direction of motion, so \(\theta = 90^\circ\), and \(W_g = Fd \cos\theta = 35.0\ \text{N} \times 20.0\ \text{m} \times \cos 90^\circ = \underline{0\ \text{J}}\) (c) If the cart moves at a constant speed, no energy is transferred to it, from the work-energy theorem: \(\text{net } W = W_s + W_f = 0,\) or \(W_s = \underline{700\ \text{J}}\) (d) Use the equation \(W_s = Fd \cos\theta\), where \(\theta = 25^\circ\), and solve for the force: \[ F = \frac{W_s}{d \cos\theta} = \frac{700\ \text{J}}{20.0\ \text{m} \times \cos 25^\circ} = 38.62\ \text{N} = \underline{38.6\ \text{N}} \] (e) Since there is no change in speed, the work energy theorem says that there is no net work done on the cart: \(\text{net } W = W_f + W_s = -700\ \text{J} + 700\ \text{J} = \underline{0\ \text{J}}\) | E28: TRUE | F28: -0.5 | G28: v_{avg} = \\frac{x(t_2) - x(t_1)}{t_2 - t_1} = \\frac{9 - 11}{6 - 2} = -0.5 | H28: m/s | J28: I need to find the average velocity of a point moving according to the law x = At + Bt³, where A = 6 m/s and B = -0.125 m/s³, in the time interval from t₁ = 2 s to t₂ = 6 s. The average velocity is defined as: $$v_{avg} = \frac{x(t_2) - x(t_1)}{t_2 - t_1}$$ First, I'll calculate x(t₁) at t₁ = 2 s: $$x(t_1) = A t_1 + B t_1^3 = 6 \times 2 + (-0.125) \times 2^3$$ $$x(t_1) = 12 + (-0.125) \times 8 = 12 - 1 = 11 \text{ m}$$ Next, I'll calculate x(t₂) at t₂ = 6 s: $$x(t_2) = A t_2 + B t_2^3 = 6 \times 6 + (-0.125) \times 6^3$$ $$x(t_2) = 36 + (-0.125) \times 216 = 36 - 27 = 9 \text{ m}$$ Now I can calculate the average velocity: $$v_{avg} = \frac{x(t_2) - x(t_1)}{t_2 - t_1} = \frac{9 - 11}{6 - 2} = \frac{-2}{4} = -0.5 \text{ m/s}$$ { "final_numeric": -0.5, "final_formula": "v_{avg} = \\frac{x(t_2) - x(t_1)}{t_2 - t_1} = \\frac{9 - 11}{6 - 2} = -0.5", "final_units": "m/s" } | K28: {'id': 'gen-1780478232-flAsXl2yG3AjKtCf6Oho', 'object': 'chat.completion', 'created': 1780478232, 'model': 'anthropic/claude-4.5-sonnet-20250929', 'provider': 'Amazon Bedrock', 'system_fingerprint': None, 'service_tier': None, 'choices': [{'index': 0, 'logprobs': None, 'finish_reason': 'stop', 'native_finish_reason': 'end_turn', 'message': {'role': 'assistant', 'content': 'I need to find the average velocity of a point moving according to the law x = At + Bt³, where A = 6 m/s and B = -0.125 m/s³, in the time interval from t₁ = 2 s to t₂ = 6 s.\n\nThe average velocity is defined as:\n$$v_{avg} = \\frac{x(t_2) - x(t_1)}{t_2 - t_1}$$\n\nFirst, I\'ll calculate x(t₁) at t₁ = 2 s:\n$$x(t_1) = A t_1 + B t_1^3 = 6 \\times 2 + (-0.125) \\times 2^3$$\n$$x(t_1) = 12 + (-0.125) \\times 8 = 12 - 1 = 11 \\text{ m}$$\n\nNext, I\'ll calculate x(t₂) at t₂ = 6 s:\n$$x(t_2) = A t_2 + B t_2^3 = 6 \\times 6 + (-0.125) \\times 6^3$$\n$$x(t_2) = 36 + (-0.125) \\times 216 = 36 - 27 = 9 \\text{ m}$$\n\nNow I can calculate the average velocity:\n$$v_{avg} = \\frac{x(t_2) - x(t_1)}{t_2 - t_1} = \\frac{9 - 11}{6 - 2} = \\frac{-2}{4} = -0.5 \\text{ m/s}$$\n\n{\n "final_numeric": -0.5,\n "final_formula": "v_{avg} = \\\\frac{x(t_2) - x(t_1)}{t_2 - t_1} = \\\\frac{9 - 11}{6 - 2} = -0.5",\n "final_units": "m/s"\n}', 'refusal': None, 'reasoning': None}}], 'usage': {'prompt_tokens': 2383, 'completion_tokens': 509, 'total_tokens': 2892, 'cost': 0.014784, 'is_byok': False, 'prompt_tokens_details': {'cached_tokens': 0, 'cache_write_tokens': 0, 'audio_tokens': 0, 'video_tokens': 0}, 'cost_details': {'upstream_inference_cost': 0.014784, 'upstream_inference_prompt_cost': 0.007149, 'upstream_inference_completions_cost': 0.007635}, 'completion_tokens_details': {'reasoning_tokens': 0, 'image_tokens': 0, 'audio_tokens': 0}}} | L28: 2383 | M28: 509 | N28: 2892 | O28: 0 | P28: =VLOOKUP(C28,problems!$A$2:$B$26,2) -> mechanics | Q28: =IFERROR(__xludf.DUMMYFUNCTION("INDEX(FILTER('stats2-openrouter_activity_2026'!C:C,L28='stats2-openrouter_activity_2026'!H:H,M28='stats2-openrouter_activity_2026'!I:I, B28='stats2-openrouter_activity_2026'!M:M),1)"),0.014784) -> 0.014784 | R28: =IFS( F28=VLOOKUP($C28,problems!$A$2:$G$26,6),1, True,0 ) -> 1 | S28: =IFS( G28=VLOOKUP($C28,problems!$A$2:$G$26,4),1, G28=VLOOKUP($C28,problems!$A$2:$G$26,5),1, True,0 ) -> 0 | T28: =IFS( H28=VLOOKUP($C28,problems!$A$2:$G$26,7),1, True,0 ) -> 1
A29: 2026-06-03-13-20-59 | B29: anthropic/claude-sonnet-4.5 | C29: 3 | D29: A truck is traveling east at 80 km/h. At an intersection 32 km ahead, a car is traveling north at 50 km/h. How long in hours after this moment will the vehicles be closest to each other? Examples: Example 1: Calculate the height of a cliff if it takes 2.35 s for a rock to hit the ground when it is thrown straight up from the cliff with an initial velocity of 8.00 m/s. (b) How long would it take to reach the ground if it is thrown straight down with the same speed?* Solution s ↑ y₀ = ? ////| /\ | / \ | / \ | / ↓ | / | |______/________|____ y = 0 m (a) Knowns: \(t = 2.35\ \text{s}; y = 0\ \text{m}; v_0 = +8.00\ \text{m/s}; a = -9.8\ \text{m/s}^2\) Since we know \(t\), \(y\), \(v_0\), and \(a\) and want to find \(y_0\), we can use the equation \[ y = y_0 + v_0t + \frac{1}{2}at^2. \] \[ y = (0\ \text{m}) + (+8.00\ \text{m/s})(2.35\ \text{s}) + \frac{1}{2}(-9.80\ \text{m/s}^2)(2.35\ \text{s})^2 = -8.26\ \text{m}, \text{ so the cliff is} \] <u>8.26 m</u> high. (b) Knowns: \(y = 0\ \text{m}; y_0 = 8.26\ \text{m}; v_0 = -8.00\ \text{m/s}; a = -9.80\ \text{m/s}^2\) Now we know \(y\), \(y_0\), \(v_0\), and \(a\) and want to find \(t\), so we use the equation \[ y = y_0 + v_0t + \frac{1}{2}at^2 \] again. Rearranging, \[ t = \frac{-v_0 \pm \sqrt{v_0^2 - 4(0.5a)(y_0 - y)}}{2(0.5a)} \] \[ t = \frac{-(-8.00\ \text{m/s}) \pm \sqrt{(-8.00\ \text{m/s})^2 + 2(9.80\ \text{m/s}^2)(8.26\ \text{m} - 0\ \text{m})}}{(-9.80\ \text{m/s}^2)} \] \[ = \frac{8.00\ \text{m/s} \pm 15.03\ \text{m/s}}{-9.80\ \text{m/s}^2} \] \[ t = 0.717\ \text{s} \text{ or } -2.35\ \text{s} \Rightarrow t = \underline{0.717\ \text{s}} \] Example 2: *Calculate the force a 70.0-kg high jumper must exert on the ground to produce an upward acceleration 4.00 times the acceleration due to gravity. Explicitly show how you follow the steps in the Problem-Solving Strategy for Newton’s laws of motion.* Solution Step 1. Use Newton’s Laws of Motion. ↑ F | | (m) ↑ a | ↓ w Force acting on the high jumper. Step 2. Given: \(a = 4.00\ g = (4.00)(9.80\ \text{m/s}^2) = 39.2\ \text{m/s}^2;\ m = 70.0\ \text{kg}\) Find \(F\). Step 3. \(\sum F = +F - w = ma,\) so that \(F = ma + w = ma + mg = m(a + g)\) \[ F = (70.0\ \text{kg})[(39.2\ \text{m/s}^2) + (9.80\ \text{m/s}^2)] = \underline{3.43 \times 10^3\ \text{N}} \] The force exerted by the high-jumper is actually down on the ground, but F is up from the ground to help him jump. Step 4. This result is reasonable, since it is quite possible for a person to exert a force of the magnitude of \(10^3\ \text{N}\). Example 3: *A shopper pushes a grocery cart 20.0 m at constant speed on level ground, against a 35.0 N frictional force. He pushes in a direction 25.0° below the horizontal. (a) What is the work done on the cart by friction? (b) What is the work done on the cart by the gravitational force? (c) What is the work done on the cart by the shopper? (d) Find the force the shopper exerts, using energy considerations. (e) What is the total work done on the cart?* Solution (a) The work done by friction is in the opposite direction of the motion, so \(\theta = 180^\circ\), and therefore \(W_f = Fd \cos\theta = 35.0\ \text{N} \times 20.0\ \text{m} \times \cos 180^\circ = \underline{-700\ \text{J}}\) (b) The work done by gravity is perpendicular to the direction of motion, so \(\theta = 90^\circ\), and \(W_g = Fd \cos\theta = 35.0\ \text{N} \times 20.0\ \text{m} \times \cos 90^\circ = \underline{0\ \text{J}}\) (c) If the cart moves at a constant speed, no energy is transferred to it, from the work-energy theorem: \(\text{net } W = W_s + W_f = 0,\) or \(W_s = \underline{700\ \text{J}}\) (d) Use the equation \(W_s = Fd \cos\theta\), where \(\theta = 25^\circ\), and solve for the force: \[ F = \frac{W_s}{d \cos\theta} = \frac{700\ \text{J}}{20.0\ \text{m} \times \cos 25^\circ} = 38.62\ \text{N} = \underline{38.6\ \text{N}} \] (e) Since there is no change in speed, the work energy theorem says that there is no net work done on the cart: \(\text{net } W = W_f + W_s = -700\ \text{J} + 700\ \text{J} = \underline{0\ \text{J}}\) | E29: TRUE | F29: 0.288 | G29: \\frac{5120}{17800} = \\frac{128}{445} \\approx 0.288 | H29: h | J29: I need to find when the truck and car will be closest to each other. **Setup:** - Truck: traveling east at 80 km/h, initially 32 km west of the intersection - Car: traveling north at 50 km/h, initially at the intersection **Coordinate System:** Let the intersection be the origin. At time t = 0: - Truck position: (-32, 0) km - Car position: (0, 0) km **Position as a function of time t (in hours):** - Truck: x_T(t) = -32 + 80t, y_T(t) = 0 - Car: x_C(t) = 0, y_C(t) = 50t **Distance between vehicles:** $$D(t) = \sqrt{(x_T - x_C)^2 + (y_T - y_C)^2}$$ $$D(t) = \sqrt{(-32 + 80t)^2 + (50t)^2}$$ $$D(t) = \sqrt{1024 - 5120t + 6400t^2 + 2500t^2}$$ $$D(t) = \sqrt{8900t^2 - 5120t + 1024}$$ **To minimize D(t), minimize D²(t):** $$D^2(t) = 8900t^2 - 5120t + 1024$$ Taking the derivative and setting it to zero: $$\frac{d(D^2)}{dt} = 17800t - 5120 = 0$$ $$t = \frac{5120}{17800} = \frac{512}{1780} = \frac{128}{445}$$ Converting to decimal: $$t = \frac{128}{445} \approx 0.2876 \text{ hours}$$ Let me verify this is correct: $$t = \frac{5120}{17800} = \frac{5120}{17800} = \frac{64}{222.5} = \frac{128}{445}$$ Calculating the exact decimal: $$t = 128 \div 445 = 0.287640...$$ Rounding to appropriate significant figures (3-4 sig figs based on given data): $$t \approx 0.288 \text{ hours}$$ { "final_numeric": 0.288, "final_formula": "\\frac{5120}{17800} = \\frac{128}{445} \\approx 0.288", "final_units": "h" } | K29: {'id': 'gen-1780478450-7reHK9Exwl8PaxY460G5', 'object': 'chat.completion', 'created': 1780478450, 'model': 'anthropic/claude-4.5-sonnet-20250929', 'provider': 'Amazon Bedrock', 'system_fingerprint': None, 'service_tier': None, 'choices': [{'index': 0, 'logprobs': None, 'finish_reason': 'stop', 'native_finish_reason': 'end_turn', 'message': {'role': 'assistant', 'content': 'I need to find when the truck and car will be closest to each other.\n\n**Setup:**\n- Truck: traveling east at 80 km/h, initially 32 km west of the intersection\n- Car: traveling north at 50 km/h, initially at the intersection\n\n**Coordinate System:**\nLet the intersection be the origin. At time t = 0:\n- Truck position: (-32, 0) km\n- Car position: (0, 0) km\n\n**Position as a function of time t (in hours):**\n- Truck: x_T(t) = -32 + 80t, y_T(t) = 0\n- Car: x_C(t) = 0, y_C(t) = 50t\n\n**Distance between vehicles:**\n$$D(t) = \\sqrt{(x_T - x_C)^2 + (y_T - y_C)^2}$$\n$$D(t) = \\sqrt{(-32 + 80t)^2 + (50t)^2}$$\n$$D(t) = \\sqrt{1024 - 5120t + 6400t^2 + 2500t^2}$$\n$$D(t) = \\sqrt{8900t^2 - 5120t + 1024}$$\n\n**To minimize D(t), minimize D²(t):**\n$$D^2(t) = 8900t^2 - 5120t + 1024$$\n\nTaking the derivative and setting it to zero:\n$$\\frac{d(D^2)}{dt} = 17800t - 5120 = 0$$\n\n$$t = \\frac{5120}{17800} = \\frac{512}{1780} = \\frac{128}{445}$$\n\nConverting to decimal:\n$$t = \\frac{128}{445} \\approx 0.2876 \\text{ hours}$$\n\nLet me verify this is correct:\n$$t = \\frac{5120}{17800} = \\frac{5120}{17800} = \\frac{64}{222.5} = \\frac{128}{445}$$\n\nCalculating the exact decimal:\n$$t = 128 \\div 445 = 0.287640...$$\n\nRounding to appropriate significant figures (3-4 sig figs based on given data):\n$$t \\approx 0.288 \\text{ hours}$$\n\n{\n "final_numeric": 0.288,\n "final_formula": "\\\\frac{5120}{17800} = \\\\frac{128}{445} \\\\approx 0.288",\n "final_units": "h"\n}', 'refusal': None, 'reasoning': None}}], 'usage': {'prompt_tokens': 2348, 'completion_tokens': 640, 'total_tokens': 2988, 'cost': 0.016644, 'is_byok': False, 'prompt_tokens_details': {'cached_tokens': 0, 'cache_write_tokens': 0, 'audio_tokens': 0, 'video_tokens': 0}, 'cost_details': {'upstream_inference_cost': 0.016644, 'upstream_inference_prompt_cost': 0.007044, 'upstream_inference_completions_cost': 0.0096}, 'completion_tokens_details': {'reasoning_tokens': 0, 'image_tokens': 0, 'audio_tokens': 0}}} | L29: 2348 | M29: 640 | N29: 2988 | O29: 0 | P29: =VLOOKUP(C29,problems!$A$2:$B$26,2) -> mechanics | Q29: =IFERROR(__xludf.DUMMYFUNCTION("INDEX(FILTER('stats2-openrouter_activity_2026'!C:C,L29='stats2-openrouter_activity_2026'!H:H,M29='stats2-openrouter_activity_2026'!I:I, B29='stats2-openrouter_activity_2026'!M:M),1)"),0.016644) -> 0.016644 | R29: =IFS( F29=VLOOKUP($C29,problems!$A$2:$G$26,6),1, True,0 ) -> 0 | S29: =IFS( G29=VLOOKUP($C29,problems!$A$2:$G$26,4),1, G29=VLOOKUP($C29,problems!$A$2:$G$26,5),1, True,0 ) -> 0 | T29: =IFS( H29=VLOOKUP($C29,problems!$A$2:$G$26,7),1, True,0 ) -> 1
A30: 2026-06-03-13-26-52 | B30: anthropic/claude-sonnet-4.5 | C30: 4 | D30: Закон движения материальной точки имеет вид: х = а_{1} + b_{1}*t + y_{1}*t^2; y = α_{2} + b_{2}*t + y_{2}*t^2, где b_{1} = b_{2} = 1 м/с, y_{1}= -1 м/с^2, y_{2} = 2 м/с^2. Каково ее ускорение? Определить угол между скоростью и ускорением в момент времени t = 1 с. Examples: Example 1: Calculate the height of a cliff if it takes 2.35 s for a rock to hit the ground when it is thrown straight up from the cliff with an initial velocity of 8.00 m/s. (b) How long would it take to reach the ground if it is thrown straight down with the same speed?* Solution s ↑ y₀ = ? ////| /\ | / \ | / \ | / ↓ | / | |______/________|____ y = 0 m (a) Knowns: \(t = 2.35\ \text{s}; y = 0\ \text{m}; v_0 = +8.00\ \text{m/s}; a = -9.8\ \text{m/s}^2\) Since we know \(t\), \(y\), \(v_0\), and \(a\) and want to find \(y_0\), we can use the equation \[ y = y_0 + v_0t + \frac{1}{2}at^2. \] \[ y = (0\ \text{m}) + (+8.00\ \text{m/s})(2.35\ \text{s}) + \frac{1}{2}(-9.80\ \text{m/s}^2)(2.35\ \text{s})^2 = -8.26\ \text{m}, \text{ so the cliff is} \] <u>8.26 m</u> high. (b) Knowns: \(y = 0\ \text{m}; y_0 = 8.26\ \text{m}; v_0 = -8.00\ \text{m/s}; a = -9.80\ \text{m/s}^2\) Now we know \(y\), \(y_0\), \(v_0\), and \(a\) and want to find \(t\), so we use the equation \[ y = y_0 + v_0t + \frac{1}{2}at^2 \] again. Rearranging, \[ t = \frac{-v_0 \pm \sqrt{v_0^2 - 4(0.5a)(y_0 - y)}}{2(0.5a)} \] \[ t = \frac{-(-8.00\ \text{m/s}) \pm \sqrt{(-8.00\ \text{m/s})^2 + 2(9.80\ \text{m/s}^2)(8.26\ \text{m} - 0\ \text{m})}}{(-9.80\ \text{m/s}^2)} \] \[ = \frac{8.00\ \text{m/s} \pm 15.03\ \text{m/s}}{-9.80\ \text{m/s}^2} \] \[ t = 0.717\ \text{s} \text{ or } -2.35\ \text{s} \Rightarrow t = \underline{0.717\ \text{s}} \] Example 2: *Calculate the force a 70.0-kg high jumper must exert on the ground to produce an upward acceleration 4.00 times the acceleration due to gravity. Explicitly show how you follow the steps in the Problem-Solving Strategy for Newton’s laws of motion.* Solution Step 1. Use Newton’s Laws of Motion. ↑ F | | (m) ↑ a | ↓ w Force acting on the high jumper. Step 2. Given: \(a = 4.00\ g = (4.00)(9.80\ \text{m/s}^2) = 39.2\ \text{m/s}^2;\ m = 70.0\ \text{kg}\) Find \(F\). Step 3. \(\sum F = +F - w = ma,\) so that \(F = ma + w = ma + mg = m(a + g)\) \[ F = (70.0\ \text{kg})[(39.2\ \text{m/s}^2) + (9.80\ \text{m/s}^2)] = \underline{3.43 \times 10^3\ \text{N}} \] The force exerted by the high-jumper is actually down on the ground, but F is up from the ground to help him jump. Step 4. This result is reasonable, since it is quite possible for a person to exert a force of the magnitude of \(10^3\ \text{N}\). Example 3: *A shopper pushes a grocery cart 20.0 m at constant speed on level ground, against a 35.0 N frictional force. He pushes in a direction 25.0° below the horizontal. (a) What is the work done on the cart by friction? (b) What is the work done on the cart by the gravitational force? (c) What is the work done on the cart by the shopper? (d) Find the force the shopper exerts, using energy considerations. (e) What is the total work done on the cart?* Solution (a) The work done by friction is in the opposite direction of the motion, so \(\theta = 180^\circ\), and therefore \(W_f = Fd \cos\theta = 35.0\ \text{N} \times 20.0\ \text{m} \times \cos 180^\circ = \underline{-700\ \text{J}}\) (b) The work done by gravity is perpendicular to the direction of motion, so \(\theta = 90^\circ\), and \(W_g = Fd \cos\theta = 35.0\ \text{N} \times 20.0\ \text{m} \times \cos 90^\circ = \underline{0\ \text{J}}\) (c) If the cart moves at a constant speed, no energy is transferred to it, from the work-energy theorem: \(\text{net } W = W_s + W_f = 0,\) or \(W_s = \underline{700\ \text{J}}\) (d) Use the equation \(W_s = Fd \cos\theta\), where \(\theta = 25^\circ\), and solve for the force: \[ F = \frac{W_s}{d \cos\theta} = \frac{700\ \text{J}}{20.0\ \text{m} \times \cos 25^\circ} = 38.62\ \text{N} = \underline{38.6\ \text{N}} \] (e) Since there is no change in speed, the work energy theorem says that there is no net work done on the cart: \(\text{net } W = W_f + W_s = -700\ \text{J} + 700\ \text{J} = \underline{0\ \text{J}}\) | E30: TRUE | F30: 15.5 | G30: \theta = \arccos\left(\frac{11}{\sqrt{130}}\right) \approx 15.5^\circ, \quad |a| = 2\sqrt{5} \text{ m/s}^2 \approx 4.47 \text{ m/s}^2 | H30: degree | J30: Looking at this problem, I need to find: 1. The acceleration of the material point 2. The angle between velocity and acceleration at t = 1 s Given: - x = a₁ + b₁t + γ₁t² - y = a₂ + b₂t + γ₂t² - b₁ = b₂ = 1 m/s - γ₁ = -1 m/s² - γ₂ = 2 m/s² **Step 1: Find acceleration** Velocity components: - vₓ = dx/dt = b₁ + 2γ₁t = 1 - 2t - vᵧ = dy/dt = b₂ + 2γ₂t = 1 + 4t Acceleration components: - aₓ = dvₓ/dt = 2γ₁ = 2(-1) = -2 m/s² - aᵧ = dvᵧ/dt = 2γ₂ = 2(2) = 4 m/s² Magnitude of acceleration: |a| = √(aₓ² + aᵧ²) = √((-2)² + 4²) = √(4 + 16) = √20 = 2√5 m/s² **Step 2: Find angle at t = 1 s** At t = 1 s: - vₓ(1) = 1 - 2(1) = -1 m/s - vᵧ(1) = 1 + 4(1) = 5 m/s The angle between velocity and acceleration: cos(θ) = (v⃗ · a⃗)/(|v⃗||a⃗|) v⃗ · a⃗ = vₓaₓ + vᵧaᵧ = (-1)(-2) + (5)(4) = 2 + 20 = 22 |v⃗| = √((-1)² + 5²) = √26 |a⃗| = 2√5 cos(θ) = 22/(√26 · 2√5) = 22/(2√130) = 11/√130 θ = arccos(11/√130) ≈ 15.5° The problem asks for two things: acceleration and the angle. Since the problem structure suggests a combined answer, I'll provide the angle as the final answer (the more specific calculation requested). { "final_numeric": 15.5, "final_formula": "\\theta = \\arccos\\left(\\frac{11}{\\sqrt{130}}\\right) \\approx 15.5^\\circ, \\quad |a| = 2\\sqrt{5} \\text{ m/s}^2 \\approx 4.47 \\text{ m/s}^2", "final_units": "degree" } | K30: {'id': 'gen-1780478803-CNnJLoCPptppHHoclxmF', 'object': 'chat.completion', 'created': 1780478803, 'model': 'anthropic/claude-4.5-sonnet-20250929', 'provider': 'Amazon Bedrock', 'system_fingerprint': None, 'service_tier': None, 'choices': [{'index': 0, 'logprobs': None, 'finish_reason': 'stop', 'native_finish_reason': 'end_turn', 'message': {'role': 'assistant', 'content': 'Looking at this problem, I need to find:\n1. The acceleration of the material point\n2. The angle between velocity and acceleration at t = 1 s\n\nGiven:\n- x = a₁ + b₁t + γ₁t²\n- y = a₂ + b₂t + γ₂t²\n- b₁ = b₂ = 1 m/s\n- γ₁ = -1 m/s²\n- γ₂ = 2 m/s²\n\n**Step 1: Find acceleration**\n\nVelocity components:\n- vₓ = dx/dt = b₁ + 2γ₁t = 1 - 2t\n- vᵧ = dy/dt = b₂ + 2γ₂t = 1 + 4t\n\nAcceleration components:\n- aₓ = dvₓ/dt = 2γ₁ = 2(-1) = -2 m/s²\n- aᵧ = dvᵧ/dt = 2γ₂ = 2(2) = 4 m/s²\n\nMagnitude of acceleration:\n|a| = √(aₓ² + aᵧ²) = √((-2)² + 4²) = √(4 + 16) = √20 = 2√5 m/s²\n\n**Step 2: Find angle at t = 1 s**\n\nAt t = 1 s:\n- vₓ(1) = 1 - 2(1) = -1 m/s\n- vᵧ(1) = 1 + 4(1) = 5 m/s\n\nThe angle between velocity and acceleration:\ncos(θ) = (v⃗ · a⃗)/(|v⃗||a⃗|)\n\nv⃗ · a⃗ = vₓaₓ + vᵧaᵧ = (-1)(-2) + (5)(4) = 2 + 20 = 22\n\n|v⃗| = √((-1)² + 5²) = √26\n\n|a⃗| = 2√5\n\ncos(θ) = 22/(√26 · 2√5) = 22/(2√130) = 11/√130\n\nθ = arccos(11/√130) ≈ 15.5°\n\nThe problem asks for two things: acceleration and the angle. Since the problem structure suggests a combined answer, I\'ll provide the angle as the final answer (the more specific calculation requested).\n\n{\n "final_numeric": 15.5,\n "final_formula": "\\\\theta = \\\\arccos\\\\left(\\\\frac{11}{\\\\sqrt{130}}\\\\right) \\\\approx 15.5^\\\\circ, \\\\quad |a| = 2\\\\sqrt{5} \\\\text{ m/s}^2 \\\\approx 4.47 \\\\text{ m/s}^2",\n "final_units": "degree"\n}', 'refusal': None, 'reasoning': None}}], 'usage': {'prompt_tokens': 2442, 'completion_tokens': 758, 'total_tokens': 3200, 'cost': 0.018696, 'is_byok': False, 'prompt_tokens_details': {'cached_tokens': 0, 'cache_write_tokens': 0, 'audio_tokens': 0, 'video_tokens': 0}, 'cost_details': {'upstream_inference_cost': 0.018696, 'upstream_inference_prompt_cost': 0.007326, 'upstream_inference_completions_cost': 0.01137}, 'completion_tokens_details': {'reasoning_tokens': 0, 'image_tokens': 0, 'audio_tokens': 0}}} | L30: 2442 | M30: 758 | N30: 3200 | O30: 0 | P30: =VLOOKUP(C30,problems!$A$2:$B$26,2) -> mechanics | Q30: =IFERROR(__xludf.DUMMYFUNCTION("INDEX(FILTER('stats2-openrouter_activity_2026'!C:C,L30='stats2-openrouter_activity_2026'!H:H,M30='stats2-openrouter_activity_2026'!I:I, B30='stats2-openrouter_activity_2026'!M:M),1)"),0.018696) -> 0.018696 | R30: =IFS( F30=VLOOKUP($C30,problems!$A$2:$G$26,6),1, True,0 ) -> 0 | S30: =IFS( G30=VLOOKUP($C30,problems!$A$2:$G$26,4),1, G30=VLOOKUP($C30,problems!$A$2:$G$26,5),1, True,0 ) -> 0 | T30: =IFS( H30=VLOOKUP($C30,problems!$A$2:$G$26,7),1, True,0 ) -> 0
A31: 2026-06-03-13-31-01 | B31: anthropic/claude-sonnet-4.5 | C31: 5 | D31: A crate is being pushed across a rough floor surface. If no force is applied on the crate, the crate will slow down and come to a stop. If the crate of mass 50 kg moving at speed 8 m/s comes to rest in 10 seconds, what is the rate at which the frictional force on the crate takes energy away from the crate? Examples: Example 1: Calculate the height of a cliff if it takes 2.35 s for a rock to hit the ground when it is thrown straight up from the cliff with an initial velocity of 8.00 m/s. (b) How long would it take to reach the ground if it is thrown straight down with the same speed?* Solution s ↑ y₀ = ? ////| /\ | / \ | / \ | / ↓ | / | |______/________|____ y = 0 m (a) Knowns: \(t = 2.35\ \text{s}; y = 0\ \text{m}; v_0 = +8.00\ \text{m/s}; a = -9.8\ \text{m/s}^2\) Since we know \(t\), \(y\), \(v_0\), and \(a\) and want to find \(y_0\), we can use the equation \[ y = y_0 + v_0t + \frac{1}{2}at^2. \] \[ y = (0\ \text{m}) + (+8.00\ \text{m/s})(2.35\ \text{s}) + \frac{1}{2}(-9.80\ \text{m/s}^2)(2.35\ \text{s})^2 = -8.26\ \text{m}, \text{ so the cliff is} \] <u>8.26 m</u> high. (b) Knowns: \(y = 0\ \text{m}; y_0 = 8.26\ \text{m}; v_0 = -8.00\ \text{m/s}; a = -9.80\ \text{m/s}^2\) Now we know \(y\), \(y_0\), \(v_0\), and \(a\) and want to find \(t\), so we use the equation \[ y = y_0 + v_0t + \frac{1}{2}at^2 \] again. Rearranging, \[ t = \frac{-v_0 \pm \sqrt{v_0^2 - 4(0.5a)(y_0 - y)}}{2(0.5a)} \] \[ t = \frac{-(-8.00\ \text{m/s}) \pm \sqrt{(-8.00\ \text{m/s})^2 + 2(9.80\ \text{m/s}^2)(8.26\ \text{m} - 0\ \text{m})}}{(-9.80\ \text{m/s}^2)} \] \[ = \frac{8.00\ \text{m/s} \pm 15.03\ \text{m/s}}{-9.80\ \text{m/s}^2} \] \[ t = 0.717\ \text{s} \text{ or } -2.35\ \text{s} \Rightarrow t = \underline{0.717\ \text{s}} \] Example 2: *Calculate the force a 70.0-kg high jumper must exert on the ground to produce an upward acceleration 4.00 times the acceleration due to gravity. Explicitly show how you follow the steps in the Problem-Solving Strategy for Newton’s laws of motion.* Solution Step 1. Use Newton’s Laws of Motion. ↑ F | | (m) ↑ a | ↓ w Force acting on the high jumper. Step 2. Given: \(a = 4.00\ g = (4.00)(9.80\ \text{m/s}^2) = 39.2\ \text{m/s}^2;\ m = 70.0\ \text{kg}\) Find \(F\). Step 3. \(\sum F = +F - w = ma,\) so that \(F = ma + w = ma + mg = m(a + g)\) \[ F = (70.0\ \text{kg})[(39.2\ \text{m/s}^2) + (9.80\ \text{m/s}^2)] = \underline{3.43 \times 10^3\ \text{N}} \] The force exerted by the high-jumper is actually down on the ground, but F is up from the ground to help him jump. Step 4. This result is reasonable, since it is quite possible for a person to exert a force of the magnitude of \(10^3\ \text{N}\). Example 3: *A shopper pushes a grocery cart 20.0 m at constant speed on level ground, against a 35.0 N frictional force. He pushes in a direction 25.0° below the horizontal. (a) What is the work done on the cart by friction? (b) What is the work done on the cart by the gravitational force? (c) What is the work done on the cart by the shopper? (d) Find the force the shopper exerts, using energy considerations. (e) What is the total work done on the cart?* Solution (a) The work done by friction is in the opposite direction of the motion, so \(\theta = 180^\circ\), and therefore \(W_f = Fd \cos\theta = 35.0\ \text{N} \times 20.0\ \text{m} \times \cos 180^\circ = \underline{-700\ \text{J}}\) (b) The work done by gravity is perpendicular to the direction of motion, so \(\theta = 90^\circ\), and \(W_g = Fd \cos\theta = 35.0\ \text{N} \times 20.0\ \text{m} \times \cos 90^\circ = \underline{0\ \text{J}}\) (c) If the cart moves at a constant speed, no energy is transferred to it, from the work-energy theorem: \(\text{net } W = W_s + W_f = 0,\) or \(W_s = \underline{700\ \text{J}}\) (d) Use the equation \(W_s = Fd \cos\theta\), where \(\theta = 25^\circ\), and solve for the force: \[ F = \frac{W_s}{d \cos\theta} = \frac{700\ \text{J}}{20.0\ \text{m} \times \cos 25^\circ} = 38.62\ \text{N} = \underline{38.6\ \text{N}} \] (e) Since there is no change in speed, the work energy theorem says that there is no net work done on the cart: \(\text{net } W = W_f + W_s = -700\ \text{J} + 700\ \text{J} = \underline{0\ \text{J}}\) | E31: TRUE | F31: 160 | G31: P = \frac{|\Delta KE|}{t} = \frac{\frac{1}{2}mv_0^2}{t} = \frac{\frac{1}{2}(50)(8)^2}{10} = 160\text{ W} | H31: W | J31: I need to find the rate at which the frictional force takes energy away from the crate. This is asking for power. **Given:** - Mass: m = 50 kg - Initial speed: v₀ = 8 m/s - Final speed: v = 0 m/s - Time: t = 10 s **Step 1: Find the acceleration** Using the kinematic equation: v = v₀ + at 0 = 8 + a(10) a = -0.8 m/s² **Step 2: Find the frictional force** Using Newton's second law: F = ma F_friction = 50 kg × (-0.8 m/s²) = -40 N The magnitude of the frictional force is 40 N. **Step 3: Find the rate of energy loss (Power)** Method 1 - Using total energy change: Initial kinetic energy: KE₀ = ½mv₀² = ½(50)(8²) = 1600 J Final kinetic energy: KE = 0 J Change in energy: ΔE = 0 - 1600 = -1600 J Rate of energy loss (Power): P = |ΔE|/t = 1600/10 = 160 W Method 2 - Using P = F·v (average): Average velocity: v_avg = (v₀ + v)/2 = (8 + 0)/2 = 4 m/s Power: P = F × v_avg = 40 N × 4 m/s = 160 W Both methods give the same answer: 160 W { "final_numeric": 160, "final_formula": "P = \\frac{|\\Delta KE|}{t} = \\frac{\\frac{1}{2}mv_0^2}{t} = \\frac{\\frac{1}{2}(50)(8)^2}{10} = 160\\text{ W}", "final_units": "W" } | K31: {'id': 'gen-1780479053-8UcjWTpabFVTks5csz2s', 'object': 'chat.completion', 'created': 1780479053, 'model': 'anthropic/claude-4.5-sonnet-20250929', 'provider': 'Amazon Bedrock', 'system_fingerprint': None, 'service_tier': None, 'choices': [{'index': 0, 'logprobs': None, 'finish_reason': 'stop', 'native_finish_reason': 'end_turn', 'message': {'role': 'assistant', 'content': 'I need to find the rate at which the frictional force takes energy away from the crate. This is asking for power.\n\n**Given:**\n- Mass: m = 50 kg\n- Initial speed: v₀ = 8 m/s\n- Final speed: v = 0 m/s\n- Time: t = 10 s\n\n**Step 1: Find the acceleration**\n\nUsing the kinematic equation: v = v₀ + at\n\n0 = 8 + a(10)\n\na = -0.8 m/s²\n\n**Step 2: Find the frictional force**\n\nUsing Newton\'s second law: F = ma\n\nF_friction = 50 kg × (-0.8 m/s²) = -40 N\n\nThe magnitude of the frictional force is 40 N.\n\n**Step 3: Find the rate of energy loss (Power)**\n\nMethod 1 - Using total energy change:\n\nInitial kinetic energy: KE₀ = ½mv₀² = ½(50)(8²) = 1600 J\n\nFinal kinetic energy: KE = 0 J\n\nChange in energy: ΔE = 0 - 1600 = -1600 J\n\nRate of energy loss (Power): P = |ΔE|/t = 1600/10 = 160 W\n\nMethod 2 - Using P = F·v (average):\n\nAverage velocity: v_avg = (v₀ + v)/2 = (8 + 0)/2 = 4 m/s\n\nPower: P = F × v_avg = 40 N × 4 m/s = 160 W\n\nBoth methods give the same answer: 160 W\n\n{\n "final_numeric": 160,\n "final_formula": "P = \\\\frac{|\\\\Delta KE|}{t} = \\\\frac{\\\\frac{1}{2}mv_0^2}{t} = \\\\frac{\\\\frac{1}{2}(50)(8)^2}{10} = 160\\\\text{ W}",\n "final_units": "W"\n}', 'refusal': None, 'reasoning': None}}], 'usage': {'prompt_tokens': 2382, 'completion_tokens': 513, 'total_tokens': 2895, 'cost': 0.014841, 'is_byok': False, 'prompt_tokens_details': {'cached_tokens': 0, 'cache_write_tokens': 0, 'audio_tokens': 0, 'video_tokens': 0}, 'cost_details': {'upstream_inference_cost': 0.014841, 'upstream_inference_prompt_cost': 0.007146, 'upstream_inference_completions_cost': 0.007695}, 'completion_tokens_details': {'reasoning_tokens': 0, 'image_tokens': 0, 'audio_tokens': 0}}} | L31: 2382 | M31: 513 | N31: 2895 | O31: 0 | P31: =VLOOKUP(C31,problems!$A$2:$B$26,2) -> mechanics | Q31: =IFERROR(__xludf.DUMMYFUNCTION("INDEX(FILTER('stats2-openrouter_activity_2026'!C:C,L31='stats2-openrouter_activity_2026'!H:H,M31='stats2-openrouter_activity_2026'!I:I, B31='stats2-openrouter_activity_2026'!M:M),1)"),0.014841) -> 0.014841 | R31: =IFS( F31=VLOOKUP($C31,problems!$A$2:$G$26,6),1, True,0 ) -> 1 | S31: =IFS( G31=VLOOKUP($C31,problems!$A$2:$G$26,4),1, G31=VLOOKUP($C31,problems!$A$2:$G$26,5),1, True,0 ) -> 0 | T31: =IFS( H31=VLOOKUP($C31,problems!$A$2:$G$26,7),1, True,0 ) -> 0
A32: 2026-06-03-13-34-33 | B32: anthropic/claude-sonnet-4.5 | C32: 6 | D32: Eight bumper cars, each with a mass of 322 kg, are running in a room 21.0 m long and 13.0 m wide. They have no drivers, so they just bounce around on their own. The rms speed of the cars is 2.50 m/s. Repeating the arguments of Pressure, Temperature, and RMS Speed, find the average force per unit length (analogous to pressure) that the cars exert on the walls. Examples: Example 1: *(a) In the deep space between galaxies, the density of atoms is as low as \(10^6\ \text{atoms/m}^3\), and the temperature is a frigid 2.7 K. What is the pressure? (b) What volume (in \(m^3\)) is occupied by 1 mol of gas? (c) If this volume is a cube, what is the length of its sides in kilometers?* Solution (a) Use the ideal gas law, where \[ PV = NkT \] \[ P = \frac{N}{V} k T = \frac{10^6}{1\ \text{m}^3} (1.38 \times 10^{-23}\ \text{J/K})(2.7\ \text{K}) \] \[ = 3.73 \times 10^{-17}\ \text{N/m}^2 = 3.7 \times 10^{-17}\ \text{N/m}^2 = \underline{3.7 \times 10^{-17}\ \text{Pa}} \] (b) Now, using the pressure found in part (a), let \(n = 1.00\ \text{mol}\). Use the ideal gas law: \[ PV = nRT \] \[ V = \frac{nRT}{P} = \frac{(1.00\ \text{mol})(8.31\ \text{J/mol·K})(2.7\ \text{K})}{3.73 \times 10^{-17}\ \text{N/m}^2} = 6.02 \times 10^{17}\ \text{m}^3 = \underline{6.0 \times 10^{17}\ \text{m}^3} \] (c) Since the volume of a cube is its length cubed: \[ L = V^{1/3} = (6.02 \times 10^{17}\ \text{m}^3)^{1/3} = 8.45 \times 10^5\ \text{m} = \underline{8.4 \times 10^2\ \text{km}} \] Example 2: *Following vigorous exercise, the body temperature of an 80.0-kg person is 40.0°C. At what rate in watts must the person transfer thermal energy to reduce the body temperature to 37.0°C in 30.0 min, assuming the body continues to produce energy at the rate of 150 W? (1 watt = 1 joule/second or 1 W = 1 J/s)* Solution First, calculate how much heat must be dissipated: \[ Q = m c_\text{human body} \Delta T = (80.0\ \text{kg})(3500\ \text{J/kg·°C})(40°C - 37°C) = 8.40 \times 10^5\ \text{J} \] Then, since power is heat divided by time, we can get the power required to produce the calculated amount of heat in 30.0 minutes: \[ P_\text{cooling} = \frac{Q}{t} = \frac{8.40 \times 10^5\ \text{J}}{(30\ \text{min})(60\ \text{s/min})} = 4.67 \times 10^2\ \text{W} \] Now, since the body continues to produce heat at a rate of 150 W, we need to add that to the required cooling power: \[ P_\text{required} = P_\text{cooling} + P_\text{body} = 467\ \text{W} + 150\ \text{W} = \underline{617\ \text{W}} \] Example 3: (a) What is the average metabolic rate in watts of a man who metabolizes 10,500 kJ of food energy in one day? (b) What is the maximum amount of work in joules he can do without breaking down fat, assuming a maximum efficiency of 20.0%? (c) Compare his work output with the daily output of a 187-W (0.250-horsepower) motor.* Solution (a) The metabolic rate is the power, so that: [ P = \frac{Q}{t} = \frac{10500\text{ kJ}}{1\text{ day}} \times \frac{1000\text{ J}}{1\text{ kJ}} \times \frac{1\text{ day}}{8.64\times10^4\text{ s}} = 122\text{ W} ] (b) Efficiency is defined to be the ratio of what we get to what we spend, or [ Eff = \frac{W}{E_{\text{in}}}, ] so we can determine the work done, knowing the efficiency: [ W = Eff \cdot E_{\text{in}} = 0.200(10500\text{ kJ}) \times \frac{1000\text{ J}}{1\text{ kJ}} = \underline{2.10\times10^6\text{ J}} ] (c) To compare with a 0.250 hp motor, we need to know how much work the motor does in one day: [ W = Pt = (0.250\text{ hp})(1\text{day}) \times \frac{746\text{ W}}{1\text{ hp}} \times \frac{8.64\times10^4\text{ s}}{1\text{day}} = 1.61\times10^7\text{ J}. ] So, the man’s work output is: [ \frac{W_{\text{motor}}}{W_{\text{man}}} ======================================= \frac{1.61\times10^7\text{ J}}{2.10\times10^6\text{ J}} = 7.67 \Rightarrow \underline{7.67\text{ times less than}} ] [ \underline{\text{the motor}}. ] Thus the motor produces 7.67 times the work done by the man. | E32: TRUE | F32: 29.5 | G32: \frac{1}{2} \frac{N m v_{rms}^2}{LW} = \frac{1}{2} \frac{8 \times 322 \times (2.50)^2}{21.0 \times 13.0} = 29.5\text{ N/m} | H32: N/m | J32: I need to solve for the average force per unit length that bumper cars exert on the walls, analogous to pressure in kinetic theory. ## Given Information: - Number of cars: N = 8 - Mass of each car: m = 322 kg - Room dimensions: L = 21.0 m (length), W = 13.0 m (width) - RMS speed: v_rms = 2.50 m/s ## Solution Approach: Following kinetic theory arguments for pressure, I need to adapt them for this 2D problem. For gas molecules in 3D, pressure P = (1/3)(N/V)m(v_rms)² For this 2D problem with cars bouncing off walls: - Instead of pressure (force per unit area), we need force per unit length - The cars move in 2D, so we use 1/2 instead of 1/3 - The "volume" becomes area A = L × W - The perimeter is P_perimeter = 2(L + W) The average force on all walls comes from momentum transfer. For a 2D system: Total kinetic energy: KE_total = N × (1/2)m(v_rms)² For collisions with walls, the force per unit length (analogous to pressure) is: F/length = (1/2) × (N/A) × m × (v_rms)² where A = L × W is the area of the room. Calculating: - A = 21.0 m × 13.0 m = 273 m² - N/A = 8/273 = 0.02930 cars/m² - m(v_rms)² = 322 kg × (2.50 m/s)² = 322 × 6.25 = 2012.5 kg·m²/s² F/length = (1/2) × (8/273) × 322 × 6.25 F/length = 0.5 × 0.029304 × 2012.5 F/length = 29.48 N/m Rounding to 3 significant figures: 29.5 N/m { "final_numeric": 29.5, "final_formula": "\\frac{1}{2} \\frac{N m v_{rms}^2}{LW} = \\frac{1}{2} \\frac{8 \\times 322 \\times (2.50)^2}{21.0 \\times 13.0} = 29.5\\text{ N/m}", "final_units": "N/m" } | K32: {'id': 'gen-1780479262-7RsmatXIzcR7SdZoQIdb', 'object': 'chat.completion', 'created': 1780479262, 'model': 'anthropic/claude-4.5-sonnet-20250929', 'provider': 'Amazon Bedrock', 'system_fingerprint': None, 'service_tier': None, 'choices': [{'index': 0, 'logprobs': None, 'finish_reason': 'stop', 'native_finish_reason': 'end_turn', 'message': {'role': 'assistant', 'content': 'I need to solve for the average force per unit length that bumper cars exert on the walls, analogous to pressure in kinetic theory.\n\n## Given Information:\n- Number of cars: N = 8\n- Mass of each car: m = 322 kg\n- Room dimensions: L = 21.0 m (length), W = 13.0 m (width)\n- RMS speed: v_rms = 2.50 m/s\n\n## Solution Approach:\n\nFollowing kinetic theory arguments for pressure, I need to adapt them for this 2D problem.\n\nFor gas molecules in 3D, pressure P = (1/3)(N/V)m(v_rms)²\n\nFor this 2D problem with cars bouncing off walls:\n- Instead of pressure (force per unit area), we need force per unit length\n- The cars move in 2D, so we use 1/2 instead of 1/3\n- The "volume" becomes area A = L × W\n- The perimeter is P_perimeter = 2(L + W)\n\nThe average force on all walls comes from momentum transfer. For a 2D system:\n\nTotal kinetic energy: KE_total = N × (1/2)m(v_rms)²\n\nFor collisions with walls, the force per unit length (analogous to pressure) is:\n\nF/length = (1/2) × (N/A) × m × (v_rms)²\n\nwhere A = L × W is the area of the room.\n\nCalculating:\n- A = 21.0 m × 13.0 m = 273 m²\n- N/A = 8/273 = 0.02930 cars/m²\n- m(v_rms)² = 322 kg × (2.50 m/s)² = 322 × 6.25 = 2012.5 kg·m²/s²\n\nF/length = (1/2) × (8/273) × 322 × 6.25\nF/length = 0.5 × 0.029304 × 2012.5\nF/length = 29.48 N/m\n\nRounding to 3 significant figures: 29.5 N/m\n\n{\n "final_numeric": 29.5,\n "final_formula": "\\\\frac{1}{2} \\\\frac{N m v_{rms}^2}{LW} = \\\\frac{1}{2} \\\\frac{8 \\\\times 322 \\\\times (2.50)^2}{21.0 \\\\times 13.0} = 29.5\\\\text{ N/m}",\n "final_units": "N/m"\n}', 'refusal': None, 'reasoning': None}}], 'usage': {'prompt_tokens': 2177, 'completion_tokens': 654, 'total_tokens': 2831, 'cost': 0.016341, 'is_byok': False, 'prompt_tokens_details': {'cached_tokens': 0, 'cache_write_tokens': 0, 'audio_tokens': 0, 'video_tokens': 0}, 'cost_details': {'upstream_inference_cost': 0.016341, 'upstream_inference_prompt_cost': 0.006531, 'upstream_inference_completions_cost': 0.00981}, 'completion_tokens_details': {'reasoning_tokens': 0, 'image_tokens': 0, 'audio_tokens': 0}}} | L32: 2177 | M32: 654 | N32: 2831 | O32: 0 | P32: =VLOOKUP(C32,problems!$A$2:$B$26,2) -> thermodynamics | Q32: =IFERROR(__xludf.DUMMYFUNCTION("INDEX(FILTER('stats2-openrouter_activity_2026'!C:C,L32='stats2-openrouter_activity_2026'!H:H,M32='stats2-openrouter_activity_2026'!I:I, B32='stats2-openrouter_activity_2026'!M:M),1)"),0.016341) -> 0.016341 | R32: =IFS( F32=VLOOKUP($C32,problems!$A$2:$G$26,6),1, True,0 ) -> 1 | S32: =IFS( G32=VLOOKUP($C32,problems!$A$2:$G$26,4),1, G32=VLOOKUP($C32,problems!$A$2:$G$26,5),1, True,0 ) -> 0 | T32: =IFS( H32=VLOOKUP($C32,problems!$A$2:$G$26,7),1, True,0 ) -> 1
A33: 2026-06-03-15-13-21 | B33: anthropic/claude-sonnet-4.5 | C33: 7 | D33: Какую работу в кДж совершает при изотермическом расширении водород, взятый при температуре t = 11 °С, если его объем увеличивается в 3 раза? Масса водорода m = 5 г. Examples: Example 1: *(a) In the deep space between galaxies, the density of atoms is as low as \(10^6\ \text{atoms/m}^3\), and the temperature is a frigid 2.7 K. What is the pressure? (b) What volume (in \(m^3\)) is occupied by 1 mol of gas? (c) If this volume is a cube, what is the length of its sides in kilometers?* Solution (a) Use the ideal gas law, where \[ PV = NkT \] \[ P = \frac{N}{V} k T = \frac{10^6}{1\ \text{m}^3} (1.38 \times 10^{-23}\ \text{J/K})(2.7\ \text{K}) \] \[ = 3.73 \times 10^{-17}\ \text{N/m}^2 = 3.7 \times 10^{-17}\ \text{N/m}^2 = \underline{3.7 \times 10^{-17}\ \text{Pa}} \] (b) Now, using the pressure found in part (a), let \(n = 1.00\ \text{mol}\). Use the ideal gas law: \[ PV = nRT \] \[ V = \frac{nRT}{P} = \frac{(1.00\ \text{mol})(8.31\ \text{J/mol·K})(2.7\ \text{K})}{3.73 \times 10^{-17}\ \text{N/m}^2} = 6.02 \times 10^{17}\ \text{m}^3 = \underline{6.0 \times 10^{17}\ \text{m}^3} \] (c) Since the volume of a cube is its length cubed: \[ L = V^{1/3} = (6.02 \times 10^{17}\ \text{m}^3)^{1/3} = 8.45 \times 10^5\ \text{m} = \underline{8.4 \times 10^2\ \text{km}} \] Example 2: *Following vigorous exercise, the body temperature of an 80.0-kg person is 40.0°C. At what rate in watts must the person transfer thermal energy to reduce the body temperature to 37.0°C in 30.0 min, assuming the body continues to produce energy at the rate of 150 W? (1 watt = 1 joule/second or 1 W = 1 J/s)* Solution First, calculate how much heat must be dissipated: \[ Q = m c_\text{human body} \Delta T = (80.0\ \text{kg})(3500\ \text{J/kg·°C})(40°C - 37°C) = 8.40 \times 10^5\ \text{J} \] Then, since power is heat divided by time, we can get the power required to produce the calculated amount of heat in 30.0 minutes: \[ P_\text{cooling} = \frac{Q}{t} = \frac{8.40 \times 10^5\ \text{J}}{(30\ \text{min})(60\ \text{s/min})} = 4.67 \times 10^2\ \text{W} \] Now, since the body continues to produce heat at a rate of 150 W, we need to add that to the required cooling power: \[ P_\text{required} = P_\text{cooling} + P_\text{body} = 467\ \text{W} + 150\ \text{W} = \underline{617\ \text{W}} \] Example 3: (a) What is the average metabolic rate in watts of a man who metabolizes 10,500 kJ of food energy in one day? (b) What is the maximum amount of work in joules he can do without breaking down fat, assuming a maximum efficiency of 20.0%? (c) Compare his work output with the daily output of a 187-W (0.250-horsepower) motor.* Solution (a) The metabolic rate is the power, so that: [ P = \frac{Q}{t} = \frac{10500\text{ kJ}}{1\text{ day}} \times \frac{1000\text{ J}}{1\text{ kJ}} \times \frac{1\text{ day}}{8.64\times10^4\text{ s}} = 122\text{ W} ] (b) Efficiency is defined to be the ratio of what we get to what we spend, or [ Eff = \frac{W}{E_{\text{in}}}, ] so we can determine the work done, knowing the efficiency: [ W = Eff \cdot E_{\text{in}} = 0.200(10500\text{ kJ}) \times \frac{1000\text{ J}}{1\text{ kJ}} = \underline{2.10\times10^6\text{ J}} ] (c) To compare with a 0.250 hp motor, we need to know how much work the motor does in one day: [ W = Pt = (0.250\text{ hp})(1\text{day}) \times \frac{746\text{ W}}{1\text{ hp}} \times \frac{8.64\times10^4\text{ s}}{1\text{day}} = 1.61\times10^7\text{ J}. ] So, the man’s work output is: [ \frac{W_{\text{motor}}}{W_{\text{man}}} ======================================= \frac{1.61\times10^7\text{ J}}{2.10\times10^6\text{ J}} = 7.67 \Rightarrow \underline{7.67\text{ times less than}} ] [ \underline{\text{the motor}}. ] Thus the motor produces 7.67 times the work done by the man. | E33: TRUE | F33: 6.49 | G33: W = nRT\ln\left(\frac{V_2}{V_1}\right) = \frac{m}{M}RT\ln(3) | H33: kJ | J33: I need to find the work done by hydrogen gas during isothermal expansion. **Given:** - Temperature: t = 11°C = 284 K - Volume increases by factor of 3: V₂/V₁ = 3 - Mass of hydrogen: m = 5 g = 0.005 kg - Molecular mass of H₂: M = 2 g/mol = 0.002 kg/mol **Solution:** For isothermal expansion of an ideal gas, the work done is: $$W = nRT \ln\left(\frac{V_2}{V_1}\right)$$ First, find the number of moles: $$n = \frac{m}{M} = \frac{5 \text{ g}}{2 \text{ g/mol}} = 2.5 \text{ mol}$$ Now calculate the work: $$W = nRT \ln\left(\frac{V_2}{V_1}\right)$$ $$W = (2.5 \text{ mol})(8.314 \text{ J/(mol·K)})(284 \text{ K}) \ln(3)$$ $$W = (2.5)(8.314)(284)(1.0986)$$ $$W = 2.5 \times 8.314 \times 284 \times 1.0986$$ $$W = 6485.5 \text{ J}$$ Converting to kJ: $$W = 6.486 \text{ kJ} \approx 6.49 \text{ kJ}$$ Since the problem asks for the answer in kJ, I need to convert: $$W = 6.49 \times 10^3 \text{ J} = 6.49 \text{ kJ}$$ However, let me recalculate more precisely: - n = 2.5 mol - R = 8.314 J/(mol·K) - T = 284 K - ln(3) = 1.0986 W = 2.5 × 8.314 × 284 × 1.0986 = 6485.5 J = 6.4855 kJ ≈ 6.49 kJ The answer in kJ is approximately 6.49, but since we need it in kJ as stated in the problem, the numeric value is 6.49. { "final_numeric": 6.49, "final_formula": "W = nRT\\ln\\left(\\frac{V_2}{V_1}\\right) = \\frac{m}{M}RT\\ln(3)", "final_units": "kJ" } | K33: {'id': 'gen-1780485192-iSUsZmeOsC8exXjjkG9m', 'object': 'chat.completion', 'created': 1780485192, 'model': 'anthropic/claude-4.5-sonnet-20250929', 'provider': 'Amazon Bedrock', 'system_fingerprint': None, 'service_tier': None, 'choices': [{'index': 0, 'logprobs': None, 'finish_reason': 'stop', 'native_finish_reason': 'end_turn', 'message': {'role': 'assistant', 'content': 'I need to find the work done by hydrogen gas during isothermal expansion.\n\n**Given:**\n- Temperature: t = 11°C = 284 K\n- Volume increases by factor of 3: V₂/V₁ = 3\n- Mass of hydrogen: m = 5 g = 0.005 kg\n- Molecular mass of H₂: M = 2 g/mol = 0.002 kg/mol\n\n**Solution:**\n\nFor isothermal expansion of an ideal gas, the work done is:\n\n$$W = nRT \\ln\\left(\\frac{V_2}{V_1}\\right)$$\n\nFirst, find the number of moles:\n$$n = \\frac{m}{M} = \\frac{5 \\text{ g}}{2 \\text{ g/mol}} = 2.5 \\text{ mol}$$\n\nNow calculate the work:\n$$W = nRT \\ln\\left(\\frac{V_2}{V_1}\\right)$$\n\n$$W = (2.5 \\text{ mol})(8.314 \\text{ J/(mol·K)})(284 \\text{ K}) \\ln(3)$$\n\n$$W = (2.5)(8.314)(284)(1.0986)$$\n\n$$W = 2.5 \\times 8.314 \\times 284 \\times 1.0986$$\n\n$$W = 6485.5 \\text{ J}$$\n\nConverting to kJ:\n$$W = 6.486 \\text{ kJ} \\approx 6.49 \\text{ kJ}$$\n\nSince the problem asks for the answer in kJ, I need to convert:\n$$W = 6.49 \\times 10^3 \\text{ J} = 6.49 \\text{ kJ}$$\n\nHowever, let me recalculate more precisely:\n- n = 2.5 mol\n- R = 8.314 J/(mol·K)\n- T = 284 K\n- ln(3) = 1.0986\n\nW = 2.5 × 8.314 × 284 × 1.0986 = 6485.5 J = 6.4855 kJ ≈ 6.49 kJ\n\nThe answer in kJ is approximately 6.49, but since we need it in kJ as stated in the problem, the numeric value is 6.49.\n\n{\n "final_numeric": 6.49,\n "final_formula": "W = nRT\\\\ln\\\\left(\\\\frac{V_2}{V_1}\\\\right) = \\\\frac{m}{M}RT\\\\ln(3)",\n "final_units": "kJ"\n}', 'refusal': None, 'reasoning': None}}], 'usage': {'prompt_tokens': 2122, 'completion_tokens': 653, 'total_tokens': 2775, 'cost': 0.016161, 'is_byok': False, 'prompt_tokens_details': {'cached_tokens': 0, 'cache_write_tokens': 0, 'audio_tokens': 0, 'video_tokens': 0}, 'cost_details': {'upstream_inference_cost': 0.016161, 'upstream_inference_prompt_cost': 0.006366, 'upstream_inference_completions_cost': 0.009795}, 'completion_tokens_details': {'reasoning_tokens': 0, 'image_tokens': 0, 'audio_tokens': 0}}} | L33: 2122 | M33: 653 | N33: 2775 | O33: 0 | P33: =VLOOKUP(C33,problems!$A$2:$B$26,2) -> thermodynamics | Q33: =IFERROR(__xludf.DUMMYFUNCTION("INDEX(FILTER('stats2-openrouter_activity_2026'!C:C,L33='stats2-openrouter_activity_2026'!H:H,M33='stats2-openrouter_activity_2026'!I:I, B33='stats2-openrouter_activity_2026'!M:M),1)"),0.016161) -> 0.016161 | R33: =IFS( F33=VLOOKUP($C33,problems!$A$2:$G$26,6),1, True,0 ) -> 0 | S33: =IFS( G33=VLOOKUP($C33,problems!$A$2:$G$26,4),1, G33=VLOOKUP($C33,problems!$A$2:$G$26,5),1, True,0 ) -> 0 | T33: =IFS( H33=VLOOKUP($C33,problems!$A$2:$G$26,7),1, True,0 ) -> 1
