Workbook

Sheet physics_results
A1: datetime | B1: ai_model | C1: statement_row_id | D1: statement | E1: ok | F1: final_numeric | G1: final_formula | H1: final_units | I1: error | J1: raw_response_text | K1: full_api_response | L1: prompt_tokens | M1: completion_tokens | N1: total_tokens | O1: prompt_version | P1: topic | Q1: cost | R1: is_correct_number | S1: is_correct_formula | T1: is_correct_units
A2: 2026-06-03-17-05-55 | B2: anthropic/claude-opus-4.7 | C2: 1 | D2: Дано: l = 2 м — расстояние, которое частица пролетает равномерно a = 5*10^5 м/с^2 — ускорение торможения, направлено против движения. Найти: v - скорость частицы, при которой полное время движения от вылета до остановки минимально в м/с | E2: TRUE | F2: 1000 | G2: v=\sqrt{la} | H2: m/s | J2: Total time: t = l/v + v/a. Minimize: dt/dv = -l/v² + 1/a = 0, v = √(la) = √(2·5×10⁵) = √10⁶ = 1000 m/s. {"final_numeric":1000,"final_formula":"v=\\sqrt{la}","final_units":"m/s"} | K2: {'id': 'gen-1780491953-Jx9tZvgl19ST4QF2NLyV', 'object': 'chat.completion', 'created': 1780491953, 'model': 'anthropic/claude-4.7-opus-20260416', 'provider': 'Anthropic', 'system_fingerprint': None, 'service_tier': 'default', 'choices': [{'index': 0, 'logprobs': None, 'finish_reason': 'stop', 'native_finish_reason': 'end_turn', 'message': {'role': 'assistant', 'content': 'Total time: t = l/v + v/a. Minimize: dt/dv = -l/v² + 1/a = 0, v = √(la) = √(2·5×10⁵) = √10⁶ = 1000 m/s.\n\n{"final_numeric":1000,"final_formula":"v=\\\\sqrt{la}","final_units":"m/s"}', 'refusal': None, 'reasoning': None}}], 'usage': {'prompt_tokens': 814, 'completion_tokens': 118, 'total_tokens': 932, 'cost': 0.00702, 'is_byok': False, 'prompt_tokens_details': {'cached_tokens': 0, 'cache_write_tokens': 0, 'audio_tokens': 0, 'video_tokens': 0}, 'cost_details': {'upstream_inference_cost': 0.00702, 'upstream_inference_prompt_cost': 0.00407, 'upstream_inference_completions_cost': 0.00295}, 'completion_tokens_details': {'reasoning_tokens': 0, 'image_tokens': 0, 'audio_tokens': 0}}} | L2: 814 | M2: 118 | N2: 932 | O2: 0 | P2: =VLOOKUP(C2,problems!$A$2:$B$26,2) -> mechanics | Q2: =IFERROR(__xludf.DUMMYFUNCTION("INDEX(FILTER('stats2-openrouter_activity_2026'!C:C,L2='stats2-openrouter_activity_2026'!H:H,M2='stats2-openrouter_activity_2026'!I:I, B2='stats2-openrouter_activity_2026'!M:M),1)"),0.00702) -> 0.00702 | R2: =IFS( F2=VLOOKUP($C2,problems!$A$2:$G$26,6),1, True,0 ) -> 1 | S2: =IFS( G2=VLOOKUP($C2,problems!$A$2:$G$26,4),1, G2=VLOOKUP($C2,problems!$A$2:$G$26,5),1, True,0 ) -> 0 | T2: =IFS( H2=VLOOKUP($C2,problems!$A$2:$G$26,7),1, True,0 ) -> 1
A3: 2026-06-03-17-06-06 | B3: anthropic/claude-opus-4.7 | C3: 2 | D3: Дано: x = At+Bt^3 — закон движения точки по оси x. A = 6 м/с B = -0.125 м/с^3 t_1 = 2 с t_2 = 6 с Найти: v_{ср} — средняя скорость точки за интервал времени от t_{1} до t_{2}​ в м/с | E3: TRUE | F3: -0.5 | G3: v_{ср}=\frac{A(t_2-t_1)+B(t_2^3-t_1^3)}{t_2-t_1} | H3: m/s | J3: x(2)=12-1=11, x(6)=36-27=9. Δx=-2, Δt=4, v=-0.5 {"final_numeric":-0.5,"final_formula":"v_{ср}=\\frac{A(t_2-t_1)+B(t_2^3-t_1^3)}{t_2-t_1}","final_units":"m/s"} | K3: {'id': 'gen-1780491964-ZmksvvRTv0CWKVn04qT8', 'object': 'chat.completion', 'created': 1780491964, 'model': 'anthropic/claude-4.7-opus-20260416', 'provider': 'Anthropic', 'system_fingerprint': None, 'service_tier': 'default', 'choices': [{'index': 0, 'logprobs': None, 'finish_reason': 'stop', 'native_finish_reason': 'end_turn', 'message': {'role': 'assistant', 'content': 'x(2)=12-1=11, x(6)=36-27=9. Δx=-2, Δt=4, v=-0.5\n\n{"final_numeric":-0.5,"final_formula":"v_{ср}=\\\\frac{A(t_2-t_1)+B(t_2^3-t_1^3)}{t_2-t_1}","final_units":"m/s"}', 'refusal': None, 'reasoning': None}}], 'usage': {'prompt_tokens': 829, 'completion_tokens': 124, 'total_tokens': 953, 'cost': 0.007245, 'is_byok': False, 'prompt_tokens_details': {'cached_tokens': 0, 'cache_write_tokens': 0, 'audio_tokens': 0, 'video_tokens': 0}, 'cost_details': {'upstream_inference_cost': 0.007245, 'upstream_inference_prompt_cost': 0.004145, 'upstream_inference_completions_cost': 0.0031}, 'completion_tokens_details': {'reasoning_tokens': 0, 'image_tokens': 0, 'audio_tokens': 0}}} | L3: 829 | M3: 124 | N3: 953 | O3: 0 | P3: =VLOOKUP(C3,problems!$A$2:$B$26,2) -> mechanics | Q3: =IFERROR(__xludf.DUMMYFUNCTION("INDEX(FILTER('stats2-openrouter_activity_2026'!C:C,L3='stats2-openrouter_activity_2026'!H:H,M3='stats2-openrouter_activity_2026'!I:I, B3='stats2-openrouter_activity_2026'!M:M),1)"),0.007245) -> 0.007245 | R3: =IFS( F3=VLOOKUP($C3,problems!$A$2:$G$26,6),1, True,0 ) -> 1 | S3: =IFS( G3=VLOOKUP($C3,problems!$A$2:$G$26,4),1, G3=VLOOKUP($C3,problems!$A$2:$G$26,5),1, True,0 ) -> 0 | T3: =IFS( H3=VLOOKUP($C3,problems!$A$2:$G$26,7),1, True,0 ) -> 1
A4: 2026-06-03-17-06-51 | B4: anthropic/claude-opus-4.7 | C4: 3 | D4: Given: v_{1} = 80 km/h — east truck's speed v_{2} = 50 km/h — north car's speed d = 32 km — distance from the truck to the intersection at the initial moment. Find: t — the time in hours after this moment when the vehicles will be closest to each other. | E4: TRUE | F4: 0.2876 | G4: t = \frac{v_1 d}{v_1^2 + v_2^2} | H4: h | J4: Truck position: x = d - v1·t (approaching intersection from west, going east). Car at intersection going north: y = v2·t. Distance² = (d-v1t)² + (v2t)² d/dt: -2v1(d-v1t) + 2v2²t = 0 t = v1·d/(v1²+v2²) = 80·32/(6400+2500) = 2560/8900 ≈ 0.2876 h {"final_numeric": 0.2876,"final_formula": "t = \\frac{v_1 d}{v_1^2 + v_2^2}","final_units": "h"} | K4: {'id': 'gen-1780492008-tVEKGWpV6fuFFIww2pcl', 'object': 'chat.completion', 'created': 1780492008, 'model': 'anthropic/claude-4.7-opus-20260416', 'provider': 'Anthropic', 'system_fingerprint': None, 'service_tier': 'default', 'choices': [{'index': 0, 'logprobs': None, 'finish_reason': 'stop', 'native_finish_reason': 'end_turn', 'message': {'role': 'assistant', 'content': 'Truck position: x = d - v1·t (approaching intersection from west, going east). Car at intersection going north: y = v2·t.\n\nDistance² = (d-v1t)² + (v2t)²\nd/dt: -2v1(d-v1t) + 2v2²t = 0\nt = v1·d/(v1²+v2²) = 80·32/(6400+2500) = 2560/8900 ≈ 0.2876 h\n\n{"final_numeric": 0.2876,"final_formula": "t = \\\\frac{v_1 d}{v_1^2 + v_2^2}","final_units": "h"}', 'refusal': None, 'reasoning': None}}], 'usage': {'prompt_tokens': 813, 'completion_tokens': 201, 'total_tokens': 1014, 'cost': 0.00909, 'is_byok': False, 'prompt_tokens_details': {'cached_tokens': 0, 'cache_write_tokens': 0, 'audio_tokens': 0, 'video_tokens': 0}, 'cost_details': {'upstream_inference_cost': 0.00909, 'upstream_inference_prompt_cost': 0.004065, 'upstream_inference_completions_cost': 0.005025}, 'completion_tokens_details': {'reasoning_tokens': 0, 'image_tokens': 0, 'audio_tokens': 0}}} | L4: 813 | M4: 201 | N4: 1014 | O4: 0 | P4: =VLOOKUP(C4,problems!$A$2:$B$26,2) -> mechanics | Q4: =IFERROR(__xludf.DUMMYFUNCTION("INDEX(FILTER('stats2-openrouter_activity_2026'!C:C,L4='stats2-openrouter_activity_2026'!H:H,M4='stats2-openrouter_activity_2026'!I:I, B4='stats2-openrouter_activity_2026'!M:M),1)"),0.00909) -> 0.00909 | R4: =IFS( F4=VLOOKUP($C4,problems!$A$2:$G$26,6),1, True,0 ) -> 0 | S4: =IFS( G4=VLOOKUP($C4,problems!$A$2:$G$26,4),1, G4=VLOOKUP($C4,problems!$A$2:$G$26,5),1, True,0 ) -> 0 | T4: =IFS( H4=VLOOKUP($C4,problems!$A$2:$G$26,7),1, True,0 ) -> 1
A5: 2026-06-03-17-08-43 | B5: anthropic/claude-opus-4.7 | C5: 4 | D5: Дано: х = а_1 + b_{1}*t + y_{1}*t^2 — закон движения точки по оси x. y = α_2 + b_{2}*t + y_{2}*t^2 — закон движения точки по оси y. b_1 = b_2 = 1 м/с y_1 = -1 м/c^2 y_2 = 2 м/с^2 t = 1 с a — ускорение материальной точки Найти: \phi — угол между скоростью и ускорением в момент времени t в градусах | E5: TRUE | F5: 15.26 | G5: \phi = \arccos\left(\frac{v_x a_x + v_y a_y}{\sqrt{v_x^2+v_y^2}\sqrt{a_x^2+a_y^2}}\right) | H5: deg | J5: vx = b1 + 2γ1 t = 1 + 2(-1)(1) = -1 vy = b2 + 2γ2 t = 1 + 2(2)(1) = 5 ax = 2γ1 = -2 ay = 2γ2 = 4 v·a = (-1)(-2) + (5)(4) = 2 + 20 = 22 |v| = √(1+25) = √26 |a| = √(4+16) = √20 cos φ = 22/(√26·√20) = 22/√520 ≈ 22/22.804 ≈ 0.9648 φ ≈ 15.26° {"final_numeric": 15.26, "final_formula": "\\phi = \\arccos\\left(\\frac{v_x a_x + v_y a_y}{\\sqrt{v_x^2+v_y^2}\\sqrt{a_x^2+a_y^2}}\\right)", "final_units": "deg"} | K5: {'id': 'gen-1780492119-iuqmf3fE0BVXrgaY2BKx', 'object': 'chat.completion', 'created': 1780492119, 'model': 'anthropic/claude-4.7-opus-20260416', 'provider': 'Anthropic', 'system_fingerprint': None, 'service_tier': 'default', 'choices': [{'index': 0, 'logprobs': None, 'finish_reason': 'stop', 'native_finish_reason': 'end_turn', 'message': {'role': 'assistant', 'content': 'vx = b1 + 2γ1 t = 1 + 2(-1)(1) = -1\nvy = b2 + 2γ2 t = 1 + 2(2)(1) = 5\nax = 2γ1 = -2\nay = 2γ2 = 4\n\nv·a = (-1)(-2) + (5)(4) = 2 + 20 = 22\n|v| = √(1+25) = √26\n|a| = √(4+16) = √20\n\ncos φ = 22/(√26·√20) = 22/√520 ≈ 22/22.804 ≈ 0.9648\nφ ≈ 15.26°\n\n{"final_numeric": 15.26, "final_formula": "\\\\phi = \\\\arccos\\\\left(\\\\frac{v_x a_x + v_y a_y}{\\\\sqrt{v_x^2+v_y^2}\\\\sqrt{a_x^2+a_y^2}}\\\\right)", "final_units": "deg"}', 'refusal': None, 'reasoning': None}}], 'usage': {'prompt_tokens': 890, 'completion_tokens': 315, 'total_tokens': 1205, 'cost': 0.012325, 'is_byok': False, 'prompt_tokens_details': {'cached_tokens': 0, 'cache_write_tokens': 0, 'audio_tokens': 0, 'video_tokens': 0}, 'cost_details': {'upstream_inference_cost': 0.012325, 'upstream_inference_prompt_cost': 0.00445, 'upstream_inference_completions_cost': 0.007875}, 'completion_tokens_details': {'reasoning_tokens': 0, 'image_tokens': 0, 'audio_tokens': 0}}} | L5: 890 | M5: 315 | N5: 1205 | O5: 0 | P5: =VLOOKUP(C5,problems!$A$2:$B$26,2) -> mechanics | Q5: =IFERROR(__xludf.DUMMYFUNCTION("INDEX(FILTER('stats2-openrouter_activity_2026'!C:C,L5='stats2-openrouter_activity_2026'!H:H,M5='stats2-openrouter_activity_2026'!I:I, B5='stats2-openrouter_activity_2026'!M:M),1)"),0.012325) -> 0.012325 | R5: =IFS( F5=VLOOKUP($C5,problems!$A$2:$G$26,6),1, True,0 ) -> 0 | S5: =IFS( G5=VLOOKUP($C5,problems!$A$2:$G$26,4),1, G5=VLOOKUP($C5,problems!$A$2:$G$26,5),1, True,0 ) -> 0 | T5: =IFS( H5=VLOOKUP($C5,problems!$A$2:$G$26,7),1, True,0 ) -> 0
A6: 2026-06-03-17-12-10 | B6: anthropic/claude-opus-4.7 | C6: 5 | D6: Given: A crate is moving across a rough floor surface. If no external pushing force is applied, friction slows the crate down until it stops. m = 50 kg — mass of the crate. v_0 = 8 m/s — initial speed of the crate. v = 0 m/s — final speed of the crate, because it comes to rest. \Delta t = 10 s — time during which the crate comes to rest. Find: P — the rate at which the frictional force takes energy away from the crate, in J/s. | E6: TRUE | F6: 160 | G6: P=\frac{\frac{1}{2}mv_0^2}{\Delta t} | H6: W | J6: {"final_numeric":160,"final_formula":"P=\\frac{\\frac{1}{2}mv_0^2}{\\Delta t}","final_units":"W"} | K6: {'id': 'gen-1780492329-Btupi8y2iJRiRMSFeEV4', 'object': 'chat.completion', 'created': 1780492329, 'model': 'anthropic/claude-4.7-opus-20260416', 'provider': 'Anthropic', 'system_fingerprint': None, 'service_tier': 'default', 'choices': [{'index': 0, 'logprobs': None, 'finish_reason': 'stop', 'native_finish_reason': 'end_turn', 'message': {'role': 'assistant', 'content': '{"final_numeric":160,"final_formula":"P=\\\\frac{\\\\frac{1}{2}mv_0^2}{\\\\Delta t}","final_units":"W"}', 'refusal': None, 'reasoning': None}}], 'usage': {'prompt_tokens': 878, 'completion_tokens': 62, 'total_tokens': 940, 'cost': 0.00594, 'is_byok': False, 'prompt_tokens_details': {'cached_tokens': 0, 'cache_write_tokens': 0, 'audio_tokens': 0, 'video_tokens': 0}, 'cost_details': {'upstream_inference_cost': 0.00594, 'upstream_inference_prompt_cost': 0.00439, 'upstream_inference_completions_cost': 0.00155}, 'completion_tokens_details': {'reasoning_tokens': 0, 'image_tokens': 0, 'audio_tokens': 0}}} | L6: 878 | M6: 62 | N6: 940 | O6: 0 | P6: =VLOOKUP(C6,problems!$A$2:$B$26,2) -> mechanics | Q6: =IFERROR(__xludf.DUMMYFUNCTION("INDEX(FILTER('stats2-openrouter_activity_2026'!C:C,L6='stats2-openrouter_activity_2026'!H:H,M6='stats2-openrouter_activity_2026'!I:I, B6='stats2-openrouter_activity_2026'!M:M),1)"),0.00594) -> 0.00594 | R6: =IFS( F6=VLOOKUP($C6,problems!$A$2:$G$26,6),1, True,0 ) -> 1 | S6: =IFS( G6=VLOOKUP($C6,problems!$A$2:$G$26,4),1, G6=VLOOKUP($C6,problems!$A$2:$G$26,5),1, True,0 ) -> 0 | T6: =IFS( H6=VLOOKUP($C6,problems!$A$2:$G$26,7),1, True,0 ) -> 0
A7: 2026-06-03-17-13-32 | B7: anthropic/claude-opus-4.7 | C7: 6 | D7: Given: N = 8 — number of bumper cars. m = 322 kg — mass of each bumper car. L = 21 m — length of the room. W = 13 m — width of the room. v_rms = 2.5 m/s — rms speed of the bumper cars. The cars move randomly and bounce off the walls, similar to gas particles. Find: P — the average force per unit length that the cars exert on the walls, in N/m. | E7: TRUE | F7: 29.49 | G7: P = \frac{N m v_{rms}^2}{2 L W} | H7: N/m | J7: Using 2D gas analogy: P*perimeter... actually pressure in 2D: P = N m v_rms² / (2A), force per unit length on walls. For 2D ideal gas: PA = N m v²/2 where P is force per length. Wait, let me think. In 2D, kinetic energy = N·(1/2)m v_rms² = (2/2)NkT = NkT (2 DOF). Pressure (force/length): P·A = NkT, so P = NkT/A = N m v_rms²/(2A). A = 21·13 = 273 m² P = 8 · 322 · 6.25 / (2·273) = 16100/546 = 29.487 N/m {"final_numeric": 29.49, "final_formula": "P = \\frac{N m v_{rms}^2}{2 L W}", "final_units": "N/m"} | K7: {'id': 'gen-1780492407-dPkSdFtFf5BkrUfDXp0o', 'object': 'chat.completion', 'created': 1780492407, 'model': 'anthropic/claude-4.7-opus-20260416', 'provider': 'Anthropic', 'system_fingerprint': None, 'service_tier': 'default', 'choices': [{'index': 0, 'logprobs': None, 'finish_reason': 'stop', 'native_finish_reason': 'end_turn', 'message': {'role': 'assistant', 'content': 'Using 2D gas analogy: P*perimeter... actually pressure in 2D: P = N m v_rms² / (2A), force per unit length on walls.\n\nFor 2D ideal gas: PA = N m v²/2 where P is force per length. Wait, let me think.\n\nIn 2D, kinetic energy = N·(1/2)m v_rms² = (2/2)NkT = NkT (2 DOF). Pressure (force/length): P·A = NkT, so P = NkT/A = N m v_rms²/(2A).\n\nA = 21·13 = 273 m²\nP = 8 · 322 · 6.25 / (2·273) = 16100/546 = 29.487 N/m\n\n{"final_numeric": 29.49, "final_formula": "P = \\\\frac{N m v_{rms}^2}{2 L W}", "final_units": "N/m"}', 'refusal': None, 'reasoning': None}}], 'usage': {'prompt_tokens': 858, 'completion_tokens': 284, 'total_tokens': 1142, 'cost': 0.01139, 'is_byok': False, 'prompt_tokens_details': {'cached_tokens': 0, 'cache_write_tokens': 0, 'audio_tokens': 0, 'video_tokens': 0}, 'cost_details': {'upstream_inference_cost': 0.01139, 'upstream_inference_prompt_cost': 0.00429, 'upstream_inference_completions_cost': 0.0071}, 'completion_tokens_details': {'reasoning_tokens': 0, 'image_tokens': 0, 'audio_tokens': 0}}} | L7: 858 | M7: 284 | N7: 1142 | O7: 0 | P7: =VLOOKUP(C7,problems!$A$2:$B$26,2) -> thermodynamics | Q7: =IFERROR(__xludf.DUMMYFUNCTION("INDEX(FILTER('stats2-openrouter_activity_2026'!C:C,L7='stats2-openrouter_activity_2026'!H:H,M7='stats2-openrouter_activity_2026'!I:I, B7='stats2-openrouter_activity_2026'!M:M),1)"),0.01139) -> 0.01139 | R7: =IFS( F7=VLOOKUP($C7,problems!$A$2:$G$26,6),1, True,0 ) -> 0 | S7: =IFS( G7=VLOOKUP($C7,problems!$A$2:$G$26,4),1, G7=VLOOKUP($C7,problems!$A$2:$G$26,5),1, True,0 ) -> 0 | T7: =IFS( H7=VLOOKUP($C7,problems!$A$2:$G$26,7),1, True,0 ) -> 1
A8: 2026-06-03-17-14-59 | B8: anthropic/claude-opus-4.7 | C8: 7 | D8: Дано: t = 11∘C — температура водорода. m = 5 г — масса водорода. V_2/V_1 = 3 — объем водорода увеличился в 3 раза. Найти: A — работу, совершенную водородом при изотермическом расширении, в кДж. | E8: TRUE | F8: 6485 | G8: A = \frac{m}{M} R T \ln\frac{V_2}{V_1} | H8: J | J8: A = (m/M)RT ln(V2/V1) = (0.005/0.002)(8.314)(284) ln3 = 2.5 × 8.314 × 284 × 1.0986 = 2.5 × 8.314 × 312.0 ≈ 6486 J ≈ 6.49 kJ Wait, let me recompute: 8.314 × 284 = 2361.18; × 1.0986 = 2594.0; × 2.5 = 6485 J { "final_numeric": 6485, "final_formula": "A = \\frac{m}{M} R T \\ln\\frac{V_2}{V_1}", "final_units": "J" } | K8: {'id': 'gen-1780492495-RUCMwoFO5hyl7WGzePxC', 'object': 'chat.completion', 'created': 1780492495, 'model': 'anthropic/claude-4.7-opus-20260416', 'provider': 'Anthropic', 'system_fingerprint': None, 'service_tier': 'default', 'choices': [{'index': 0, 'logprobs': None, 'finish_reason': 'stop', 'native_finish_reason': 'end_turn', 'message': {'role': 'assistant', 'content': 'A = (m/M)RT ln(V2/V1) = (0.005/0.002)(8.314)(284) ln3\n= 2.5 × 8.314 × 284 × 1.0986\n= 2.5 × 8.314 × 312.0 ≈ 6486 J ≈ 6.49 kJ\n\nWait, let me recompute: 8.314 × 284 = 2361.18; × 1.0986 = 2594.0; × 2.5 = 6485 J\n\n{\n "final_numeric": 6485,\n "final_formula": "A = \\\\frac{m}{M} R T \\\\ln\\\\frac{V_2}{V_1}",\n "final_units": "J"\n}', 'refusal': None, 'reasoning': None}}], 'usage': {'prompt_tokens': 810, 'completion_tokens': 228, 'total_tokens': 1038, 'cost': 0.00975, 'is_byok': False, 'prompt_tokens_details': {'cached_tokens': 0, 'cache_write_tokens': 0, 'audio_tokens': 0, 'video_tokens': 0}, 'cost_details': {'upstream_inference_cost': 0.00975, 'upstream_inference_prompt_cost': 0.00405, 'upstream_inference_completions_cost': 0.0057}, 'completion_tokens_details': {'reasoning_tokens': 0, 'image_tokens': 0, 'audio_tokens': 0}}} | L8: 810 | M8: 228 | N8: 1038 | O8: 0 | P8: =VLOOKUP(C8,problems!$A$2:$B$26,2) -> thermodynamics | Q8: =IFERROR(__xludf.DUMMYFUNCTION("INDEX(FILTER('stats2-openrouter_activity_2026'!C:C,L8='stats2-openrouter_activity_2026'!H:H,M8='stats2-openrouter_activity_2026'!I:I, B8='stats2-openrouter_activity_2026'!M:M),1)"),0.00975) -> 0.00975 | R8: =IFS( F8=VLOOKUP($C8,problems!$A$2:$G$26,6),1, True,0 ) -> 0 | S8: =IFS( G8=VLOOKUP($C8,problems!$A$2:$G$26,4),1, G8=VLOOKUP($C8,problems!$A$2:$G$26,5),1, True,0 ) -> 0 | T8: =IFS( H8=VLOOKUP($C8,problems!$A$2:$G$26,7),1, True,0 ) -> 0
A9: 2026-06-03-17-17-45 | B9: anthropic/claude-opus-4.7 | C9: 8 | D9: Find: An air bubble rises from the bottom to the top of a freshwater lake. V_2/V_1 = 1.8 — the bubble’s volume increases by 80%. T_1 = 4∘C — temperature at the bottom of the lake. T_2 = 10∘C — temperature at the top of the lake. p_0 = 1.01 * 10^5 Pa — atmospheric pressure at the surface of the lake. p = 1000 kg/m^3 — density of freshwater. Find: h — the depth of the lake, in meters. | E9: TRUE | F9: 7.85 | G9: h = \frac{p_0}{\rho g}\left(\frac{V_2 T_1}{V_1 T_2} - 1\right) | H9: m | J9: p1V1/T1 = p2V2/T2 p1 = p2(V2/V1)(T1/T2) = 1.01e5 * 1.8 * 277/283 = 1.01e5 * 1.8 * 0.97881 = 1.7795e5 p1 - p0 = ρgh h = (1.7795e5 - 1.01e5)/(1000*9.8) = 76950/9800 = 7.852 m {"final_numeric": 7.85, "final_formula": "h = \\frac{p_0}{\\rho g}\\left(\\frac{V_2 T_1}{V_1 T_2} - 1\\right)", "final_units": "m"} | K9: {'id': 'gen-1780492661-aFcCv8XjiqdOFgOTlFWU', 'object': 'chat.completion', 'created': 1780492661, 'model': 'anthropic/claude-4.7-opus-20260416', 'provider': 'Anthropic', 'system_fingerprint': None, 'service_tier': 'default', 'choices': [{'index': 0, 'logprobs': None, 'finish_reason': 'stop', 'native_finish_reason': 'end_turn', 'message': {'role': 'assistant', 'content': 'p1V1/T1 = p2V2/T2\np1 = p2(V2/V1)(T1/T2) = 1.01e5 * 1.8 * 277/283\n= 1.01e5 * 1.8 * 0.97881 = 1.7795e5\np1 - p0 = ρgh\nh = (1.7795e5 - 1.01e5)/(1000*9.8) = 76950/9800 = 7.852 m\n\n{"final_numeric": 7.85, "final_formula": "h = \\\\frac{p_0}{\\\\rho g}\\\\left(\\\\frac{V_2 T_1}{V_1 T_2} - 1\\\\right)", "final_units": "m"}', 'refusal': None, 'reasoning': None}}], 'usage': {'prompt_tokens': 900, 'completion_tokens': 228, 'total_tokens': 1128, 'cost': 0.0102, 'is_byok': False, 'prompt_tokens_details': {'cached_tokens': 0, 'cache_write_tokens': 0, 'audio_tokens': 0, 'video_tokens': 0}, 'cost_details': {'upstream_inference_cost': 0.0102, 'upstream_inference_prompt_cost': 0.0045, 'upstream_inference_completions_cost': 0.0057}, 'completion_tokens_details': {'reasoning_tokens': 0, 'image_tokens': 0, 'audio_tokens': 0}}} | L9: 900 | M9: 228 | N9: 1128 | O9: 0 | P9: =VLOOKUP(C9,problems!$A$2:$B$26,2) -> thermodynamics | Q9: =IFERROR(__xludf.DUMMYFUNCTION("INDEX(FILTER('stats2-openrouter_activity_2026'!C:C,L9='stats2-openrouter_activity_2026'!H:H,M9='stats2-openrouter_activity_2026'!I:I, B9='stats2-openrouter_activity_2026'!M:M),1)"),0.0102) -> 0.0102 | R9: =IFS( F9=VLOOKUP($C9,problems!$A$2:$G$26,6),1, True,0 ) -> 0 | S9: =IFS( G9=VLOOKUP($C9,problems!$A$2:$G$26,4),1, G9=VLOOKUP($C9,problems!$A$2:$G$26,5),1, True,0 ) -> 0 | T9: =IFS( H9=VLOOKUP($C9,problems!$A$2:$G$26,7),1, True,0 ) -> 1
A10: 2026-06-03-17-19-27 | B10: anthropic/claude-opus-4.7 | C10: 9 | D10: Given: T = 30∘C — air temperature. T_d = 15∘C — dew-point temperature, because condensation first appears when the can reaches 15∘C. Find: \phi\ — relative humidity of the air, in percent. | E10: TRUE | F10: 40.1 | G10: \phi = \frac{p_s(T_d)}{p_s(T)} = \frac{1.705\,\text{kPa}}{4.246\,\text{kPa}} \approx 0.40 | H10: % | J10: {"final_numeric":40.1,"final_formula":"\\phi = \\frac{p_s(T_d)}{p_s(T)} = \\frac{1.705\\,\\text{kPa}}{4.246\\,\\text{kPa}} \\approx 0.40","final_units":"%"} | K10: {'id': 'gen-1780492765-WSex6mz8YTf7mChXmTrJ', 'object': 'chat.completion', 'created': 1780492765, 'model': 'anthropic/claude-4.7-opus-20260416', 'provider': 'Anthropic', 'system_fingerprint': None, 'service_tier': 'default', 'choices': [{'index': 0, 'logprobs': None, 'finish_reason': 'stop', 'native_finish_reason': 'end_turn', 'message': {'role': 'assistant', 'content': '{"final_numeric":40.1,"final_formula":"\\\\phi = \\\\frac{p_s(T_d)}{p_s(T)} = \\\\frac{1.705\\\\,\\\\text{kPa}}{4.246\\\\,\\\\text{kPa}} \\\\approx 0.40","final_units":"%"}', 'refusal': None, 'reasoning': None}}], 'usage': {'prompt_tokens': 793, 'completion_tokens': 104, 'total_tokens': 897, 'cost': 0.006565, 'is_byok': False, 'prompt_tokens_details': {'cached_tokens': 0, 'cache_write_tokens': 0, 'audio_tokens': 0, 'video_tokens': 0}, 'cost_details': {'upstream_inference_cost': 0.006565, 'upstream_inference_prompt_cost': 0.003965, 'upstream_inference_completions_cost': 0.0026}, 'completion_tokens_details': {'reasoning_tokens': 0, 'image_tokens': 0, 'audio_tokens': 0}}} | L10: 793 | M10: 104 | N10: 897 | O10: 0 | P10: =VLOOKUP(C10,problems!$A$2:$B$26,2) -> thermodynamics | Q10: =IFERROR(__xludf.DUMMYFUNCTION("INDEX(FILTER('stats2-openrouter_activity_2026'!C:C,L10='stats2-openrouter_activity_2026'!H:H,M10='stats2-openrouter_activity_2026'!I:I, B10='stats2-openrouter_activity_2026'!M:M),1)"),0.006565) -> 0.006565 | R10: =IFS( F10=VLOOKUP($C10,problems!$A$2:$G$26,6),1, True,0 ) -> 0 | S10: =IFS( G10=VLOOKUP($C10,problems!$A$2:$G$26,4),1, G10=VLOOKUP($C10,problems!$A$2:$G$26,5),1, True,0 ) -> 0 | T10: =IFS( H10=VLOOKUP($C10,problems!$A$2:$G$26,7),1, True,0 ) -> 1
A11: 2026-06-03-17-21-21 | B11: anthropic/claude-opus-4.7 | C11: 10 | D11: Дано: V_1 = 10л — начальный объем газа. p_1 = 2 * 10^5 Па — начальное давление газа. V_2 = 28 л — конечный объем газа. Процесс - изотермический Найти: A — работа, совершенная газом при изотермическом расширении, в кДж. | E11: TRUE | F11: 2.06 | G11: A = p_1 V_1 \ln\frac{V_2}{V_1} | H11: kJ | J11: {"final_numeric":2.06,"final_formula":"A = p_1 V_1 \\ln\\frac{V_2}{V_1}","final_units":"kJ"} | K11: {'id': 'gen-1780492878-SjHM6dJzshN6FvKMuu3T', 'object': 'chat.completion', 'created': 1780492878, 'model': 'anthropic/claude-4.7-opus-20260416', 'provider': 'Anthropic', 'system_fingerprint': None, 'service_tier': 'default', 'choices': [{'index': 0, 'logprobs': None, 'finish_reason': 'stop', 'native_finish_reason': 'end_turn', 'message': {'role': 'assistant', 'content': '{"final_numeric":2.06,"final_formula":"A = p_1 V_1 \\\\ln\\\\frac{V_2}{V_1}","final_units":"kJ"}', 'refusal': None, 'reasoning': None}}], 'usage': {'prompt_tokens': 823, 'completion_tokens': 62, 'total_tokens': 885, 'cost': 0.005665, 'is_byok': False, 'prompt_tokens_details': {'cached_tokens': 0, 'cache_write_tokens': 0, 'audio_tokens': 0, 'video_tokens': 0}, 'cost_details': {'upstream_inference_cost': 0.005665, 'upstream_inference_prompt_cost': 0.004115, 'upstream_inference_completions_cost': 0.00155}, 'completion_tokens_details': {'reasoning_tokens': 0, 'image_tokens': 0, 'audio_tokens': 0}}} | L11: 823 | M11: 62 | N11: 885 | O11: 0 | P11: =VLOOKUP(C11,problems!$A$2:$B$26,2) -> thermodynamics | Q11: =IFERROR(__xludf.DUMMYFUNCTION("INDEX(FILTER('stats2-openrouter_activity_2026'!C:C,L11='stats2-openrouter_activity_2026'!H:H,M11='stats2-openrouter_activity_2026'!I:I, B11='stats2-openrouter_activity_2026'!M:M),1)"),0.005665) -> 0.005665 | R11: =IFS( F11=VLOOKUP($C11,problems!$A$2:$G$26,6),1, True,0 ) -> 1 | S11: =IFS( G11=VLOOKUP($C11,problems!$A$2:$G$26,4),1, G11=VLOOKUP($C11,problems!$A$2:$G$26,5),1, True,0 ) -> 0 | T11: =IFS( H11=VLOOKUP($C11,problems!$A$2:$G$26,7),1, True,0 ) -> 1
A12: 2026-06-03-17-24-27 | B12: anthropic/claude-opus-4.7 | C12: 11 | D12: Given: h_0 = 3.5 mm — height of the object, the printed letters. d_c = 30 cm — distance from the book to the eye. d_i = 2 cm — distance from the eye lens to the retina. Find: h_i — the height of the image of the print on the retina, in millimeters. | E12: TRUE | F12: 0.233 | G12: h_i = h_0 \cdot \frac{d_i}{d_c} | H12: mm | J12: {"final_numeric":0.233,"final_formula":"h_i = h_0 \\cdot \\frac{d_i}{d_c}","final_units":"mm"} | K12: {'id': 'gen-1780493065-Br9cqqmhRgnQnfpwnvQB', 'object': 'chat.completion', 'created': 1780493065, 'model': 'anthropic/claude-4.7-opus-20260416', 'provider': 'Anthropic', 'system_fingerprint': None, 'service_tier': 'default', 'choices': [{'index': 0, 'logprobs': None, 'finish_reason': 'stop', 'native_finish_reason': 'end_turn', 'message': {'role': 'assistant', 'content': '{"final_numeric":0.233,"final_formula":"h_i = h_0 \\\\cdot \\\\frac{d_i}{d_c}","final_units":"mm"}', 'refusal': None, 'reasoning': None}}], 'usage': {'prompt_tokens': 815, 'completion_tokens': 60, 'total_tokens': 875, 'cost': 0.005575, 'is_byok': False, 'prompt_tokens_details': {'cached_tokens': 0, 'cache_write_tokens': 0, 'audio_tokens': 0, 'video_tokens': 0}, 'cost_details': {'upstream_inference_cost': 0.005575, 'upstream_inference_prompt_cost': 0.004075, 'upstream_inference_completions_cost': 0.0015}, 'completion_tokens_details': {'reasoning_tokens': 0, 'image_tokens': 0, 'audio_tokens': 0}}} | L12: 815 | M12: 60 | N12: 875 | O12: 0 | P12: =VLOOKUP(C12,problems!$A$2:$B$26,2) -> optics | Q12: =IFERROR(__xludf.DUMMYFUNCTION("INDEX(FILTER('stats2-openrouter_activity_2026'!C:C,L12='stats2-openrouter_activity_2026'!H:H,M12='stats2-openrouter_activity_2026'!I:I, B12='stats2-openrouter_activity_2026'!M:M),1)"),0.005575) -> 0.005575 | R12: =IFS( F12=VLOOKUP($C12,problems!$A$2:$G$26,6),1, True,0 ) -> 0 | S12: =IFS( G12=VLOOKUP($C12,problems!$A$2:$G$26,4),1, G12=VLOOKUP($C12,problems!$A$2:$G$26,5),1, True,0 ) -> 0 | T12: =IFS( H12=VLOOKUP($C12,problems!$A$2:$G$26,7),1, True,0 ) -> 1
A13: 2026-06-03-17-26-23 | B13: anthropic/claude-opus-4.7 | C13: 12 | D13: Given: f_{obj} = 100 cm — focal length of the objective lens. f_{eye} = 2.50 cm — focal length of the eyepiece. Find: M — angular magnification of the telescope. | E13: TRUE | F13: -40 | G13: M=-\frac{f_{obj}}{f_{eye}} | H13: 1 | J13: {"final_numeric":-40,"final_formula":"M=-\\frac{f_{obj}}{f_{eye}}","final_units":"1"} | K13: {'id': 'gen-1780493182-YiuPMVUJWvzwww3ZQS7x', 'object': 'chat.completion', 'created': 1780493182, 'model': 'anthropic/claude-4.7-opus-20260416', 'provider': 'Anthropic', 'system_fingerprint': None, 'service_tier': 'default', 'choices': [{'index': 0, 'logprobs': None, 'finish_reason': 'stop', 'native_finish_reason': 'end_turn', 'message': {'role': 'assistant', 'content': '{"final_numeric":-40,"final_formula":"M=-\\\\frac{f_{obj}}{f_{eye}}","final_units":"1"}', 'refusal': None, 'reasoning': None}}], 'usage': {'prompt_tokens': 786, 'completion_tokens': 54, 'total_tokens': 840, 'cost': 0.00528, 'is_byok': False, 'prompt_tokens_details': {'cached_tokens': 0, 'cache_write_tokens': 0, 'audio_tokens': 0, 'video_tokens': 0}, 'cost_details': {'upstream_inference_cost': 0.00528, 'upstream_inference_prompt_cost': 0.00393, 'upstream_inference_completions_cost': 0.00135}, 'completion_tokens_details': {'reasoning_tokens': 0, 'image_tokens': 0, 'audio_tokens': 0}}} | L13: 786 | M13: 54 | N13: 840 | O13: 0 | P13: =VLOOKUP(C13,problems!$A$2:$B$26,2) -> optics | Q13: =IFERROR(__xludf.DUMMYFUNCTION("INDEX(FILTER('stats2-openrouter_activity_2026'!C:C,L13='stats2-openrouter_activity_2026'!H:H,M13='stats2-openrouter_activity_2026'!I:I, B13='stats2-openrouter_activity_2026'!M:M),1)"),0.00528) -> 0.00528 | R13: =IFS( F13=VLOOKUP($C13,problems!$A$2:$G$26,6),1, True,0 ) -> 1 | S13: =IFS( G13=VLOOKUP($C13,problems!$A$2:$G$26,4),1, G13=VLOOKUP($C13,problems!$A$2:$G$26,5),1, True,0 ) -> 0 | T13: =IFS( H13=VLOOKUP($C13,problems!$A$2:$G$26,7),1, True,0 ) -> 1
A14: 2026-06-03-17-27-19 | B14: anthropic/claude-opus-4.7 | C14: 13 | D14: Дано: Луч последовательно отражается от двух плоских зеркал. Луч, падающий на первое зеркало, параллелен плоскости второго зеркала. Дважды отражённый луч параллелен плоскости первого зеркала. Найти: phi — угол между зеркалами, в градусах. | E14: TRUE | F14: 60 | G14: \varphi = \arccos\frac{1}{2} = 60^\circ | H14: deg | J14: Angle between mirrors φ. Incident ray parallel to mirror 2, so angle with mirror 1 is φ, meaning angle of incidence (from normal) is 90-φ. After reflection, ray makes angle φ with mirror 1 on other side. Let me set mirror 1 along direction making angle 0, mirror 2 at angle φ. Incident ray parallel to mirror 2. After two reflections, total deviation... Final ray parallel to mirror 1. Using angles: incident ray direction parallel to mirror 2. After reflecting off mirror 1, then mirror 2, ray is parallel to mirror 1. The angle between incident and final ray after two reflections from mirrors at angle φ is 2φ (or 180-2φ). Let me think more carefully. Incident ray parallel to mirror 2 → angle with mirror 1 = φ. Reflects, makes angle φ with mirror 1 on other side. This ray hits mirror 2; angle with mirror 2 = ? The reflected ray from mirror 1 and mirror 2 — angle between them = φ - ... Set mirror 1 along x-axis, mirror 2 at angle φ above. Incident ray parallel to mirror 2, direction (-cos φ, -sin φ) coming down to mirror 1. Reflects off mirror 1 (flip y): direction (-cos φ, sin φ). This hits mirror 2. Mirror 2 normal: (-sin φ, cos φ). Reflect: r = d - 2(d·n)n. d·n = (-cos φ)(-sin φ) + (sin φ)(cos φ) = 2 sin φ cos φ = sin 2φ. r = (-cos φ + 2 sin 2φ sin φ, sin φ - 2 sin 2φ cos φ) = (-cos φ + 4 sin²φ cos φ, sin φ - 4 sin φ cos²φ) = (cos φ(4sin²φ - 1), sin φ(1 - 4cos²φ)) For this to be parallel to mirror 1 (x-axis), y-component = 0: sin φ(1 - 4cos²φ) = 0 cos²φ = 1/4, cos φ = 1/2, φ = 60°. {"final_numeric":60,"final_formula":"\\varphi = \\arccos\\frac{1}{2} = 60^\\circ","final_units":"deg"} | K14: {'id': 'gen-1780493228-k12menPo8MPxQae6Y2BJ', 'object': 'chat.completion', 'created': 1780493228, 'model': 'anthropic/claude-4.7-opus-20260416', 'provider': 'Anthropic', 'system_fingerprint': None, 'service_tier': 'default', 'choices': [{'index': 0, 'logprobs': None, 'finish_reason': 'stop', 'native_finish_reason': 'end_turn', 'message': {'role': 'assistant', 'content': 'Angle between mirrors φ. Incident ray parallel to mirror 2, so angle with mirror 1 is φ, meaning angle of incidence (from normal) is 90-φ. After reflection, ray makes angle φ with mirror 1 on other side.\n\nLet me set mirror 1 along direction making angle 0, mirror 2 at angle φ. Incident ray parallel to mirror 2.\n\nAfter two reflections, total deviation... Final ray parallel to mirror 1.\n\nUsing angles: incident ray direction parallel to mirror 2. After reflecting off mirror 1, then mirror 2, ray is parallel to mirror 1.\n\nThe angle between incident and final ray after two reflections from mirrors at angle φ is 2φ (or 180-2φ). \n\nLet me think more carefully. Incident ray parallel to mirror 2 → angle with mirror 1 = φ. Reflects, makes angle φ with mirror 1 on other side. This ray hits mirror 2; angle with mirror 2 = ? The reflected ray from mirror 1 and mirror 2 — angle between them = φ - ... \n\nSet mirror 1 along x-axis, mirror 2 at angle φ above. Incident ray parallel to mirror 2, direction (-cos φ, -sin φ) coming down to mirror 1. Reflects off mirror 1 (flip y): direction (-cos φ, sin φ). This hits mirror 2. Mirror 2 normal: (-sin φ, cos φ). Reflect: r = d - 2(d·n)n.\nd·n = (-cos φ)(-sin φ) + (sin φ)(cos φ) = 2 sin φ cos φ = sin 2φ.\nr = (-cos φ + 2 sin 2φ sin φ, sin φ - 2 sin 2φ cos φ)\n= (-cos φ + 4 sin²φ cos φ, sin φ - 4 sin φ cos²φ)\n= (cos φ(4sin²φ - 1), sin φ(1 - 4cos²φ))\n\nFor this to be parallel to mirror 1 (x-axis), y-component = 0:\nsin φ(1 - 4cos²φ) = 0\ncos²φ = 1/4, cos φ = 1/2, φ = 60°.\n\n{"final_numeric":60,"final_formula":"\\\\varphi = \\\\arccos\\\\frac{1}{2} = 60^\\\\circ","final_units":"deg"}', 'refusal': None, 'reasoning': None}}], 'usage': {'prompt_tokens': 820, 'completion_tokens': 823, 'total_tokens': 1643, 'cost': 0.024675, 'is_byok': False, 'prompt_tokens_details': {'cached_tokens': 0, 'cache_write_tokens': 0, 'audio_tokens': 0, 'video_tokens': 0}, 'cost_details': {'upstream_inference_cost': 0.024675, 'upstream_inference_prompt_cost': 0.0041, 'upstream_inference_completions_cost': 0.020575}, 'completion_tokens_details': {'reasoning_tokens': 0, 'image_tokens': 0, 'audio_tokens': 0}}} | L14: 820 | M14: 823 | N14: 1643 | O14: 0 | P14: =VLOOKUP(C14,problems!$A$2:$B$26,2) -> optics | Q14: =IFERROR(__xludf.DUMMYFUNCTION("INDEX(FILTER('stats2-openrouter_activity_2026'!C:C,L14='stats2-openrouter_activity_2026'!H:H,M14='stats2-openrouter_activity_2026'!I:I, B14='stats2-openrouter_activity_2026'!M:M),1)"),0.024675) -> 0.024675 | R14: =IFS( F14=VLOOKUP($C14,problems!$A$2:$G$26,6),1, True,0 ) -> 1 | S14: =IFS( G14=VLOOKUP($C14,problems!$A$2:$G$26,4),1, G14=VLOOKUP($C14,problems!$A$2:$G$26,5),1, True,0 ) -> 0 | T14: =IFS( H14=VLOOKUP($C14,problems!$A$2:$G$26,7),1, True,0 ) -> 0
A15: 2026-06-03-17-29-59 | B15: anthropic/claude-opus-4.7 | C15: 14 | D15: Дано: Сосуд заполнен водой, на дне лежит плоское зеркало. d = 25 см — расстояние, на котором человек видит изображение своего лица в зеркале. h = 5 см — расстояние от лица до поверхности воды. n = \frac{4}{3} — показатель преломления воды. Найти: l — глубину сосуда, в сантиметрах. | E15: TRUE | F15: 13.33 | G15: l = \frac{n(d-h)}{2} | H15: cm | J15: Distance person sees image = d = 25 cm = h + apparent depth of image. Image is at 2l below surface (mirror image), apparent depth = 2l/n. So d = h + 2l/n → 2l/n = 20 → l = 20·(4/3)/2 = 40/3 ≈ 13.33 cm. {"final_numeric":13.33,"final_formula":"l = \\frac{n(d-h)}{2}","final_units":"cm"} | K15: {'id': 'gen-1780493395-t5BI4PCNmk7MWqI2J0Nt', 'object': 'chat.completion', 'created': 1780493395, 'model': 'anthropic/claude-4.7-opus-20260416', 'provider': 'Anthropic', 'system_fingerprint': None, 'service_tier': 'default', 'choices': [{'index': 0, 'logprobs': None, 'finish_reason': 'stop', 'native_finish_reason': 'end_turn', 'message': {'role': 'assistant', 'content': 'Distance person sees image = d = 25 cm = h + apparent depth of image.\nImage is at 2l below surface (mirror image), apparent depth = 2l/n.\nSo d = h + 2l/n → 2l/n = 20 → l = 20·(4/3)/2 = 40/3 ≈ 13.33 cm.\n\n{"final_numeric":13.33,"final_formula":"l = \\\\frac{n(d-h)}{2}","final_units":"cm"}', 'refusal': None, 'reasoning': None}}], 'usage': {'prompt_tokens': 847, 'completion_tokens': 159, 'total_tokens': 1006, 'cost': 0.00821, 'is_byok': False, 'prompt_tokens_details': {'cached_tokens': 0, 'cache_write_tokens': 0, 'audio_tokens': 0, 'video_tokens': 0}, 'cost_details': {'upstream_inference_cost': 0.00821, 'upstream_inference_prompt_cost': 0.004235, 'upstream_inference_completions_cost': 0.003975}, 'completion_tokens_details': {'reasoning_tokens': 0, 'image_tokens': 0, 'audio_tokens': 0}}} | L15: 847 | M15: 159 | N15: 1006 | O15: 0 | P15: =VLOOKUP(C15,problems!$A$2:$B$26,2) -> optics | Q15: =IFERROR(__xludf.DUMMYFUNCTION("INDEX(FILTER('stats2-openrouter_activity_2026'!C:C,L15='stats2-openrouter_activity_2026'!H:H,M15='stats2-openrouter_activity_2026'!I:I, B15='stats2-openrouter_activity_2026'!M:M),1)"),0.00821) -> 0.00821 | R15: =IFS( F15=VLOOKUP($C15,problems!$A$2:$G$26,6),1, True,0 ) -> 0 | S15: =IFS( G15=VLOOKUP($C15,problems!$A$2:$G$26,4),1, G15=VLOOKUP($C15,problems!$A$2:$G$26,5),1, True,0 ) -> 0 | T15: =IFS( H15=VLOOKUP($C15,problems!$A$2:$G$26,7),1, True,0 ) -> 1
A16: 2026-06-03-17-32-45 | B16: anthropic/claude-opus-4.7 | C16: 15 | D16: Given: A beam of light falls on a single slit. a = 1.00𝜇m — width of the single slit. theta = 36.9∘ — angle at which the first minimum occurs. m = 1 — order of the first minimum. Find: lambda — wavelength of the light, in nanometers. | E16: TRUE | F16: 600 | G16: \lambda = \frac{a \sin\theta}{m} | H16: nm | J16: {"final_numeric":600,"final_formula":"\\lambda = \\frac{a \\sin\\theta}{m}","final_units":"nm"} | K16: {'id': 'gen-1780493563-YB4ZTzmX81CkWOSWALqi', 'object': 'chat.completion', 'created': 1780493563, 'model': 'anthropic/claude-4.7-opus-20260416', 'provider': 'Anthropic', 'system_fingerprint': None, 'service_tier': 'default', 'choices': [{'index': 0, 'logprobs': None, 'finish_reason': 'stop', 'native_finish_reason': 'end_turn', 'message': {'role': 'assistant', 'content': '{"final_numeric":600,"final_formula":"\\\\lambda = \\\\frac{a \\\\sin\\\\theta}{m}","final_units":"nm"}', 'refusal': None, 'reasoning': None}}], 'usage': {'prompt_tokens': 814, 'completion_tokens': 55, 'total_tokens': 869, 'cost': 0.005445, 'is_byok': False, 'prompt_tokens_details': {'cached_tokens': 0, 'cache_write_tokens': 0, 'audio_tokens': 0, 'video_tokens': 0}, 'cost_details': {'upstream_inference_cost': 0.005445, 'upstream_inference_prompt_cost': 0.00407, 'upstream_inference_completions_cost': 0.001375}, 'completion_tokens_details': {'reasoning_tokens': 0, 'image_tokens': 0, 'audio_tokens': 0}}} | L16: 814 | M16: 55 | N16: 869 | O16: 0 | P16: =VLOOKUP(C16,problems!$A$2:$B$26,2) -> optics | Q16: =IFERROR(__xludf.DUMMYFUNCTION("INDEX(FILTER('stats2-openrouter_activity_2026'!C:C,L16='stats2-openrouter_activity_2026'!H:H,M16='stats2-openrouter_activity_2026'!I:I, B16='stats2-openrouter_activity_2026'!M:M),1)"),0.005445) -> 0.005445 | R16: =IFS( F16=VLOOKUP($C16,problems!$A$2:$G$26,6),1, True,0 ) -> 1 | S16: =IFS( G16=VLOOKUP($C16,problems!$A$2:$G$26,4),1, G16=VLOOKUP($C16,problems!$A$2:$G$26,5),1, True,0 ) -> 0 | T16: =IFS( H16=VLOOKUP($C16,problems!$A$2:$G$26,7),1, True,0 ) -> 1
A17: 2026-06-03-17-36-12 | B17: anthropic/claude-opus-4.7 | C17: 16 | D17: Дано: l = 1 м — длина тонкого непроводящего горизонтального стержня На концах стержня закреплены две маленькие бусинки. Третья бусинка надета на стержень и может двигаться по нему без трения. Всем бусинкам сообщены одинаковые заряды q = 10^-6 Кл m = 5 г — масса подвижной бусинки Подвижная бусинка совершает малые колебания около середины стержня. Найти: T — период малых колебаний подвижной бусинки, в секундах. | E17: TRUE | F17: 0.828 | G17: T = 2\pi\sqrt{\dfrac{m l^3}{32 k q^2}} = \pi\sqrt{\dfrac{m l^3}{8 k q^2}} | H17: s | J17: Let me set up: bead at position x from center, distance to ends l/2-x and l/2+x. Force = kq²[1/(l/2-x)² - 1/(l/2+x)²] For small x: expand. 1/(l/2-x)² ≈ (4/l²)(1+4x/l), 1/(l/2+x)² ≈ (4/l²)(1-4x/l) Difference ≈ (4/l²)(8x/l) = 32x/l³ F = kq² · 32x/l³, this is restoring? Force pushes away from nearer charge, so when x>0, force is in +x direction (away from center toward... wait). Charge at +l/2 pushes bead (at x) toward -x: force = -kq²/(l/2-x)² Charge at -l/2 pushes toward +x: force = +kq²/(l/2+x)² Net F = kq²/(l/2+x)² - kq²/(l/2-x)² ≈ -kq²·32x/l³ So restoring. ω² = 32kq²/(ml³) k = 8.99e9, q² = 1e-12, m = 5e-3, l³ = 1 ω² = 32 · 8.99e9 · 1e-12 / 5e-3 = 32 · 8.99e-3/5e-3 = 32·1.798 = 57.536 ω = 7.585 T = 2π/ω = 0.828 s {"final_numeric": 0.828, "final_formula": "T = 2\\pi\\sqrt{\\dfrac{m l^3}{32 k q^2}} = \\pi\\sqrt{\\dfrac{m l^3}{8 k q^2}}", "final_units": "s"} | K17: {'id': 'gen-1780493763-KO6i76ziFgkgvNZzgeQ7', 'object': 'chat.completion', 'created': 1780493763, 'model': 'anthropic/claude-4.7-opus-20260416', 'provider': 'Anthropic', 'system_fingerprint': None, 'service_tier': 'default', 'choices': [{'index': 0, 'logprobs': None, 'finish_reason': 'stop', 'native_finish_reason': 'end_turn', 'message': {'role': 'assistant', 'content': 'Let me set up: bead at position x from center, distance to ends l/2-x and l/2+x.\n\nForce = kq²[1/(l/2-x)² - 1/(l/2+x)²]\n\nFor small x: expand. 1/(l/2-x)² ≈ (4/l²)(1+4x/l), 1/(l/2+x)² ≈ (4/l²)(1-4x/l)\nDifference ≈ (4/l²)(8x/l) = 32x/l³\n\nF = kq² · 32x/l³, this is restoring? Force pushes away from nearer charge, so when x>0, force is in +x direction (away from center toward... wait).\n\nCharge at +l/2 pushes bead (at x) toward -x: force = -kq²/(l/2-x)²\nCharge at -l/2 pushes toward +x: force = +kq²/(l/2+x)²\n\nNet F = kq²/(l/2+x)² - kq²/(l/2-x)² ≈ -kq²·32x/l³\n\nSo restoring. ω² = 32kq²/(ml³)\n\nk = 8.99e9, q² = 1e-12, m = 5e-3, l³ = 1\nω² = 32 · 8.99e9 · 1e-12 / 5e-3 = 32 · 8.99e-3/5e-3 = 32·1.798 = 57.536\nω = 7.585\nT = 2π/ω = 0.828 s\n\n{"final_numeric": 0.828, "final_formula": "T = 2\\\\pi\\\\sqrt{\\\\dfrac{m l^3}{32 k q^2}} = \\\\pi\\\\sqrt{\\\\dfrac{m l^3}{8 k q^2}}", "final_units": "s"}', 'refusal': None, 'reasoning': None}}], 'usage': {'prompt_tokens': 897, 'completion_tokens': 570, 'total_tokens': 1467, 'cost': 0.018735, 'is_byok': False, 'prompt_tokens_details': {'cached_tokens': 0, 'cache_write_tokens': 0, 'audio_tokens': 0, 'video_tokens': 0}, 'cost_details': {'upstream_inference_cost': 0.018735, 'upstream_inference_prompt_cost': 0.004485, 'upstream_inference_completions_cost': 0.01425}, 'completion_tokens_details': {'reasoning_tokens': 0, 'image_tokens': 0, 'audio_tokens': 0}}} | L17: 897 | M17: 570 | N17: 1467 | O17: 0 | P17: =VLOOKUP(C17,problems!$A$2:$B$26,2) -> electrostatics | Q17: =IFERROR(__xludf.DUMMYFUNCTION("INDEX(FILTER('stats2-openrouter_activity_2026'!C:C,L17='stats2-openrouter_activity_2026'!H:H,M17='stats2-openrouter_activity_2026'!I:I, B17='stats2-openrouter_activity_2026'!M:M),1)"),0.018735) -> 0.018735 | R17: =IFS( F17=VLOOKUP($C17,problems!$A$2:$G$26,6),1, True,0 ) -> 0 | S17: =IFS( G17=VLOOKUP($C17,problems!$A$2:$G$26,4),1, G17=VLOOKUP($C17,problems!$A$2:$G$26,5),1, True,0 ) -> 0 | T17: =IFS( H17=VLOOKUP($C17,problems!$A$2:$G$26,7),1, True,0 ) -> 1
A18: 2026-06-03-17-40-40 | B18: anthropic/claude-opus-4.7 | C18: 17 | D18: E = 10^6 В/м — максимальная напряжённость электрического поля, при которой воздух ещё остаётся изолятором. q = 1 Кл — заряд металлического шара. Найти: R — радиус металлического шара, при котором на нём может удержаться заряд, в метрах. | E18: TRUE | F18: 94.87 | G18: R = \sqrt{\dfrac{kq}{E}} | H18: m | J18: R = sqrt(kq/E) = sqrt(9e9 * 1 / 1e6) = sqrt(9000) ≈ 94.87 m { "final_numeric": 94.87, "final_formula": "R = \\sqrt{\\dfrac{kq}{E}}", "final_units": "m" } | K18: {'id': 'gen-1780494037-whFuhtsC1ARAFO2VXkFs', 'object': 'chat.completion', 'created': 1780494037, 'model': 'anthropic/claude-4.7-opus-20260416', 'provider': 'Anthropic', 'system_fingerprint': None, 'service_tier': 'default', 'choices': [{'index': 0, 'logprobs': None, 'finish_reason': 'stop', 'native_finish_reason': 'end_turn', 'message': {'role': 'assistant', 'content': 'R = sqrt(kq/E) = sqrt(9e9 * 1 / 1e6) = sqrt(9000) ≈ 94.87 m\n\n{\n "final_numeric": 94.87,\n "final_formula": "R = \\\\sqrt{\\\\dfrac{kq}{E}}",\n "final_units": "m"\n}', 'refusal': None, 'reasoning': None}}], 'usage': {'prompt_tokens': 814, 'completion_tokens': 116, 'total_tokens': 930, 'cost': 0.00697, 'is_byok': False, 'prompt_tokens_details': {'cached_tokens': 0, 'cache_write_tokens': 0, 'audio_tokens': 0, 'video_tokens': 0}, 'cost_details': {'upstream_inference_cost': 0.00697, 'upstream_inference_prompt_cost': 0.00407, 'upstream_inference_completions_cost': 0.0029}, 'completion_tokens_details': {'reasoning_tokens': 0, 'image_tokens': 0, 'audio_tokens': 0}}} | L18: 814 | M18: 116 | N18: 930 | O18: 0 | P18: =VLOOKUP(C18,problems!$A$2:$B$26,2) -> electrostatics | Q18: =IFERROR(__xludf.DUMMYFUNCTION("INDEX(FILTER('stats2-openrouter_activity_2026'!C:C,L18='stats2-openrouter_activity_2026'!H:H,M18='stats2-openrouter_activity_2026'!I:I, B18='stats2-openrouter_activity_2026'!M:M),1)"),0.00697) -> 0.00697 | R18: =IFS( F18=VLOOKUP($C18,problems!$A$2:$G$26,6),1, True,0 ) -> 0 | S18: =IFS( G18=VLOOKUP($C18,problems!$A$2:$G$26,4),1, G18=VLOOKUP($C18,problems!$A$2:$G$26,5),1, True,0 ) -> 0 | T18: =IFS( H18=VLOOKUP($C18,problems!$A$2:$G$26,7),1, True,0 ) -> 1
A19: 2026-06-03-17-43-08 | B19: anthropic/claude-opus-4.7 | C19: 18 | D19: Дано: E = 100 В/м — напряжённость однородного электрического поля. v_0 = 10^6 м/с — начальная скорость электрона. v = 0 — конечная скорость электрона Электрон движется вдоль силовой линии поля, но сила, действующая на электрон, направлена противоположно полю, поэтому электрон тормозит. Найти: s — расстояние до полной остановки электрона, в сантиметрах. | E19: TRUE | F19: 2.85 | G19: s = \frac{m_e v_0^2}{2eE} | H19: cm | J19: s = mv²/(2eE) = (9.11e-31 × 1e12)/(2 × 1.6e-19 × 100) = 9.11e-19/3.2e-17 = 0.02847 m ≈ 2.85 cm {"final_numeric":2.85,"final_formula":"s = \\frac{m_e v_0^2}{2eE}","final_units":"cm"} | K19: {'id': 'gen-1780494185-pTMyFWHXV0Z4cQudlNTA', 'object': 'chat.completion', 'created': 1780494185, 'model': 'anthropic/claude-4.7-opus-20260416', 'provider': 'Anthropic', 'system_fingerprint': None, 'service_tier': 'default', 'choices': [{'index': 0, 'logprobs': None, 'finish_reason': 'stop', 'native_finish_reason': 'end_turn', 'message': {'role': 'assistant', 'content': 's = mv²/(2eE) = (9.11e-31 × 1e12)/(2 × 1.6e-19 × 100) = 9.11e-19/3.2e-17 = 0.02847 m ≈ 2.85 cm\n\n{"final_numeric":2.85,"final_formula":"s = \\\\frac{m_e v_0^2}{2eE}","final_units":"cm"}', 'refusal': None, 'reasoning': None}}], 'usage': {'prompt_tokens': 866, 'completion_tokens': 133, 'total_tokens': 999, 'cost': 0.007655, 'is_byok': False, 'prompt_tokens_details': {'cached_tokens': 0, 'cache_write_tokens': 0, 'audio_tokens': 0, 'video_tokens': 0}, 'cost_details': {'upstream_inference_cost': 0.007655, 'upstream_inference_prompt_cost': 0.00433, 'upstream_inference_completions_cost': 0.003325}, 'completion_tokens_details': {'reasoning_tokens': 0, 'image_tokens': 0, 'audio_tokens': 0}}} | L19: 866 | M19: 133 | N19: 999 | O19: 0 | P19: =VLOOKUP(C19,problems!$A$2:$B$26,2) -> electrostatics | Q19: =IFERROR(__xludf.DUMMYFUNCTION("INDEX(FILTER('stats2-openrouter_activity_2026'!C:C,L19='stats2-openrouter_activity_2026'!H:H,M19='stats2-openrouter_activity_2026'!I:I, B19='stats2-openrouter_activity_2026'!M:M),1)"),0.007655) -> 0.007655 | R19: =IFS( F19=VLOOKUP($C19,problems!$A$2:$G$26,6),1, True,0 ) -> 0 | S19: =IFS( G19=VLOOKUP($C19,problems!$A$2:$G$26,4),1, G19=VLOOKUP($C19,problems!$A$2:$G$26,5),1, True,0 ) -> 0 | T19: =IFS( H19=VLOOKUP($C19,problems!$A$2:$G$26,7),1, True,0 ) -> 1
A20: 2026-06-03-17-45-46 | B20: anthropic/claude-opus-4.7 | C20: 19 | D20: Дано: Два одинаковых воздушных конденсатора соединены последовательно. Они подключены к батарее с постоянной ЭДС, поэтому U = const Один из конденсаторов заполняют диэлектриком: epsilon — диэлектрическая проницаемость вещества. До внесения диэлектрика оба конденсатора были одинаковыми: C_1 = C_2 = C После внесения диэлектрика ёмкость одного конденсатора становится: C'_{1} = epsilon*C Найти: E/E_0 — во сколько раз изменится напряжённость электрического поля в конденсаторе, заполненном диэлектриком. | E20: TRUE | G20: \dfrac{E}{E_0} = \dfrac{2}{\varepsilon+1} | H20: 1 | J20: Initially: C_series = C/2, U on each = U/2, E_0 = U/(2d). After: C'_1 = εC, C_2 = C. Series total. Voltage on dielectric cap: U_1 = U·C_2/(C_1'+C_2) = U/(ε+1). Field in dielectric: E = U_1/(ε·d)... wait, field in dielectric E = U_1/d (the geometric distance), but reduced by ε from free charge. Actually E = U_1/d where d is plate separation. E/E_0 = [U/((ε+1)d)] / [U/(2d)] = 2/(ε+1). { "final_numeric": null, "final_formula": "\\dfrac{E}{E_0} = \\dfrac{2}{\\varepsilon+1}", "final_units": "1" } | K20: {'id': 'gen-1780494341-LJ5rk885W2fkwpkdZEiQ', 'object': 'chat.completion', 'created': 1780494341, 'model': 'anthropic/claude-4.7-opus-20260416', 'provider': 'Anthropic', 'system_fingerprint': None, 'service_tier': 'default', 'choices': [{'index': 0, 'logprobs': None, 'finish_reason': 'stop', 'native_finish_reason': 'end_turn', 'message': {'role': 'assistant', 'content': 'Initially: C_series = C/2, U on each = U/2, E_0 = U/(2d).\n\nAfter: C\'_1 = εC, C_2 = C. Series total. Voltage on dielectric cap: U_1 = U·C_2/(C_1\'+C_2) = U/(ε+1).\n\nField in dielectric: E = U_1/(ε·d)... wait, field in dielectric E = U_1/d (the geometric distance), but reduced by ε from free charge. Actually E = U_1/d where d is plate separation.\n\nE/E_0 = [U/((ε+1)d)] / [U/(2d)] = 2/(ε+1).\n\n{\n "final_numeric": null,\n "final_formula": "\\\\dfrac{E}{E_0} = \\\\dfrac{2}{\\\\varepsilon+1}",\n "final_units": "1"\n}', 'refusal': None, 'reasoning': None}}], 'usage': {'prompt_tokens': 940, 'completion_tokens': 285, 'total_tokens': 1225, 'cost': 0.011825, 'is_byok': False, 'prompt_tokens_details': {'cached_tokens': 0, 'cache_write_tokens': 0, 'audio_tokens': 0, 'video_tokens': 0}, 'cost_details': {'upstream_inference_cost': 0.011825, 'upstream_inference_prompt_cost': 0.0047, 'upstream_inference_completions_cost': 0.007125}, 'completion_tokens_details': {'reasoning_tokens': 0, 'image_tokens': 0, 'audio_tokens': 0}}} | L20: 940 | M20: 285 | N20: 1225 | O20: 0 | P20: =VLOOKUP(C20,problems!$A$2:$B$26,2) -> electrostatics | Q20: =IFERROR(__xludf.DUMMYFUNCTION("INDEX(FILTER('stats2-openrouter_activity_2026'!C:C,L20='stats2-openrouter_activity_2026'!H:H,M20='stats2-openrouter_activity_2026'!I:I, B20='stats2-openrouter_activity_2026'!M:M),1)"),0.011825) -> 0.011825 | R20: =IFS( F20=VLOOKUP($C20,problems!$A$2:$G$26,6),1, True,0 ) -> 0 | S20: =IFS( G20=VLOOKUP($C20,problems!$A$2:$G$26,4),1, G20=VLOOKUP($C20,problems!$A$2:$G$26,5),1, True,0 ) -> 0 | T20: =IFS( H20=VLOOKUP($C20,problems!$A$2:$G$26,7),1, True,0 ) -> 1
A21: 2026-06-03-17-47-33 | B21: anthropic/claude-opus-4.7 | C21: 20 | D21: GIven: m — particle's mass -q — charge Particle moves along a straight line away from a fixed particle with charge: Q When the distance between the two particles is r_0 the particle has speed v_0 The interaction between the particles is electrostatic. Find: v_0 — the assumption about the initial speed needed to make the calculation valid. | E21: TRUE | G21: v_0 > \sqrt{\dfrac{kQq}{2\pi\varepsilon_0 m r_0}} = \sqrt{\dfrac{Qq}{2\pi\varepsilon_0 m r_0}} | H21: m/s | J21: {"final_numeric":null,"final_formula":"v_0 > \\sqrt{\\dfrac{kQq}{2\\pi\\varepsilon_0 m r_0}} = \\sqrt{\\dfrac{Qq}{2\\pi\\varepsilon_0 m r_0}}","final_units":"m/s"} | K21: {'id': 'gen-1780494450-JY6O48awL4GWy0htpCJB', 'object': 'chat.completion', 'created': 1780494450, 'model': 'anthropic/claude-4.7-opus-20260416', 'provider': 'Anthropic', 'system_fingerprint': None, 'service_tier': 'default', 'choices': [{'index': 0, 'logprobs': None, 'finish_reason': 'stop', 'native_finish_reason': 'end_turn', 'message': {'role': 'assistant', 'content': '{"final_numeric":null,"final_formula":"v_0 > \\\\sqrt{\\\\dfrac{kQq}{2\\\\pi\\\\varepsilon_0 m r_0}} = \\\\sqrt{\\\\dfrac{Qq}{2\\\\pi\\\\varepsilon_0 m r_0}}","final_units":"m/s"}', 'refusal': None, 'reasoning': None}}], 'usage': {'prompt_tokens': 828, 'completion_tokens': 118, 'total_tokens': 946, 'cost': 0.00709, 'is_byok': False, 'prompt_tokens_details': {'cached_tokens': 0, 'cache_write_tokens': 0, 'audio_tokens': 0, 'video_tokens': 0}, 'cost_details': {'upstream_inference_cost': 0.00709, 'upstream_inference_prompt_cost': 0.00414, 'upstream_inference_completions_cost': 0.00295}, 'completion_tokens_details': {'reasoning_tokens': 0, 'image_tokens': 0, 'audio_tokens': 0}}} | L21: 828 | M21: 118 | N21: 946 | O21: 0 | P21: =VLOOKUP(C21,problems!$A$2:$B$26,2) -> electrostatics | Q21: =IFERROR(__xludf.DUMMYFUNCTION("INDEX(FILTER('stats2-openrouter_activity_2026'!C:C,L21='stats2-openrouter_activity_2026'!H:H,M21='stats2-openrouter_activity_2026'!I:I, B21='stats2-openrouter_activity_2026'!M:M),1)"),0.00709) -> 0.00709 | R21: =IFS( F21=VLOOKUP($C21,problems!$A$2:$G$26,6),1, True,0 ) -> 1 | S21: =IFS( G21=VLOOKUP($C21,problems!$A$2:$G$26,4),1, G21=VLOOKUP($C21,problems!$A$2:$G$26,5),1, True,0 ) -> 0 | T21: =IFS( H21=VLOOKUP($C21,problems!$A$2:$G$26,7),1, True,0 ) -> 0
A22: 2026-06-03-17-48-54 | B22: anthropic/claude-opus-4.7 | C22: 21 | D22: Дано: Атомы водорода испускают монохроматический свет при переходе электронов с некоторой более удалённой орбиты на вторую боровскую орбиту: n -> 2 k — порядок дифракционного максимума. phi — угол дифракции. d = 2.6 мкм — постоянная дифракционной решётки. Пучок света падает на дифракционную решётку по нормали. R — постоянная Ридберга. c — скорость света. Найти: lambda — длина волны испущенного света. | E22: TRUE | G22: \lambda = \frac{d \sin\varphi}{k} | H22: m | J22: {"final_numeric":null,"final_formula":"\\lambda = \\frac{d \\sin\\varphi}{k}","final_units":"m"} | K22: {'id': 'gen-1780494533-WnHctGhkF5QOkNw2pZTo', 'object': 'chat.completion', 'created': 1780494533, 'model': 'anthropic/claude-4.7-opus-20260416', 'provider': 'Anthropic', 'system_fingerprint': None, 'service_tier': 'default', 'choices': [{'index': 0, 'logprobs': None, 'finish_reason': 'stop', 'native_finish_reason': 'end_turn', 'message': {'role': 'assistant', 'content': '{"final_numeric":null,"final_formula":"\\\\lambda = \\\\frac{d \\\\sin\\\\varphi}{k}","final_units":"m"}', 'refusal': None, 'reasoning': None}}], 'usage': {'prompt_tokens': 889, 'completion_tokens': 55, 'total_tokens': 944, 'cost': 0.00582, 'is_byok': False, 'prompt_tokens_details': {'cached_tokens': 0, 'cache_write_tokens': 0, 'audio_tokens': 0, 'video_tokens': 0}, 'cost_details': {'upstream_inference_cost': 0.00582, 'upstream_inference_prompt_cost': 0.004445, 'upstream_inference_completions_cost': 0.001375}, 'completion_tokens_details': {'reasoning_tokens': 0, 'image_tokens': 0, 'audio_tokens': 0}}} | L22: 889 | M22: 55 | N22: 944 | O22: 0 | P22: =VLOOKUP(C22,problems!$A$2:$B$26,2) -> nuclear | Q22: =IFERROR(__xludf.DUMMYFUNCTION("INDEX(FILTER('stats2-openrouter_activity_2026'!C:C,L22='stats2-openrouter_activity_2026'!H:H,M22='stats2-openrouter_activity_2026'!I:I, B22='stats2-openrouter_activity_2026'!M:M),1)"),0.00582) -> 0.00582 | R22: =IFS( F22=VLOOKUP($C22,problems!$A$2:$G$26,6),1, True,0 ) -> 0 | S22: =IFS( G22=VLOOKUP($C22,problems!$A$2:$G$26,4),1, G22=VLOOKUP($C22,problems!$A$2:$G$26,5),1, True,0 ) -> 0 | T22: =IFS( H22=VLOOKUP($C22,problems!$A$2:$G$26,7),1, True,0 ) -> 0
A23: 2026-06-03-17-51-02 | B23: anthropic/claude-opus-4.7 | C23: 22 | D23: Дано: Подводная лодка имеет мощность топливных установок: P = 14.7 МВт n = 25% — КПД установки m_0 = 1 кг — масса урана, для которой дана энергия деления E = 6.9 * 10^13 Дж — энергия, выделяющаяся при делении ядер урана t = 1 год — время плавания Найти: m — масса урана, необходимая для годового плавания лодки, в килограммах. | E23: TRUE | F23: 26.87 | G23: m = \frac{P \cdot t \cdot m_0}{\eta \cdot E} | H23: kg | J23: P*t / n = energy needed from fuel t = 365*24*3600 = 31536000 s P*t = 14.7e6 * 31536000 = 4.6358e14 J /0.25 = 1.8543e15 J m = m0 * E_needed / E = 1.8543e15 / 6.9e13 = 26.87 kg { "final_numeric": 26.87, "final_formula": "m = \\frac{P \\cdot t \\cdot m_0}{\\eta \\cdot E}", "final_units": "kg" } | K23: {'id': 'gen-1780494657-LxdRSJ6JmXx8qk4u54Ru', 'object': 'chat.completion', 'created': 1780494657, 'model': 'anthropic/claude-4.7-opus-20260416', 'provider': 'Anthropic', 'system_fingerprint': None, 'service_tier': 'default', 'choices': [{'index': 0, 'logprobs': None, 'finish_reason': 'stop', 'native_finish_reason': 'end_turn', 'message': {'role': 'assistant', 'content': 'P*t / n = energy needed from fuel\nt = 365*24*3600 = 31536000 s\nP*t = 14.7e6 * 31536000 = 4.6358e14 J\n/0.25 = 1.8543e15 J\nm = m0 * E_needed / E = 1.8543e15 / 6.9e13 = 26.87 kg\n\n{\n "final_numeric": 26.87,\n "final_formula": "m = \\\\frac{P \\\\cdot t \\\\cdot m_0}{\\\\eta \\\\cdot E}",\n "final_units": "kg"\n}', 'refusal': None, 'reasoning': None}}], 'usage': {'prompt_tokens': 870, 'completion_tokens': 192, 'total_tokens': 1062, 'cost': 0.00915, 'is_byok': False, 'prompt_tokens_details': {'cached_tokens': 0, 'cache_write_tokens': 0, 'audio_tokens': 0, 'video_tokens': 0}, 'cost_details': {'upstream_inference_cost': 0.00915, 'upstream_inference_prompt_cost': 0.00435, 'upstream_inference_completions_cost': 0.0048}, 'completion_tokens_details': {'reasoning_tokens': 0, 'image_tokens': 0, 'audio_tokens': 0}}} | L23: 870 | M23: 192 | N23: 1062 | O23: 0 | P23: =VLOOKUP(C23,problems!$A$2:$B$26,2) -> nuclear | Q23: =IFERROR(__xludf.DUMMYFUNCTION("INDEX(FILTER('stats2-openrouter_activity_2026'!C:C,L23='stats2-openrouter_activity_2026'!H:H,M23='stats2-openrouter_activity_2026'!I:I, B23='stats2-openrouter_activity_2026'!M:M),1)"),0.00915) -> 0.00915 | R23: =IFS( F23=VLOOKUP($C23,problems!$A$2:$G$26,6),1, True,0 ) -> 0 | S23: =IFS( G23=VLOOKUP($C23,problems!$A$2:$G$26,4),1, G23=VLOOKUP($C23,problems!$A$2:$G$26,5),1, True,0 ) -> 0 | T23: =IFS( H23=VLOOKUP($C23,problems!$A$2:$G$26,7),1, True,0 ) -> 1
A24: 2026-06-03-17-53-08 | B24: anthropic/claude-opus-4.7 | C24: 23 | D24: Дано: delta n_0 = 250 — начальное число импульсов за минуту. t = 1 ч delta n = 92 — число импульсов за минуту через время t. Найти: T_{1/2} — период полураспада данного изотопа, в минутах. | E24: TRUE | F24: 41.6 | G24: T_{1/2}=\frac{t\ln 2}{\ln(\Delta n_0/\Delta n)} | H24: min | J24: {"final_numeric":41.6,"final_formula":"T_{1/2}=\\frac{t\\ln 2}{\\ln(\\Delta n_0/\\Delta n)}","final_units":"min"} | K24: {'id': 'gen-1780494786-yc2cxFSbAUNAFqh0WwE7', 'object': 'chat.completion', 'created': 1780494786, 'model': 'anthropic/claude-4.7-opus-20260416', 'provider': 'Anthropic', 'system_fingerprint': None, 'service_tier': 'default', 'choices': [{'index': 0, 'logprobs': None, 'finish_reason': 'stop', 'native_finish_reason': 'end_turn', 'message': {'role': 'assistant', 'content': '{"final_numeric":41.6,"final_formula":"T_{1/2}=\\\\frac{t\\\\ln 2}{\\\\ln(\\\\Delta n_0/\\\\Delta n)}","final_units":"min"}', 'refusal': None, 'reasoning': None}}], 'usage': {'prompt_tokens': 804, 'completion_tokens': 76, 'total_tokens': 880, 'cost': 0.00592, 'is_byok': False, 'prompt_tokens_details': {'cached_tokens': 0, 'cache_write_tokens': 0, 'audio_tokens': 0, 'video_tokens': 0}, 'cost_details': {'upstream_inference_cost': 0.00592, 'upstream_inference_prompt_cost': 0.00402, 'upstream_inference_completions_cost': 0.0019}, 'completion_tokens_details': {'reasoning_tokens': 0, 'image_tokens': 0, 'audio_tokens': 0}}} | L24: 804 | M24: 76 | N24: 880 | O24: 0 | P24: =VLOOKUP(C24,problems!$A$2:$B$26,2) -> nuclear | Q24: =IFERROR(__xludf.DUMMYFUNCTION("INDEX(FILTER('stats2-openrouter_activity_2026'!C:C,L24='stats2-openrouter_activity_2026'!H:H,M24='stats2-openrouter_activity_2026'!I:I, B24='stats2-openrouter_activity_2026'!M:M),1)"),0.00592) -> 0.00592 | R24: =IFS( F24=VLOOKUP($C24,problems!$A$2:$G$26,6),1, True,0 ) -> 0 | S24: =IFS( G24=VLOOKUP($C24,problems!$A$2:$G$26,4),1, G24=VLOOKUP($C24,problems!$A$2:$G$26,5),1, True,0 ) -> 0 | T24: =IFS( H24=VLOOKUP($C24,problems!$A$2:$G$26,7),1, True,0 ) -> 1
A25: 2026-06-03-17-56-11 | B25: anthropic/claude-opus-4.7 | C25: 24 | D25: Given: M = 40 g/mol — atomic mass of chlorine Chlorine has two most common stable isotopes: {}^{35}_{17}\mathrm{Cl} {}^{37}_{17}\mathrm{Cl} M_{35} = 35 g/mol — atomic mass of chlorine 35 M_{37} = 37 g/mol — atomic mass of chlorine 37 f_{35} = 75.8% — abundance of chlorine-35 f_{37} = 24.2% — abundance of chlorine-37 Find: M_{avg} — the average atomic mass of chlorine, in g/mol, and check whether 40g/mol is correct. | E25: TRUE | F25: 35.484 | G25: M_{avg} = f_{35} M_{35} + f_{37} M_{37} | H25: g/mol | J25: {"final_numeric":35.484,"final_formula":"M_{avg} = f_{35} M_{35} + f_{37} M_{37}","final_units":"g/mol"} | K25: {'id': 'gen-1780494968-ElNRy6bicmTnLxjB4Is1', 'object': 'chat.completion', 'created': 1780494968, 'model': 'anthropic/claude-4.7-opus-20260416', 'provider': 'Anthropic', 'system_fingerprint': None, 'service_tier': 'default', 'choices': [{'index': 0, 'logprobs': None, 'finish_reason': 'stop', 'native_finish_reason': 'end_turn', 'message': {'role': 'assistant', 'content': '{"final_numeric":35.484,"final_formula":"M_{avg} = f_{35} M_{35} + f_{37} M_{37}","final_units":"g/mol"}', 'refusal': None, 'reasoning': None}}], 'usage': {'prompt_tokens': 943, 'completion_tokens': 63, 'total_tokens': 1006, 'cost': 0.00629, 'is_byok': False, 'prompt_tokens_details': {'cached_tokens': 0, 'cache_write_tokens': 0, 'audio_tokens': 0, 'video_tokens': 0}, 'cost_details': {'upstream_inference_cost': 0.00629, 'upstream_inference_prompt_cost': 0.004715, 'upstream_inference_completions_cost': 0.001575}, 'completion_tokens_details': {'reasoning_tokens': 0, 'image_tokens': 0, 'audio_tokens': 0}}} | L25: 943 | M25: 63 | N25: 1006 | O25: 0 | P25: =VLOOKUP(C25,problems!$A$2:$B$26,2) -> nuclear | Q25: =IFERROR(__xludf.DUMMYFUNCTION("INDEX(FILTER('stats2-openrouter_activity_2026'!C:C,L25='stats2-openrouter_activity_2026'!H:H,M25='stats2-openrouter_activity_2026'!I:I, B25='stats2-openrouter_activity_2026'!M:M),1)"),0.00629) -> 0.00629 | R25: =IFS( F25=VLOOKUP($C25,problems!$A$2:$G$26,6),1, True,0 ) -> 0 | S25: =IFS( G25=VLOOKUP($C25,problems!$A$2:$G$26,4),1, G25=VLOOKUP($C25,problems!$A$2:$G$26,5),1, True,0 ) -> 0 | T25: =IFS( H25=VLOOKUP($C25,problems!$A$2:$G$26,7),1, True,0 ) -> 1
A26: 2026-06-03-17-58-02 | B26: anthropic/claude-opus-4.7 | C26: 25 | D26: Given: lambda = 1 pm — photon's wavelength h — Planck’s constant c — speed of light Find: E — energy of the photon, in \text{MeV}. | E26: TRUE | F26: 1.24 | G26: E=\frac{hc}{\lambda} | H26: MeV | J26: {"final_numeric":1.24,"final_formula":"E=\\frac{hc}{\\lambda}","final_units":"MeV"} | K26: {'id': 'gen-1780495081-Rj1pOPm3s6emCvmD1CHn', 'object': 'chat.completion', 'created': 1780495081, 'model': 'anthropic/claude-4.7-opus-20260416', 'provider': 'Anthropic', 'system_fingerprint': None, 'service_tier': 'default', 'choices': [{'index': 0, 'logprobs': None, 'finish_reason': 'stop', 'native_finish_reason': 'end_turn', 'message': {'role': 'assistant', 'content': '{"final_numeric":1.24,"final_formula":"E=\\\\frac{hc}{\\\\lambda}","final_units":"MeV"}', 'refusal': None, 'reasoning': None}}], 'usage': {'prompt_tokens': 775, 'completion_tokens': 51, 'total_tokens': 826, 'cost': 0.00515, 'is_byok': False, 'prompt_tokens_details': {'cached_tokens': 0, 'cache_write_tokens': 0, 'audio_tokens': 0, 'video_tokens': 0}, 'cost_details': {'upstream_inference_cost': 0.00515, 'upstream_inference_prompt_cost': 0.003875, 'upstream_inference_completions_cost': 0.001275}, 'completion_tokens_details': {'reasoning_tokens': 0, 'image_tokens': 0, 'audio_tokens': 0}}} | L26: 775 | M26: 51 | N26: 826 | O26: 0 | P26: =VLOOKUP(C26,problems!$A$2:$B$26,2) -> nuclear | Q26: =IFERROR(__xludf.DUMMYFUNCTION("INDEX(FILTER('stats2-openrouter_activity_2026'!C:C,L26='stats2-openrouter_activity_2026'!H:H,M26='stats2-openrouter_activity_2026'!I:I, B26='stats2-openrouter_activity_2026'!M:M),1)"),0.00515) -> 0.00515 | R26: =IFS( F26=VLOOKUP($C26,problems!$A$2:$G$26,6),1, True,0 ) -> 1 | S26: =IFS( G26=VLOOKUP($C26,problems!$A$2:$G$26,4),1, G26=VLOOKUP($C26,problems!$A$2:$G$26,5),1, True,0 ) -> 0 | T26: =IFS( H26=VLOOKUP($C26,problems!$A$2:$G$26,7),1, True,0 ) -> 1
A27: 2026-06-03-17-06-01 | B27: anthropic/claude-sonnet-4.5 | C27: 1 | D27: Дано: l = 2 м — расстояние, которое частица пролетает равномерно a = 5*10^5 м/с^2 — ускорение торможения, направлено против движения. Найти: v - скорость частицы, при которой полное время движения от вылета до остановки минимально в м/с | E27: TRUE | F27: 1000 | G27: v = \sqrt{2la} = \sqrt{2 \cdot 2 \cdot 5 \times 10^5} = 1000 | H27: m/s | J27: I need to find the velocity that minimizes the total time of motion from launch until the particle stops. The particle moves in two phases: 1. Uniform motion (constant velocity v) over distance l = 2 m 2. Deceleration with a = 5×10⁵ m/s² until it stops **Phase 1 - Uniform motion:** - Distance: l = 2 m - Velocity: v (constant) - Time: t₁ = l/v = 2/v **Phase 2 - Deceleration:** - Initial velocity: v - Final velocity: 0 - Acceleration: -a = -5×10⁵ m/s² - Time: t₂ = v/a = v/(5×10⁵) - Distance: s₂ = v²/(2a) = v²/(2×5×10⁵) = v²/(10⁶) **Total time:** T = t₁ + t₂ = l/v + v/a = 2/v + v/(5×10⁵) **To minimize T, take derivative and set to zero:** dT/dv = -l/v² + 1/a = -2/v² + 1/(5×10⁵) = 0 Solving for v: 2/v² = 1/(5×10⁵) v² = 2 × 5×10⁵ v² = 10⁶ v = 10³ = 1000 m/s **Verification (second derivative):** d²T/dv² = 2l/v³ = 4/v³ > 0 for v > 0, confirming this is a minimum. **General formula:** v = √(2la) = √(2 × 2 × 5×10⁵) = √(2×10⁶) = 10³ m/s { "final_numeric": 1000, "final_formula": "v = \\sqrt{2la} = \\sqrt{2 \\cdot 2 \\cdot 5 \\times 10^5} = 1000", "final_units": "m/s" } | K27: {'id': 'gen-1780491953-YmB8b3V570IxwGSjjDtY', 'object': 'chat.completion', 'created': 1780491953, 'model': 'anthropic/claude-4.5-sonnet-20250929', 'provider': 'Amazon Bedrock', 'system_fingerprint': None, 'service_tier': None, 'choices': [{'index': 0, 'logprobs': None, 'finish_reason': 'stop', 'native_finish_reason': 'end_turn', 'message': {'role': 'assistant', 'content': 'I need to find the velocity that minimizes the total time of motion from launch until the particle stops.\n\nThe particle moves in two phases:\n1. Uniform motion (constant velocity v) over distance l = 2 m\n2. Deceleration with a = 5×10⁵ m/s² until it stops\n\n**Phase 1 - Uniform motion:**\n- Distance: l = 2 m\n- Velocity: v (constant)\n- Time: t₁ = l/v = 2/v\n\n**Phase 2 - Deceleration:**\n- Initial velocity: v\n- Final velocity: 0\n- Acceleration: -a = -5×10⁵ m/s²\n- Time: t₂ = v/a = v/(5×10⁵)\n- Distance: s₂ = v²/(2a) = v²/(2×5×10⁵) = v²/(10⁶)\n\n**Total time:**\nT = t₁ + t₂ = l/v + v/a = 2/v + v/(5×10⁵)\n\n**To minimize T, take derivative and set to zero:**\ndT/dv = -l/v² + 1/a = -2/v² + 1/(5×10⁵) = 0\n\nSolving for v:\n2/v² = 1/(5×10⁵)\nv² = 2 × 5×10⁵\nv² = 10⁶\nv = 10³ = 1000 m/s\n\n**Verification (second derivative):**\nd²T/dv² = 2l/v³ = 4/v³ > 0 for v > 0, confirming this is a minimum.\n\n**General formula:**\nv = √(2la) = √(2 × 2 × 5×10⁵) = √(2×10⁶) = 10³ m/s\n\n{\n "final_numeric": 1000,\n "final_formula": "v = \\\\sqrt{2la} = \\\\sqrt{2 \\\\cdot 2 \\\\cdot 5 \\\\times 10^5} = 1000",\n "final_units": "m/s"\n}', 'refusal': None, 'reasoning': None}}], 'usage': {'prompt_tokens': 590, 'completion_tokens': 554, 'total_tokens': 1144, 'cost': 0.01008, 'is_byok': False, 'prompt_tokens_details': {'cached_tokens': 0, 'cache_write_tokens': 0, 'audio_tokens': 0, 'video_tokens': 0}, 'cost_details': {'upstream_inference_cost': 0.01008, 'upstream_inference_prompt_cost': 0.00177, 'upstream_inference_completions_cost': 0.00831}, 'completion_tokens_details': {'reasoning_tokens': 0, 'image_tokens': 0, 'audio_tokens': 0}}} | L27: 590 | M27: 554 | N27: 1144 | O27: 0 | P27: =VLOOKUP(C27,problems!$A$2:$B$26,2) -> mechanics | Q27: =IFERROR(__xludf.DUMMYFUNCTION("INDEX(FILTER('stats2-openrouter_activity_2026'!C:C,L27='stats2-openrouter_activity_2026'!H:H,M27='stats2-openrouter_activity_2026'!I:I, B27='stats2-openrouter_activity_2026'!M:M),1)"),0.01008) -> 0.01008 | R27: =IFS( F27=VLOOKUP($C27,problems!$A$2:$G$26,6),1, True,0 ) -> 1 | S27: =IFS( G27=VLOOKUP($C27,problems!$A$2:$G$26,4),1, G27=VLOOKUP($C27,problems!$A$2:$G$26,5),1, True,0 ) -> 0 | T27: =IFS( H27=VLOOKUP($C27,problems!$A$2:$G$26,7),1, True,0 ) -> 1
A28: 2026-06-03-17-06-07 | B28: anthropic/claude-sonnet-4.5 | C28: 2 | D28: Дано: x = At+Bt^3 — закон движения точки по оси x. A = 6 м/с B = -0.125 м/с^3 t_1 = 2 с t_2 = 6 с Найти: v_{ср} — средняя скорость точки за интервал времени от t_{1} до t_{2}​ в м/с | E28: TRUE | F28: -1 | G28: v_{\text{ср}} = \frac{x(t_2) - x(t_1)}{t_2 - t_1} = \frac{A(t_2 - t_1) + B(t_2^3 - t_1^3)}{t_2 - t_1} | H28: m/s | J28: { "final_numeric": -1, "final_formula": "v_{\\text{ср}} = \\frac{x(t_2) - x(t_1)}{t_2 - t_1} = \\frac{A(t_2 - t_1) + B(t_2^3 - t_1^3)}{t_2 - t_1}", "final_units": "m/s" } | K28: {'id': 'gen-1780491964-9bIjBeFerV72pChIz6Oe', 'object': 'chat.completion', 'created': 1780491964, 'model': 'anthropic/claude-4.5-sonnet-20250929', 'provider': 'Amazon Bedrock', 'system_fingerprint': None, 'service_tier': None, 'choices': [{'index': 0, 'logprobs': None, 'finish_reason': 'stop', 'native_finish_reason': 'end_turn', 'message': {'role': 'assistant', 'content': '{\n "final_numeric": -1,\n "final_formula": "v_{\\\\text{ср}} = \\\\frac{x(t_2) - x(t_1)}{t_2 - t_1} = \\\\frac{A(t_2 - t_1) + B(t_2^3 - t_1^3)}{t_2 - t_1}",\n "final_units": "m/s"\n}', 'refusal': None, 'reasoning': None}}], 'usage': {'prompt_tokens': 601, 'completion_tokens': 117, 'total_tokens': 718, 'cost': 0.003558, 'is_byok': False, 'prompt_tokens_details': {'cached_tokens': 0, 'cache_write_tokens': 0, 'audio_tokens': 0, 'video_tokens': 0}, 'cost_details': {'upstream_inference_cost': 0.003558, 'upstream_inference_prompt_cost': 0.001803, 'upstream_inference_completions_cost': 0.001755}, 'completion_tokens_details': {'reasoning_tokens': 0, 'image_tokens': 0, 'audio_tokens': 0}}} | L28: 601 | M28: 117 | N28: 718 | O28: 0 | P28: =VLOOKUP(C28,problems!$A$2:$B$26,2) -> mechanics | Q28: =IFERROR(__xludf.DUMMYFUNCTION("INDEX(FILTER('stats2-openrouter_activity_2026'!C:C,L28='stats2-openrouter_activity_2026'!H:H,M28='stats2-openrouter_activity_2026'!I:I, B28='stats2-openrouter_activity_2026'!M:M),1)"),0.003558) -> 0.003558 | R28: =IFS( F28=VLOOKUP($C28,problems!$A$2:$G$26,6),1, True,0 ) -> 0 | S28: =IFS( G28=VLOOKUP($C28,problems!$A$2:$G$26,4),1, G28=VLOOKUP($C28,problems!$A$2:$G$26,5),1, True,0 ) -> 0 | T28: =IFS( H28=VLOOKUP($C28,problems!$A$2:$G$26,7),1, True,0 ) -> 1
A29: 2026-06-03-17-07-05 | B29: anthropic/claude-sonnet-4.5 | C29: 3 | D29: Given: v_{1} = 80 km/h — east truck's speed v_{2} = 50 km/h — north car's speed d = 32 km — distance from the truck to the intersection at the initial moment. Find: t — the time in hours after this moment when the vehicles will be closest to each other. | E29: TRUE | F29: 1035.5056 | G29: \frac{460800}{445} | H29: s | J29: I need to find when two vehicles will be closest to each other. **Setup:** - Truck moves east at v₁ = 80 km/h, starting 32 km from intersection - Car moves north at v₂ = 50 km/h, starting at intersection (assumed) **Coordinate system:** - Intersection at origin - East is positive x-direction - North is positive y-direction **Positions at time t:** - Truck: x₁(t) = 32 - 80t (moving toward intersection from east) - Car: x₂(t) = 0, y₂(t) = 50t (moving north from intersection) **Distance between vehicles:** D(t) = √[(32 - 80t)² + (50t)²] To minimize, I'll minimize D²(t): D²(t) = (32 - 80t)² + (50t)² D²(t) = 1024 - 5120t + 6400t² + 2500t² D²(t) = 1024 - 5120t + 8900t² **Finding minimum:** d(D²)/dt = -5120 + 17800t = 0 Solving for t: 17800t = 5120 t = 5120/17800 t = 512/1780 t = 128/445 Simplifying: t = 128/445 hours **Converting to decimal:** t ≈ 0.2876404494 hours **Converting to SI units (seconds):** t = (128/445) × 3600 seconds t = 460800/445 seconds t ≈ 1035.506 seconds Let me recalculate in SI: - v₁ = 80 km/h = 80000/3600 m/s = 200/9 m/s - v₂ = 50 km/h = 50000/3600 m/s = 125/9 m/s - d = 32 km = 32000 m D²(t) = (32000 - (200/9)t)² + ((125/9)t)² d(D²)/dt = 2(32000 - (200/9)t)(-200/9) + 2((125/9)t)(125/9) = 0 -2(32000)(200/9) + 2(200/9)²t + 2(125/9)²t = 0 2t[(200/9)² + (125/9)²] = 2(32000)(200/9) t = (32000 × 200/9) / [(40000 + 15625)/81] t = (6400000/9) / (55625/81) t = (6400000/9) × (81/55625) t = 6400000 × 9 / 55625 t = 57600000/55625 t = 460800/445 seconds t ≈ 1035.506 seconds { "final_numeric": 1035.5056179775281, "final_formula": "\\frac{460800}{445}", "final_units": "s" } | K29: {'id': 'gen-1780492012-QggAbWr1ngW37UiglGkU', 'object': 'chat.completion', 'created': 1780492012, 'model': 'anthropic/claude-4.5-sonnet-20250929', 'provider': 'Amazon Bedrock', 'system_fingerprint': None, 'service_tier': None, 'choices': [{'index': 0, 'logprobs': None, 'finish_reason': 'stop', 'native_finish_reason': 'end_turn', 'message': {'role': 'assistant', 'content': 'I need to find when two vehicles will be closest to each other.\n\n**Setup:**\n- Truck moves east at v₁ = 80 km/h, starting 32 km from intersection\n- Car moves north at v₂ = 50 km/h, starting at intersection (assumed)\n\n**Coordinate system:**\n- Intersection at origin\n- East is positive x-direction\n- North is positive y-direction\n\n**Positions at time t:**\n- Truck: x₁(t) = 32 - 80t (moving toward intersection from east)\n- Car: x₂(t) = 0, y₂(t) = 50t (moving north from intersection)\n\n**Distance between vehicles:**\nD(t) = √[(32 - 80t)² + (50t)²]\n\nTo minimize, I\'ll minimize D²(t):\nD²(t) = (32 - 80t)² + (50t)²\nD²(t) = 1024 - 5120t + 6400t² + 2500t²\nD²(t) = 1024 - 5120t + 8900t²\n\n**Finding minimum:**\nd(D²)/dt = -5120 + 17800t = 0\n\nSolving for t:\n17800t = 5120\nt = 5120/17800\nt = 512/1780\nt = 128/445\n\nSimplifying:\nt = 128/445 hours\n\n**Converting to decimal:**\nt ≈ 0.2876404494 hours\n\n**Converting to SI units (seconds):**\nt = (128/445) × 3600 seconds\nt = 460800/445 seconds\nt ≈ 1035.506 seconds\n\nLet me recalculate in SI:\n- v₁ = 80 km/h = 80000/3600 m/s = 200/9 m/s\n- v₂ = 50 km/h = 50000/3600 m/s = 125/9 m/s\n- d = 32 km = 32000 m\n\nD²(t) = (32000 - (200/9)t)² + ((125/9)t)²\n\nd(D²)/dt = 2(32000 - (200/9)t)(-200/9) + 2((125/9)t)(125/9) = 0\n\n-2(32000)(200/9) + 2(200/9)²t + 2(125/9)²t = 0\n\n2t[(200/9)² + (125/9)²] = 2(32000)(200/9)\n\nt = (32000 × 200/9) / [(40000 + 15625)/81]\nt = (6400000/9) / (55625/81)\nt = (6400000/9) × (81/55625)\nt = 6400000 × 9 / 55625\nt = 57600000/55625\nt = 460800/445 seconds\n\nt ≈ 1035.506 seconds\n\n{\n "final_numeric": 1035.5056179775281,\n "final_formula": "\\\\frac{460800}{445}",\n "final_units": "s"\n}', 'refusal': None, 'reasoning': None}}], 'usage': {'prompt_tokens': 570, 'completion_tokens': 803, 'total_tokens': 1373, 'cost': 0.013755, 'is_byok': False, 'prompt_tokens_details': {'cached_tokens': 0, 'cache_write_tokens': 0, 'audio_tokens': 0, 'video_tokens': 0}, 'cost_details': {'upstream_inference_cost': 0.013755, 'upstream_inference_prompt_cost': 0.00171, 'upstream_inference_completions_cost': 0.012045}, 'completion_tokens_details': {'reasoning_tokens': 0, 'image_tokens': 0, 'audio_tokens': 0}}} | L29: 570 | M29: 803 | N29: 1373 | O29: 0 | P29: =VLOOKUP(C29,problems!$A$2:$B$26,2) -> mechanics | Q29: =IFERROR(__xludf.DUMMYFUNCTION("INDEX(FILTER('stats2-openrouter_activity_2026'!C:C,L29='stats2-openrouter_activity_2026'!H:H,M29='stats2-openrouter_activity_2026'!I:I, B29='stats2-openrouter_activity_2026'!M:M),1)"),0.013755) -> 0.013755 | R29: =IFS( F29=VLOOKUP($C29,problems!$A$2:$G$26,6),1, True,0 ) -> 0 | S29: =IFS( G29=VLOOKUP($C29,problems!$A$2:$G$26,4),1, G29=VLOOKUP($C29,problems!$A$2:$G$26,5),1, True,0 ) -> 0 | T29: =IFS( H29=VLOOKUP($C29,problems!$A$2:$G$26,7),1, True,0 ) -> 0
A30: 2026-06-03-17-08-54 | B30: anthropic/claude-sonnet-4.5 | C30: 4 | D30: Дано: х = а_1 + b_{1}*t + y_{1}*t^2 — закон движения точки по оси x. y = α_2 + b_{2}*t + y_{2}*t^2 — закон движения точки по оси y. b_1 = b_2 = 1 м/с y_1 = -1 м/c^2 y_2 = 2 м/с^2 t = 1 с a — ускорение материальной точки Найти: \phi — угол между скоростью и ускорением в момент времени t в градусах | E30: TRUE | F30: 15.1 | G30: \phi = \arccos\left(\frac{11}{\sqrt{130}}\right) \approx 15.1^\circ | H30: ° | J30: I need to find the angle between velocity and acceleration vectors at time t = 1 s. **Step 1: Find velocity components** Given: - x = a₁ + b₁·t + γ₁·t² - y = a₂ + b₂·t + γ₂·t² Velocity components: - vₓ = dx/dt = b₁ + 2γ₁·t - vᵧ = dy/dt = b₂ + 2γ₂·t **Step 2: Find acceleration components** Acceleration components: - aₓ = d²x/dt² = 2γ₁ - aᵧ = d²y/dt² = 2γ₂ **Step 3: Calculate at t = 1 s** Given values: - b₁ = 1 m/s - b₂ = 1 m/s - γ₁ = -1 m/s² - γ₂ = 2 m/s² At t = 1 s: - vₓ = 1 + 2(-1)(1) = 1 - 2 = -1 m/s - vᵧ = 1 + 2(2)(1) = 1 + 4 = 5 m/s Acceleration (constant): - aₓ = 2(-1) = -2 m/s² - aᵧ = 2(2) = 4 m/s² **Step 4: Calculate angle between vectors** The angle φ between velocity and acceleration vectors: cos(φ) = (v⃗ · a⃗)/(|v⃗| · |a⃗|) Dot product: v⃗ · a⃗ = vₓ·aₓ + vᵧ·aᵧ = (-1)(-2) + (5)(4) = 2 + 20 = 22 Magnitudes: |v⃗| = √(vₓ² + vᵧ²) = √((-1)² + 5²) = √(1 + 25) = √26 |a⃗| = √(aₓ² + aᵧ²) = √((-2)² + 4²) = √(4 + 16) = √20 = 2√5 cos(φ) = 22/(√26 · 2√5) = 22/(2√130) = 11/√130 φ = arccos(11/√130) **Step 5: Calculate numerical value** √130 ≈ 11.4018 11/√130 ≈ 0.9649 φ = arccos(0.9649) ≈ 0.2636 radians Converting to degrees: φ ≈ 0.2636 × (180/π) ≈ 15.1° ```json { "final_numeric": 15.1, "final_formula": "\\phi = \\arccos\\left(\\frac{11}{\\sqrt{130}}\\right) \\approx 15.1^\\circ", "final_units": "°" } ``` | K30: {'id': 'gen-1780492124-KaK8QXr5CWIHle7Z7pkV', 'object': 'chat.completion', 'created': 1780492124, 'model': 'anthropic/claude-4.5-sonnet-20250929', 'provider': 'Amazon Bedrock', 'system_fingerprint': None, 'service_tier': None, 'choices': [{'index': 0, 'logprobs': None, 'finish_reason': 'stop', 'native_finish_reason': 'end_turn', 'message': {'role': 'assistant', 'content': 'I need to find the angle between velocity and acceleration vectors at time t = 1 s.\n\n**Step 1: Find velocity components**\n\nGiven:\n- x = a₁ + b₁·t + γ₁·t²\n- y = a₂ + b₂·t + γ₂·t²\n\nVelocity components:\n- vₓ = dx/dt = b₁ + 2γ₁·t\n- vᵧ = dy/dt = b₂ + 2γ₂·t\n\n**Step 2: Find acceleration components**\n\nAcceleration components:\n- aₓ = d²x/dt² = 2γ₁\n- aᵧ = d²y/dt² = 2γ₂\n\n**Step 3: Calculate at t = 1 s**\n\nGiven values:\n- b₁ = 1 m/s\n- b₂ = 1 m/s\n- γ₁ = -1 m/s²\n- γ₂ = 2 m/s²\n\nAt t = 1 s:\n- vₓ = 1 + 2(-1)(1) = 1 - 2 = -1 m/s\n- vᵧ = 1 + 2(2)(1) = 1 + 4 = 5 m/s\n\nAcceleration (constant):\n- aₓ = 2(-1) = -2 m/s²\n- aᵧ = 2(2) = 4 m/s²\n\n**Step 4: Calculate angle between vectors**\n\nThe angle φ between velocity and acceleration vectors:\n\ncos(φ) = (v⃗ · a⃗)/(|v⃗| · |a⃗|)\n\nDot product:\nv⃗ · a⃗ = vₓ·aₓ + vᵧ·aᵧ = (-1)(-2) + (5)(4) = 2 + 20 = 22\n\nMagnitudes:\n|v⃗| = √(vₓ² + vᵧ²) = √((-1)² + 5²) = √(1 + 25) = √26\n\n|a⃗| = √(aₓ² + aᵧ²) = √((-2)² + 4²) = √(4 + 16) = √20 = 2√5\n\ncos(φ) = 22/(√26 · 2√5) = 22/(2√130) = 11/√130\n\nφ = arccos(11/√130)\n\n**Step 5: Calculate numerical value**\n\n√130 ≈ 11.4018\n11/√130 ≈ 0.9649\n\nφ = arccos(0.9649) ≈ 0.2636 radians\n\nConverting to degrees:\nφ ≈ 0.2636 × (180/π) ≈ 15.1°\n\n```json\n{\n "final_numeric": 15.1,\n "final_formula": "\\\\phi = \\\\arccos\\\\left(\\\\frac{11}{\\\\sqrt{130}}\\\\right) \\\\approx 15.1^\\\\circ",\n "final_units": "°"\n}\n```', 'refusal': None, 'reasoning': None}}], 'usage': {'prompt_tokens': 661, 'completion_tokens': 828, 'total_tokens': 1489, 'cost': 0.014403, 'is_byok': False, 'prompt_tokens_details': {'cached_tokens': 0, 'cache_write_tokens': 0, 'audio_tokens': 0, 'video_tokens': 0}, 'cost_details': {'upstream_inference_cost': 0.014403, 'upstream_inference_prompt_cost': 0.001983, 'upstream_inference_completions_cost': 0.01242}, 'completion_tokens_details': {'reasoning_tokens': 0, 'image_tokens': 0, 'audio_tokens': 0}}} | L30: 661 | M30: 828 | N30: 1489 | O30: 0 | P30: =VLOOKUP(C30,problems!$A$2:$B$26,2) -> mechanics | Q30: =IFERROR(__xludf.DUMMYFUNCTION("INDEX(FILTER('stats2-openrouter_activity_2026'!C:C,L30='stats2-openrouter_activity_2026'!H:H,M30='stats2-openrouter_activity_2026'!I:I, B30='stats2-openrouter_activity_2026'!M:M),1)"),0.014403) -> 0.014403 | R30: =IFS( F30=VLOOKUP($C30,problems!$A$2:$G$26,6),1, True,0 ) -> 0 | S30: =IFS( G30=VLOOKUP($C30,problems!$A$2:$G$26,4),1, G30=VLOOKUP($C30,problems!$A$2:$G$26,5),1, True,0 ) -> 0 | T30: =IFS( H30=VLOOKUP($C30,problems!$A$2:$G$26,7),1, True,0 ) -> 0
A31: 2026-06-03-17-12-17 | B31: anthropic/claude-sonnet-4.5 | C31: 5 | D31: Given: A crate is moving across a rough floor surface. If no external pushing force is applied, friction slows the crate down until it stops. m = 50 kg — mass of the crate. v_0 = 8 m/s — initial speed of the crate. v = 0 m/s — final speed of the crate, because it comes to rest. \Delta t = 10 s — time during which the crate comes to rest. Find: P — the rate at which the frictional force takes energy away from the crate, in J/s. | E31: TRUE | F31: 160 | G31: P = \frac{\frac{1}{2}mv_0^2}{\Delta t} = \frac{\frac{1}{2}(50)(8)^2}{10} | H31: W | J31: I need to find the rate at which the frictional force takes energy away from the crate, which is the power dissipated by friction. **Step 1: Find the initial kinetic energy** $$KE_0 = \frac{1}{2}mv_0^2 = \frac{1}{2}(50)(8)^2 = \frac{1}{2}(50)(64) = 1600 \text{ J}$$ **Step 2: Find the final kinetic energy** $$KE_f = \frac{1}{2}mv^2 = \frac{1}{2}(50)(0)^2 = 0 \text{ J}$$ **Step 3: Find the energy dissipated by friction** $$\Delta E = KE_0 - KE_f = 1600 - 0 = 1600 \text{ J}$$ **Step 4: Find the average power (rate of energy dissipation)** $$P = \frac{\Delta E}{\Delta t} = \frac{1600}{10} = 160 \text{ W}$$ Since power is measured in Watts (W) and 1 W = 1 J/s, the answer is 160 J/s. The formula can be expressed as: $$P = \frac{\frac{1}{2}mv_0^2}{\Delta t}$$ { "final_numeric": 160, "final_formula": "P = \\frac{\\frac{1}{2}mv_0^2}{\\Delta t} = \\frac{\\frac{1}{2}(50)(8)^2}{10}", "final_units": "W" } | K31: {'id': 'gen-1780492332-hG5lV8qMfcbe930vfZqy', 'object': 'chat.completion', 'created': 1780492332, 'model': 'anthropic/claude-4.5-sonnet-20250929', 'provider': 'Amazon Bedrock', 'system_fingerprint': None, 'service_tier': None, 'choices': [{'index': 0, 'logprobs': None, 'finish_reason': 'stop', 'native_finish_reason': 'end_turn', 'message': {'role': 'assistant', 'content': 'I need to find the rate at which the frictional force takes energy away from the crate, which is the power dissipated by friction.\n\n**Step 1: Find the initial kinetic energy**\n$$KE_0 = \\frac{1}{2}mv_0^2 = \\frac{1}{2}(50)(8)^2 = \\frac{1}{2}(50)(64) = 1600 \\text{ J}$$\n\n**Step 2: Find the final kinetic energy**\n$$KE_f = \\frac{1}{2}mv^2 = \\frac{1}{2}(50)(0)^2 = 0 \\text{ J}$$\n\n**Step 3: Find the energy dissipated by friction**\n$$\\Delta E = KE_0 - KE_f = 1600 - 0 = 1600 \\text{ J}$$\n\n**Step 4: Find the average power (rate of energy dissipation)**\n$$P = \\frac{\\Delta E}{\\Delta t} = \\frac{1600}{10} = 160 \\text{ W}$$\n\nSince power is measured in Watts (W) and 1 W = 1 J/s, the answer is 160 J/s.\n\nThe formula can be expressed as:\n$$P = \\frac{\\frac{1}{2}mv_0^2}{\\Delta t}$$\n\n{\n "final_numeric": 160,\n "final_formula": "P = \\\\frac{\\\\frac{1}{2}mv_0^2}{\\\\Delta t} = \\\\frac{\\\\frac{1}{2}(50)(8)^2}{10}",\n "final_units": "W"\n}', 'refusal': None, 'reasoning': None}}], 'usage': {'prompt_tokens': 629, 'completion_tokens': 424, 'total_tokens': 1053, 'cost': 0.008247, 'is_byok': False, 'prompt_tokens_details': {'cached_tokens': 0, 'cache_write_tokens': 0, 'audio_tokens': 0, 'video_tokens': 0}, 'cost_details': {'upstream_inference_cost': 0.008247, 'upstream_inference_prompt_cost': 0.001887, 'upstream_inference_completions_cost': 0.00636}, 'completion_tokens_details': {'reasoning_tokens': 0, 'image_tokens': 0, 'audio_tokens': 0}}} | L31: 629 | M31: 424 | N31: 1053 | O31: 0 | P31: =VLOOKUP(C31,problems!$A$2:$B$26,2) -> mechanics | Q31: =IFERROR(__xludf.DUMMYFUNCTION("INDEX(FILTER('stats2-openrouter_activity_2026'!C:C,L31='stats2-openrouter_activity_2026'!H:H,M31='stats2-openrouter_activity_2026'!I:I, B31='stats2-openrouter_activity_2026'!M:M),1)"),0.008247) -> 0.008247 | R31: =IFS( F31=VLOOKUP($C31,problems!$A$2:$G$26,6),1, True,0 ) -> 1 | S31: =IFS( G31=VLOOKUP($C31,problems!$A$2:$G$26,4),1, G31=VLOOKUP($C31,problems!$A$2:$G$26,5),1, True,0 ) -> 0 | T31: =IFS( H31=VLOOKUP($C31,problems!$A$2:$G$26,7),1, True,0 ) -> 0
A32: 2026-06-03-17-13-42 | B32: anthropic/claude-sonnet-4.5 | C32: 6 | D32: Given: N = 8 — number of bumper cars. m = 322 kg — mass of each bumper car. L = 21 m — length of the room. W = 13 m — width of the room. v_rms = 2.5 m/s — rms speed of the bumper cars. The cars move randomly and bounce off the walls, similar to gas particles. Find: P — the average force per unit length that the cars exert on the walls, in N/m. | E32: TRUE | F32: 29.487179 | G32: P = \frac{N m v_{rms}^2}{2LW} | H32: N/m | J32: I need to find the average force per unit length that bumper cars exert on the walls. This problem is analogous to kinetic theory of gases, where particles collide with walls and exert pressure. For a 2D system (bumper cars on a floor), I'll use kinetic theory principles. **Step 1: Find the pressure on the walls** For a 2D ideal gas, the pressure is related to kinetic energy: $$P = \frac{N m v_{rms}^2}{2A}$$ where A is the area of the room. However, in 2D, we need to consider that pressure acts on the perimeter, not area. **Step 2: Use kinetic theory for 2D** The force on a wall segment comes from momentum transfer. For a 2D system: The average force on a wall of length ℓ is: $$F = \frac{N m v_{rms}^2 \cdot \ell}{2 \cdot \text{perimeter} \cdot L_{perpendicular}}$$ Actually, let me reconsider using the proper 2D kinetic theory approach. **Step 3: Correct approach - 2D kinetic theory** For a rectangular enclosure, the pressure (force per unit length in 2D) is: $$P_{2D} = \frac{N m v_{rms}^2}{2A}$$ where A = L × W is the area. In 2D kinetic theory, pressure has units of force per length, and: $$P = \frac{N m v_{rms}^2}{2LW}$$ **Step 4: Calculate** Given: - N = 8 - m = 322 kg - L = 21 m - W = 13 m - v_rms = 2.5 m/s $$P = \frac{8 \times 322 \times (2.5)^2}{2 \times 21 \times 13}$$ $$P = \frac{8 \times 322 \times 6.25}{2 \times 273}$$ $$P = \frac{16100}{546}$$ $$P = 29.487... \approx 29.49 \text{ N/m}$$ Let me verify the calculation: - Numerator: 8 × 322 × 6.25 = 2576 × 6.25 = 16100 - Denominator: 2 × 21 × 13 = 2 × 273 = 546 - Result: 16100/546 ≈ 29.487 { "final_numeric": 29.487179487179485, "final_formula": "P = \\frac{N m v_{rms}^2}{2LW}", "final_units": "N/m" } | K32: {'id': 'gen-1780492411-hJWgo41Bs5TZELznfXyR', 'object': 'chat.completion', 'created': 1780492411, 'model': 'anthropic/claude-4.5-sonnet-20250929', 'provider': 'Amazon Bedrock', 'system_fingerprint': None, 'service_tier': None, 'choices': [{'index': 0, 'logprobs': None, 'finish_reason': 'stop', 'native_finish_reason': 'end_turn', 'message': {'role': 'assistant', 'content': 'I need to find the average force per unit length that bumper cars exert on the walls.\n\nThis problem is analogous to kinetic theory of gases, where particles collide with walls and exert pressure.\n\nFor a 2D system (bumper cars on a floor), I\'ll use kinetic theory principles.\n\n**Step 1: Find the pressure on the walls**\n\nFor a 2D ideal gas, the pressure is related to kinetic energy:\n$$P = \\frac{N m v_{rms}^2}{2A}$$\n\nwhere A is the area of the room.\n\nHowever, in 2D, we need to consider that pressure acts on the perimeter, not area.\n\n**Step 2: Use kinetic theory for 2D**\n\nThe force on a wall segment comes from momentum transfer. For a 2D system:\n\nThe average force on a wall of length ℓ is:\n$$F = \\frac{N m v_{rms}^2 \\cdot \\ell}{2 \\cdot \\text{perimeter} \\cdot L_{perpendicular}}$$\n\nActually, let me reconsider using the proper 2D kinetic theory approach.\n\n**Step 3: Correct approach - 2D kinetic theory**\n\nFor a rectangular enclosure, the pressure (force per unit length in 2D) is:\n\n$$P_{2D} = \\frac{N m v_{rms}^2}{2A}$$\n\nwhere A = L × W is the area.\n\nIn 2D kinetic theory, pressure has units of force per length, and:\n$$P = \\frac{N m v_{rms}^2}{2LW}$$\n\n**Step 4: Calculate**\n\nGiven:\n- N = 8\n- m = 322 kg\n- L = 21 m\n- W = 13 m\n- v_rms = 2.5 m/s\n\n$$P = \\frac{8 \\times 322 \\times (2.5)^2}{2 \\times 21 \\times 13}$$\n\n$$P = \\frac{8 \\times 322 \\times 6.25}{2 \\times 273}$$\n\n$$P = \\frac{16100}{546}$$\n\n$$P = 29.487... \\approx 29.49 \\text{ N/m}$$\n\nLet me verify the calculation:\n- Numerator: 8 × 322 × 6.25 = 2576 × 6.25 = 16100\n- Denominator: 2 × 21 × 13 = 2 × 273 = 546\n- Result: 16100/546 ≈ 29.487\n\n{\n "final_numeric": 29.487179487179485,\n "final_formula": "P = \\\\frac{N m v_{rms}^2}{2LW}",\n "final_units": "N/m"\n}', 'refusal': None, 'reasoning': None}}], 'usage': {'prompt_tokens': 612, 'completion_tokens': 699, 'total_tokens': 1311, 'cost': 0.012321, 'is_byok': False, 'prompt_tokens_details': {'cached_tokens': 0, 'cache_write_tokens': 0, 'audio_tokens': 0, 'video_tokens': 0}, 'cost_details': {'upstream_inference_cost': 0.012321, 'upstream_inference_prompt_cost': 0.001836, 'upstream_inference_completions_cost': 0.010485}, 'completion_tokens_details': {'reasoning_tokens': 0, 'image_tokens': 0, 'audio_tokens': 0}}} | L32: 612 | M32: 699 | N32: 1311 | O32: 0 | P32: =VLOOKUP(C32,problems!$A$2:$B$26,2) -> thermodynamics | Q32: =IFERROR(__xludf.DUMMYFUNCTION("INDEX(FILTER('stats2-openrouter_activity_2026'!C:C,L32='stats2-openrouter_activity_2026'!H:H,M32='stats2-openrouter_activity_2026'!I:I, B32='stats2-openrouter_activity_2026'!M:M),1)"),0.012321) -> 0.012321 | R32: =IFS( F32=VLOOKUP($C32,problems!$A$2:$G$26,6),1, True,0 ) -> 0 | S32: =IFS( G32=VLOOKUP($C32,problems!$A$2:$G$26,4),1, G32=VLOOKUP($C32,problems!$A$2:$G$26,5),1, True,0 ) -> 0 | T32: =IFS( H32=VLOOKUP($C32,problems!$A$2:$G$26,7),1, True,0 ) -> 1
A33: 2026-06-03-17-15-08 | B33: anthropic/claude-sonnet-4.5 | C33: 7 | D33: Дано: t = 11∘C — температура водорода. m = 5 г — масса водорода. V_2/V_1 = 3 — объем водорода увеличился в 3 раза. Найти: A — работу, совершенную водородом при изотермическом расширении, в кДж. | E33: TRUE | F33: 6489.66 | G33: A = \nu RT \ln\left(\frac{V_2}{V_1}\right) = \frac{m}{M}RT\ln(3) | H33: J | J33: I need to find the work done by hydrogen during isothermal expansion. **Given:** - t = 11°C, so T = 11 + 273 = 284 K - m = 5 g = 0.005 kg - V₂/V₁ = 3 - Hydrogen is diatomic (H₂), so M = 2 g/mol = 0.002 kg/mol **Formula for isothermal work:** For an isothermal process, the work done by an ideal gas is: $$A = \nu RT \ln\left(\frac{V_2}{V_1}\right)$$ where ν is the number of moles. **Calculate number of moles:** $$\nu = \frac{m}{M} = \frac{5 \text{ g}}{2 \text{ g/mol}} = 2.5 \text{ mol}$$ **Calculate work:** $$A = \nu RT \ln\left(\frac{V_2}{V_1}\right)$$ $$A = 2.5 \times 8.314 \times 284 \times \ln(3)$$ $$A = 2.5 \times 8.314 \times 284 \times 1.0986$$ $$A = 2.5 \times 8.314 \times 284 \times 1.0986$$ $$A = 6489.7 \text{ J}$$ $$A = 6.49 \text{ kJ}$$ Rounding to appropriate significant figures: A ≈ 6.49 kJ Converting to SI base units (Joules): A = 6489.7 J ≈ 6490 J Since the problem asks for the answer in kJ, I'll provide the answer in kJ but note that SI base unit is J. Let me recalculate more precisely: - ν = 2.5 mol - R = 8.314 J/(mol·K) - T = 284 K - ln(3) = 1.0986 A = 2.5 × 8.314 × 284 × 1.0986 = 6489.66 J = 6.48966 kJ Since the problem specifically asks for kJ, the answer is approximately 6.49 kJ or 6490 J in SI base units. { "final_numeric": 6489.66, "final_formula": "A = \\nu RT \\ln\\left(\\frac{V_2}{V_1}\\right) = \\frac{m}{M}RT\\ln(3)", "final_units": "J" } | K33: {'id': 'gen-1780492500-tDoeHQqTRmdq6pcmwH0W', 'object': 'chat.completion', 'created': 1780492500, 'model': 'anthropic/claude-4.5-sonnet-20250929', 'provider': 'Amazon Bedrock', 'system_fingerprint': None, 'service_tier': None, 'choices': [{'index': 0, 'logprobs': None, 'finish_reason': 'stop', 'native_finish_reason': 'end_turn', 'message': {'role': 'assistant', 'content': 'I need to find the work done by hydrogen during isothermal expansion.\n\n**Given:**\n- t = 11°C, so T = 11 + 273 = 284 K\n- m = 5 g = 0.005 kg\n- V₂/V₁ = 3\n- Hydrogen is diatomic (H₂), so M = 2 g/mol = 0.002 kg/mol\n\n**Formula for isothermal work:**\nFor an isothermal process, the work done by an ideal gas is:\n$$A = \\nu RT \\ln\\left(\\frac{V_2}{V_1}\\right)$$\n\nwhere ν is the number of moles.\n\n**Calculate number of moles:**\n$$\\nu = \\frac{m}{M} = \\frac{5 \\text{ g}}{2 \\text{ g/mol}} = 2.5 \\text{ mol}$$\n\n**Calculate work:**\n$$A = \\nu RT \\ln\\left(\\frac{V_2}{V_1}\\right)$$\n\n$$A = 2.5 \\times 8.314 \\times 284 \\times \\ln(3)$$\n\n$$A = 2.5 \\times 8.314 \\times 284 \\times 1.0986$$\n\n$$A = 2.5 \\times 8.314 \\times 284 \\times 1.0986$$\n\n$$A = 6489.7 \\text{ J}$$\n\n$$A = 6.49 \\text{ kJ}$$\n\nRounding to appropriate significant figures: A ≈ 6.49 kJ\n\nConverting to SI base units (Joules): A = 6489.7 J ≈ 6490 J\n\nSince the problem asks for the answer in kJ, I\'ll provide the answer in kJ but note that SI base unit is J.\n\nLet me recalculate more precisely:\n- ν = 2.5 mol\n- R = 8.314 J/(mol·K)\n- T = 284 K\n- ln(3) = 1.0986\n\nA = 2.5 × 8.314 × 284 × 1.0986 = 6489.66 J = 6.48966 kJ\n\nSince the problem specifically asks for kJ, the answer is approximately 6.49 kJ or 6490 J in SI base units.\n\n{\n "final_numeric": 6489.66,\n "final_formula": "A = \\\\nu RT \\\\ln\\\\left(\\\\frac{V_2}{V_1}\\\\right) = \\\\frac{m}{M}RT\\\\ln(3)",\n "final_units": "J"\n}', 'refusal': None, 'reasoning': None}}], 'usage': {'prompt_tokens': 586, 'completion_tokens': 660, 'total_tokens': 1246, 'cost': 0.011658, 'is_byok': False, 'prompt_tokens_details': {'cached_tokens': 0, 'cache_write_tokens': 0, 'audio_tokens': 0, 'video_tokens': 0}, 'cost_details': {'upstream_inference_cost': 0.011658, 'upstream_inference_prompt_cost': 0.001758, 'upstream_inference_completions_cost': 0.0099}, 'completion_tokens_details': {'reasoning_tokens': 0, 'image_tokens': 0, 'audio_tokens': 0}}} | L33: 586 | M33: 660 | N33: 1246 | O33: 0 | P33: =VLOOKUP(C33,problems!$A$2:$B$26,2) -> thermodynamics | Q33: =IFERROR(__xludf.DUMMYFUNCTION("INDEX(FILTER('stats2-openrouter_activity_2026'!C:C,L33='stats2-openrouter_activity_2026'!H:H,M33='stats2-openrouter_activity_2026'!I:I, B33='stats2-openrouter_activity_2026'!M:M),1)"),0.011658) -> 0.011658 | R33: =IFS( F33=VLOOKUP($C33,problems!$A$2:$G$26,6),1, True,0 ) -> 0 | S33: =IFS( G33=VLOOKUP($C33,problems!$A$2:$G$26,4),1, G33=VLOOKUP($C33,problems!$A$2:$G$26,5),1, True,0 ) -> 0 | T33: =IFS( H33=VLOOKUP($C33,problems!$A$2:$G$26,7),1, True,0 ) -> 0
A34: 2026-06-03-17-17-53 | B34: anthropic/claude-sonnet-4.5 | C34: 8 | D34: Find: An air bubble rises from the bottom to the top of a freshwater lake. V_2/V_1 = 1.8 — the bubble’s volume increases by 80%. T_1 = 4∘C — temperature at the bottom of the lake. T_2 = 10∘C — temperature at the top of the lake. p_0 = 1.01 * 10^5 Pa — atmospheric pressure at the surface of the lake. p = 1000 kg/m^3 — density of freshwater. Find: h — the depth of the lake, in meters. | E34: TRUE | F34: 7.85 | G34: h = \frac{p_0}{\rho g} \left(\frac{V_2}{V_1} \cdot \frac{T_1}{T_2} - 1\right) | H34: m | J34: I need to find the depth of the lake using the ideal gas law and pressure relationships. **Given:** - V₂/V₁ = 1.8 - T₁ = 4°C = 277 K - T₂ = 10°C = 283 K - p₀ = 1.01 × 10⁵ Pa - ρ = 1000 kg/m³ - g = 9.8 m/s² (standard) **Solution:** At the bottom of the lake (depth h): - Pressure: p₁ = p₀ + ρgh - Temperature: T₁ = 277 K - Volume: V₁ At the top of the lake: - Pressure: p₂ = p₀ - Temperature: T₂ = 283 K - Volume: V₂ Using the ideal gas law for the same amount of gas: $$\frac{p_1 V_1}{T_1} = \frac{p_2 V_2}{T_2}$$ Rearranging: $$\frac{p_1}{p_2} = \frac{V_2}{V_1} \cdot \frac{T_1}{T_2}$$ Substituting p₁ = p₀ + ρgh and p₂ = p₀: $$\frac{p_0 + \rho g h}{p_0} = \frac{V_2}{V_1} \cdot \frac{T_1}{T_2}$$ $$1 + \frac{\rho g h}{p_0} = \frac{V_2}{V_1} \cdot \frac{T_1}{T_2}$$ $$\frac{\rho g h}{p_0} = \frac{V_2}{V_1} \cdot \frac{T_1}{T_2} - 1$$ $$h = \frac{p_0}{\rho g} \left(\frac{V_2}{V_1} \cdot \frac{T_1}{T_2} - 1\right)$$ **Calculating:** $$\frac{V_2}{V_1} \cdot \frac{T_1}{T_2} = 1.8 \times \frac{277}{283} = 1.8 \times 0.9788 = 1.7618$$ $$h = \frac{1.01 \times 10^5}{1000 \times 9.8} \times (1.7618 - 1)$$ $$h = \frac{1.01 \times 10^5}{9800} \times 0.7618$$ $$h = 10.306 \times 0.7618 = 7.851$$ m Rounding to appropriate significant figures: h ≈ 7.85 m ```json { "final_numeric": 7.85, "final_formula": "h = \\frac{p_0}{\\rho g} \\left(\\frac{V_2}{V_1} \\cdot \\frac{T_1}{T_2} - 1\\right)", "final_units": "m" } ``` | K34: {'id': 'gen-1780492664-HNY4KMjVZBUBnZ3zZEmC', 'object': 'chat.completion', 'created': 1780492664, 'model': 'anthropic/claude-4.5-sonnet-20250929', 'provider': 'Amazon Bedrock', 'system_fingerprint': None, 'service_tier': None, 'choices': [{'index': 0, 'logprobs': None, 'finish_reason': 'stop', 'native_finish_reason': 'end_turn', 'message': {'role': 'assistant', 'content': 'I need to find the depth of the lake using the ideal gas law and pressure relationships.\n\n**Given:**\n- V₂/V₁ = 1.8\n- T₁ = 4°C = 277 K\n- T₂ = 10°C = 283 K\n- p₀ = 1.01 × 10⁵ Pa\n- ρ = 1000 kg/m³\n- g = 9.8 m/s² (standard)\n\n**Solution:**\n\nAt the bottom of the lake (depth h):\n- Pressure: p₁ = p₀ + ρgh\n- Temperature: T₁ = 277 K\n- Volume: V₁\n\nAt the top of the lake:\n- Pressure: p₂ = p₀\n- Temperature: T₂ = 283 K\n- Volume: V₂\n\nUsing the ideal gas law for the same amount of gas:\n$$\\frac{p_1 V_1}{T_1} = \\frac{p_2 V_2}{T_2}$$\n\nRearranging:\n$$\\frac{p_1}{p_2} = \\frac{V_2}{V_1} \\cdot \\frac{T_1}{T_2}$$\n\nSubstituting p₁ = p₀ + ρgh and p₂ = p₀:\n$$\\frac{p_0 + \\rho g h}{p_0} = \\frac{V_2}{V_1} \\cdot \\frac{T_1}{T_2}$$\n\n$$1 + \\frac{\\rho g h}{p_0} = \\frac{V_2}{V_1} \\cdot \\frac{T_1}{T_2}$$\n\n$$\\frac{\\rho g h}{p_0} = \\frac{V_2}{V_1} \\cdot \\frac{T_1}{T_2} - 1$$\n\n$$h = \\frac{p_0}{\\rho g} \\left(\\frac{V_2}{V_1} \\cdot \\frac{T_1}{T_2} - 1\\right)$$\n\n**Calculating:**\n$$\\frac{V_2}{V_1} \\cdot \\frac{T_1}{T_2} = 1.8 \\times \\frac{277}{283} = 1.8 \\times 0.9788 = 1.7618$$\n\n$$h = \\frac{1.01 \\times 10^5}{1000 \\times 9.8} \\times (1.7618 - 1)$$\n\n$$h = \\frac{1.01 \\times 10^5}{9800} \\times 0.7618$$\n\n$$h = 10.306 \\times 0.7618 = 7.851$$ m\n\nRounding to appropriate significant figures: h ≈ 7.85 m\n\n```json\n{\n "final_numeric": 7.85,\n "final_formula": "h = \\\\frac{p_0}{\\\\rho g} \\\\left(\\\\frac{V_2}{V_1} \\\\cdot \\\\frac{T_1}{T_2} - 1\\\\right)",\n "final_units": "m"\n}\n```', 'refusal': None, 'reasoning': None}}], 'usage': {'prompt_tokens': 636, 'completion_tokens': 821, 'total_tokens': 1457, 'cost': 0.014223, 'is_byok': False, 'prompt_tokens_details': {'cached_tokens': 0, 'cache_write_tokens': 0, 'audio_tokens': 0, 'video_tokens': 0}, 'cost_details': {'upstream_inference_cost': 0.014223, 'upstream_inference_prompt_cost': 0.001908, 'upstream_inference_completions_cost': 0.012315}, 'completion_tokens_details': {'reasoning_tokens': 0, 'image_tokens': 0, 'audio_tokens': 0}}} | L34: 636 | M34: 821 | N34: 1457 | O34: 0 | P34: =VLOOKUP(C34,problems!$A$2:$B$26,2) -> thermodynamics | Q34: =IFERROR(__xludf.DUMMYFUNCTION("INDEX(FILTER('stats2-openrouter_activity_2026'!C:C,L34='stats2-openrouter_activity_2026'!H:H,M34='stats2-openrouter_activity_2026'!I:I, B34='stats2-openrouter_activity_2026'!M:M),1)"),0.014223) -> 0.014223 | R34: =IFS( F34=VLOOKUP($C34,problems!$A$2:$G$26,6),1, True,0 ) -> 0 | S34: =IFS( G34=VLOOKUP($C34,problems!$A$2:$G$26,4),1, G34=VLOOKUP($C34,problems!$A$2:$G$26,5),1, True,0 ) -> 0 | T34: =IFS( H34=VLOOKUP($C34,problems!$A$2:$G$26,7),1, True,0 ) -> 1
A35: 2026-06-03-17-19-37 | B35: anthropic/claude-sonnet-4.5 | C35: 9 | D35: Given: T = 30∘C — air temperature. T_d = 15∘C — dew-point temperature, because condensation first appears when the can reaches 15∘C. Find: \phi\ — relative humidity of the air, in percent. | E35: TRUE | F35: 40.2 | G35: \phi = \frac{e_s(T_d)}{e_s(T)} \times 100\% \approx 40.2\% | H35: 1 | J35: I need to find the relative humidity given the air temperature and dew-point temperature. The relative humidity φ is defined as: φ = (e/e_s) × 100% where: - e is the actual vapor pressure at temperature T - e_s is the saturation vapor pressure at temperature T At the dew point temperature T_d, the air is saturated, so the actual vapor pressure e equals the saturation vapor pressure at T_d: e = e_s(T_d) Therefore: φ = (e_s(T_d)/e_s(T)) × 100% Using the Magnus formula for saturation vapor pressure: e_s(T) = 6.11 × exp((17.27 × T)/(T + 237.3)) [in hPa, with T in °C] For T = 30°C: e_s(30) = 6.11 × exp((17.27 × 30)/(30 + 237.3)) e_s(30) = 6.11 × exp(518.1/267.3) e_s(30) = 6.11 × exp(1.9385) e_s(30) = 6.11 × 6.946 e_s(30) ≈ 42.44 hPa For T_d = 15°C: e_s(15) = 6.11 × exp((17.27 × 15)/(15 + 237.3)) e_s(15) = 6.11 × exp(259.05/252.3) e_s(15) = 6.11 × exp(1.0268) e_s(15) = 6.11 × 2.792 e_s(15) ≈ 17.06 hPa Therefore: φ = (17.06/42.44) × 100% φ = 0.402 × 100% φ ≈ 40.2% Since relative humidity is typically expressed as a percentage (dimensionless), the units are "1" (unitless). { "final_numeric": 40.2, "final_formula": "\\phi = \\frac{e_s(T_d)}{e_s(T)} \\times 100\\% \\approx 40.2\\%", "final_units": "1" } | K35: {'id': 'gen-1780492769-sbJnG0oGLzG75czaRY62', 'object': 'chat.completion', 'created': 1780492769, 'model': 'anthropic/claude-4.5-sonnet-20250929', 'provider': 'Amazon Bedrock', 'system_fingerprint': None, 'service_tier': None, 'choices': [{'index': 0, 'logprobs': None, 'finish_reason': 'stop', 'native_finish_reason': 'end_turn', 'message': {'role': 'assistant', 'content': 'I need to find the relative humidity given the air temperature and dew-point temperature.\n\nThe relative humidity φ is defined as:\nφ = (e/e_s) × 100%\n\nwhere:\n- e is the actual vapor pressure at temperature T\n- e_s is the saturation vapor pressure at temperature T\n\nAt the dew point temperature T_d, the air is saturated, so the actual vapor pressure e equals the saturation vapor pressure at T_d:\ne = e_s(T_d)\n\nTherefore:\nφ = (e_s(T_d)/e_s(T)) × 100%\n\nUsing the Magnus formula for saturation vapor pressure:\ne_s(T) = 6.11 × exp((17.27 × T)/(T + 237.3)) [in hPa, with T in °C]\n\nFor T = 30°C:\ne_s(30) = 6.11 × exp((17.27 × 30)/(30 + 237.3))\ne_s(30) = 6.11 × exp(518.1/267.3)\ne_s(30) = 6.11 × exp(1.9385)\ne_s(30) = 6.11 × 6.946\ne_s(30) ≈ 42.44 hPa\n\nFor T_d = 15°C:\ne_s(15) = 6.11 × exp((17.27 × 15)/(15 + 237.3))\ne_s(15) = 6.11 × exp(259.05/252.3)\ne_s(15) = 6.11 × exp(1.0268)\ne_s(15) = 6.11 × 2.792\ne_s(15) ≈ 17.06 hPa\n\nTherefore:\nφ = (17.06/42.44) × 100%\nφ = 0.402 × 100%\nφ ≈ 40.2%\n\nSince relative humidity is typically expressed as a percentage (dimensionless), the units are "1" (unitless).\n\n{\n "final_numeric": 40.2,\n "final_formula": "\\\\phi = \\\\frac{e_s(T_d)}{e_s(T)} \\\\times 100\\\\% \\\\approx 40.2\\\\%",\n "final_units": "1"\n}', 'refusal': None, 'reasoning': None}}], 'usage': {'prompt_tokens': 553, 'completion_tokens': 594, 'total_tokens': 1147, 'cost': 0.010569, 'is_byok': False, 'prompt_tokens_details': {'cached_tokens': 0, 'cache_write_tokens': 0, 'audio_tokens': 0, 'video_tokens': 0}, 'cost_details': {'upstream_inference_cost': 0.010569, 'upstream_inference_prompt_cost': 0.001659, 'upstream_inference_completions_cost': 0.00891}, 'completion_tokens_details': {'reasoning_tokens': 0, 'image_tokens': 0, 'audio_tokens': 0}}} | L35: 553 | M35: 594 | N35: 1147 | O35: 0 | P35: =VLOOKUP(C35,problems!$A$2:$B$26,2) -> thermodynamics | Q35: =IFERROR(__xludf.DUMMYFUNCTION("INDEX(FILTER('stats2-openrouter_activity_2026'!C:C,L35='stats2-openrouter_activity_2026'!H:H,M35='stats2-openrouter_activity_2026'!I:I, B35='stats2-openrouter_activity_2026'!M:M),1)"),0.010569) -> 0.010569 | R35: =IFS( F35=VLOOKUP($C35,problems!$A$2:$G$26,6),1, True,0 ) -> 0 | S35: =IFS( G35=VLOOKUP($C35,problems!$A$2:$G$26,4),1, G35=VLOOKUP($C35,problems!$A$2:$G$26,5),1, True,0 ) -> 0 | T35: =IFS( H35=VLOOKUP($C35,problems!$A$2:$G$26,7),1, True,0 ) -> 0
A36: 2026-06-03-17-21-24 | B36: anthropic/claude-sonnet-4.5 | C36: 10 | D36: Дано: V_1 = 10л — начальный объем газа. p_1 = 2 * 10^5 Па — начальное давление газа. V_2 = 28 л — конечный объем газа. Процесс - изотермический Найти: A — работа, совершенная газом при изотермическом расширении, в кДж. | E36: TRUE | F36: 2.06 | G36: A = p_1 V_1 \ln\left(\frac{V_2}{V_1}\right) = 2 \times 10^5 \times 0.01 \times \ln\left(\frac{0.028}{0.01}\right) | H36: kJ | J36: { "final_numeric": 2.06, "final_formula": "A = p_1 V_1 \\ln\\left(\\frac{V_2}{V_1}\\right) = 2 \\times 10^5 \\times 0.01 \\times \\ln\\left(\\frac{0.028}{0.01}\\right)", "final_units": "kJ" } | K36: {'id': 'gen-1780492882-TnOqMoltBmvlH9oDrBOc', 'object': 'chat.completion', 'created': 1780492882, 'model': 'anthropic/claude-4.5-sonnet-20250929', 'provider': 'Amazon Bedrock', 'system_fingerprint': None, 'service_tier': None, 'choices': [{'index': 0, 'logprobs': None, 'finish_reason': 'stop', 'native_finish_reason': 'end_turn', 'message': {'role': 'assistant', 'content': '{\n "final_numeric": 2.06,\n "final_formula": "A = p_1 V_1 \\\\ln\\\\left(\\\\frac{V_2}{V_1}\\\\right) = 2 \\\\times 10^5 \\\\times 0.01 \\\\times \\\\ln\\\\left(\\\\frac{0.028}{0.01}\\\\right)",\n "final_units": "kJ"\n}', 'refusal': None, 'reasoning': None}}], 'usage': {'prompt_tokens': 599, 'completion_tokens': 112, 'total_tokens': 711, 'cost': 0.003477, 'is_byok': False, 'prompt_tokens_details': {'cached_tokens': 0, 'cache_write_tokens': 0, 'audio_tokens': 0, 'video_tokens': 0}, 'cost_details': {'upstream_inference_cost': 0.003477, 'upstream_inference_prompt_cost': 0.001797, 'upstream_inference_completions_cost': 0.00168}, 'completion_tokens_details': {'reasoning_tokens': 0, 'image_tokens': 0, 'audio_tokens': 0}}} | L36: 599 | M36: 112 | N36: 711 | O36: 0 | P36: =VLOOKUP(C36,problems!$A$2:$B$26,2) -> thermodynamics | Q36: =IFERROR(__xludf.DUMMYFUNCTION("INDEX(FILTER('stats2-openrouter_activity_2026'!C:C,L36='stats2-openrouter_activity_2026'!H:H,M36='stats2-openrouter_activity_2026'!I:I, B36='stats2-openrouter_activity_2026'!M:M),1)"),0.003477) -> 0.003477 | R36: =IFS( F36=VLOOKUP($C36,problems!$A$2:$G$26,6),1, True,0 ) -> 1 | S36: =IFS( G36=VLOOKUP($C36,problems!$A$2:$G$26,4),1, G36=VLOOKUP($C36,problems!$A$2:$G$26,5),1, True,0 ) -> 0 | T36: =IFS( H36=VLOOKUP($C36,problems!$A$2:$G$26,7),1, True,0 ) -> 1
A37: 2026-06-03-17-24-38 | B37: anthropic/claude-sonnet-4.5 | C37: 11 | D37: Given: h_0 = 3.5 mm — height of the object, the printed letters. d_c = 30 cm — distance from the book to the eye. d_i = 2 cm — distance from the eye lens to the retina. Find: h_i — the height of the image of the print on the retina, in millimeters. | E37: TRUE | F37: 0.00023333333 | G37: h_i = h_0 \frac{d_i}{d_o} = 3.5 \times 10^{-3} \times \frac{0.02}{0.30} = \frac{7}{30000} | H37: m | J37: I need to find the height of the image of the print on the retina using the thin lens equation and magnification. Given: - h₀ = 3.5 mm (object height) - dₒ = 30 cm = 300 mm (object distance from eye) - dᵢ = 2 cm = 20 mm (image distance - distance from lens to retina) For a thin lens (the eye lens), the magnification is: M = -dᵢ/dₒ = hᵢ/h₀ Where: - M is the magnification - dᵢ is the image distance - dₒ is the object distance - hᵢ is the image height - h₀ is the object height Solving for hᵢ: hᵢ = h₀ × (-dᵢ/dₒ) The negative sign indicates the image is inverted, but we're asked for the height (magnitude). |hᵢ| = h₀ × (dᵢ/dₒ) Substituting values: |hᵢ| = 3.5 mm × (20 mm / 300 mm) |hᵢ| = 3.5 mm × (1/15) |hᵢ| = 3.5/15 mm |hᵢ| = 0.2333... mm Converting to meters (SI units): hᵢ = 0.2333... × 10⁻³ m = 2.333... × 10⁻⁴ m Let me recalculate more precisely: hᵢ = 3.5 × (20/300) = 3.5 × (2/30) = 7/30 mm ≈ 0.23333333... mm In SI units: 7/30 × 10⁻³ m = 0.00023333... m For the numeric value in meters: hᵢ = 0.000233333... m ≈ 0.000233 m (or 2.33 × 10⁻⁴ m) Actually, let me express this more precisely: hᵢ = 7/30000 m = 0.00023333333333333333 m { "final_numeric": 0.00023333333333333333, "final_formula": "h_i = h_0 \\frac{d_i}{d_o} = 3.5 \\times 10^{-3} \\times \\frac{0.02}{0.30} = \\frac{7}{30000}", "final_units": "m" } | K37: {'id': 'gen-1780493068-GmzM957R1MzBYM0PXAxZ', 'object': 'chat.completion', 'created': 1780493068, 'model': 'anthropic/claude-4.5-sonnet-20250929', 'provider': 'Amazon Bedrock', 'system_fingerprint': None, 'service_tier': None, 'choices': [{'index': 0, 'logprobs': None, 'finish_reason': 'stop', 'native_finish_reason': 'end_turn', 'message': {'role': 'assistant', 'content': 'I need to find the height of the image of the print on the retina using the thin lens equation and magnification.\n\nGiven:\n- h₀ = 3.5 mm (object height)\n- dₒ = 30 cm = 300 mm (object distance from eye)\n- dᵢ = 2 cm = 20 mm (image distance - distance from lens to retina)\n\nFor a thin lens (the eye lens), the magnification is:\nM = -dᵢ/dₒ = hᵢ/h₀\n\nWhere:\n- M is the magnification\n- dᵢ is the image distance\n- dₒ is the object distance\n- hᵢ is the image height\n- h₀ is the object height\n\nSolving for hᵢ:\nhᵢ = h₀ × (-dᵢ/dₒ)\n\nThe negative sign indicates the image is inverted, but we\'re asked for the height (magnitude).\n\n|hᵢ| = h₀ × (dᵢ/dₒ)\n\nSubstituting values:\n|hᵢ| = 3.5 mm × (20 mm / 300 mm)\n|hᵢ| = 3.5 mm × (1/15)\n|hᵢ| = 3.5/15 mm\n|hᵢ| = 0.2333... mm\n\nConverting to meters (SI units):\nhᵢ = 0.2333... × 10⁻³ m = 2.333... × 10⁻⁴ m\n\nLet me recalculate more precisely:\nhᵢ = 3.5 × (20/300) = 3.5 × (2/30) = 7/30 mm ≈ 0.23333333... mm\n\nIn SI units: 7/30 × 10⁻³ m = 0.00023333... m\n\nFor the numeric value in meters:\nhᵢ = 0.000233333... m ≈ 0.000233 m (or 2.33 × 10⁻⁴ m)\n\nActually, let me express this more precisely:\nhᵢ = 7/30000 m = 0.00023333333333333333 m\n\n{\n "final_numeric": 0.00023333333333333333,\n "final_formula": "h_i = h_0 \\\\frac{d_i}{d_o} = 3.5 \\\\times 10^{-3} \\\\times \\\\frac{0.02}{0.30} = \\\\frac{7}{30000}",\n "final_units": "m"\n}', 'refusal': None, 'reasoning': None}}], 'usage': {'prompt_tokens': 578, 'completion_tokens': 685, 'total_tokens': 1263, 'cost': 0.012009, 'is_byok': False, 'prompt_tokens_details': {'cached_tokens': 0, 'cache_write_tokens': 0, 'audio_tokens': 0, 'video_tokens': 0}, 'cost_details': {'upstream_inference_cost': 0.012009, 'upstream_inference_prompt_cost': 0.001734, 'upstream_inference_completions_cost': 0.010275}, 'completion_tokens_details': {'reasoning_tokens': 0, 'image_tokens': 0, 'audio_tokens': 0}}} | L37: 578 | M37: 685 | N37: 1263 | O37: 0 | P37: =VLOOKUP(C37,problems!$A$2:$B$26,2) -> optics | Q37: =IFERROR(__xludf.DUMMYFUNCTION("INDEX(FILTER('stats2-openrouter_activity_2026'!C:C,L37='stats2-openrouter_activity_2026'!H:H,M37='stats2-openrouter_activity_2026'!I:I, B37='stats2-openrouter_activity_2026'!M:M),1)"),0.012009) -> 0.012009 | R37: =IFS( F37=VLOOKUP($C37,problems!$A$2:$G$26,6),1, True,0 ) -> 0 | S37: =IFS( G37=VLOOKUP($C37,problems!$A$2:$G$26,4),1, G37=VLOOKUP($C37,problems!$A$2:$G$26,5),1, True,0 ) -> 0 | T37: =IFS( H37=VLOOKUP($C37,problems!$A$2:$G$26,7),1, True,0 ) -> 0
A38: 2026-06-03-17-26-24 | B38: anthropic/claude-sonnet-4.5 | C38: 12 | D38: Given: f_{obj} = 100 cm — focal length of the objective lens. f_{eye} = 2.50 cm — focal length of the eyepiece. Find: M — angular magnification of the telescope. | E38: TRUE | F38: -40 | G38: M = -\frac{f_{obj}}{f_{eye}} = -\frac{100}{2.50} = -40 | H38: 1 | J38: { "final_numeric": -40, "final_formula": "M = -\\frac{f_{obj}}{f_{eye}} = -\\frac{100}{2.50} = -40", "final_units": "1" } | K38: {'id': 'gen-1780493182-BxDnFA4J6SKZGuD7O3bC', 'object': 'chat.completion', 'created': 1780493182, 'model': 'anthropic/claude-4.5-sonnet-20250929', 'provider': 'Amazon Bedrock', 'system_fingerprint': None, 'service_tier': None, 'choices': [{'index': 0, 'logprobs': None, 'finish_reason': 'stop', 'native_finish_reason': 'end_turn', 'message': {'role': 'assistant', 'content': '{\n "final_numeric": -40,\n "final_formula": "M = -\\\\frac{f_{obj}}{f_{eye}} = -\\\\frac{100}{2.50} = -40",\n "final_units": "1"\n}', 'refusal': None, 'reasoning': None}}], 'usage': {'prompt_tokens': 544, 'completion_tokens': 66, 'total_tokens': 610, 'cost': 0.002622, 'is_byok': False, 'prompt_tokens_details': {'cached_tokens': 0, 'cache_write_tokens': 0, 'audio_tokens': 0, 'video_tokens': 0}, 'cost_details': {'upstream_inference_cost': 0.002622, 'upstream_inference_prompt_cost': 0.001632, 'upstream_inference_completions_cost': 0.00099}, 'completion_tokens_details': {'reasoning_tokens': 0, 'image_tokens': 0, 'audio_tokens': 0}}} | L38: 544 | M38: 66 | N38: 610 | O38: 0 | P38: =VLOOKUP(C38,problems!$A$2:$B$26,2) -> optics | Q38: =IFERROR(__xludf.DUMMYFUNCTION("INDEX(FILTER('stats2-openrouter_activity_2026'!C:C,L38='stats2-openrouter_activity_2026'!H:H,M38='stats2-openrouter_activity_2026'!I:I, B38='stats2-openrouter_activity_2026'!M:M),1)"),0.002622) -> 0.002622 | R38: =IFS( F38=VLOOKUP($C38,problems!$A$2:$G$26,6),1, True,0 ) -> 1 | S38: =IFS( G38=VLOOKUP($C38,problems!$A$2:$G$26,4),1, G38=VLOOKUP($C38,problems!$A$2:$G$26,5),1, True,0 ) -> 0 | T38: =IFS( H38=VLOOKUP($C38,problems!$A$2:$G$26,7),1, True,0 ) -> 1
A39: 2026-06-03-17-27-19 | B39: anthropic/claude-sonnet-4.5 | C39: 13 | D39: Дано: Луч последовательно отражается от двух плоских зеркал. Луч, падающий на первое зеркало, параллелен плоскости второго зеркала. Дважды отражённый луч параллелен плоскости первого зеркала. Найти: phi — угол между зеркалами, в градусах. | E39: TRUE | F39: 45 | G39: \phi = 45^\circ | H39: 1 | J39: Looking at this problem, I need to analyze the geometry of light reflection from two plane mirrors. **Given:** - A ray reflects sequentially from two plane mirrors - The incident ray on the first mirror is parallel to the second mirror's plane - The twice-reflected ray is parallel to the first mirror's plane **Setting up the geometry:** Let me denote: - The angle between the two mirrors as φ - The incident ray is parallel to mirror 2 - The final ray (after two reflections) is parallel to mirror 1 **Analysis:** When a ray is parallel to a mirror's plane, it makes an angle of 90° with the normal to that plane. For the first mirror: - The incident ray is parallel to mirror 2 - If the angle between mirrors is φ, and the incident ray is parallel to mirror 2, the angle of incidence on mirror 1 can be determined from geometry Let me use the property that when a ray reflects from two plane mirrors, the total deviation angle depends on the angle between the mirrors. **Key geometric relationship:** If the incident ray is parallel to mirror 2 and the emergent ray is parallel to mirror 1, this creates a specific geometric constraint. When the incident ray is parallel to one mirror and the final ray is parallel to the other mirror, the angle between the mirrors must be such that: The incident ray makes angle (90° - φ) with mirror 1's normal. After reflection from mirror 1, the ray travels to mirror 2. After reflection from mirror 2, the ray is parallel to mirror 1. Using the law of reflection and geometric analysis: - The total angular deviation through two reflections from mirrors at angle φ is 2φ - For the specific condition given (incident parallel to mirror 2, final parallel to mirror 1), this requires the rays to be perpendicular to each other This means: 90° = 2φ Therefore: φ = 45° **Verification:** With φ = 45°: - Incident ray parallel to mirror 2 hits mirror 1 at 45° angle of incidence - Reflects at 45°, travels to mirror 2 - Hits mirror 2 at 45° angle of incidence - Reflects to become parallel to mirror 1 ✓ { "final_numeric": 45, "final_formula": "\\phi = 45^\\circ", "final_units": "1" } | K39: {'id': 'gen-1780493228-WhJgmvpU5evhlZzI7Lu7', 'object': 'chat.completion', 'created': 1780493228, 'model': 'anthropic/claude-4.5-sonnet-20250929', 'provider': 'Amazon Bedrock', 'system_fingerprint': None, 'service_tier': None, 'choices': [{'index': 0, 'logprobs': None, 'finish_reason': 'stop', 'native_finish_reason': 'end_turn', 'message': {'role': 'assistant', 'content': 'Looking at this problem, I need to analyze the geometry of light reflection from two plane mirrors.\n\n**Given:**\n- A ray reflects sequentially from two plane mirrors\n- The incident ray on the first mirror is parallel to the second mirror\'s plane\n- The twice-reflected ray is parallel to the first mirror\'s plane\n\n**Setting up the geometry:**\n\nLet me denote:\n- The angle between the two mirrors as φ\n- The incident ray is parallel to mirror 2\n- The final ray (after two reflections) is parallel to mirror 1\n\n**Analysis:**\n\nWhen a ray is parallel to a mirror\'s plane, it makes an angle of 90° with the normal to that plane.\n\nFor the first mirror:\n- The incident ray is parallel to mirror 2\n- If the angle between mirrors is φ, and the incident ray is parallel to mirror 2, the angle of incidence on mirror 1 can be determined from geometry\n\nLet me use the property that when a ray reflects from two plane mirrors, the total deviation angle depends on the angle between the mirrors.\n\n**Key geometric relationship:**\n\nIf the incident ray is parallel to mirror 2 and the emergent ray is parallel to mirror 1, this creates a specific geometric constraint.\n\nWhen the incident ray is parallel to one mirror and the final ray is parallel to the other mirror, the angle between the mirrors must be such that:\n\nThe incident ray makes angle (90° - φ) with mirror 1\'s normal.\nAfter reflection from mirror 1, the ray travels to mirror 2.\nAfter reflection from mirror 2, the ray is parallel to mirror 1.\n\nUsing the law of reflection and geometric analysis:\n- The total angular deviation through two reflections from mirrors at angle φ is 2φ\n- For the specific condition given (incident parallel to mirror 2, final parallel to mirror 1), this requires the rays to be perpendicular to each other\n\nThis means: 90° = 2φ\n\nTherefore: φ = 45°\n\n**Verification:**\nWith φ = 45°:\n- Incident ray parallel to mirror 2 hits mirror 1 at 45° angle of incidence\n- Reflects at 45°, travels to mirror 2\n- Hits mirror 2 at 45° angle of incidence\n- Reflects to become parallel to mirror 1 ✓\n\n{\n "final_numeric": 45,\n "final_formula": "\\\\phi = 45^\\\\circ",\n "final_units": "1"\n}', 'refusal': None, 'reasoning': None}}], 'usage': {'prompt_tokens': 595, 'completion_tokens': 566, 'total_tokens': 1161, 'cost': 0.010275, 'is_byok': False, 'prompt_tokens_details': {'cached_tokens': 0, 'cache_write_tokens': 0, 'audio_tokens': 0, 'video_tokens': 0}, 'cost_details': {'upstream_inference_cost': 0.010275, 'upstream_inference_prompt_cost': 0.001785, 'upstream_inference_completions_cost': 0.00849}, 'completion_tokens_details': {'reasoning_tokens': 0, 'image_tokens': 0, 'audio_tokens': 0}}} | L39: 595 | M39: 566 | N39: 1161 | O39: 0 | P39: =VLOOKUP(C39,problems!$A$2:$B$26,2) -> optics | Q39: =IFERROR(__xludf.DUMMYFUNCTION("INDEX(FILTER('stats2-openrouter_activity_2026'!C:C,L39='stats2-openrouter_activity_2026'!H:H,M39='stats2-openrouter_activity_2026'!I:I, B39='stats2-openrouter_activity_2026'!M:M),1)"),0.010275) -> 0.010275 | R39: =IFS( F39=VLOOKUP($C39,problems!$A$2:$G$26,6),1, True,0 ) -> 0 | S39: =IFS( G39=VLOOKUP($C39,problems!$A$2:$G$26,4),1, G39=VLOOKUP($C39,problems!$A$2:$G$26,5),1, True,0 ) -> 0 | T39: =IFS( H39=VLOOKUP($C39,problems!$A$2:$G$26,7),1, True,0 ) -> 0
A40: 2026-06-03-17-30-13 | B40: anthropic/claude-sonnet-4.5 | C40: 14 | D40: Дано: Сосуд заполнен водой, на дне лежит плоское зеркало. d = 25 см — расстояние, на котором человек видит изображение своего лица в зеркале. h = 5 см — расстояние от лица до поверхности воды. n = \frac{4}{3} — показатель преломления воды. Найти: l — глубину сосуда, в сантиметрах. | E40: TRUE | F40: 0.10833333 | G40: \frac{dn - h(n+1)}{2} = \frac{25 \cdot \frac{4}{3} - 5 \cdot \frac{7}{3}}{2} = \frac{65}{6} \text{ cm} | H40: m | J40: Looking at this problem, I need to find the depth of the vessel when a person sees their face's image in a mirror at the bottom through water. Given: - d = 25 cm (distance at which person sees the image) - h = 5 cm (distance from face to water surface) - n = 4/3 (refractive index of water) - l = depth of vessel (to find) The setup: 1. The face is at height h above the water surface 2. The mirror is at depth l below the water surface 3. Light travels from face → water surface → mirror → water surface → eye The actual distance from face to mirror is: h + l For the image formation: - The mirror creates a virtual image at distance (h + l) behind the mirror - So the image is at depth (h + l) below the mirror, or at total depth l + (h + l) = 2l + h below water surface When viewing from above through water: - The apparent depth of an object at real depth D in water is D/n - The image appears at depth (2l + h)/n below the water surface - The total apparent distance from the face to the image is: h + (2l + h)/n This apparent distance equals d: d = h + (2l + h)/n Solving for l: d = h + (2l + h)/n d = h + 2l/n + h/n d = h(1 + 1/n) + 2l/n d = h(n + 1)/n + 2l/n dn = h(n + 1) + 2l 2l = dn - h(n + 1) l = [dn - h(n + 1)]/2 Substituting values: l = [25 × (4/3) - 5 × (4/3 + 1)]/2 l = [25 × 4/3 - 5 × 7/3]/2 l = [100/3 - 35/3]/2 l = [65/3]/2 l = 65/6 l ≈ 10.833... cm Converting to meters (SI units): l ≈ 0.108333... m Let me verify: 65/6 = 10.8333... cm = 0.108333... m Actually, checking if the answer should be exactly 65/6 cm = 0.065/6 m... No, 65/6 cm = 0.65/6 m = 13/120 m ≈ 0.1083333 m { "final_numeric": 0.10833333333333334, "final_formula": "\\frac{dn - h(n+1)}{2} = \\frac{25 \\cdot \\frac{4}{3} - 5 \\cdot \\frac{7}{3}}{2} = \\frac{65}{6} \\text{ cm}", "final_units": "m" } | K40: {'id': 'gen-1780493400-TTHNdiVNQ4gnGkWE2Dyc', 'object': 'chat.completion', 'created': 1780493400, 'model': 'anthropic/claude-4.5-sonnet-20250929', 'provider': 'Amazon Bedrock', 'system_fingerprint': None, 'service_tier': None, 'choices': [{'index': 0, 'logprobs': None, 'finish_reason': 'stop', 'native_finish_reason': 'end_turn', 'message': {'role': 'assistant', 'content': 'Looking at this problem, I need to find the depth of the vessel when a person sees their face\'s image in a mirror at the bottom through water.\n\nGiven:\n- d = 25 cm (distance at which person sees the image)\n- h = 5 cm (distance from face to water surface)\n- n = 4/3 (refractive index of water)\n- l = depth of vessel (to find)\n\nThe setup:\n1. The face is at height h above the water surface\n2. The mirror is at depth l below the water surface\n3. Light travels from face → water surface → mirror → water surface → eye\n\nThe actual distance from face to mirror is: h + l\n\nFor the image formation:\n- The mirror creates a virtual image at distance (h + l) behind the mirror\n- So the image is at depth (h + l) below the mirror, or at total depth l + (h + l) = 2l + h below water surface\n\nWhen viewing from above through water:\n- The apparent depth of an object at real depth D in water is D/n\n- The image appears at depth (2l + h)/n below the water surface\n- The total apparent distance from the face to the image is: h + (2l + h)/n\n\nThis apparent distance equals d:\n\nd = h + (2l + h)/n\n\nSolving for l:\nd = h + (2l + h)/n\nd = h + 2l/n + h/n\nd = h(1 + 1/n) + 2l/n\nd = h(n + 1)/n + 2l/n\ndn = h(n + 1) + 2l\n2l = dn - h(n + 1)\nl = [dn - h(n + 1)]/2\n\nSubstituting values:\nl = [25 × (4/3) - 5 × (4/3 + 1)]/2\nl = [25 × 4/3 - 5 × 7/3]/2\nl = [100/3 - 35/3]/2\nl = [65/3]/2\nl = 65/6\nl ≈ 10.833... cm\n\nConverting to meters (SI units): l ≈ 0.108333... m\n\nLet me verify: 65/6 = 10.8333... cm = 0.108333... m\n\nActually, checking if the answer should be exactly 65/6 cm = 0.065/6 m... No, 65/6 cm = 0.65/6 m = 13/120 m ≈ 0.1083333 m\n\n{\n "final_numeric": 0.10833333333333334,\n "final_formula": "\\\\frac{dn - h(n+1)}{2} = \\\\frac{25 \\\\cdot \\\\frac{4}{3} - 5 \\\\cdot \\\\frac{7}{3}}{2} = \\\\frac{65}{6} \\\\text{ cm}",\n "final_units": "m"\n}', 'refusal': None, 'reasoning': None}}], 'usage': {'prompt_tokens': 622, 'completion_tokens': 739, 'total_tokens': 1361, 'cost': 0.012951, 'is_byok': False, 'prompt_tokens_details': {'cached_tokens': 0, 'cache_write_tokens': 0, 'audio_tokens': 0, 'video_tokens': 0}, 'cost_details': {'upstream_inference_cost': 0.012951, 'upstream_inference_prompt_cost': 0.001866, 'upstream_inference_completions_cost': 0.011085}, 'completion_tokens_details': {'reasoning_tokens': 0, 'image_tokens': 0, 'audio_tokens': 0}}} | L40: 622 | M40: 739 | N40: 1361 | O40: 0 | P40: =VLOOKUP(C40,problems!$A$2:$B$26,2) -> optics | Q40: =IFERROR(__xludf.DUMMYFUNCTION("INDEX(FILTER('stats2-openrouter_activity_2026'!C:C,L40='stats2-openrouter_activity_2026'!H:H,M40='stats2-openrouter_activity_2026'!I:I, B40='stats2-openrouter_activity_2026'!M:M),1)"),0.012951) -> 0.012951 | R40: =IFS( F40=VLOOKUP($C40,problems!$A$2:$G$26,6),1, True,0 ) -> 0 | S40: =IFS( G40=VLOOKUP($C40,problems!$A$2:$G$26,4),1, G40=VLOOKUP($C40,problems!$A$2:$G$26,5),1, True,0 ) -> 0 | T40: =IFS( H40=VLOOKUP($C40,problems!$A$2:$G$26,7),1, True,0 ) -> 0
A41: 2026-06-03-17-32-49 | B41: anthropic/claude-sonnet-4.5 | C41: 15 | D41: Given: A beam of light falls on a single slit. a = 1.00𝜇m — width of the single slit. theta = 36.9∘ — angle at which the first minimum occurs. m = 1 — order of the first minimum. Find: lambda — wavelength of the light, in nanometers. | E41: TRUE | F41: 600 | G41: \lambda = \frac{a \sin\theta}{m} = \frac{1.00 \times 10^{-6} \times \sin(36.9^\circ)}{1} = 6.00 \times 10^{-7} \text{ m} = 600 \text{ nm} | H41: nm | J41: { "final_numeric": 600, "final_formula": "\\lambda = \\frac{a \\sin\\theta}{m} = \\frac{1.00 \\times 10^{-6} \\times \\sin(36.9^\\circ)}{1} = 6.00 \\times 10^{-7} \\text{ m} = 600 \\text{ nm}", "final_units": "nm" } | K41: {'id': 'gen-1780493566-leFnesLCj5FObySIuYpo', 'object': 'chat.completion', 'created': 1780493566, 'model': 'anthropic/claude-4.5-sonnet-20250929', 'provider': 'Amazon Bedrock', 'system_fingerprint': None, 'service_tier': None, 'choices': [{'index': 0, 'logprobs': None, 'finish_reason': 'stop', 'native_finish_reason': 'end_turn', 'message': {'role': 'assistant', 'content': '{\n "final_numeric": 600,\n "final_formula": "\\\\lambda = \\\\frac{a \\\\sin\\\\theta}{m} = \\\\frac{1.00 \\\\times 10^{-6} \\\\times \\\\sin(36.9^\\\\circ)}{1} = 6.00 \\\\times 10^{-7} \\\\text{ m} = 600 \\\\text{ nm}",\n "final_units": "nm"\n}', 'refusal': None, 'reasoning': None}}], 'usage': {'prompt_tokens': 573, 'completion_tokens': 122, 'total_tokens': 695, 'cost': 0.003549, 'is_byok': False, 'prompt_tokens_details': {'cached_tokens': 0, 'cache_write_tokens': 0, 'audio_tokens': 0, 'video_tokens': 0}, 'cost_details': {'upstream_inference_cost': 0.003549, 'upstream_inference_prompt_cost': 0.001719, 'upstream_inference_completions_cost': 0.00183}, 'completion_tokens_details': {'reasoning_tokens': 0, 'image_tokens': 0, 'audio_tokens': 0}}} | L41: 573 | M41: 122 | N41: 695 | O41: 0 | P41: =VLOOKUP(C41,problems!$A$2:$B$26,2) -> optics | Q41: =IFERROR(__xludf.DUMMYFUNCTION("INDEX(FILTER('stats2-openrouter_activity_2026'!C:C,L41='stats2-openrouter_activity_2026'!H:H,M41='stats2-openrouter_activity_2026'!I:I, B41='stats2-openrouter_activity_2026'!M:M),1)"),0.003549) -> 0.003549 | R41: =IFS( F41=VLOOKUP($C41,problems!$A$2:$G$26,6),1, True,0 ) -> 1 | S41: =IFS( G41=VLOOKUP($C41,problems!$A$2:$G$26,4),1, G41=VLOOKUP($C41,problems!$A$2:$G$26,5),1, True,0 ) -> 0 | T41: =IFS( H41=VLOOKUP($C41,problems!$A$2:$G$26,7),1, True,0 ) -> 1
A42: 2026-06-03-17-36-25 | B42: anthropic/claude-sonnet-4.5 | C42: 16 | D42: Дано: l = 1 м — длина тонкого непроводящего горизонтального стержня На концах стержня закреплены две маленькие бусинки. Третья бусинка надета на стержень и может двигаться по нему без трения. Всем бусинкам сообщены одинаковые заряды q = 10^-6 Кл m = 5 г — масса подвижной бусинки Подвижная бусинка совершает малые колебания около середины стержня. Найти: T — период малых колебаний подвижной бусинки, в секундах. | E42: TRUE | F42: 0.828 | G42: T = 2\pi\sqrt{\frac{ml^3}{32kq^2}} | H42: s | J42: I need to find the period of small oscillations of a charged bead on a rod with two fixed charged beads at the ends. **Setup:** - Rod length: l = 1 m - Two fixed beads at the ends (positions x = 0 and x = l) - One movable bead that oscillates around the center (x = l/2) - All beads have charge q = 10⁻⁶ C - Mass of movable bead: m = 5 g = 5×10⁻³ kg **Analysis:** Let the movable bead be displaced by a small distance ξ from the center. Position of movable bead: x = l/2 + ξ Distance from left fixed bead: r₁ = l/2 + ξ Distance from right fixed bead: r₂ = l/2 - ξ **Forces:** Coulomb force from left bead (repulsive, pointing right): F₁ = kq²/(l/2 + ξ)² Coulomb force from right bead (repulsive, pointing left): F₂ = -kq²/(l/2 - ξ)² Net force: F = F₁ + F₂ = kq²/(l/2 + ξ)² - kq²/(l/2 - ξ)² **Small oscillation approximation (ξ << l/2):** Using binomial expansion: (l/2 ± ξ)⁻² ≈ (l/2)⁻²(1 ∓ 2ξ/(l/2)) F ≈ kq²(4/l²)(1 - 4ξ/l) - kq²(4/l²)(1 + 4ξ/l) F ≈ kq²(4/l²)(-8ξ/l) F ≈ -32kq²ξ/l³ This is a restoring force: F = -Kξ where K = 32kq²/l³ **Period of oscillation:** For simple harmonic motion: T = 2π√(m/K) T = 2π√(ml³/(32kq²)) **Numerical calculation:** k = 8.99×10⁹ N·m²/C² m = 5×10⁻³ kg l = 1 m q = 10⁻⁶ C K = 32 × 8.99×10⁹ × (10⁻⁶)² / 1³ K = 32 × 8.99×10⁹ × 10⁻¹² / 1 K = 32 × 8.99×10⁻³ K = 287.68×10⁻³ = 0.28768 N/m T = 2π√(5×10⁻³/0.28768) T = 2π√(0.01738) T = 2π × 0.1318 T = 0.828 s { "final_numeric": 0.828, "final_formula": "T = 2\\pi\\sqrt{\\frac{ml^3}{32kq^2}}", "final_units": "s" } | K42: {'id': 'gen-1780493773-gy3DyRMnPqE8EfMuSTAM', 'object': 'chat.completion', 'created': 1780493773, 'model': 'anthropic/claude-4.5-sonnet-20250929', 'provider': 'Amazon Bedrock', 'system_fingerprint': None, 'service_tier': None, 'choices': [{'index': 0, 'logprobs': None, 'finish_reason': 'stop', 'native_finish_reason': 'end_turn', 'message': {'role': 'assistant', 'content': 'I need to find the period of small oscillations of a charged bead on a rod with two fixed charged beads at the ends.\n\n**Setup:**\n- Rod length: l = 1 m\n- Two fixed beads at the ends (positions x = 0 and x = l)\n- One movable bead that oscillates around the center (x = l/2)\n- All beads have charge q = 10⁻⁶ C\n- Mass of movable bead: m = 5 g = 5×10⁻³ kg\n\n**Analysis:**\n\nLet the movable bead be displaced by a small distance ξ from the center.\nPosition of movable bead: x = l/2 + ξ\n\nDistance from left fixed bead: r₁ = l/2 + ξ\nDistance from right fixed bead: r₂ = l/2 - ξ\n\n**Forces:**\n\nCoulomb force from left bead (repulsive, pointing right):\nF₁ = kq²/(l/2 + ξ)²\n\nCoulomb force from right bead (repulsive, pointing left):\nF₂ = -kq²/(l/2 - ξ)²\n\nNet force:\nF = F₁ + F₂ = kq²/(l/2 + ξ)² - kq²/(l/2 - ξ)²\n\n**Small oscillation approximation (ξ << l/2):**\n\nUsing binomial expansion: (l/2 ± ξ)⁻² ≈ (l/2)⁻²(1 ∓ 2ξ/(l/2))\n\nF ≈ kq²(4/l²)(1 - 4ξ/l) - kq²(4/l²)(1 + 4ξ/l)\nF ≈ kq²(4/l²)(-8ξ/l)\nF ≈ -32kq²ξ/l³\n\nThis is a restoring force: F = -Kξ where K = 32kq²/l³\n\n**Period of oscillation:**\n\nFor simple harmonic motion: T = 2π√(m/K)\n\nT = 2π√(ml³/(32kq²))\n\n**Numerical calculation:**\n\nk = 8.99×10⁹ N·m²/C²\nm = 5×10⁻³ kg\nl = 1 m\nq = 10⁻⁶ C\n\nK = 32 × 8.99×10⁹ × (10⁻⁶)² / 1³\nK = 32 × 8.99×10⁹ × 10⁻¹² / 1\nK = 32 × 8.99×10⁻³\nK = 287.68×10⁻³ = 0.28768 N/m\n\nT = 2π√(5×10⁻³/0.28768)\nT = 2π√(0.01738)\nT = 2π × 0.1318\nT = 0.828 s\n\n{\n "final_numeric": 0.828,\n "final_formula": "T = 2\\\\pi\\\\sqrt{\\\\frac{ml^3}{32kq^2}}",\n "final_units": "s"\n}', 'refusal': None, 'reasoning': None}}], 'usage': {'prompt_tokens': 673, 'completion_tokens': 837, 'total_tokens': 1510, 'cost': 0.014574, 'is_byok': False, 'prompt_tokens_details': {'cached_tokens': 0, 'cache_write_tokens': 0, 'audio_tokens': 0, 'video_tokens': 0}, 'cost_details': {'upstream_inference_cost': 0.014574, 'upstream_inference_prompt_cost': 0.002019, 'upstream_inference_completions_cost': 0.012555}, 'completion_tokens_details': {'reasoning_tokens': 0, 'image_tokens': 0, 'audio_tokens': 0}}} | L42: 673 | M42: 837 | N42: 1510 | O42: 0 | P42: =VLOOKUP(C42,problems!$A$2:$B$26,2) -> electrostatics | Q42: =IFERROR(__xludf.DUMMYFUNCTION("INDEX(FILTER('stats2-openrouter_activity_2026'!C:C,L42='stats2-openrouter_activity_2026'!H:H,M42='stats2-openrouter_activity_2026'!I:I, B42='stats2-openrouter_activity_2026'!M:M),1)"),0.014574) -> 0.014574 | R42: =IFS( F42=VLOOKUP($C42,problems!$A$2:$G$26,6),1, True,0 ) -> 0 | S42: =IFS( G42=VLOOKUP($C42,problems!$A$2:$G$26,4),1, G42=VLOOKUP($C42,problems!$A$2:$G$26,5),1, True,0 ) -> 0 | T42: =IFS( H42=VLOOKUP($C42,problems!$A$2:$G$26,7),1, True,0 ) -> 1
A43: 2026-06-03-17-40-48 | B43: anthropic/claude-sonnet-4.5 | C43: 17 | D43: E = 10^6 В/м — максимальная напряжённость электрического поля, при которой воздух ещё остаётся изолятором. q = 1 Кл — заряд металлического шара. Найти: R — радиус металлического шара, при котором на нём может удержаться заряд, в метрах. | E43: TRUE | F43: 94.868 | G43: R = \sqrt{\frac{kq}{E_{max}}} = \sqrt{\frac{9 \times 10^9 \times 1}{10^6}} = 30\sqrt{10} | H43: m | J43: I need to find the minimum radius of a metallic sphere that can hold a charge of 1 C without causing electrical breakdown in air. For a metallic sphere with charge q, the electric field at its surface is maximum and given by: $$E = \frac{kq}{R^2}$$ where: - k = 9 × 10^9 N·m²/C² (Coulomb's constant) - q = charge on the sphere - R = radius of the sphere For the charge to be held on the sphere without breakdown, the electric field at the surface must not exceed the maximum field strength: $$E_{max} = \frac{kq}{R^2}$$ Solving for R: $$R^2 = \frac{kq}{E_{max}}$$ $$R = \sqrt{\frac{kq}{E_{max}}}$$ Substituting the values: - k = 9 × 10^9 N·m²/C² - q = 1 C - E_max = 10^6 V/m $$R = \sqrt{\frac{9 \times 10^9 \times 1}{10^6}}$$ $$R = \sqrt{\frac{9 \times 10^9}{10^6}}$$ $$R = \sqrt{9 \times 10^3}$$ $$R = \sqrt{9000}$$ $$R = 3\sqrt{1000}$$ $$R = 3 \times 31.62...$$ $$R \approx 94.87 \text{ m}$$ More precisely: $$R = \sqrt{9000} = 30\sqrt{10} \approx 94.868 \text{ m}$$ { "final_numeric": 94.868, "final_formula": "R = \\sqrt{\\frac{kq}{E_{max}}} = \\sqrt{\\frac{9 \\times 10^9 \\times 1}{10^6}} = 30\\sqrt{10}", "final_units": "m" } | K43: {'id': 'gen-1780494041-qZ7wlQR4qGJhLHohNRMC', 'object': 'chat.completion', 'created': 1780494041, 'model': 'anthropic/claude-4.5-sonnet-20250929', 'provider': 'Amazon Bedrock', 'system_fingerprint': None, 'service_tier': None, 'choices': [{'index': 0, 'logprobs': None, 'finish_reason': 'stop', 'native_finish_reason': 'end_turn', 'message': {'role': 'assistant', 'content': 'I need to find the minimum radius of a metallic sphere that can hold a charge of 1 C without causing electrical breakdown in air.\n\nFor a metallic sphere with charge q, the electric field at its surface is maximum and given by:\n\n$$E = \\frac{kq}{R^2}$$\n\nwhere:\n- k = 9 × 10^9 N·m²/C² (Coulomb\'s constant)\n- q = charge on the sphere\n- R = radius of the sphere\n\nFor the charge to be held on the sphere without breakdown, the electric field at the surface must not exceed the maximum field strength:\n\n$$E_{max} = \\frac{kq}{R^2}$$\n\nSolving for R:\n\n$$R^2 = \\frac{kq}{E_{max}}$$\n\n$$R = \\sqrt{\\frac{kq}{E_{max}}}$$\n\nSubstituting the values:\n- k = 9 × 10^9 N·m²/C²\n- q = 1 C\n- E_max = 10^6 V/m\n\n$$R = \\sqrt{\\frac{9 \\times 10^9 \\times 1}{10^6}}$$\n\n$$R = \\sqrt{\\frac{9 \\times 10^9}{10^6}}$$\n\n$$R = \\sqrt{9 \\times 10^3}$$\n\n$$R = \\sqrt{9000}$$\n\n$$R = 3\\sqrt{1000}$$\n\n$$R = 3 \\times 31.62...$$\n\n$$R \\approx 94.87 \\text{ m}$$\n\nMore precisely:\n$$R = \\sqrt{9000} = 30\\sqrt{10} \\approx 94.868 \\text{ m}$$\n\n{\n "final_numeric": 94.868,\n "final_formula": "R = \\\\sqrt{\\\\frac{kq}{E_{max}}} = \\\\sqrt{\\\\frac{9 \\\\times 10^9 \\\\times 1}{10^6}} = 30\\\\sqrt{10}",\n "final_units": "m"\n}', 'refusal': None, 'reasoning': None}}], 'usage': {'prompt_tokens': 590, 'completion_tokens': 507, 'total_tokens': 1097, 'cost': 0.009375, 'is_byok': False, 'prompt_tokens_details': {'cached_tokens': 0, 'cache_write_tokens': 0, 'audio_tokens': 0, 'video_tokens': 0}, 'cost_details': {'upstream_inference_cost': 0.009375, 'upstream_inference_prompt_cost': 0.00177, 'upstream_inference_completions_cost': 0.007605}, 'completion_tokens_details': {'reasoning_tokens': 0, 'image_tokens': 0, 'audio_tokens': 0}}} | L43: 590 | M43: 507 | N43: 1097 | O43: 0 | P43: =VLOOKUP(C43,problems!$A$2:$B$26,2) -> electrostatics | Q43: =IFERROR(__xludf.DUMMYFUNCTION("INDEX(FILTER('stats2-openrouter_activity_2026'!C:C,L43='stats2-openrouter_activity_2026'!H:H,M43='stats2-openrouter_activity_2026'!I:I, B43='stats2-openrouter_activity_2026'!M:M),1)"),0.009375) -> 0.009375 | R43: =IFS( F43=VLOOKUP($C43,problems!$A$2:$G$26,6),1, True,0 ) -> 0 | S43: =IFS( G43=VLOOKUP($C43,problems!$A$2:$G$26,4),1, G43=VLOOKUP($C43,problems!$A$2:$G$26,5),1, True,0 ) -> 0 | T43: =IFS( H43=VLOOKUP($C43,problems!$A$2:$G$26,7),1, True,0 ) -> 1
A44: 2026-06-03-17-43-16 | B44: anthropic/claude-sonnet-4.5 | C44: 18 | D44: Дано: E = 100 В/м — напряжённость однородного электрического поля. v_0 = 10^6 м/с — начальная скорость электрона. v = 0 — конечная скорость электрона Электрон движется вдоль силовой линии поля, но сила, действующая на электрон, направлена противоположно полю, поэтому электрон тормозит. Найти: s — расстояние до полной остановки электрона, в сантиметрах. | E44: TRUE | F44: 0.0284 | G44: s = \frac{m_e v_0^2}{2eE} | H44: m | J44: I need to find the distance an electron travels before stopping in a uniform electric field. **Given:** - E = 100 V/m (electric field strength) - v₀ = 10⁶ m/s (initial velocity) - v = 0 (final velocity) - The electron moves along field lines but the force opposes its motion (electron decelerates) **Solution:** The force on the electron: F = eE (where e is elementary charge) The acceleration: a = F/m = eE/m (directed opposite to velocity) Using the kinematic equation: v² = v₀² - 2as Since v = 0: 0 = v₀² - 2as Solving for s: s = v₀²/(2a) = v₀²/(2eE/m) = mv₀²/(2eE) **Substituting values:** - m = 9.109 × 10⁻³¹ kg (electron mass) - e = 1.602 × 10⁻¹⁹ C (elementary charge) - v₀ = 10⁶ m/s - E = 100 V/m s = (9.109 × 10⁻³¹ × (10⁶)²)/(2 × 1.602 × 10⁻¹⁹ × 100) s = (9.109 × 10⁻³¹ × 10¹²)/(3.204 × 10⁻¹⁷) s = (9.109 × 10⁻¹⁹)/(3.204 × 10⁻¹⁷) s = 2.843 × 10⁻² m Converting to centimeters: s = 2.843 cm The problem asks for the answer in centimeters, but I need to provide the answer in SI units (meters) with the numeric value. Actually, re-reading: "Найти: s — расстояние до полной остановки электрона, в сантиметрах" means find in centimeters, so the numeric answer should be in cm. However, the OUTPUT REQUIREMENTS state to use SI units. In SI, the distance unit is meters. s = 0.02843 m ≈ 0.0284 m { "final_numeric": 0.0284, "final_formula": "s = \\frac{m_e v_0^2}{2eE}", "final_units": "m" } | K44: {'id': 'gen-1780494187-soWOXt6sMydyzR1SM60u', 'object': 'chat.completion', 'created': 1780494187, 'model': 'anthropic/claude-4.5-sonnet-20250929', 'provider': 'Amazon Bedrock', 'system_fingerprint': None, 'service_tier': None, 'choices': [{'index': 0, 'logprobs': None, 'finish_reason': 'stop', 'native_finish_reason': 'end_turn', 'message': {'role': 'assistant', 'content': 'I need to find the distance an electron travels before stopping in a uniform electric field.\n\n**Given:**\n- E = 100 V/m (electric field strength)\n- v₀ = 10⁶ m/s (initial velocity)\n- v = 0 (final velocity)\n- The electron moves along field lines but the force opposes its motion (electron decelerates)\n\n**Solution:**\n\nThe force on the electron: F = eE (where e is elementary charge)\n\nThe acceleration: a = F/m = eE/m (directed opposite to velocity)\n\nUsing the kinematic equation:\nv² = v₀² - 2as\n\nSince v = 0:\n0 = v₀² - 2as\n\nSolving for s:\ns = v₀²/(2a) = v₀²/(2eE/m) = mv₀²/(2eE)\n\n**Substituting values:**\n- m = 9.109 × 10⁻³¹ kg (electron mass)\n- e = 1.602 × 10⁻¹⁹ C (elementary charge)\n- v₀ = 10⁶ m/s\n- E = 100 V/m\n\ns = (9.109 × 10⁻³¹ × (10⁶)²)/(2 × 1.602 × 10⁻¹⁹ × 100)\n\ns = (9.109 × 10⁻³¹ × 10¹²)/(3.204 × 10⁻¹⁷)\n\ns = (9.109 × 10⁻¹⁹)/(3.204 × 10⁻¹⁷)\n\ns = 2.843 × 10⁻² m\n\nConverting to centimeters:\ns = 2.843 cm\n\nThe problem asks for the answer in centimeters, but I need to provide the answer in SI units (meters) with the numeric value.\n\nActually, re-reading: "Найти: s — расстояние до полной остановки электрона, в сантиметрах" means find in centimeters, so the numeric answer should be in cm.\n\nHowever, the OUTPUT REQUIREMENTS state to use SI units. In SI, the distance unit is meters.\n\ns = 0.02843 m ≈ 0.0284 m\n\n{\n "final_numeric": 0.0284,\n "final_formula": "s = \\\\frac{m_e v_0^2}{2eE}",\n "final_units": "m"\n}', 'refusal': None, 'reasoning': None}}], 'usage': {'prompt_tokens': 642, 'completion_tokens': 637, 'total_tokens': 1279, 'cost': 0.011481, 'is_byok': False, 'prompt_tokens_details': {'cached_tokens': 0, 'cache_write_tokens': 0, 'audio_tokens': 0, 'video_tokens': 0}, 'cost_details': {'upstream_inference_cost': 0.011481, 'upstream_inference_prompt_cost': 0.001926, 'upstream_inference_completions_cost': 0.009555}, 'completion_tokens_details': {'reasoning_tokens': 0, 'image_tokens': 0, 'audio_tokens': 0}}} | L44: 642 | M44: 637 | N44: 1279 | O44: 0 | P44: =VLOOKUP(C44,problems!$A$2:$B$26,2) -> electrostatics | Q44: =IFERROR(__xludf.DUMMYFUNCTION("INDEX(FILTER('stats2-openrouter_activity_2026'!C:C,L44='stats2-openrouter_activity_2026'!H:H,M44='stats2-openrouter_activity_2026'!I:I, B44='stats2-openrouter_activity_2026'!M:M),1)"),0.011481) -> 0.011481 | R44: =IFS( F44=VLOOKUP($C44,problems!$A$2:$G$26,6),1, True,0 ) -> 0 | S44: =IFS( G44=VLOOKUP($C44,problems!$A$2:$G$26,4),1, G44=VLOOKUP($C44,problems!$A$2:$G$26,5),1, True,0 ) -> 0 | T44: =IFS( H44=VLOOKUP($C44,problems!$A$2:$G$26,7),1, True,0 ) -> 0
A45: 2026-06-03-17-45-55 | B45: anthropic/claude-sonnet-4.5 | C45: 19 | D45: Дано: Два одинаковых воздушных конденсатора соединены последовательно. Они подключены к батарее с постоянной ЭДС, поэтому U = const Один из конденсаторов заполняют диэлектриком: epsilon — диэлектрическая проницаемость вещества. До внесения диэлектрика оба конденсатора были одинаковыми: C_1 = C_2 = C После внесения диэлектрика ёмкость одного конденсатора становится: C'_{1} = epsilon*C Найти: E/E_0 — во сколько раз изменится напряжённость электрического поля в конденсаторе, заполненном диэлектриком. | E45: TRUE | G45: \frac{2}{\varepsilon + 1} | H45: 1 | J45: I need to find how the electric field changes in the capacitor filled with dielectric. **Initial situation (before dielectric):** - Two identical capacitors in series: C₁ = C₂ = C - Total capacitance: C₀ = C/2 - Voltage across each: U₀/2 (where U₀ is the battery voltage) - Electric field in each: E₀ = U₀/(2d) where d is the plate separation **Final situation (after dielectric in capacitor 1):** - C'₁ = εC (with dielectric) - C₂ = C (without dielectric) - Total capacitance: C_total = (εC · C)/(εC + C) = εC/(ε + 1) - Total charge: Q = U₀ · C_total = U₀εC/(ε + 1) For capacitors in series, the charge is the same on both: - Voltage across capacitor 1: U₁ = Q/C'₁ = [U₀εC/(ε + 1)]/(εC) = U₀/(ε + 1) - Voltage across capacitor 2: U₂ = Q/C₂ = [U₀εC/(ε + 1)]/C = U₀ε/(ε + 1) Electric field in capacitor 1 (with dielectric): E = U₁/d = U₀/[d(ε + 1)] Initial electric field in capacitor 1: E₀ = U₀/(2d) Ratio: E/E₀ = [U₀/(d(ε + 1))]/[U₀/(2d)] = 2/(ε + 1) { "final_numeric": null, "final_formula": "\\frac{2}{\\varepsilon + 1}", "final_units": "1" } | K45: {'id': 'gen-1780494347-fGWuzD05TDy7FDxFrwPl', 'object': 'chat.completion', 'created': 1780494347, 'model': 'anthropic/claude-4.5-sonnet-20250929', 'provider': 'Amazon Bedrock', 'system_fingerprint': None, 'service_tier': None, 'choices': [{'index': 0, 'logprobs': None, 'finish_reason': 'stop', 'native_finish_reason': 'end_turn', 'message': {'role': 'assistant', 'content': 'I need to find how the electric field changes in the capacitor filled with dielectric.\n\n**Initial situation (before dielectric):**\n- Two identical capacitors in series: C₁ = C₂ = C\n- Total capacitance: C₀ = C/2\n- Voltage across each: U₀/2 (where U₀ is the battery voltage)\n- Electric field in each: E₀ = U₀/(2d) where d is the plate separation\n\n**Final situation (after dielectric in capacitor 1):**\n- C\'₁ = εC (with dielectric)\n- C₂ = C (without dielectric)\n- Total capacitance: C_total = (εC · C)/(εC + C) = εC/(ε + 1)\n- Total charge: Q = U₀ · C_total = U₀εC/(ε + 1)\n\nFor capacitors in series, the charge is the same on both:\n- Voltage across capacitor 1: U₁ = Q/C\'₁ = [U₀εC/(ε + 1)]/(εC) = U₀/(ε + 1)\n- Voltage across capacitor 2: U₂ = Q/C₂ = [U₀εC/(ε + 1)]/C = U₀ε/(ε + 1)\n\nElectric field in capacitor 1 (with dielectric):\nE = U₁/d = U₀/[d(ε + 1)]\n\nInitial electric field in capacitor 1:\nE₀ = U₀/(2d)\n\nRatio:\nE/E₀ = [U₀/(d(ε + 1))]/[U₀/(2d)] = 2/(ε + 1)\n\n{\n "final_numeric": null,\n "final_formula": "\\\\frac{2}{\\\\varepsilon + 1}",\n "final_units": "1"\n}', 'refusal': None, 'reasoning': None}}], 'usage': {'prompt_tokens': 709, 'completion_tokens': 484, 'total_tokens': 1193, 'cost': 0.009387, 'is_byok': False, 'prompt_tokens_details': {'cached_tokens': 0, 'cache_write_tokens': 0, 'audio_tokens': 0, 'video_tokens': 0}, 'cost_details': {'upstream_inference_cost': 0.009387, 'upstream_inference_prompt_cost': 0.002127, 'upstream_inference_completions_cost': 0.00726}, 'completion_tokens_details': {'reasoning_tokens': 0, 'image_tokens': 0, 'audio_tokens': 0}}} | L45: 709 | M45: 484 | N45: 1193 | O45: 0 | P45: =VLOOKUP(C45,problems!$A$2:$B$26,2) -> electrostatics | Q45: =IFERROR(__xludf.DUMMYFUNCTION("INDEX(FILTER('stats2-openrouter_activity_2026'!C:C,L45='stats2-openrouter_activity_2026'!H:H,M45='stats2-openrouter_activity_2026'!I:I, B45='stats2-openrouter_activity_2026'!M:M),1)"),0.009387) -> 0.009387 | R45: =IFS( F45=VLOOKUP($C45,problems!$A$2:$G$26,6),1, True,0 ) -> 0 | S45: =IFS( G45=VLOOKUP($C45,problems!$A$2:$G$26,4),1, G45=VLOOKUP($C45,problems!$A$2:$G$26,5),1, True,0 ) -> 0 | T45: =IFS( H45=VLOOKUP($C45,problems!$A$2:$G$26,7),1, True,0 ) -> 1
A46: 2026-06-03-17-47-41 | B46: anthropic/claude-sonnet-4.5 | C46: 20 | D46: GIven: m — particle's mass -q — charge Particle moves along a straight line away from a fixed particle with charge: Q When the distance between the two particles is r_0 the particle has speed v_0 The interaction between the particles is electrostatic. Find: v_0 — the assumption about the initial speed needed to make the calculation valid. | E46: TRUE | G46: v_0 \geq \sqrt{\frac{2kqQ}{mr_0}} = \sqrt{\frac{qQ}{2\pi\epsilon_0 mr_0}} | H46: m/s | J46: I need to find the assumption about the initial speed v₀ needed to make the calculation valid. Given: - Particle with mass m and charge -q - Fixed particle with charge Q - Initial distance r₀ - Initial speed v₀ - Electrostatic interaction For the particle to move away from the fixed particle and escape to infinity, the initial kinetic energy must be sufficient to overcome the electrostatic potential energy. The electrostatic potential energy at distance r₀ is: U(r₀) = k(-q)Q/r₀ = -kqQ/r₀ where k = 1/(4πε₀) is Coulomb's constant. For the particle to escape to infinity (where U = 0), using energy conservation: ½mv₀² + U(r₀) ≥ 0 ½mv₀² - kqQ/r₀ ≥ 0 ½mv₀² ≥ kqQ/r₀ v₀² ≥ 2kqQ/(mr₀) v₀ ≥ √(2kqQ/(mr₀)) Since k = 1/(4πε₀): v₀ ≥ √(qQ/(2πε₀mr₀)) Or equivalently: v₀ ≥ √(2kqQ/(mr₀)) = √(qQ/(2πε₀mr₀)) The assumption needed is that v₀ must be greater than or equal to the escape velocity. Using k notation: v₀ ≥ √(2kqQ/(mr₀)) { "final_numeric": null, "final_formula": "v_0 \\geq \\sqrt{\\frac{2kqQ}{mr_0}} = \\sqrt{\\frac{qQ}{2\\pi\\epsilon_0 mr_0}}", "final_units": "m/s" } | K46: {'id': 'gen-1780494454-jh4noNguwLe88sOQsNpT', 'object': 'chat.completion', 'created': 1780494454, 'model': 'anthropic/claude-4.5-sonnet-20250929', 'provider': 'Amazon Bedrock', 'system_fingerprint': None, 'service_tier': None, 'choices': [{'index': 0, 'logprobs': None, 'finish_reason': 'stop', 'native_finish_reason': 'end_turn', 'message': {'role': 'assistant', 'content': 'I need to find the assumption about the initial speed v₀ needed to make the calculation valid.\n\nGiven:\n- Particle with mass m and charge -q\n- Fixed particle with charge Q\n- Initial distance r₀\n- Initial speed v₀\n- Electrostatic interaction\n\nFor the particle to move away from the fixed particle and escape to infinity, the initial kinetic energy must be sufficient to overcome the electrostatic potential energy.\n\nThe electrostatic potential energy at distance r₀ is:\nU(r₀) = k(-q)Q/r₀ = -kqQ/r₀\n\nwhere k = 1/(4πε₀) is Coulomb\'s constant.\n\nFor the particle to escape to infinity (where U = 0), using energy conservation:\n½mv₀² + U(r₀) ≥ 0\n\n½mv₀² - kqQ/r₀ ≥ 0\n\n½mv₀² ≥ kqQ/r₀\n\nv₀² ≥ 2kqQ/(mr₀)\n\nv₀ ≥ √(2kqQ/(mr₀))\n\nSince k = 1/(4πε₀):\n\nv₀ ≥ √(qQ/(2πε₀mr₀))\n\nOr equivalently:\n\nv₀ ≥ √(2kqQ/(mr₀)) = √(qQ/(2πε₀mr₀))\n\nThe assumption needed is that v₀ must be greater than or equal to the escape velocity.\n\nUsing k notation:\nv₀ ≥ √(2kqQ/(mr₀))\n\n{\n "final_numeric": null,\n "final_formula": "v_0 \\\\geq \\\\sqrt{\\\\frac{2kqQ}{mr_0}} = \\\\sqrt{\\\\frac{qQ}{2\\\\pi\\\\epsilon_0 mr_0}}",\n "final_units": "m/s"\n}', 'refusal': None, 'reasoning': None}}], 'usage': {'prompt_tokens': 575, 'completion_tokens': 481, 'total_tokens': 1056, 'cost': 0.00894, 'is_byok': False, 'prompt_tokens_details': {'cached_tokens': 0, 'cache_write_tokens': 0, 'audio_tokens': 0, 'video_tokens': 0}, 'cost_details': {'upstream_inference_cost': 0.00894, 'upstream_inference_prompt_cost': 0.001725, 'upstream_inference_completions_cost': 0.007215}, 'completion_tokens_details': {'reasoning_tokens': 0, 'image_tokens': 0, 'audio_tokens': 0}}} | L46: 575 | M46: 481 | N46: 1056 | O46: 0 | P46: =VLOOKUP(C46,problems!$A$2:$B$26,2) -> electrostatics | Q46: =IFERROR(__xludf.DUMMYFUNCTION("INDEX(FILTER('stats2-openrouter_activity_2026'!C:C,L46='stats2-openrouter_activity_2026'!H:H,M46='stats2-openrouter_activity_2026'!I:I, B46='stats2-openrouter_activity_2026'!M:M),1)"),0.00894) -> 0.00894 | R46: =IFS( F46=VLOOKUP($C46,problems!$A$2:$G$26,6),1, True,0 ) -> 1 | S46: =IFS( G46=VLOOKUP($C46,problems!$A$2:$G$26,4),1, G46=VLOOKUP($C46,problems!$A$2:$G$26,5),1, True,0 ) -> 0 | T46: =IFS( H46=VLOOKUP($C46,problems!$A$2:$G$26,7),1, True,0 ) -> 0
A47: 2026-06-03-17-49-04 | B47: anthropic/claude-sonnet-4.5 | C47: 21 | D47: Дано: Атомы водорода испускают монохроматический свет при переходе электронов с некоторой более удалённой орбиты на вторую боровскую орбиту: n -> 2 k — порядок дифракционного максимума. phi — угол дифракции. d = 2.6 мкм — постоянная дифракционной решётки. Пучок света падает на дифракционную решётку по нормали. R — постоянная Ридберга. c — скорость света. Найти: lambda — длина волны испущенного света. | E47: TRUE | G47: \lambda = \frac{d\sin\phi}{k} | H47: m | J47: I need to solve for the wavelength of light emitted when hydrogen atoms transition to n=2. For hydrogen atom transitions, the wavelength is given by the Rydberg formula: $$\frac{1}{\lambda} = R \left(\frac{1}{n_f^2} - \frac{1}{n_i^2}\right)$$ where $n_f = 2$ (final state) and $n_i = n$ (initial state). For transitions to n=2: $$\frac{1}{\lambda} = R \left(\frac{1}{4} - \frac{1}{n^2}\right)$$ Therefore: $$\lambda = \frac{1}{R \left(\frac{1}{4} - \frac{1}{n^2}\right)} = \frac{4n^2}{R(n^2 - 4)}$$ However, the problem mentions a diffraction grating with: - d = 2.6 μm = 2.6 × 10⁻⁶ m - Normal incidence - Diffraction angle φ - Order k The diffraction grating equation is: $$d \sin\phi = k\lambda$$ But the problem doesn't provide specific values for k, φ, or n. Looking at the problem structure, it appears we need to express λ in terms of the given parameters. Since the problem asks to find λ and mentions the diffraction grating setup, if we had k and φ, we would use: $$\lambda = \frac{d \sin\phi}{k}$$ However, without specific numerical values for k, φ, and n, the answer must be symbolic. The most general formula for the wavelength using the Rydberg formula for transitions to n=2 is: $$\lambda = \frac{4n^2}{R(n^2-4)}$$ Or if using the diffraction grating data: $$\lambda = \frac{d\sin\phi}{k}$$ Since the problem emphasizes the diffraction grating parameters and gives d explicitly, the answer likely expects: $$\lambda = \frac{d\sin\phi}{k}$$ But without numerical values for k and φ, I cannot compute a numeric answer. Given only d = 2.6 × 10⁻⁶ m is provided numerically, and the problem structure suggests we should find λ, the formula would be: $$\lambda = \frac{d\sin\phi}{k}$$ { "final_numeric": null, "final_formula": "\\lambda = \\frac{d\\sin\\phi}{k}", "final_units": "m" } | K47: {'id': 'gen-1780494534-obfWrAq9c2Doa3mGdzLG', 'object': 'chat.completion', 'created': 1780494534, 'model': 'anthropic/claude-4.5-sonnet-20250929', 'provider': 'Amazon Bedrock', 'system_fingerprint': None, 'service_tier': None, 'choices': [{'index': 0, 'logprobs': None, 'finish_reason': 'stop', 'native_finish_reason': 'end_turn', 'message': {'role': 'assistant', 'content': 'I need to solve for the wavelength of light emitted when hydrogen atoms transition to n=2.\n\nFor hydrogen atom transitions, the wavelength is given by the Rydberg formula:\n\n$$\\frac{1}{\\lambda} = R \\left(\\frac{1}{n_f^2} - \\frac{1}{n_i^2}\\right)$$\n\nwhere $n_f = 2$ (final state) and $n_i = n$ (initial state).\n\nFor transitions to n=2:\n$$\\frac{1}{\\lambda} = R \\left(\\frac{1}{4} - \\frac{1}{n^2}\\right)$$\n\nTherefore:\n$$\\lambda = \\frac{1}{R \\left(\\frac{1}{4} - \\frac{1}{n^2}\\right)} = \\frac{4n^2}{R(n^2 - 4)}$$\n\nHowever, the problem mentions a diffraction grating with:\n- d = 2.6 μm = 2.6 × 10⁻⁶ m\n- Normal incidence\n- Diffraction angle φ\n- Order k\n\nThe diffraction grating equation is:\n$$d \\sin\\phi = k\\lambda$$\n\nBut the problem doesn\'t provide specific values for k, φ, or n. Looking at the problem structure, it appears we need to express λ in terms of the given parameters.\n\nSince the problem asks to find λ and mentions the diffraction grating setup, if we had k and φ, we would use:\n$$\\lambda = \\frac{d \\sin\\phi}{k}$$\n\nHowever, without specific numerical values for k, φ, and n, the answer must be symbolic.\n\nThe most general formula for the wavelength using the Rydberg formula for transitions to n=2 is:\n\n$$\\lambda = \\frac{4n^2}{R(n^2-4)}$$\n\nOr if using the diffraction grating data:\n$$\\lambda = \\frac{d\\sin\\phi}{k}$$\n\nSince the problem emphasizes the diffraction grating parameters and gives d explicitly, the answer likely expects:\n\n$$\\lambda = \\frac{d\\sin\\phi}{k}$$\n\nBut without numerical values for k and φ, I cannot compute a numeric answer.\n\nGiven only d = 2.6 × 10⁻⁶ m is provided numerically, and the problem structure suggests we should find λ, the formula would be:\n\n$$\\lambda = \\frac{d\\sin\\phi}{k}$$\n\n{\n "final_numeric": null,\n "final_formula": "\\\\lambda = \\\\frac{d\\\\sin\\\\phi}{k}",\n "final_units": "m"\n}', 'refusal': None, 'reasoning': None}}], 'usage': {'prompt_tokens': 661, 'completion_tokens': 647, 'total_tokens': 1308, 'cost': 0.011688, 'is_byok': False, 'prompt_tokens_details': {'cached_tokens': 0, 'cache_write_tokens': 0, 'audio_tokens': 0, 'video_tokens': 0}, 'cost_details': {'upstream_inference_cost': 0.011688, 'upstream_inference_prompt_cost': 0.001983, 'upstream_inference_completions_cost': 0.009705}, 'completion_tokens_details': {'reasoning_tokens': 0, 'image_tokens': 0, 'audio_tokens': 0}}} | L47: 661 | M47: 647 | N47: 1308 | O47: 0 | P47: =VLOOKUP(C47,problems!$A$2:$B$26,2) -> nuclear | Q47: =IFERROR(__xludf.DUMMYFUNCTION("INDEX(FILTER('stats2-openrouter_activity_2026'!C:C,L47='stats2-openrouter_activity_2026'!H:H,M47='stats2-openrouter_activity_2026'!I:I, B47='stats2-openrouter_activity_2026'!M:M),1)"),0.011688) -> 0.011688 | R47: =IFS( F47=VLOOKUP($C47,problems!$A$2:$G$26,6),1, True,0 ) -> 0 | S47: =IFS( G47=VLOOKUP($C47,problems!$A$2:$G$26,4),1, G47=VLOOKUP($C47,problems!$A$2:$G$26,5),1, True,0 ) -> 0 | T47: =IFS( H47=VLOOKUP($C47,problems!$A$2:$G$26,7),1, True,0 ) -> 0
A48: 2026-06-03-17-51-10 | B48: anthropic/claude-sonnet-4.5 | C48: 22 | D48: Дано: Подводная лодка имеет мощность топливных установок: P = 14.7 МВт n = 25% — КПД установки m_0 = 1 кг — масса урана, для которой дана энергия деления E = 6.9 * 10^13 Дж — энергия, выделяющаяся при делении ядер урана t = 1 год — время плавания Найти: m — масса урана, необходимая для годового плавания лодки, в килограммах. | E48: TRUE | F48: 26.9 | G48: m = \frac{P \cdot t}{\eta \cdot \frac{E}{m_0}} | H48: kg | J48: Looking at this problem, I need to find the mass of uranium required for a submarine to operate for one year. **Given:** - P = 14.7 MW = 14.7 × 10⁶ W (power of fuel installations) - η = 25% = 0.25 (efficiency) - m₀ = 1 kg (reference mass of uranium) - E = 6.9 × 10¹³ J (energy released from fission of m₀) - t = 1 year (operation time) **Solution:** First, I'll convert time to seconds: t = 1 year = 365.25 × 24 × 3600 = 31,557,600 s The total energy required by the submarine over one year: E_required = P × t = 14.7 × 10⁶ × 31,557,600 = 4.639 × 10¹⁴ J Since the efficiency is 25%, the actual energy that must be produced from uranium fission: E_total = E_required / η = 4.639 × 10¹⁴ / 0.25 = 1.856 × 10¹⁵ J The specific energy from uranium (energy per kg): e = E / m₀ = 6.9 × 10¹³ / 1 = 6.9 × 10¹³ J/kg The mass of uranium needed: m = E_total / e = (P × t) / (η × e) m = (14.7 × 10⁶ × 31,557,600) / (0.25 × 6.9 × 10¹³) m = 4.639 × 10¹⁴ / (1.725 × 10¹³) m = 26.89 kg Rounding to appropriate significant figures: m ≈ 26.9 kg ```json { "final_numeric": 26.9, "final_formula": "m = \\frac{P \\cdot t}{\\eta \\cdot \\frac{E}{m_0}}", "final_units": "kg" } ``` | K48: {'id': 'gen-1780494662-G31FRNRR6IxR1M5VLpcN', 'object': 'chat.completion', 'created': 1780494662, 'model': 'anthropic/claude-4.5-sonnet-20250929', 'provider': 'Amazon Bedrock', 'system_fingerprint': None, 'service_tier': None, 'choices': [{'index': 0, 'logprobs': None, 'finish_reason': 'stop', 'native_finish_reason': 'end_turn', 'message': {'role': 'assistant', 'content': 'Looking at this problem, I need to find the mass of uranium required for a submarine to operate for one year.\n\n**Given:**\n- P = 14.7 MW = 14.7 × 10⁶ W (power of fuel installations)\n- η = 25% = 0.25 (efficiency)\n- m₀ = 1 kg (reference mass of uranium)\n- E = 6.9 × 10¹³ J (energy released from fission of m₀)\n- t = 1 year (operation time)\n\n**Solution:**\n\nFirst, I\'ll convert time to seconds:\nt = 1 year = 365.25 × 24 × 3600 = 31,557,600 s\n\nThe total energy required by the submarine over one year:\nE_required = P × t = 14.7 × 10⁶ × 31,557,600 = 4.639 × 10¹⁴ J\n\nSince the efficiency is 25%, the actual energy that must be produced from uranium fission:\nE_total = E_required / η = 4.639 × 10¹⁴ / 0.25 = 1.856 × 10¹⁵ J\n\nThe specific energy from uranium (energy per kg):\ne = E / m₀ = 6.9 × 10¹³ / 1 = 6.9 × 10¹³ J/kg\n\nThe mass of uranium needed:\nm = E_total / e = (P × t) / (η × e)\n\nm = (14.7 × 10⁶ × 31,557,600) / (0.25 × 6.9 × 10¹³)\n\nm = 4.639 × 10¹⁴ / (1.725 × 10¹³)\n\nm = 26.89 kg\n\nRounding to appropriate significant figures: m ≈ 26.9 kg\n\n```json\n{\n "final_numeric": 26.9,\n "final_formula": "m = \\\\frac{P \\\\cdot t}{\\\\eta \\\\cdot \\\\frac{E}{m_0}}",\n "final_units": "kg"\n}\n```', 'refusal': None, 'reasoning': None}}], 'usage': {'prompt_tokens': 646, 'completion_tokens': 554, 'total_tokens': 1200, 'cost': 0.010248, 'is_byok': False, 'prompt_tokens_details': {'cached_tokens': 0, 'cache_write_tokens': 0, 'audio_tokens': 0, 'video_tokens': 0}, 'cost_details': {'upstream_inference_cost': 0.010248, 'upstream_inference_prompt_cost': 0.001938, 'upstream_inference_completions_cost': 0.00831}, 'completion_tokens_details': {'reasoning_tokens': 0, 'image_tokens': 0, 'audio_tokens': 0}}} | L48: 646 | M48: 554 | N48: 1200 | O48: 0 | P48: =VLOOKUP(C48,problems!$A$2:$B$26,2) -> nuclear | Q48: =IFERROR(__xludf.DUMMYFUNCTION("INDEX(FILTER('stats2-openrouter_activity_2026'!C:C,L48='stats2-openrouter_activity_2026'!H:H,M48='stats2-openrouter_activity_2026'!I:I, B48='stats2-openrouter_activity_2026'!M:M),1)"),0.010248) -> 0.010248 | R48: =IFS( F48=VLOOKUP($C48,problems!$A$2:$G$26,6),1, True,0 ) -> 1 | S48: =IFS( G48=VLOOKUP($C48,problems!$A$2:$G$26,4),1, G48=VLOOKUP($C48,problems!$A$2:$G$26,5),1, True,0 ) -> 0 | T48: =IFS( H48=VLOOKUP($C48,problems!$A$2:$G$26,7),1, True,0 ) -> 1
A49: 2026-06-03-17-53-11 | B49: anthropic/claude-sonnet-4.5 | C49: 23 | D49: Дано: delta n_0 = 250 — начальное число импульсов за минуту. t = 1 ч delta n = 92 — число импульсов за минуту через время t. Найти: T_{1/2} — период полураспада данного изотопа, в минутах. | E49: TRUE | F49: 60 | G49: T_{1/2} = \frac{t \ln 2}{\ln(\Delta n_0 / \Delta n)} = \frac{60 \ln 2}{\ln(250/92)} \approx 60 \text{ мин} | H49: s | J49: { "final_numeric": 60, "final_formula": "T_{1/2} = \\frac{t \\ln 2}{\\ln(\\Delta n_0 / \\Delta n)} = \\frac{60 \\ln 2}{\\ln(250/92)} \\approx 60 \\text{ мин}", "final_units": "s" } | K49: {'id': 'gen-1780494789-YfgT8H3A4MivdW2ZVIuS', 'object': 'chat.completion', 'created': 1780494789, 'model': 'anthropic/claude-4.5-sonnet-20250929', 'provider': 'Amazon Bedrock', 'system_fingerprint': None, 'service_tier': None, 'choices': [{'index': 0, 'logprobs': None, 'finish_reason': 'stop', 'native_finish_reason': 'end_turn', 'message': {'role': 'assistant', 'content': '{\n "final_numeric": 60,\n "final_formula": "T_{1/2} = \\\\frac{t \\\\ln 2}{\\\\ln(\\\\Delta n_0 / \\\\Delta n)} = \\\\frac{60 \\\\ln 2}{\\\\ln(250/92)} \\\\approx 60 \\\\text{ мин}",\n "final_units": "s"\n}', 'refusal': None, 'reasoning': None}}], 'usage': {'prompt_tokens': 577, 'completion_tokens': 104, 'total_tokens': 681, 'cost': 0.003291, 'is_byok': False, 'prompt_tokens_details': {'cached_tokens': 0, 'cache_write_tokens': 0, 'audio_tokens': 0, 'video_tokens': 0}, 'cost_details': {'upstream_inference_cost': 0.003291, 'upstream_inference_prompt_cost': 0.001731, 'upstream_inference_completions_cost': 0.00156}, 'completion_tokens_details': {'reasoning_tokens': 0, 'image_tokens': 0, 'audio_tokens': 0}}} | L49: 577 | M49: 104 | N49: 681 | O49: 0 | P49: =VLOOKUP(C49,problems!$A$2:$B$26,2) -> nuclear | Q49: =IFERROR(__xludf.DUMMYFUNCTION("INDEX(FILTER('stats2-openrouter_activity_2026'!C:C,L49='stats2-openrouter_activity_2026'!H:H,M49='stats2-openrouter_activity_2026'!I:I, B49='stats2-openrouter_activity_2026'!M:M),1)"),0.003291) -> 0.003291 | R49: =IFS( F49=VLOOKUP($C49,problems!$A$2:$G$26,6),1, True,0 ) -> 0 | S49: =IFS( G49=VLOOKUP($C49,problems!$A$2:$G$26,4),1, G49=VLOOKUP($C49,problems!$A$2:$G$26,5),1, True,0 ) -> 0 | T49: =IFS( H49=VLOOKUP($C49,problems!$A$2:$G$26,7),1, True,0 ) -> 0
A50: 2026-06-03-17-56-17 | B50: anthropic/claude-sonnet-4.5 | C50: 24 | D50: Given: M = 40 g/mol — atomic mass of chlorine Chlorine has two most common stable isotopes: {}^{35}_{17}\mathrm{Cl} {}^{37}_{17}\mathrm{Cl} M_{35} = 35 g/mol — atomic mass of chlorine 35 M_{37} = 37 g/mol — atomic mass of chlorine 37 f_{35} = 75.8% — abundance of chlorine-35 f_{37} = 24.2% — abundance of chlorine-37 Find: M_{avg} — the average atomic mass of chlorine, in g/mol, and check whether 40g/mol is correct. | E50: TRUE | F50: 35.484 | G50: M_{avg} = f_{35} \cdot M_{35} + f_{37} \cdot M_{37} = 0.758 \times 35 + 0.242 \times 37 = 35.484 \text{ g/mol} | H50: g/mol | J50: I need to calculate the average atomic mass of chlorine based on the abundances of its isotopes. The average atomic mass is calculated using the weighted average formula: $$M_{avg} = f_{35} \cdot M_{35} + f_{37} \cdot M_{37}$$ Converting percentages to decimals: - $f_{35} = 75.8\% = 0.758$ - $f_{37} = 24.2\% = 0.242$ Calculating: $$M_{avg} = 0.758 \times 35 + 0.242 \times 37$$ $$M_{avg} = 26.53 + 8.954$$ $$M_{avg} = 35.484 \text{ g/mol}$$ This shows that the given value of M = 40 g/mol is **incorrect**. The actual average atomic mass of chlorine is approximately 35.5 g/mol, which matches the known value. { "final_numeric": 35.484, "final_formula": "M_{avg} = f_{35} \\cdot M_{35} + f_{37} \\cdot M_{37} = 0.758 \\times 35 + 0.242 \\times 37 = 35.484 \\text{ g/mol}", "final_units": "g/mol" } | K50: {'id': 'gen-1780494972-laYNuv6kGWqnNHG2L9n5', 'object': 'chat.completion', 'created': 1780494972, 'model': 'anthropic/claude-4.5-sonnet-20250929', 'provider': 'Amazon Bedrock', 'system_fingerprint': None, 'service_tier': None, 'choices': [{'index': 0, 'logprobs': None, 'finish_reason': 'stop', 'native_finish_reason': 'end_turn', 'message': {'role': 'assistant', 'content': 'I need to calculate the average atomic mass of chlorine based on the abundances of its isotopes.\n\nThe average atomic mass is calculated using the weighted average formula:\n\n$$M_{avg} = f_{35} \\cdot M_{35} + f_{37} \\cdot M_{37}$$\n\nConverting percentages to decimals:\n- $f_{35} = 75.8\\% = 0.758$\n- $f_{37} = 24.2\\% = 0.242$\n\nCalculating:\n$$M_{avg} = 0.758 \\times 35 + 0.242 \\times 37$$\n$$M_{avg} = 26.53 + 8.954$$\n$$M_{avg} = 35.484 \\text{ g/mol}$$\n\nThis shows that the given value of M = 40 g/mol is **incorrect**. The actual average atomic mass of chlorine is approximately 35.5 g/mol, which matches the known value.\n\n{\n "final_numeric": 35.484,\n "final_formula": "M_{avg} = f_{35} \\\\cdot M_{35} + f_{37} \\\\cdot M_{37} = 0.758 \\\\times 35 + 0.242 \\\\times 37 = 35.484 \\\\text{ g/mol}",\n "final_units": "g/mol"\n}', 'refusal': None, 'reasoning': None}}], 'usage': {'prompt_tokens': 661, 'completion_tokens': 337, 'total_tokens': 998, 'cost': 0.007038, 'is_byok': False, 'prompt_tokens_details': {'cached_tokens': 0, 'cache_write_tokens': 0, 'audio_tokens': 0, 'video_tokens': 0}, 'cost_details': {'upstream_inference_cost': 0.007038, 'upstream_inference_prompt_cost': 0.001983, 'upstream_inference_completions_cost': 0.005055}, 'completion_tokens_details': {'reasoning_tokens': 0, 'image_tokens': 0, 'audio_tokens': 0}}} | L50: 661 | M50: 337 | N50: 998 | O50: 0 | P50: =VLOOKUP(C50,problems!$A$2:$B$26,2) -> nuclear | Q50: =IFERROR(__xludf.DUMMYFUNCTION("INDEX(FILTER('stats2-openrouter_activity_2026'!C:C,L50='stats2-openrouter_activity_2026'!H:H,M50='stats2-openrouter_activity_2026'!I:I, B50='stats2-openrouter_activity_2026'!M:M),1)"),0.007038) -> 0.007038 | R50: =IFS( F50=VLOOKUP($C50,problems!$A$2:$G$26,6),1, True,0 ) -> 0 | S50: =IFS( G50=VLOOKUP($C50,problems!$A$2:$G$26,4),1, G50=VLOOKUP($C50,problems!$A$2:$G$26,5),1, True,0 ) -> 0 | T50: =IFS( H50=VLOOKUP($C50,problems!$A$2:$G$26,7),1, True,0 ) -> 1
A51: 2026-06-03-17-58-03 | B51: anthropic/claude-sonnet-4.5 | C51: 25 | D51: Given: lambda = 1 pm — photon's wavelength h — Planck’s constant c — speed of light Find: E — energy of the photon, in \text{MeV}. | E51: TRUE | F51: 1.24 | G51: E = \frac{hc}{\lambda} = \frac{(6.626 \times 10^{-34})(3 \times 10^8)}{1 \times 10^{-12}} \approx 1.24 \text{ MeV} | H51: MeV | J51: { "final_numeric": 1.24, "final_formula": "E = \\frac{hc}{\\lambda} = \\frac{(6.626 \\times 10^{-34})(3 \\times 10^8)}{1 \\times 10^{-12}} \\approx 1.24 \\text{ MeV}", "final_units": "MeV" } | K51: {'id': 'gen-1780495081-iQYcDmZjckZqaYERZQ7T', 'object': 'chat.completion', 'created': 1780495081, 'model': 'anthropic/claude-4.5-sonnet-20250929', 'provider': 'Amazon Bedrock', 'system_fingerprint': None, 'service_tier': None, 'choices': [{'index': 0, 'logprobs': None, 'finish_reason': 'stop', 'native_finish_reason': 'end_turn', 'message': {'role': 'assistant', 'content': '{\n "final_numeric": 1.24,\n "final_formula": "E = \\\\frac{hc}{\\\\lambda} = \\\\frac{(6.626 \\\\times 10^{-34})(3 \\\\times 10^8)}{1 \\\\times 10^{-12}} \\\\approx 1.24 \\\\text{ MeV}",\n "final_units": "MeV"\n}', 'refusal': None, 'reasoning': None}}], 'usage': {'prompt_tokens': 539, 'completion_tokens': 114, 'total_tokens': 653, 'cost': 0.003327, 'is_byok': False, 'prompt_tokens_details': {'cached_tokens': 0, 'cache_write_tokens': 0, 'audio_tokens': 0, 'video_tokens': 0}, 'cost_details': {'upstream_inference_cost': 0.003327, 'upstream_inference_prompt_cost': 0.001617, 'upstream_inference_completions_cost': 0.00171}, 'completion_tokens_details': {'reasoning_tokens': 0, 'image_tokens': 0, 'audio_tokens': 0}}} | L51: 539 | M51: 114 | N51: 653 | O51: 0 | P51: =VLOOKUP(C51,problems!$A$2:$B$26,2) -> nuclear | Q51: =IFERROR(__xludf.DUMMYFUNCTION("INDEX(FILTER('stats2-openrouter_activity_2026'!C:C,L51='stats2-openrouter_activity_2026'!H:H,M51='stats2-openrouter_activity_2026'!I:I, B51='stats2-openrouter_activity_2026'!M:M),1)"),0.003327) -> 0.003327 | R51: =IFS( F51=VLOOKUP($C51,problems!$A$2:$G$26,6),1, True,0 ) -> 1 | S51: =IFS( G51=VLOOKUP($C51,problems!$A$2:$G$26,4),1, G51=VLOOKUP($C51,problems!$A$2:$G$26,5),1, True,0 ) -> 0 | T51: =IFS( H51=VLOOKUP($C51,problems!$A$2:$G$26,7),1, True,0 ) -> 1
A52: 2026-06-03-17-06-01 | B52: deepseek/deepseek-r1 | C52: 1 | D52: Дано: l = 2 м — расстояние, которое частица пролетает равномерно a = 5*10^5 м/с^2 — ускорение торможения, направлено против движения. Найти: v - скорость частицы, при которой полное время движения от вылета до остановки минимально в м/с | E52: TRUE | F52: 1000 | G52: \sqrt{a l} | H52: m/s | J52: { "final_numeric": 1000, "final_formula": "\\sqrt{a l}", "final_units": "m/s" } | K52: {'id': 'gen-1780491953-d2URwnpA93bPPh0DCSXd', 'object': 'chat.completion', 'created': 1780491953, 'model': 'deepseek/deepseek-r1', 'provider': 'Azure', 'system_fingerprint': None, 'service_tier': None, 'choices': [{'index': 0, 'logprobs': None, 'finish_reason': 'stop', 'native_finish_reason': 'stop', 'message': {'role': 'assistant', 'content': '{\n "final_numeric": 1000,\n "final_formula": "\\\\sqrt{a l}",\n "final_units": "m/s"\n}', 'refusal': None, 'reasoning': 'Okay, let\'s tackle this physics problem. So, the problem states that a particle travels a distance l = 2 meters uniformly, and then decelerates with acceleration a = 5*10^5 m/s² opposite to its direction of motion. We need to find the initial velocity v that minimizes the total time from launch to stopping.\n\nHmm, wait. The particle is moving, covers a distance l uniformly, but then starts decelerating until it stops. Wait, maybe I need to clarify the motion here. Is the particle moving with a constant velocity for the first part (distance l) and then starts decelerating? Or is the entire motion under the influence of this acceleration? Wait, the problem says "расстояние, которое частица пролетает равномерно" which translates to "the distance the particle travels uniformly". So, uniform motion (constant speed) for distance l, and then starts decelerating with acceleration a until it stops. So the total time is the time during uniform motion plus the time during deceleration.\n\nWait, but the problem is to find the initial velocity v such that the total time is minimized. Wait, but if the particle is first moving at constant velocity v for distance l, then starts decelerating with acceleration a (which is a negative acceleration, since it\'s directed against the motion), then the time for the first part is t1 = l / v. Then, during the deceleration phase, the particle comes to rest. The time taken to stop would be t2 = v / a, since the deceleration is a (assuming a is the magnitude here). So the total time T = t1 + t2 = (l / v) + (v / a). We need to find the value of v that minimizes T.\n\nAh, right. So this is a calculus optimization problem. To find the total time as a function of v, then take its derivative with respect to v, set it to zero, and solve for v.\n\nSo let\'s write T(v) = l/v + v/a. To find the minimum, take derivative dT/dv = -l / v² + 1/a. Setting this equal to zero:\n\n-l / v² + 1/a = 0 → 1/a = l / v² → v² = a*l → v = sqrt(a*l).\n\nSo the minimal time occurs when v is the square root of a times l. Then, substituting the given values: a = 5e5 m/s², l = 2 m.\n\nCalculating that: sqrt(5e5 * 2) = sqrt(1e6) = 1000 m/s. Wait, 5e5 is 500,000. 500,000 * 2 is 1,000,000. Square root of 1e6 is 1000. So the numeric value is 1000 m/s.\n\nSo the final formula is v = \\sqrt{a l}, units in m/s. The numeric value is 1000 m/s. Units are m/s.\n\nSo the JSON should have final_numeric 1000, formula \\sqrt{a l}, units m/s.\n', 'reasoning_details': [{'type': 'reasoning.text', 'text': 'Okay, let\'s tackle this physics problem. So, the problem states that a particle travels a distance l = 2 meters uniformly, and then decelerates with acceleration a = 5*10^5 m/s² opposite to its direction of motion. We need to find the initial velocity v that minimizes the total time from launch to stopping.\n\nHmm, wait. The particle is moving, covers a distance l uniformly, but then starts decelerating until it stops. Wait, maybe I need to clarify the motion here. Is the particle moving with a constant velocity for the first part (distance l) and then starts decelerating? Or is the entire motion under the influence of this acceleration? Wait, the problem says "расстояние, которое частица пролетает равномерно" which translates to "the distance the particle travels uniformly". So, uniform motion (constant speed) for distance l, and then starts decelerating with acceleration a until it stops. So the total time is the time during uniform motion plus the time during deceleration.\n\nWait, but the problem is to find the initial velocity v such that the total time is minimized. Wait, but if the particle is first moving at constant velocity v for distance l, then starts decelerating with acceleration a (which is a negative acceleration, since it\'s directed against the motion), then the time for the first part is t1 = l / v. Then, during the deceleration phase, the particle comes to rest. The time taken to stop would be t2 = v / a, since the deceleration is a (assuming a is the magnitude here). So the total time T = t1 + t2 = (l / v) + (v / a). We need to find the value of v that minimizes T.\n\nAh, right. So this is a calculus optimization problem. To find the total time as a function of v, then take its derivative with respect to v, set it to zero, and solve for v.\n\nSo let\'s write T(v) = l/v + v/a. To find the minimum, take derivative dT/dv = -l / v² + 1/a. Setting this equal to zero:\n\n-l / v² + 1/a = 0 → 1/a = l / v² → v² = a*l → v = sqrt(a*l).\n\nSo the minimal time occurs when v is the square root of a times l. Then, substituting the given values: a = 5e5 m/s², l = 2 m.\n\nCalculating that: sqrt(5e5 * 2) = sqrt(1e6) = 1000 m/s. Wait, 5e5 is 500,000. 500,000 * 2 is 1,000,000. Square root of 1e6 is 1000. So the numeric value is 1000 m/s.\n\nSo the final formula is v = \\sqrt{a l}, units in m/s. The numeric value is 1000 m/s. Units are m/s.\n\nSo the JSON should have final_numeric 1000, formula \\sqrt{a l}, units m/s.\n', 'format': 'unknown', 'index': 0}]}}], 'usage': {'prompt_tokens': 527, 'completion_tokens': 696, 'total_tokens': 1223, 'cost': 0.004916835, 'is_byok': False, 'prompt_tokens_details': {'cached_tokens': 0, 'cache_write_tokens': 0, 'audio_tokens': 0, 'video_tokens': 0}, 'cost_details': {'upstream_inference_cost': 0.004916835, 'upstream_inference_prompt_cost': 0.000782595, 'upstream_inference_completions_cost': 0.00413424}, 'completion_tokens_details': {'reasoning_tokens': 664, 'image_tokens': 0, 'audio_tokens': 0}}} | L52: 527 | M52: 696 | N52: 1223 | O52: 0 | P52: =VLOOKUP(C52,problems!$A$2:$B$26,2) -> mechanics | Q52: =IFERROR(__xludf.DUMMYFUNCTION("INDEX(FILTER('stats2-openrouter_activity_2026'!C:C,L52='stats2-openrouter_activity_2026'!H:H,M52='stats2-openrouter_activity_2026'!I:I, B52='stats2-openrouter_activity_2026'!M:M),1)"),0.004916) -> 0.004916 | R52: =IFS( F52=VLOOKUP($C52,problems!$A$2:$G$26,6),1, True,0 ) -> 1 | S52: =IFS( G52=VLOOKUP($C52,problems!$A$2:$G$26,4),1, G52=VLOOKUP($C52,problems!$A$2:$G$26,5),1, True,0 ) -> 1 | T52: =IFS( H52=VLOOKUP($C52,problems!$A$2:$G$26,7),1, True,0 ) -> 1
A53: 2026-06-03-17-06-46 | B53: deepseek/deepseek-r1 | C53: 2 | D53: Дано: x = At+Bt^3 — закон движения точки по оси x. A = 6 м/с B = -0.125 м/с^3 t_1 = 2 с t_2 = 6 с Найти: v_{ср} — средняя скорость точки за интервал времени от t_{1} до t_{2}​ в м/с | E53: TRUE | F53: -0.5 | G53: \frac{6 \cdot 6 + (-0.125) \cdot 6^3 - 6 \cdot 2 - (-0.125) \cdot 2^3}{6 - 2} | H53: m/s | J53: { "final_numeric": -0.5, "final_formula": "\\frac{6 \\cdot 6 + (-0.125) \\cdot 6^3 - 6 \\cdot 2 - (-0.125) \\cdot 2^3}{6 - 2}", "final_units": "m/s" } | K53: {'id': 'gen-1780491966-nUgMVHl1qfV89aad35BA', 'object': 'chat.completion', 'created': 1780491966, 'model': 'deepseek/deepseek-r1', 'provider': 'Azure', 'system_fingerprint': None, 'service_tier': None, 'choices': [{'index': 0, 'logprobs': None, 'finish_reason': 'stop', 'native_finish_reason': 'stop', 'message': {'role': 'assistant', 'content': '{\n "final_numeric": -0.5,\n "final_formula": "\\\\frac{6 \\\\cdot 6 + (-0.125) \\\\cdot 6^3 - 6 \\\\cdot 2 - (-0.125) \\\\cdot 2^3}{6 - 2}",\n "final_units": "m/s"\n}', 'refusal': None, 'reasoning': 'Okay, let\'s tackle this physics problem. The question is about finding the average velocity of a point moving along the x-axis between two times, t₁ = 2 seconds and t₂ = 6 seconds. The position is given by the equation x(t) = At + Bt³, where A is 6 m/s and B is -0.125 m/s³. \n\nFirst, I remember that average velocity is the total displacement divided by the total time interval. So the formula should be (x(t₂) - x(t₁)) / (t₂ - t₁). That makes sense because average velocity is all about the change in position over the change in time.\n\nLet me start by calculating the displacement. I need to find x at t=6 and x at t=2, then subtract them. \n\nFor t₂ = 6s:\nx(6) = A*6 + B*(6)^3. Plugging in the values: 6 m/s *6 = 36 m. Then B is -0.125, so 6^3 is 216. Multiply that by B: -0.125 * 216? Wait, 6³ is 216. So -0.125 * 216 = -27. So x(6) is 36 -27 = 9 meters.\n\nWait, let me check that again. 6*6 is 36, yes. Then 6³ is 216. 0.125 * 216 is 27, but since B is negative, it\'s -27. So 36 -27 is indeed 9. So x(6) = 9 m.\n\nNow for t₁ = 2s:\nx(2) = A*2 + B*(2)^3. A is 6, so 6*2=12. B is -0.125, 2³ is 8. So -0.125 *8 = -1. So x(2) is 12 -1 = 11 meters.\n\nWait, that can\'t be right. Wait, 0.125 *8 is 1, so with the negative, it\'s -1. So 12 -1 = 11. So x(2) is 11 m. \n\nSo the displacement is x(6) - x(2) = 9 -11 = -2 meters. \n\nThe time interval is t₂ - t₁ = 6 -2 =4 seconds. \n\nSo average velocity is displacement over time: -2 m /4 s = -0.5 m/s. \n\nWait, but let me double-check the calculations. Maybe I made a mistake in the exponents or the multiplication. Let me recalculate x(6):\n\nA=6, t=6: 6*6=36. B=-0.125, t³=216. 0.125 *216 is 27, so -0.125*216= -27. 36-27=9. Correct. x(6)=9 m.\n\nx(2): 6*2=12. 2=8. 0.125*8=1, so -1. 12-1=11. Correct. So displacement is 9-11= -2. Time is 4s. So -2/4= -0.5 m/s. \n\nSo the average velocity is -0.5 m/s. \n\nThe formula for average velocity would be (A t₂ + B t₂³ - A t₁ - B t₁³)/(t₂ - t₁). Which can be factored as [A(t₂ - t₁) + B(t₂³ - t₁³)]/(t₂ - t₁). Then, simplifying, that\'s A + B(t₂² + t₂ t₁ + t₁²). But maybe the problem just wants the direct formula (x(t₂)-x(t₁))/(t₂ - t₁). \n\nBut since the answer requires the final formula as a LaTeX expression, perhaps the formula is written as v_{\\text{ср}} = \\frac{x(t_2) - x(t_1)}{t_2 - t_1}. But substituting the given values, but maybe they want the symbolic expression. Wait, the problem says to write the final answer as a formula. Wait, the problem says "final_formula": a string containing the final answer as a formula/expression written as valid LaTeX. So perhaps the formula is the expression evaluated with the numbers. Let me see. \n\nAlternatively, maybe the formula is written in terms of A, B, t1, t2. But since the problem gives numerical values, perhaps the formula is the calculation steps. But the problem says "final answer as a formula/expression". Hmm. Let me think. For example, if the answer is (A t2 + B t2³ - A t1 - B t1³)/(t2 - t1). But substituting the numbers, perhaps. Wait, but the problem statement says "final formula" is the expression. So maybe the formula is written as \\frac{A t_2 + B t_2^3 - A t_1 - B t_1^3}{t_2 - t_1}. Then substituting the numbers, but perhaps the problem expects the formula in terms of the variables given. Wait, but the problem statement says "final answer as a formula/expression written as valid LaTeX". So perhaps the formula is the general expression for average velocity, which is (x(t2) - x(t1))/(t2 - t1). But since x(t) is given as At + Bt³, substituting that in, the formula would be [A(t2 - t1) + B(t2³ - t1³)] / (t2 - t1). Which simplifies to A + B(t2² + t2 t1 + t1²). But maybe the problem wants the formula as written with the given variables. Alternatively, since the problem gives numerical values for A, B, t1, t2, perhaps the formula is written with those numbers plugged in. Let me check the examples. \n\nLooking at the examples, in example 1, the formula is "LATEX_FORMULA_INSERT_HERE", but the user probably expects the actual formula. For instance, if the answer is (9 m - 11 m)/(6 s - 2 s) = (-2 m)/(4 s) = -0.5 m/s. But the formula would be written as \\frac{(6 \\cdot 6 + (-0.125) \\cdot 6^3) - (6 \\cdot 2 + (-0.125) \\cdot 2^3)}{6 - 2}. But that\'s a bit messy. Alternatively, the formula could be written as \\frac{A(t_2) + B(t_2^3) - A(t_1) - B(t_1^3)}{t_2 - t_1} but substituting the values. \n\nAlternatively, maybe the problem expects the formula in terms of the variables, but since the answer is numeric, perhaps the formula is the expression with the numbers substituted. Let me think. The problem says "final formula" is the final answer as a formula. So perhaps the formula is the expression that leads to the numeric answer, with the given numbers. For example, \\frac{(6 \\cdot 6 + (-0.125) \\cdot 6^3) - (6 \\cdot 2 + (-0.125) \\cdot 2^3)}{6 - 2}. But that\'s a bit long. Alternatively, simplifying the numerator: 6 - x2 = (6*6 -0.125*6^3) - (6*2 -0.125*2^3). Wait, no, 6^3 is 216. So substituting:\n\nx6 = 6*6 + (-0.125)*6^3 = 36 - 0.125*216 = 36 -27=9.\n\nx2=6*2 + (-0.125)*8=12 -1=11.\n\nSo x6 -x2=9-11= -2. So the average velocity is -2 /4= -0.5 m/s.\n\nSo the formula would be \\frac{(6 \\cdot 6 + (-0.125) \\cdot 6^3) - (6 \\cdot 2 + (-0.125) \\cdot 2^3)}{6 - 2} = \\frac{-2}{4} = -0.5 \\, \\text{м/с}. But the problem wants the formula as a LaTeX expression. So perhaps the formula is written as \\frac{x(t_2) - x(t_1)}{t_2 - t_1} = \\frac{(6) \\cdot 6 + (-0.125) \\cdot 6^3 - [6 \\cdot 2 + (-0.125) \\cdot 2^3]}{6 - 2}. But maybe the problem expects the formula in terms of the given variables, not the numbers. Hmm. Let me check the problem statement again. The problem says "final formula: a string containing the final answer as a formula/expression written as valid LaTeX". So perhaps the formula is the general expression for average velocity, which is (x(t2) -x(t1))/(t2 -t1). But since x(t) is given as At + Bt³, substituting that in, the formula would be \\frac{A t_2 + B t_2^3 - A t_1 - B t_1^3}{t_2 - t_1}. But since the problem gives numerical values for A and B, maybe the formula should include those numbers. For example, substituting A=6 and B=-0.125, the formula becomes \\frac{6 t_2 - 0.125 t_2^3 - 6 t_1 + 0.125 t_1^3}{t_2 - t_1}. But then substituting t1=2 and t2=6, but maybe the formula is written with the numbers. Alternatively, the problem might expect the formula to be written with the numerical values substituted. For example, \\frac{6 \\cdot 6 + (-0.125) \\cdot 6^3 - (6 \\cdot 2 + (-0.125) \\cdot 2^3)}{6 - 2}. But that\'s quite detailed. Alternatively, the formula can be written as \\frac{(6 \\cdot 6 - 0.125 \\cdot 6^3) - (6 \\cdot 2 - 0.125 \\cdot 2^3)}{6 - 2}. \n\nBut perhaps the problem expects the formula in the general form, using the given variables. But since the answer is numeric, maybe the formula is the expression evaluated with the numbers, leading to the numeric result. So the formula would be \\frac{9\\, \\text{м} - 11\\, \\text{м}}{6\\, \\text{с} - 2\\, \\text{с}} = -0.5\\, \\text{м/с}. But the problem says the formula should be written as valid LaTeX. So perhaps the formula is written as \\frac{(6 \\cdot 6 + (-0.125) \\cdot 6^3) - (6 \\cdot 2 + (-0.125) \\cdot 2^3)}{6 - 2} = -0.5 \\, \\text{м/с}. But the problem requires the formula to be in the "final_formula" key. However, the example outputs show that the formula field is just the formula, not the calculation steps. For example, in example 1, the formula is "LATEX_FORMULA_INSERT_HERE", which probably is the symbolic formula. But in this case, since the answer is numeric, maybe the formula is the expression that represents the average velocity, which is (x(t2) -x(t1))/(t2 -t1). But since x(t) is given, substituting that in, the formula would be \\frac{A(t_2 - t_1) + B(t_2^3 - t_1^3)}{t_2 - t_1} = A + B(t_2^2 + t_1 t_2 + t_1^2). But that\'s a simplified version. Alternatively, the formula can be written as \\frac{A t_2 + B t_2^3 - A t_1 - B t_1^3}{t_2 - t_1}. \n\nBut given that the problem provides numerical values, perhaps the formula should include those numbers. For example, substituting A=6, B=-0.125, t1=2, t2=6, the formula becomes \\frac{6 \\cdot 6 + (-0.125) \\cdot 6^3 - 6 \\cdot 2 - (-0.125) \\cdot 2^3}{6 - 2}. Which simplifies to \\frac{36 -27 -12 +1}{4} = \\frac{-2}{4} = -0.5. So the formula would be written as \\frac{6 \\cdot 6 + (-0.125) \\cdot 6^3 - (6 \\cdot 2 + (-0.125) \\cdot 2^3)}{6 - 2} = -0.5 \\, \\text{м/с}. But the problem requires the formula to be a string, so perhaps the formula is written as the expression with the numbers substituted. \n\nAlternatively, maybe the problem expects the formula to be written in terms of the variables, but since the answer is numeric, the formula is the expression that leads to the numeric value. So the formula would be \\frac{x(t_2) - x(t_1)}{t_2 - t_1} = \\frac{(6 \\cdot 6 - 0.125 \\cdot 6^3) - (6 \\cdot 2 - 0.125 \\cdot 2^3)}{6 - 2} = \\frac{-2}{4} = -0.5. But the formula field should only contain the formula, not the calculation steps. So perhaps the formula is written as \\frac{A(t_2) + B(t_2)^3 - A(t_1) - B(t_1)^3}{t_2 - t_1} with the numbers substituted. \n\nBut I\'m a bit confused about the exact requirement. Let me check the problem statement again. The "final_formula" is a string containing the final answer as a formula/expression. So if the answer is numeric, the formula would be the expression that when evaluated gives the numeric value. So substituting the given values into the general expression. \n\nSo the general formula is (A t₂ + B t₂³ - A t₁ - B t₁³)/(t₂ - t₁). Substituting A=6, B=-0.125, t₁=2, t₂=6, the formula becomes (6*6 + (-0.125)*6³ -6*2 - (-0.125)*2³)/(6-2). So the LaTeX for this would be:\n\n\\frac{6 \\cdot 6 + (-0.125) \\cdot 6^3 - 6 \\cdot 2 - (-0.125) \\cdot 2^3}{6 - 2}\n\nWhich simplifies to the numeric value. So this is the formula that should be in the "final_formula" field. \n\nThe final numeric value is -0.5 m/s, and the units are m/s. \n\nSo putting it all together, the JSON should be:\n\n{\n "final_numeric": -0.5,\n "final_formula": "\\\\frac{6 \\\\cdot 6 + (-0.125) \\\\cdot 6^3 - 6 \\\\cdot 2 - (-0.125) \\\\cdot 2^3}{6 - 2}",\n "final_units": "m/s"\n}\n\nBut I need to make sure that the LaTeX is correctly escaped. For example, each backslash in LaTeX needs to be represented as two backslashes in JSON. So the formula string should have double backslashes. For example, \\frac becomes \\\\frac, and \\cdot becomes \\\\cdot. \n\nSo the correct LaTeX expression with proper escaping would be:\n\n"final_formula": "\\\\frac{6 \\\\cdot 6 + (-0.125) \\\\cdot 6^3 - 6 \\\\cdot 2 - (-0.125) \\\\cdot 2^3}{6 - 2}"\n\nYes. \n\nThe final_units is "m/s", which in SI is meters per second, so "m/s".\n\nSo the final answer should have final_numeric as -0.5, the formula as the substituted expression, and units as m/s.\n', 'reasoning_details': [{'type': 'reasoning.text', 'text': 'Okay, let\'s tackle this physics problem. The question is about finding the average velocity of a point moving along the x-axis between two times, t₁ = 2 seconds and t₂ = 6 seconds. The position is given by the equation x(t) = At + Bt³, where A is 6 m/s and B is -0.125 m/s³. \n\nFirst, I remember that average velocity is the total displacement divided by the total time interval. So the formula should be (x(t₂) - x(t₁)) / (t₂ - t₁). That makes sense because average velocity is all about the change in position over the change in time.\n\nLet me start by calculating the displacement. I need to find x at t=6 and x at t=2, then subtract them. \n\nFor t₂ = 6s:\nx(6) = A*6 + B*(6)^3. Plugging in the values: 6 m/s *6 = 36 m. Then B is -0.125, so 6^3 is 216. Multiply that by B: -0.125 * 216? Wait, 6³ is 216. So -0.125 * 216 = -27. So x(6) is 36 -27 = 9 meters.\n\nWait, let me check that again. 6*6 is 36, yes. Then 6³ is 216. 0.125 * 216 is 27, but since B is negative, it\'s -27. So 36 -27 is indeed 9. So x(6) = 9 m.\n\nNow for t₁ = 2s:\nx(2) = A*2 + B*(2)^3. A is 6, so 6*2=12. B is -0.125, 2³ is 8. So -0.125 *8 = -1. So x(2) is 12 -1 = 11 meters.\n\nWait, that can\'t be right. Wait, 0.125 *8 is 1, so with the negative, it\'s -1. So 12 -1 = 11. So x(2) is 11 m. \n\nSo the displacement is x(6) - x(2) = 9 -11 = -2 meters. \n\nThe time interval is t₂ - t₁ = 6 -2 =4 seconds. \n\nSo average velocity is displacement over time: -2 m /4 s = -0.5 m/s. \n\nWait, but let me double-check the calculations. Maybe I made a mistake in the exponents or the multiplication. Let me recalculate x(6):\n\nA=6, t=6: 6*6=36. B=-0.125, t³=216. 0.125 *216 is 27, so -0.125*216= -27. 36-27=9. Correct. x(6)=9 m.\n\nx(2): 6*2=12. 2=8. 0.125*8=1, so -1. 12-1=11. Correct. So displacement is 9-11= -2. Time is 4s. So -2/4= -0.5 m/s. \n\nSo the average velocity is -0.5 m/s. \n\nThe formula for average velocity would be (A t₂ + B t₂³ - A t₁ - B t₁³)/(t₂ - t₁). Which can be factored as [A(t₂ - t₁) + B(t₂³ - t₁³)]/(t₂ - t₁). Then, simplifying, that\'s A + B(t₂² + t₂ t₁ + t₁²). But maybe the problem just wants the direct formula (x(t₂)-x(t₁))/(t₂ - t₁). \n\nBut since the answer requires the final formula as a LaTeX expression, perhaps the formula is written as v_{\\text{ср}} = \\frac{x(t_2) - x(t_1)}{t_2 - t_1}. But substituting the given values, but maybe they want the symbolic expression. Wait, the problem says to write the final answer as a formula. Wait, the problem says "final_formula": a string containing the final answer as a formula/expression written as valid LaTeX. So perhaps the formula is the expression evaluated with the numbers. Let me see. \n\nAlternatively, maybe the formula is written in terms of A, B, t1, t2. But since the problem gives numerical values, perhaps the formula is the calculation steps. But the problem says "final answer as a formula/expression". Hmm. Let me think. For example, if the answer is (A t2 + B t2³ - A t1 - B t1³)/(t2 - t1). But substituting the numbers, perhaps. Wait, but the problem statement says "final formula" is the expression. So maybe the formula is written as \\frac{A t_2 + B t_2^3 - A t_1 - B t_1^3}{t_2 - t_1}. Then substituting the numbers, but perhaps the problem expects the formula in terms of the variables given. Wait, but the problem statement says "final answer as a formula/expression written as valid LaTeX". So perhaps the formula is the general expression for average velocity, which is (x(t2) - x(t1))/(t2 - t1). But since x(t) is given as At + Bt³, substituting that in, the formula would be [A(t2 - t1) + B(t2³ - t1³)] / (t2 - t1). Which simplifies to A + B(t2² + t2 t1 + t1²). But maybe the problem wants the formula as written with the given variables. Alternatively, since the problem gives numerical values for A, B, t1, t2, perhaps the formula is written with those numbers plugged in. Let me check the examples. \n\nLooking at the examples, in example 1, the formula is "LATEX_FORMULA_INSERT_HERE", but the user probably expects the actual formula. For instance, if the answer is (9 m - 11 m)/(6 s - 2 s) = (-2 m)/(4 s) = -0.5 m/s. But the formula would be written as \\frac{(6 \\cdot 6 + (-0.125) \\cdot 6^3) - (6 \\cdot 2 + (-0.125) \\cdot 2^3)}{6 - 2}. But that\'s a bit messy. Alternatively, the formula could be written as \\frac{A(t_2) + B(t_2^3) - A(t_1) - B(t_1^3)}{t_2 - t_1} but substituting the values. \n\nAlternatively, maybe the problem expects the formula in terms of the variables, but since the answer is numeric, perhaps the formula is the expression with the numbers substituted. Let me think. The problem says "final formula" is the final answer as a formula. So perhaps the formula is the expression that leads to the numeric answer, with the given numbers. For example, \\frac{(6 \\cdot 6 + (-0.125) \\cdot 6^3) - (6 \\cdot 2 + (-0.125) \\cdot 2^3)}{6 - 2}. But that\'s a bit long. Alternatively, simplifying the numerator: 6 - x2 = (6*6 -0.125*6^3) - (6*2 -0.125*2^3). Wait, no, 6^3 is 216. So substituting:\n\nx6 = 6*6 + (-0.125)*6^3 = 36 - 0.125*216 = 36 -27=9.\n\nx2=6*2 + (-0.125)*8=12 -1=11.\n\nSo x6 -x2=9-11= -2. So the average velocity is -2 /4= -0.5 m/s.\n\nSo the formula would be \\frac{(6 \\cdot 6 + (-0.125) \\cdot 6^3) - (6 \\cdot 2 + (-0.125) \\cdot 2^3)}{6 - 2} = \\frac{-2}{4} = -0.5 \\, \\text{м/с}. But the problem wants the formula as a LaTeX expression. So perhaps the formula is written as \\frac{x(t_2) - x(t_1)}{t_2 - t_1} = \\frac{(6) \\cdot 6 + (-0.125) \\cdot 6^3 - [6 \\cdot 2 + (-0.125) \\cdot 2^3]}{6 - 2}. But maybe the problem expects the formula in terms of the given variables, not the numbers. Hmm. Let me check the problem statement again. The problem says "final formula: a string containing the final answer as a formula/expression written as valid LaTeX". So perhaps the formula is the general expression for average velocity, which is (x(t2) -x(t1))/(t2 -t1). But since x(t) is given as At + Bt³, substituting that in, the formula would be \\frac{A t_2 + B t_2^3 - A t_1 - B t_1^3}{t_2 - t_1}. But since the problem gives numerical values for A and B, maybe the formula should include those numbers. For example, substituting A=6 and B=-0.125, the formula becomes \\frac{6 t_2 - 0.125 t_2^3 - 6 t_1 + 0.125 t_1^3}{t_2 - t_1}. But then substituting t1=2 and t2=6, but maybe the formula is written with the numbers. Alternatively, the problem might expect the formula to be written with the numerical values substituted. For example, \\frac{6 \\cdot 6 + (-0.125) \\cdot 6^3 - (6 \\cdot 2 + (-0.125) \\cdot 2^3)}{6 - 2}. But that\'s quite detailed. Alternatively, the formula can be written as \\frac{(6 \\cdot 6 - 0.125 \\cdot 6^3) - (6 \\cdot 2 - 0.125 \\cdot 2^3)}{6 - 2}. \n\nBut perhaps the problem expects the formula in the general form, using the given variables. But since the answer is numeric, maybe the formula is the expression evaluated with the numbers, leading to the numeric result. So the formula would be \\frac{9\\, \\text{м} - 11\\, \\text{м}}{6\\, \\text{с} - 2\\, \\text{с}} = -0.5\\, \\text{м/с}. But the problem says the formula should be written as valid LaTeX. So perhaps the formula is written as \\frac{(6 \\cdot 6 + (-0.125) \\cdot 6^3) - (6 \\cdot 2 + (-0.125) \\cdot 2^3)}{6 - 2} = -0.5 \\, \\text{м/с}. But the problem requires the formula to be in the "final_formula" key. However, the example outputs show that the formula field is just the formula, not the calculation steps. For example, in example 1, the formula is "LATEX_FORMULA_INSERT_HERE", which probably is the symbolic formula. But in this case, since the answer is numeric, maybe the formula is the expression that represents the average velocity, which is (x(t2) -x(t1))/(t2 -t1). But since x(t) is given, substituting that in, the formula would be \\frac{A(t_2 - t_1) + B(t_2^3 - t_1^3)}{t_2 - t_1} = A + B(t_2^2 + t_1 t_2 + t_1^2). But that\'s a simplified version. Alternatively, the formula can be written as \\frac{A t_2 + B t_2^3 - A t_1 - B t_1^3}{t_2 - t_1}. \n\nBut given that the problem provides numerical values, perhaps the formula should include those numbers. For example, substituting A=6, B=-0.125, t1=2, t2=6, the formula becomes \\frac{6 \\cdot 6 + (-0.125) \\cdot 6^3 - 6 \\cdot 2 - (-0.125) \\cdot 2^3}{6 - 2}. Which simplifies to \\frac{36 -27 -12 +1}{4} = \\frac{-2}{4} = -0.5. So the formula would be written as \\frac{6 \\cdot 6 + (-0.125) \\cdot 6^3 - (6 \\cdot 2 + (-0.125) \\cdot 2^3)}{6 - 2} = -0.5 \\, \\text{м/с}. But the problem requires the formula to be a string, so perhaps the formula is written as the expression with the numbers substituted. \n\nAlternatively, maybe the problem expects the formula to be written in terms of the variables, but since the answer is numeric, the formula is the expression that leads to the numeric value. So the formula would be \\frac{x(t_2) - x(t_1)}{t_2 - t_1} = \\frac{(6 \\cdot 6 - 0.125 \\cdot 6^3) - (6 \\cdot 2 - 0.125 \\cdot 2^3)}{6 - 2} = \\frac{-2}{4} = -0.5. But the formula field should only contain the formula, not the calculation steps. So perhaps the formula is written as \\frac{A(t_2) + B(t_2)^3 - A(t_1) - B(t_1)^3}{t_2 - t_1} with the numbers substituted. \n\nBut I\'m a bit confused about the exact requirement. Let me check the problem statement again. The "final_formula" is a string containing the final answer as a formula/expression. So if the answer is numeric, the formula would be the expression that when evaluated gives the numeric value. So substituting the given values into the general expression. \n\nSo the general formula is (A t₂ + B t₂³ - A t₁ - B t₁³)/(t₂ - t₁). Substituting A=6, B=-0.125, t₁=2, t₂=6, the formula becomes (6*6 + (-0.125)*6³ -6*2 - (-0.125)*2³)/(6-2). So the LaTeX for this would be:\n\n\\frac{6 \\cdot 6 + (-0.125) \\cdot 6^3 - 6 \\cdot 2 - (-0.125) \\cdot 2^3}{6 - 2}\n\nWhich simplifies to the numeric value. So this is the formula that should be in the "final_formula" field. \n\nThe final numeric value is -0.5 m/s, and the units are m/s. \n\nSo putting it all together, the JSON should be:\n\n{\n "final_numeric": -0.5,\n "final_formula": "\\\\frac{6 \\\\cdot 6 + (-0.125) \\\\cdot 6^3 - 6 \\\\cdot 2 - (-0.125) \\\\cdot 2^3}{6 - 2}",\n "final_units": "m/s"\n}\n\nBut I need to make sure that the LaTeX is correctly escaped. For example, each backslash in LaTeX needs to be represented as two backslashes in JSON. So the formula string should have double backslashes. For example, \\frac becomes \\\\frac, and \\cdot becomes \\\\cdot. \n\nSo the correct LaTeX expression with proper escaping would be:\n\n"final_formula": "\\\\frac{6 \\\\cdot 6 + (-0.125) \\\\cdot 6^3 - 6 \\\\cdot 2 - (-0.125) \\\\cdot 2^3}{6 - 2}"\n\nYes. \n\nThe final_units is "m/s", which in SI is meters per second, so "m/s".\n\nSo the final answer should have final_numeric as -0.5, the formula as the substituted expression, and units as m/s.\n', 'format': 'unknown', 'index': 0}]}}], 'usage': {'prompt_tokens': 536, 'completion_tokens': 3650, 'total_tokens': 4186, 'cost': 0.02247696, 'is_byok': False, 'prompt_tokens_details': {'cached_tokens': 0, 'cache_write_tokens': 0, 'audio_tokens': 0, 'video_tokens': 0}, 'cost_details': {'upstream_inference_cost': 0.02247696, 'upstream_inference_prompt_cost': 0.00079596, 'upstream_inference_completions_cost': 0.021681}, 'completion_tokens_details': {'reasoning_tokens': 2791, 'image_tokens': 0, 'audio_tokens': 0}}} | L53: 536 | M53: 3650 | N53: 4186 | O53: 0 | P53: =VLOOKUP(C53,problems!$A$2:$B$26,2) -> mechanics | Q53: =IFERROR(__xludf.DUMMYFUNCTION("INDEX(FILTER('stats2-openrouter_activity_2026'!C:C,L53='stats2-openrouter_activity_2026'!H:H,M53='stats2-openrouter_activity_2026'!I:I, B53='stats2-openrouter_activity_2026'!M:M),1)"),0.022476) -> 0.022476 | R53: =IFS( F53=VLOOKUP($C53,problems!$A$2:$G$26,6),1, True,0 ) -> 1 | S53: =IFS( G53=VLOOKUP($C53,problems!$A$2:$G$26,4),1, G53=VLOOKUP($C53,problems!$A$2:$G$26,5),1, True,0 ) -> 0 | T53: =IFS( H53=VLOOKUP($C53,problems!$A$2:$G$26,7),1, True,0 ) -> 1
